Workbook

Sheet Roster
A1: ROSTER - Ultimate Frisbee Team
A4: Full Name | B4: Dues Amount ($) | C4: Dues Paid? | D4: Role | E4: Status | F4: Notes | G4: Guest Of
A5: ='Access Codes'!A6 -> At | B5: {=IFERROR(INDEX('Player Balances'!$B$7:$B$206,MATCH(A5,'Player Balances'!$A$7:$A$206,0)),"")} -> 0 | C5: =IF(A5="","",IF(OR(D5="Coach",D5="Treasurer"),"Waived",IF(OR(B5="",B5=0),"",IF(SUMIFS(Transactions!$F$7:$F$989,Transactions!$D$7:$D$989,"Income",Transactions!$C$7:$C$989,"Dues",Transactions!$E$7:$E$989,A5)>=B5,"Paid",IF(SUMIFS(Transactions!$F$7:$F$989,Transactions!$D$7:$D$989,"Income",Transactions!$C$7:$C$989,"Dues",Transactions!$E$7:$E$989,A5)>0,"Partial","Unpaid"))))) | D5: ='Access Codes'!C6 -> Captain | E5: ='Access Codes'!D6 -> Active
A6: ='Access Codes'!A7 -> Alex Warrington | B6: {=IFERROR(INDEX('Player Balances'!$B$7:$B$206,MATCH(A6,'Player Balances'!$A$7:$A$206,0)),"")} -> 0 | C6: =IF(A6="","",IF(OR(D6="Coach",D6="Treasurer"),"Waived",IF(OR(B6="",B6=0),"",IF(SUMIFS(Transactions!$F$7:$F$989,Transactions!$D$7:$D$989,"Income",Transactions!$C$7:$C$989,"Dues",Transactions!$E$7:$E$989,A6)>=B6,"Paid",IF(SUMIFS(Transactions!$F$7:$F$989,Transactions!$D$7:$D$989,"Income",Transactions!$C$7:$C$989,"Dues",Transactions!$E$7:$E$989,A6)>0,"Partial","Unpaid"))))) | D6: ='Access Codes'!C7 -> Player | E6: ='Access Codes'!D7 -> Active
A7: ='Access Codes'!A8 -> Chris Wohl | B7: {=IFERROR(INDEX('Player Balances'!$B$7:$B$206,MATCH(A7,'Player Balances'!$A$7:$A$206,0)),"")} -> 0 | C7: =IF(A7="","",IF(OR(D7="Coach",D7="Treasurer"),"Waived",IF(OR(B7="",B7=0),"",IF(SUMIFS(Transactions!$F$7:$F$989,Transactions!$D$7:$D$989,"Income",Transactions!$C$7:$C$989,"Dues",Transactions!$E$7:$E$989,A7)>=B7,"Paid",IF(SUMIFS(Transactions!$F$7:$F$989,Transactions!$D$7:$D$989,"Income",Transactions!$C$7:$C$989,"Dues",Transactions!$E$7:$E$989,A7)>0,"Partial","Unpaid"))))) | D7: ='Access Codes'!C8 -> Player | E7: ='Access Codes'!D8 -> Active | F7: Paid $75
A8: ='Access Codes'!A9 -> Darra Reppermund | B8: {=IFERROR(INDEX('Player Balances'!$B$7:$B$206,MATCH(A8,'Player Balances'!$A$7:$A$206,0)),"")} -> 0 | C8: =IF(A8="","",IF(OR(D8="Coach",D8="Treasurer"),"Waived",IF(OR(B8="",B8=0),"",IF(SUMIFS(Transactions!$F$7:$F$989,Transactions!$D$7:$D$989,"Income",Transactions!$C$7:$C$989,"Dues",Transactions!$E$7:$E$989,A8)>=B8,"Paid",IF(SUMIFS(Transactions!$F$7:$F$989,Transactions!$D$7:$D$989,"Income",Transactions!$C$7:$C$989,"Dues",Transactions!$E$7:$E$989,A8)>0,"Partial","Unpaid"))))) | D8: ='Access Codes'!C9 -> Player | E8: ='Access Codes'!D9 -> Active
A9: ='Access Codes'!A10 -> Dylan Best | B9: {=IFERROR(INDEX('Player Balances'!$B$7:$B$206,MATCH(A9,'Player Balances'!$A$7:$A$206,0)),"")} -> 0 | C9: =IF(A9="","",IF(OR(D9="Coach",D9="Treasurer"),"Waived",IF(OR(B9="",B9=0),"",IF(SUMIFS(Transactions!$F$7:$F$989,Transactions!$D$7:$D$989,"Income",Transactions!$C$7:$C$989,"Dues",Transactions!$E$7:$E$989,A9)>=B9,"Paid",IF(SUMIFS(Transactions!$F$7:$F$989,Transactions!$D$7:$D$989,"Income",Transactions!$C$7:$C$989,"Dues",Transactions!$E$7:$E$989,A9)>0,"Partial","Unpaid"))))) | D9: ='Access Codes'!C10 -> Player | E9: ='Access Codes'!D10 -> Active
A10: ='Access Codes'!A11 -> Griffin O'Neal-Freeman | B10: {=IFERROR(INDEX('Player Balances'!$B$7:$B$206,MATCH(A10,'Player Balances'!$A$7:$A$206,0)),"")} -> 0 | C10: =IF(A10="","",IF(OR(D10="Coach",D10="Treasurer"),"Waived",IF(OR(B10="",B10=0),"",IF(SUMIFS(Transactions!$F$7:$F$989,Transactions!$D$7:$D$989,"Income",Transactions!$C$7:$C$989,"Dues",Transactions!$E$7:$E$989,A10)>=B10,"Paid",IF(SUMIFS(Transactions!$F$7:$F$989,Transactions!$D$7:$D$989,"Income",Transactions!$C$7:$C$989,"Dues",Transactions!$E$7:$E$989,A10)>0,"Partial","Unpaid"))))) | D10: ='Access Codes'!C11 -> Player | E10: ='Access Codes'!D11 -> Active
A11: ='Access Codes'!A12 -> Haley Young | B11: {=IFERROR(INDEX('Player Balances'!$B$7:$B$206,MATCH(A11,'Player Balances'!$A$7:$A$206,0)),"")} -> 0 | C11: =IF(A11="","",IF(OR(D11="Coach",D11="Treasurer"),"Waived",IF(OR(B11="",B11=0),"",IF(SUMIFS(Transactions!$F$7:$F$989,Transactions!$D$7:$D$989,"Income",Transactions!$C$7:$C$989,"Dues",Transactions!$E$7:$E$989,A11)>=B11,"Paid",IF(SUMIFS(Transactions!$F$7:$F$989,Transactions!$D$7:$D$989,"Income",Transactions!$C$7:$C$989,"Dues",Transactions!$E$7:$E$989,A11)>0,"Partial","Unpaid"))))) | D11: ='Access Codes'!C12 -> Player | E11: ='Access Codes'!D12 -> Active
A12: ='Access Codes'!A13 -> Harry Park | B12: {=IFERROR(INDEX('Player Balances'!$B$7:$B$206,MATCH(A12,'Player Balances'!$A$7:$A$206,0)),"")} -> 0 | C12: =IF(A12="","",IF(OR(D12="Coach",D12="Treasurer"),"Waived",IF(OR(B12="",B12=0),"",IF(SUMIFS(Transactions!$F$7:$F$989,Transactions!$D$7:$D$989,"Income",Transactions!$C$7:$C$989,"Dues",Transactions!$E$7:$E$989,A12)>=B12,"Paid",IF(SUMIFS(Transactions!$F$7:$F$989,Transactions!$D$7:$D$989,"Income",Transactions!$C$7:$C$989,"Dues",Transactions!$E$7:$E$989,A12)>0,"Partial","Unpaid"))))) | D12: ='Access Codes'!C13 -> Player | E12: ='Access Codes'!D13 -> Active
A13: ='Access Codes'!A14 -> Ian Piper | B13: {=IFERROR(INDEX('Player Balances'!$B$7:$B$206,MATCH(A13,'Player Balances'!$A$7:$A$206,0)),"")} -> 0 | C13: =IF(A13="","",IF(OR(D13="Coach",D13="Treasurer"),"Waived",IF(OR(B13="",B13=0),"",IF(SUMIFS(Transactions!$F$7:$F$989,Transactions!$D$7:$D$989,"Income",Transactions!$C$7:$C$989,"Dues",Transactions!$E$7:$E$989,A13)>=B13,"Paid",IF(SUMIFS(Transactions!$F$7:$F$989,Transactions!$D$7:$D$989,"Income",Transactions!$C$7:$C$989,"Dues",Transactions!$E$7:$E$989,A13)>0,"Partial","Unpaid"))))) | D13: ='Access Codes'!C14 -> Player | E13: ='Access Codes'!D14 -> Active
A14: ='Access Codes'!A15 -> Jake Murray | B14: {=IFERROR(INDEX('Player Balances'!$B$7:$B$206,MATCH(A14,'Player Balances'!$A$7:$A$206,0)),"")} -> 0 | C14: =IF(A14="","",IF(OR(D14="Coach",D14="Treasurer"),"Waived",IF(OR(B14="",B14=0),"",IF(SUMIFS(Transactions!$F$7:$F$989,Transactions!$D$7:$D$989,"Income",Transactions!$C$7:$C$989,"Dues",Transactions!$E$7:$E$989,A14)>=B14,"Paid",IF(SUMIFS(Transactions!$F$7:$F$989,Transactions!$D$7:$D$989,"Income",Transactions!$C$7:$C$989,"Dues",Transactions!$E$7:$E$989,A14)>0,"Partial","Unpaid"))))) -> Waived | D14: ='Access Codes'!C15 -> Treasurer | E14: ='Access Codes'!D15 -> Active
A15: ='Access Codes'!A16 -> Jenna Nold | B15: {=IFERROR(INDEX('Player Balances'!$B$7:$B$206,MATCH(A15,'Player Balances'!$A$7:$A$206,0)),"")} -> 0 | C15: =IF(A15="","",IF(OR(D15="Coach",D15="Treasurer"),"Waived",IF(OR(B15="",B15=0),"",IF(SUMIFS(Transactions!$F$7:$F$989,Transactions!$D$7:$D$989,"Income",Transactions!$C$7:$C$989,"Dues",Transactions!$E$7:$E$989,A15)>=B15,"Paid",IF(SUMIFS(Transactions!$F$7:$F$989,Transactions!$D$7:$D$989,"Income",Transactions!$C$7:$C$989,"Dues",Transactions!$E$7:$E$989,A15)>0,"Partial","Unpaid"))))) | D15: ='Access Codes'!C16 -> Captain | E15: ='Access Codes'!D16 -> Active
A16: ='Access Codes'!A17 -> Jimmy Towle | B16: {=IFERROR(INDEX('Player Balances'!$B$7:$B$206,MATCH(A16,'Player Balances'!$A$7:$A$206,0)),"")} -> 0 | C16: =IF(A16="","",IF(OR(D16="Coach",D16="Treasurer"),"Waived",IF(OR(B16="",B16=0),"",IF(SUMIFS(Transactions!$F$7:$F$989,Transactions!$D$7:$D$989,"Income",Transactions!$C$7:$C$989,"Dues",Transactions!$E$7:$E$989,A16)>=B16,"Paid",IF(SUMIFS(Transactions!$F$7:$F$989,Transactions!$D$7:$D$989,"Income",Transactions!$C$7:$C$989,"Dues",Transactions!$E$7:$E$989,A16)>0,"Partial","Unpaid"))))) | D16: ='Access Codes'!C17 -> Player | E16: ='Access Codes'!D17 -> Active
A17: ='Access Codes'!A18 -> Kailey Rugani | B17: {=IFERROR(INDEX('Player Balances'!$B$7:$B$206,MATCH(A17,'Player Balances'!$A$7:$A$206,0)),"")} -> 0 | C17: =IF(A17="","",IF(OR(D17="Coach",D17="Treasurer"),"Waived",IF(OR(B17="",B17=0),"",IF(SUMIFS(Transactions!$F$7:$F$989,Transactions!$D$7:$D$989,"Income",Transactions!$C$7:$C$989,"Dues",Transactions!$E$7:$E$989,A17)>=B17,"Paid",IF(SUMIFS(Transactions!$F$7:$F$989,Transactions!$D$7:$D$989,"Income",Transactions!$C$7:$C$989,"Dues",Transactions!$E$7:$E$989,A17)>0,"Partial","Unpaid"))))) | D17: ='Access Codes'!C18 -> Player | E17: ='Access Codes'!D18 -> Active
A18: ='Access Codes'!A19 -> Kasey Schock | B18: {=IFERROR(INDEX('Player Balances'!$B$7:$B$206,MATCH(A18,'Player Balances'!$A$7:$A$206,0)),"")} -> 0 | C18: =IF(A18="","",IF(OR(D18="Coach",D18="Treasurer"),"Waived",IF(OR(B18="",B18=0),"",IF(SUMIFS(Transactions!$F$7:$F$989,Transactions!$D$7:$D$989,"Income",Transactions!$C$7:$C$989,"Dues",Transactions!$E$7:$E$989,A18)>=B18,"Paid",IF(SUMIFS(Transactions!$F$7:$F$989,Transactions!$D$7:$D$989,"Income",Transactions!$C$7:$C$989,"Dues",Transactions!$E$7:$E$989,A18)>0,"Partial","Unpaid"))))) | D18: ='Access Codes'!C19 -> Player | E18: ='Access Codes'!D19 -> Active
A19: ='Access Codes'!A20 -> Kevin Nicholl | B19: {=IFERROR(INDEX('Player Balances'!$B$7:$B$206,MATCH(A19,'Player Balances'!$A$7:$A$206,0)),"")} -> 0 | C19: =IF(A19="","",IF(OR(D19="Coach",D19="Treasurer"),"Waived",IF(OR(B19="",B19=0),"",IF(SUMIFS(Transactions!$F$7:$F$989,Transactions!$D$7:$D$989,"Income",Transactions!$C$7:$C$989,"Dues",Transactions!$E$7:$E$989,A19)>=B19,"Paid",IF(SUMIFS(Transactions!$F$7:$F$989,Transactions!$D$7:$D$989,"Income",Transactions!$C$7:$C$989,"Dues",Transactions!$E$7:$E$989,A19)>0,"Partial","Unpaid"))))) | D19: ='Access Codes'!C20 -> Player | E19: ='Access Codes'!D20 -> Active
... A39: ='Access Codes'!A40 -> Nick Blair | B39: {=IFERROR(INDEX('Player Balances'!$B$7:$B$206,MATCH(A39,'Player Balances'!$A$7:$A$206,0)),"")} -> 0 | C39: =IF(A39="","",IF(OR(D39="Coach",D39="Treasurer"),"Waived",IF(OR(B39="",B39=0),"",IF(SUMIFS(Transactions!$F$7:$F$989,Transactions!$D$7:$D$989,"Income",Transactions!$C$7:$C$989,"Dues",Transactions!$E$7:$E$989,A39)>=B39,"Paid",IF(SUMIFS(Transactions!$F$7:$F$989,Transactions!$D$7:$D$989,"Income",Transactions!$C$7:$C$989,"Dues",Transactions!$E$7:$E$989,A39)>0,"Partial","Unpaid"))))) | D39: ='Access Codes'!C40 -> Support | E39: ='Access Codes'!D40 -> Active
A40: ='Access Codes'!A41 -> Lily Nguyen | B40: {=IFERROR(INDEX('Player Balances'!$B$7:$B$206,MATCH(A40,'Player Balances'!$A$7:$A$206,0)),"")} -> 0 | C40: =IF(A40="","",IF(OR(D40="Coach",D40="Treasurer"),"Waived",IF(OR(B40="",B40=0),"",IF(SUMIFS(Transactions!$F$7:$F$989,Transactions!$D$7:$D$989,"Income",Transactions!$C$7:$C$989,"Dues",Transactions!$E$7:$E$989,A40)>=B40,"Paid",IF(SUMIFS(Transactions!$F$7:$F$989,Transactions!$D$7:$D$989,"Income",Transactions!$C$7:$C$989,"Dues",Transactions!$E$7:$E$989,A40)>0,"Partial","Unpaid"))))) | D40: ='Access Codes'!C41 -> Support | E40: ='Access Codes'!D41 -> Active | G40: Ryan Kindell
A41: ='Access Codes'!A42 -> Griff Soren | B41: {=IFERROR(INDEX('Player Balances'!$B$7:$B$206,MATCH(A41,'Player Balances'!$A$7:$A$206,0)),"")} -> 0 | C41: =IF(A41="","",IF(OR(D41="Coach",D41="Treasurer"),"Waived",IF(OR(B41="",B41=0),"",IF(SUMIFS(Transactions!$F$7:$F$989,Transactions!$D$7:$D$989,"Income",Transactions!$C$7:$C$989,"Dues",Transactions!$E$7:$E$989,A41)>=B41,"Paid",IF(SUMIFS(Transactions!$F$7:$F$989,Transactions!$D$7:$D$989,"Income",Transactions!$C$7:$C$989,"Dues",Transactions!$E$7:$E$989,A41)>0,"Partial","Unpaid"))))) | D41: ='Access Codes'!C42 -> Support | E41: ='Access Codes'!D42 -> Active | G41: Griffin O'Neal-Freeman
A42: ='Access Codes'!A43 -> Griff Alice | B42: {=IFERROR(INDEX('Player Balances'!$B$7:$B$206,MATCH(A42,'Player Balances'!$A$7:$A$206,0)),"")} -> 0 | C42: =IF(A42="","",IF(OR(D42="Coach",D42="Treasurer"),"Waived",IF(OR(B42="",B42=0),"",IF(SUMIFS(Transactions!$F$7:$F$989,Transactions!$D$7:$D$989,"Income",Transactions!$C$7:$C$989,"Dues",Transactions!$E$7:$E$989,A42)>=B42,"Paid",IF(SUMIFS(Transactions!$F$7:$F$989,Transactions!$D$7:$D$989,"Income",Transactions!$C$7:$C$989,"Dues",Transactions!$E$7:$E$989,A42)>0,"Partial","Unpaid"))))) | D42: ='Access Codes'!C43 -> Support | E42: ='Access Codes'!D43 -> Active | G42: Griffin O'Neal-Freeman

Sheet Events
A4: Event Name | B4: Start Date | C4: End Date | D4: Category | E4: Location | F4: Budgeted Cost ($) | G4: Actual Cost ($) | I4: Split Method | J4: Season Group
A5: May-July Fields | B5: 03/15/2025 | D5: Practice | E5: Dan Marino | F5: 850 | G5: =IFERROR(SUMIFS(Transactions!$F$7:$F$989,Transactions!$G$7:$G$989,A5,Transactions!$D$7:$D$989,"Expense"),0) -> 2326 | I5: Attendance | J5: In-Season 2026
A6: PEC | B6: 46199 | D6: Tournament | E6: Browns Summit | F6: 1310 | G6: 1310 | I6: Attendance | J6: In-Season 2026
A7: SFI | B7: 46227 | D7: Tournament | E7: Holiday Inn Downtown | F7: 1050 | G7: 1050 | I7: Attendance | J7: In-Season 2026
A8: Natties Watch Party | D8: Fundraiser | E8: Goodlander | F8: 0 | G8: -123 | J8: Pre-Season 2026
A9: Fantapalooza | B9: 45706 | D9: Fundraiser | E9: Goodlander | F9: 0 | G9: -956 | J9: Pre-Season 2026
A10: 2025 Fundraising | B10: 45706 | D10: Fundraiser | E10: Mult. | F10: 0 | G10: 1030 | J10: Pre-Season 2026
A11: GHP Sessions | D11: Event | E11: GHP | F11: 600 | G11: =IFERROR(SUMIFS(Transactions!$F$7:$F$989,Transactions!$G$7:$G$989,A11,Transactions!$D$7:$D$989,"Expense"),0) -> 0 | I11: Attendance | J11: Pre-Season 2026
A12: ESC | G12: =IFERROR(SUMIFS(Transactions!$F$7:$F$989,Transactions!$G$7:$G$989,A12,Transactions!$D$7:$D$989,"Expense"),0) -> 5345.86 | I12: Attendance | J12: In-Season 2026
A13: Sectionals | G13: =IFERROR(SUMIFS(Transactions!$F$7:$F$989,Transactions!$G$7:$G$989,A13,Transactions!$D$7:$D$989,"Expense"),0) -> 560.85 | I13: Attendance | J13: In-Season 2026
A14: Regionals | G14: =IFERROR(SUMIFS(Transactions!$F$7:$F$989,Transactions!$G$7:$G$989,A14,Transactions!$D$7:$D$989,"Expense"),0) -> 5965.16 | I14: Attendance | J14: In-Season 2026
A15: Retreat | G15: =IFERROR(SUMIFS(Transactions!$F$7:$F$989,Transactions!$G$7:$G$989,A15,Transactions!$D$7:$D$989,"Expense"),0) -> 9054.59 | I15: Attendance | J15: In-Season 2026
A16: Misc | G16: =IFERROR(SUMIFS(Transactions!$F$7:$F$989,Transactions!$G$7:$G$989,A16,Transactions!$D$7:$D$989,"Expense"),0) -> 0 | I16: Attendance | J16: In-Season 2026
A17: Nationals | G17: =IFERROR(SUMIFS(Transactions!$F$7:$F$989,Transactions!$G$7:$G$989,A17,Transactions!$D$7:$D$989,"Expense"),0) -> 7150 | I17: Attendance | J17: In-Season 2026
A18: Fan Stores | G18: =IFERROR(SUMIFS(Transactions!$F$7:$F$989,Transactions!$G$7:$G$989,A18,Transactions!$D$7:$D$989,"Expense"),0) -> 0
G19: =IFERROR(SUMIFS(Transactions!$F$7:$F$989,Transactions!$G$7:$G$989,A19,Transactions!$D$7:$D$989,"Expense"),0) -> 0
G20: =IFERROR(SUMIFS(Transactions!$F$7:$F$989,Transactions!$G$7:$G$989,A20,Transactions!$D$7:$D$989,"Expense"),0) -> 0
G21: =IFERROR(SUMIFS(Transactions!$F$7:$F$989,Transactions!$G$7:$G$989,A21,Transactions!$D$7:$D$989,"Expense"),0) -> 0
G22: =IFERROR(SUMIFS(Transactions!$F$7:$F$989,Transactions!$G$7:$G$989,A22,Transactions!$D$7:$D$989,"Expense"),0) -> 0
G23: =IFERROR(SUMIFS(Transactions!$F$7:$F$989,Transactions!$G$7:$G$989,A23,Transactions!$D$7:$D$989,"Expense"),0) -> 0
G24: =IFERROR(SUMIFS(Transactions!$F$7:$F$989,Transactions!$G$7:$G$989,A24,Transactions!$D$7:$D$989,"Expense"),0) -> 0
G25: =IFERROR(SUMIFS(Transactions!$F$7:$F$989,Transactions!$G$7:$G$989,A25,Transactions!$D$7:$D$989,"Expense"),0) -> 0
G26: =IFERROR(SUMIFS(Transactions!$F$7:$F$989,Transactions!$G$7:$G$989,A26,Transactions!$D$7:$D$989,"Expense"),0) -> 0
G27: =IFERROR(SUMIFS(Transactions!$F$7:$F$989,Transactions!$G$7:$G$989,A27,Transactions!$D$7:$D$989,"Expense"),0) -> 0
G28: =IFERROR(SUMIFS(Transactions!$F$7:$F$989,Transactions!$G$7:$G$989,A28,Transactions!$D$7:$D$989,"Expense"),0) -> 0
G29: =IFERROR(SUMIFS(Transactions!$F$7:$F$989,Transactions!$G$7:$G$989,A29,Transactions!$D$7:$D$989,"Expense"),0) -> 0
G30: =IFERROR(SUMIFS(Transactions!$F$7:$F$989,Transactions!$G$7:$G$989,A30,Transactions!$D$7:$D$989,"Expense"),0) -> 0
... G504: =IFERROR(SUMIFS(Transactions!$F$7:$F$989,Transactions!$G$7:$G$989,A504,Transactions!$D$7:$D$989,"Expense"),0) -> 0

Sheet Attendance
B1: ATTENDANCE TRACKER | AZ1: 57 | BA1: 58 | BB1: 59 | BC1: 60 | BD1: 61 | BY1: 62 | BZ1: 63 | CA1: 64 | CB1: 65 | CC1: 66 | CD1: 67 | CE1: 68 | CF1: 69 | CG1: 70 | CH1: 71 | CI1: 72 | CJ1: 73 | CK1: 74 | CL1: 75 | CM1: 76 | CN1: 77 | CO1: 78 | CP1: 79 | CQ1: 80 | CR1: 81 | CS1: 82 | CT1: 83 | CU1: 84 | CV1: 85 | CW1: 86 | CX1: 87 | CY1: 88 | CZ1: 89 | DA1: 90 | DB1: 91 | DC1: 92 | DD1: 93 | DE1: 94 | DF1: 95 | DG1: 96 | DH1: 97 | DI1: 98 | DJ1: 99
B2: =IF(AND(Transactions!$D7="Expense",Transactions!$G7<>""),"-> "&Transactions!$G7,"") -> -> PEC | C2: =IF(AND(Transactions!$D8="Expense",Transactions!$G8<>""),"-> "&Transactions!$G8,"") -> -> SFI | D2: =IF(AND(Transactions!$D9="Expense",Transactions!$G9<>""),"-> "&Transactions!$G9,"") | E2: =IF(AND(Transactions!$D10="Expense",Transactions!$G10<>""),"-> "&Transactions!$G10,"") | F2: =IF(AND(Transactions!$D11="Expense",Transactions!$G11<>""),"-> "&Transactions!$G11,"") | G2: =IF(AND(Transactions!$D12="Expense",Transactions!$G12<>""),"-> "&Transactions!$G12,"") -> -> May-July Fields | H2: =IF(AND(Transactions!$D13="Expense",Transactions!$G13<>""),"-> "&Transactions!$G13,"") -> -> PEC | I2: =IF(AND(Transactions!$D14="Expense",Transactions!$G14<>""),"-> "&Transactions!$G14,"") -> -> PEC | J2: =IF(AND(Transactions!$D15="Expense",Transactions!$G15<>""),"-> "&Transactions!$G15,"") | K2: =IF(AND(Transactions!$D16="Expense",Transactions!$G16<>""),"-> "&Transactions!$G16,"") | L2: =IF(AND(Transactions!$D17="Expense",Transactions!$G17<>""),"-> "&Transactions!$G17,"") -> -> PEC | M2: =IF(AND(Transactions!$D18="Expense",Transactions!$G18<>""),"-> "&Transactions!$G18,"") -> -> PEC | N2: =IF(AND(Transactions!$D19="Expense",Transactions!$G19<>""),"-> "&Transactions!$G19,"") | O2: =IF(AND(Transactions!$D20="Expense",Transactions!$G20<>""),"-> "&Transactions!$G20,"") -> -> PEC | P2: =IF(AND(Transactions!$D21="Expense",Transactions!$G21<>""),"-> "&Transactions!$G21,"") -> -> PEC | Q2: =IF(AND(Transactions!$D22="Expense",Transactions!$G22<>""),"-> "&Transactions!$G22,"") | R2: =IF(AND(Transactions!$D23="Expense",Transactions!$G23<>""),"-> "&Transactions!$G23,"") | S2: =IF(AND(Transactions!$D24="Expense",Transactions!$G24<>""),"-> "&Transactions!$G24,"") | T2: =IF(AND(Transactions!$D25="Expense",Transactions!$G25<>""),"-> "&Transactions!$G25,"") | U2: =IF(AND(Transactions!$D26="Expense",Transactions!$G26<>""),"-> "&Transactions!$G26,"") | V2: =IF(AND(Transactions!$D27="Expense",Transactions!$G27<>""),"-> "&Transactions!$G27,"") | W2: =IF(AND(Transactions!$D28="Expense",Transactions!$G28<>""),"-> "&Transactions!$G28,"") | X2: =IF(AND(Transactions!$D29="Expense",Transactions!$G29<>""),"-> "&Transactions!$G29,"") | Y2: =IF(AND(Transactions!$D30="Expense",Transactions!$G30<>""),"-> "&Transactions!$G30,"") | Z2: =IF(AND(Transactions!$D31="Expense",Transactions!$G31<>""),"-> "&Transactions!$G31,"") | AA2: =IF(AND(Transactions!$D32="Expense",Transactions!$G32<>""),"-> "&Transactions!$G32,"") | AB2: =IF(AND(Transactions!$D33="Expense",Transactions!$G33<>""),"-> "&Transactions!$G33,"") -> -> PEC | AC2: =IF(AND(Transactions!$D34="Expense",Transactions!$G34<>""),"-> "&Transactions!$G34,"") | AD2: =IF(AND(Transactions!$D35="Expense",Transactions!$G35<>""),"-> "&Transactions!$G35,"") -> -> ESC | AE2: =IF(AND(Transactions!$D36="Expense",Transactions!$G36<>""),"-> "&Transactions!$G36,"") | AF2: =IF(AND(Transactions!$D37="Expense",Transactions!$G37<>""),"-> "&Transactions!$G37,"") | AG2: =IF(AND(Transactions!$D38="Expense",Transactions!$G38<>""),"-> "&Transactions!$G38,"") | AH2: =IF(AND(Transactions!$D39="Expense",Transactions!$G39<>""),"-> "&Transactions!$G39,"") | AI2: =IF(AND(Transactions!$D40="Expense",Transactions!$G40<>""),"-> "&Transactions!$G40,"") -> -> SFI | AJ2: =IF(AND(Transactions!$D41="Expense",Transactions!$G41<>""),"-> "&Transactions!$G41,"") -> -> SFI | AK2: =IF(AND(Transactions!$D42="Expense",Transactions!$G42<>""),"-> "&Transactions!$G42,"") -> -> PEC | AL2: =IF(AND(Transactions!$D43="Expense",Transactions!$G43<>""),"-> "&Transactions!$G43,"") -> -> May-July Fields | AM2: =IF(AND(Transactions!$D44="Expense",Transactions!$G44<>""),"-> "&Transactions!$G44,"") | AN2: =IF(AND(Transactions!$D45="Expense",Transactions!$G45<>""),"-> "&Transactions!$G45,"") | AO2: =IF(AND(Transactions!$D46="Expense",Transactions!$G46<>""),"-> "&Transactions!$G46,"") | AP2: =IF(AND(Transactions!$D47="Expense",Transactions!$G47<>""),"-> "&Transactions!$G47,"") | AQ2: =IF(AND(Transactions!$D48="Expense",Transactions!$G48<>""),"-> "&Transactions!$G48,"") | AR2: =IF(AND(Transactions!$D49="Expense",Transactions!$G49<>""),"-> "&Transactions!$G49,"") -> -> Sectionals | AS2: =IF(AND(Transactions!$D50="Expense",Transactions!$G50<>""),"-> "&Transactions!$G50,"") -> -> ESC | AT2: =IF(AND(#REF!="Expense",#REF!<>""),"-> "&#REF!,"") -> #REF! | AU2: =IF(AND(Transactions!$D51="Expense",Transactions!$G51<>""),"-> "&Transactions!$G51,"") | AV2: =IF(AND(Transactions!$D53="Expense",Transactions!$G53<>""),"-> "&Transactions!$G53,"") -> -> ESC | AW2: {=IF(AND(INDEX(Transactions!$D:$D, COLUMN()+5)="Expense", INDEX(Transactions!$G:$G, COLUMN()+5)<>""), "-> "&INDEX(Transactions!$G:$G, COLUMN()+5), "")} | AX2: {=IF(AND(INDEX(Transactions!$D:$D, COLUMN()+5)="Expense", INDEX(Transactions!$G:$G, COLUMN()+5)<>""), "-> "&INDEX(Transactions!$G:$G, COLUMN()+5), "")} | AY2: {=IF(AND(INDEX(Transactions!$D:$D, COLUMN()+5)="Expense", INDEX(Transactions!$G:$G, COLUMN()+5)<>""), "-> "&INDEX(Transactions!$G:$G, COLUMN()+5), "")} -> -> PEC | AZ2: {=IF(AND(INDEX(Transactions!$D:$D, COLUMN()+5)="Expense", INDEX(Transactions!$G:$G, COLUMN()+5)<>""), "-> "&INDEX(Transactions!$G:$G, COLUMN()+5), "")} -> -> PEC | BA2: {=IF(AND(INDEX(Transactions!$D:$D, COLUMN()+5)="Expense", INDEX(Transactions!$G:$G, COLUMN()+5)<>""), "-> "&INDEX(Transactions!$G:$G, COLUMN()+5), "")} -> -> PEC | BB2: {=IF(AND(INDEX(Transactions!$D:$D, COLUMN()+5)="Expense", INDEX(Transactions!$G:$G, COLUMN()+5)<>""), "-> "&INDEX(Transactions!$G:$G, COLUMN()+5), "")} -> -> PEC | BC2: {=IF(AND(INDEX(Transactions!$D:$D, COLUMN()+5)="Expense", INDEX(Transactions!$G:$G, COLUMN()+5)<>""), "-> "&INDEX(Transactions!$G:$G, COLUMN()+5), "")} -> -> PEC | BD2: {=IF(AND(INDEX(Transactions!$D:$D, COLUMN()+5)="Expense", INDEX(Transactions!$G:$G, COLUMN()+5)<>""), "-> "&INDEX(Transactions!$G:$G, COLUMN()+5), "")} -> -> SFI | ... EE2: {=IF(AND(INDEX(Transactions!$D:$D, COLUMN()+5)="Expense", INDEX(Transactions!$G:$G, COLUMN()+5)<>""), "-> "&INDEX(Transactions!$G:$G, COLUMN()+5), "")}
A3: Player Name | B3: =IF(AND(Transactions!$D7="Expense",Transactions!$G7<>""),Transactions!$B7,"") -> PEC Bid Fee | C3: =IF(AND(Transactions!$D8="Expense",Transactions!$G8<>""),Transactions!$B8,"") -> SFI Bid Fee | D3: =IF(AND(Transactions!$D9="Expense",Transactions!$G9<>""),Transactions!$B9,"") | E3: =IF(AND(Transactions!$D10="Expense",Transactions!$G10<>""),Transactions!$B10,"") | F3: =IF(AND(Transactions!$D11="Expense",Transactions!$G11<>""),Transactions!$B11,"") | G3: =IF(AND(Transactions!$D12="Expense",Transactions!$G12<>""),Transactions!$B12,"") -> Wednesday Tryout Field | H3: =IF(AND(Transactions!$D13="Expense",Transactions!$G13<>""),Transactions!$B13,"") -> tshirts and spray paint | I3: =IF(AND(Transactions!$D14="Expense",Transactions!$G14<>""),Transactions!$B14,"") -> gso airport minivan | J3: =IF(AND(Transactions!$D15="Expense",Transactions!$G15<>""),Transactions!$B15,"") | K3: =IF(AND(Transactions!$D16="Expense",Transactions!$G16<>""),Transactions!$B16,"") | L3: =IF(AND(Transactions!$D17="Expense",Transactions!$G17<>""),Transactions!$B17,"") -> pec megavan | M3: =IF(AND(Transactions!$D18="Expense",Transactions!$G18<>""),Transactions!$B18,"") -> PEC Hotel | N3: =IF(AND(Transactions!$D19="Expense",Transactions!$G19<>""),Transactions!$B19,"") | O3: =IF(AND(Transactions!$D20="Expense",Transactions!$G20<>""),Transactions!$B20,"") -> gso minivan gas | P3: =IF(AND(Transactions!$D21="Expense",Transactions!$G21<>""),Transactions!$B21,"") -> Jake's Car Airport Parking | Q3: =IF(AND(Transactions!$D22="Expense",Transactions!$G22<>""),Transactions!$B22,"") | R3: =IF(AND(Transactions!$D23="Expense",Transactions!$G23<>""),Transactions!$B23,"") | S3: =IF(AND(Transactions!$D24="Expense",Transactions!$G24<>""),Transactions!$B24,"") | T3: =IF(AND(Transactions!$D25="Expense",Transactions!$G25<>""),Transactions!$B25,"") | U3: =IF(AND(Transactions!$D26="Expense",Transactions!$G26<>""),Transactions!$B26,"") | V3: =IF(AND(Transactions!$D27="Expense",Transactions!$G27<>""),Transactions!$B27,"") | W3: =IF(AND(Transactions!$D28="Expense",Transactions!$G28<>""),Transactions!$B28,"") | X3: =IF(AND(Transactions!$D29="Expense",Transactions!$G29<>""),Transactions!$B29,"") | Y3: =IF(AND(Transactions!$D30="Expense",Transactions!$G30<>""),Transactions!$B30,"") | Z3: =IF(AND(Transactions!$D31="Expense",Transactions!$G31<>""),Transactions!$B31,"") | AA3: =IF(AND(Transactions!$D32="Expense",Transactions!$G32<>""),Transactions!$B32,"") | AB3: =IF(AND(Transactions!$D33="Expense",Transactions!$G33<>""),Transactions!$B33,"") -> PEC Team Snacks | AC3: =IF(AND(Transactions!$D34="Expense",Transactions!$G34<>""),Transactions!$B34,"") | AD3: =IF(AND(Transactions!$D35="Expense",Transactions!$G35<>""),Transactions!$B35,"") -> ESC Bid Fee | AE3: =IF(AND(Transactions!$D36="Expense",Transactions!$G36<>""),Transactions!$B36,"") | AF3: =IF(AND(Transactions!$D37="Expense",Transactions!$G37<>""),Transactions!$B37,"") | AG3: =IF(AND(Transactions!$D38="Expense",Transactions!$G38<>""),Transactions!$B38,"") | AH3: =IF(AND(Transactions!$D39="Expense",Transactions!$G39<>""),Transactions!$B39,"") | AI3: =IF(AND(Transactions!$D40="Expense",Transactions!$G40<>""),Transactions!$B40,"") -> SFI Team snacks | AJ3: =IF(AND(Transactions!$D41="Expense",Transactions!$G41<>""),Transactions!$B41,"") -> SFI Hotels | AK3: =IF(AND(Transactions!$D42="Expense",Transactions!$G42<>""),Transactions!$B42,"") -> Mega Van Tolls | AL3: =IF(AND(Transactions!$D43="Expense",Transactions!$G43<>""),Transactions!$B43,"") -> Practice Fields thru July | AM3: =IF(AND(Transactions!$D44="Expense",Transactions!$G44<>""),Transactions!$B44,"") | AN3: =IF(AND(Transactions!$D45="Expense",Transactions!$G45<>""),Transactions!$B45,"") | AO3: =IF(AND(Transactions!$D46="Expense",Transactions!$G46<>""),Transactions!$B46,"") | AP3: =IF(AND(Transactions!$D47="Expense",Transactions!$G47<>""),Transactions!$B47,"") | AQ3: =IF(AND(Transactions!$D48="Expense",Transactions!$G48<>""),Transactions!$B48,"") | AR3: =IF(AND(Transactions!$D49="Expense",Transactions!$G49<>""),Transactions!$B49,"") -> Sectionals Bid Fee | AS3: =IF(AND(Transactions!$D50="Expense",Transactions!$G50<>""),Transactions!$B50,"") -> ESC Hotel | AT3: =IF(AND(#REF!="Expense",#REF!<>""),#REF!,"") -> #REF! | AU3: =IF(AND(Transactions!$D51="Expense",Transactions!$G51<>""),Transactions!$B51,"") | AV3: =IF(AND(Transactions!$D53="Expense",Transactions!$G53<>""),Transactions!$B53,"") -> ESC Team Snacks | AW3: {=IF(AND(INDEX(Transactions!$D:$D, 5 + COLUMN())="Expense", INDEX(Transactions!$G:$G, 5 + COLUMN())<>""), INDEX(Transactions!$B:$B, 5 + COLUMN()), "")} | AX3: {=IF(AND(INDEX(Transactions!$D:$D, 5 + COLUMN())="Expense", INDEX(Transactions!$G:$G, 5 + COLUMN())<>""), INDEX(Transactions!$B:$B, 5 + COLUMN()), "")} | AY3: {=IF(AND(INDEX(Transactions!$D:$D, 5 + COLUMN())="Expense", INDEX(Transactions!$G:$G, 5 + COLUMN())<>""), INDEX(Transactions!$B:$B, 5 + COLUMN()), "")} -> Sarah KH Car Credit | AZ3: {=IF(AND(INDEX(Transactions!$D:$D, 5 + COLUMN())="Expense", INDEX(Transactions!$G:$G, 5 + COLUMN())<>""), INDEX(Transactions!$B:$B, 5 + COLUMN()), "")} -> Sarah KH Car Credit | BA3: {=IF(AND(INDEX(Transactions!$D:$D, 5 + COLUMN())="Expense", INDEX(Transactions!$G:$G, 5 + COLUMN())<>""), INDEX(Transactions!$B:$B, 5 + COLUMN()), "")} -> Sarah KH Car Credit | BB3: {=IF(AND(INDEX(Transactions!$D:$D, 5 + COLUMN())="Expense", INDEX(Transactions!$G:$G, 5 + COLUMN())<>""), INDEX(Transactions!$B:$B, 5 + COLUMN()), "")} -> Sarah KH Car Credit | BC3: {=IF(AND(INDEX(Transactions!$D:$D, 5 + COLUMN())="Expense", INDEX(Transactions!$G:$G, 5 + COLUMN())<>""), INDEX(Transactions!$B:$B, 5 + COLUMN()), "")} -> PEC Pooled Car Fees | BD3: {=IF(AND(INDEX(Transactions!$D:$D, 5 + COLUMN())="Expense", INDEX(Transactions!$G:$G, 5 + COLUMN())<>""), INDEX(Transactions!$B:$B, 5 + COLUMN()), "")} -> SFI Pooled Car Fees | ... EE3: {=IF(AND(INDEX(Transactions!$D:$D, 5 + COLUMN())="Expense", INDEX(Transactions!$G:$G, 5 + COLUMN())<>""), INDEX(Transactions!$B:$B, 5 + COLUMN()), "")}
A4: Cost per Person ($) [auto] | B4: {=IF(B3="","",IFERROR(IF(INDEX(Events!$I$5:$I$204,MATCH(Transactions!$G7,Events!$A$5:$A$204,0))="Equal Split",Transactions!$F7/MAX(1,COUNTIFS('Access Codes'!$C$6:$C$105,"Player",'Access Codes'!$D$6:$D$105,"Active")),IF(INDEX(Events!$I$5:$I$204,MATCH(Transactions!$G7,Events!$A$5:$A$204,0))="Attendance",Transactions!$F7/MAX(1,COUNTIF(B$7:B$206,"1")),0)),0))} -> 36.8 | C4: {=IF(C3="","",IFERROR(IF(INDEX(Events!$I$5:$I$204,MATCH(Transactions!$G8,Events!$A$5:$A$204,0))="Equal Split",Transactions!$F8/MAX(1,COUNTIFS('Access Codes'!$C$6:$C$105,"Player",'Access Codes'!$D$6:$D$105,"Active")),IF(INDEX(Events!$I$5:$I$204,MATCH(Transactions!$G8,Events!$A$5:$A$204,0))="Attendance",Transactions!$F8/MAX(1,COUNTIF(C$7:C$206,"1")),0)),0))} -> 50 | D4: {=IF(D3="","",IFERROR(IF(INDEX(Events!$I$5:$I$204,MATCH(Transactions!$G9,Events!$A$5:$A$204,0))="Equal Split",Transactions!$F9/MAX(1,COUNTIFS('Access Codes'!$C$6:$C$105,"Player",'Access Codes'!$D$6:$D$105,"Active")),IF(INDEX(Events!$I$5:$I$204,MATCH(Transactions!$G9,Events!$A$5:$A$204,0))="Attendance",Transactions!$F9/MAX(1,COUNTIF(D$7:D$206,"1")),0)),0))} | E4: {=IF(E3="","",IFERROR(IF(INDEX(Events!$I$5:$I$204,MATCH(Transactions!$G10,Events!$A$5:$A$204,0))="Equal Split",Transactions!$F10/MAX(1,COUNTIFS('Access Codes'!$C$6:$C$105,"Player",'Access Codes'!$D$6:$D$105,"Active")),IF(INDEX(Events!$I$5:$I$204,MATCH(Transactions!$G10,Events!$A$5:$A$204,0))="Attendance",Transactions!$F10/MAX(1,COUNTIF(E$7:E$206,"1")),0)),0))} | F4: {=IF(F3="","",IFERROR(IF(INDEX(Events!$I$5:$I$204,MATCH(Transactions!$G11,Events!$A$5:$A$204,0))="Equal Split",Transactions!$F11/MAX(1,COUNTIFS('Access Codes'!$C$6:$C$105,"Player",'Access Codes'!$D$6:$D$105,"Active")),IF(INDEX(Events!$I$5:$I$204,MATCH(Transactions!$G11,Events!$A$5:$A$204,0))="Attendance",Transactions!$F11/MAX(1,COUNTIF(F$7:F$206,"1")),0)),0))} | G4: {=IF(G3="","",IFERROR(IF(INDEX(Events!$I$5:$I$204,MATCH(Transactions!$G12,Events!$A$5:$A$204,0))="Equal Split",Transactions!$F12/MAX(1,COUNTIFS('Access Codes'!$C$6:$C$105,"Player",'Access Codes'!$D$6:$D$105,"Active")),IF(INDEX(Events!$I$5:$I$204,MATCH(Transactions!$G12,Events!$A$5:$A$204,0))="Attendance",Transactions!$F12/MAX(1,COUNTIF(G$7:G$206,"1")),0)),0))} -> 2.3 | H4: {=IF(H3="","",IFERROR(IF(INDEX(Events!$I$5:$I$204,MATCH(Transactions!$G13,Events!$A$5:$A$204,0))="Equal Split",Transactions!$F13/MAX(1,COUNTIFS('Access Codes'!$C$6:$C$105,"Player",'Access Codes'!$D$6:$D$105,"Active")),IF(INDEX(Events!$I$5:$I$204,MATCH(Transactions!$G13,Events!$A$5:$A$204,0))="Attendance",Transactions!$F13/MAX(1,COUNTIF(H$7:H$206,"1")),0)),0))} -> 7.1419231 | I4: {=IF(I3="","",IFERROR(IF(INDEX(Events!$I$5:$I$204,MATCH(Transactions!$G14,Events!$A$5:$A$204,0))="Equal Split",Transactions!$F14/MAX(1,COUNTIFS('Access Codes'!$C$6:$C$105,"Player",'Access Codes'!$D$6:$D$105,"Active")),IF(INDEX(Events!$I$5:$I$204,MATCH(Transactions!$G14,Events!$A$5:$A$204,0))="Attendance",Transactions!$F14/MAX(1,COUNTIF(I$7:I$206,"1")),0)),0))} -> 38.073333 | J4: {=IF(J3="","",IFERROR(IF(INDEX(Events!$I$5:$I$204,MATCH(Transactions!$G15,Events!$A$5:$A$204,0))="Equal Split",Transactions!$F15/MAX(1,COUNTIFS('Access Codes'!$C$6:$C$105,"Player",'Access Codes'!$D$6:$D$105,"Active")),IF(INDEX(Events!$I$5:$I$204,MATCH(Transactions!$G15,Events!$A$5:$A$204,0))="Attendance",Transactions!$F15/MAX(1,COUNTIF(J$7:J$206,"1")),0)),0))} | K4: {=IF(K3="","",IFERROR(IF(INDEX(Events!$I$5:$I$204,MATCH(Transactions!$G16,Events!$A$5:$A$204,0))="Equal Split",Transactions!$F16/MAX(1,COUNTIFS('Access Codes'!$C$6:$C$105,"Player",'Access Codes'!$D$6:$D$105,"Active")),IF(INDEX(Events!$I$5:$I$204,MATCH(Transactions!$G16,Events!$A$5:$A$204,0))="Attendance",Transactions!$F16/MAX(1,COUNTIF(K$7:K$206,"1")),0)),0))} | L4: {=IF(L3="","",IFERROR(IF(INDEX(Events!$I$5:$I$204,MATCH(Transactions!$G17,Events!$A$5:$A$204,0))="Equal Split",Transactions!$F17/MAX(1,COUNTIFS('Access Codes'!$C$6:$C$105,"Player",'Access Codes'!$D$6:$D$105,"Active")),IF(INDEX(Events!$I$5:$I$204,MATCH(Transactions!$G17,Events!$A$5:$A$204,0))="Attendance",Transactions!$F17/MAX(1,COUNTIF(L$7:L$206,"1")),0)),0))} -> 0 | M4: {=IF(M3="","",IFERROR(IF(INDEX(Events!$I$5:$I$204,MATCH(Transactions!$G18,Events!$A$5:$A$204,0))="Equal Split",Transactions!$F18/MAX(1,COUNTIFS('Access Codes'!$C$6:$C$105,"Player",'Access Codes'!$D$6:$D$105,"Active")),IF(INDEX(Events!$I$5:$I$204,MATCH(Transactions!$G18,Events!$A$5:$A$204,0))="Attendance",Transactions!$F18/MAX(1,COUNTIF(M$7:M$206,"1")),0)),0))} -> 129.17 | N4: {=IF(N3="","",IFERROR(IF(INDEX(Events!$I$5:$I$204,MATCH(Transactions!$G19,Events!$A$5:$A$204,0))="Equal Split",Transactions!$F19/MAX(1,COUNTIFS('Access Codes'!$C$6:$C$105,"Player",'Access Codes'!$D$6:$D$105,"Active")),IF(INDEX(Events!$I$5:$I$204,MATCH(Transactions!$G19,Events!$A$5:$A$204,0))="Attendance",Transactions!$F19/MAX(1,COUNTIF(N$7:N$206,"1")),0)),0))} | O4: {=IF(O3="","",IFERROR(IF(INDEX(Events!$I$5:$I$204,MATCH(Transactions!$G20,Events!$A$5:$A$204,0))="Equal Split",Transactions!$F20/MAX(1,COUNTIFS('Access Codes'!$C$6:$C$105,"Player",'Access Codes'!$D$6:$D$105,"Active")),IF(INDEX(Events!$I$5:$I$204,MATCH(Transactions!$G20,Events!$A$5:$A$204,0))="Attendance",Transactions!$F20/MAX(1,COUNTIF(O$7:O$206,"1")),0)),0))} -> 2.5433333 | P4: {=IF(P3="","",IFERROR(IF(INDEX(Events!$I$5:$I$204,MATCH(Transactions!$G21,Events!$A$5:$A$204,0))="Equal Split",Transactions!$F21/MAX(1,COUNTIFS('Access Codes'!$C$6:$C$105,"Player",'Access Codes'!$D$6:$D$105,"Active")),IF(INDEX(Events!$I$5:$I$204,MATCH(Transactions!$G21,Events!$A$5:$A$204,0))="Attendance",Transactions!$F21/MAX(1,COUNTIF(P$7:P$206,"1")),0)),0))} -> 20.91 | Q4: {=IF(Q3="","",IFERROR(IF(INDEX(Events!$I$5:$I$204,MATCH(Transactions!$G22,Events!$A$5:$A$204,0))="Equal Split",Transactions!$F22/MAX(1,COUNTIFS('Access Codes'!$C$6:$C$105,"Player",'Access Codes'!$D$6:$D$105,"Active")),IF(INDEX(Events!$I$5:$I$204,MATCH(Transactions!$G22,Events!$A$5:$A$204,0))="Attendance",Transactions!$F22/MAX(1,COUNTIF(Q$7:Q$206,"1")),0)),0))} | R4: {=IF(R3="","",IFERROR(IF(INDEX(Events!$I$5:$I$204,MATCH(Transactions!$G23,Events!$A$5:$A$204,0))="Equal Split",Transactions!$F23/MAX(1,COUNTIFS('Access Codes'!$C$6:$C$105,"Player",'Access Codes'!$D$6:$D$105,"Active")),IF(INDEX(Events!$I$5:$I$204,MATCH(Transactions!$G23,Events!$A$5:$A$204,0))="Attendance",Transactions!$F23/MAX(1,COUNTIF(R$7:R$206,"1")),0)),0))} | S4: {=IF(S3="","",IFERROR(IF(INDEX(Events!$I$5:$I$204,MATCH(Transactions!$G24,Events!$A$5:$A$204,0))="Equal Split",Transactions!$F24/MAX(1,COUNTIFS('Access Codes'!$C$6:$C$105,"Player",'Access Codes'!$D$6:$D$105,"Active")),IF(INDEX(Events!$I$5:$I$204,MATCH(Transactions!$G24,Events!$A$5:$A$204,0))="Attendance",Transactions!$F24/MAX(1,COUNTIF(S$7:S$206,"1")),0)),0))} | T4: {=IF(T3="","",IFERROR(IF(INDEX(Events!$I$5:$I$204,MATCH(Transactions!$G25,Events!$A$5:$A$204,0))="Equal Split",Transactions!$F25/MAX(1,COUNTIFS('Access Codes'!$C$6:$C$105,"Player",'Access Codes'!$D$6:$D$105,"Active")),IF(INDEX(Events!$I$5:$I$204,MATCH(Transactions!$G25,Events!$A$5:$A$204,0))="Attendance",Transactions!$F25/MAX(1,COUNTIF(T$7:T$206,"1")),0)),0))} | U4: {=IF(U3="","",IFERROR(IF(INDEX(Events!$I$5:$I$204,MATCH(Transactions!$G26,Events!$A$5:$A$204,0))="Equal Split",Transactions!$F26/MAX(1,COUNTIFS('Access Codes'!$C$6:$C$105,"Player",'Access Codes'!$D$6:$D$105,"Active")),IF(INDEX(Events!$I$5:$I$204,MATCH(Transactions!$G26,Events!$A$5:$A$204,0))="Attendance",Transactions!$F26/MAX(1,COUNTIF(U$7:U$206,"1")),0)),0))} | V4: {=IF(V3="","",IFERROR(IF(INDEX(Events!$I$5:$I$204,MATCH(Transactions!$G27,Events!$A$5:$A$204,0))="Equal Split",Transactions!$F27/MAX(1,COUNTIFS('Access Codes'!$C$6:$C$105,"Player",'Access Codes'!$D$6:$D$105,"Active")),IF(INDEX(Events!$I$5:$I$204,MATCH(Transactions!$G27,Events!$A$5:$A$204,0))="Attendance",Transactions!$F27/MAX(1,COUNTIF(V$7:V$206,"1")),0)),0))} | W4: {=IF(W3="","",IFERROR(IF(INDEX(Events!$I$5:$I$204,MATCH(Transactions!$G28,Events!$A$5:$A$204,0))="Equal Split",Transactions!$F28/MAX(1,COUNTIFS('Access Codes'!$C$6:$C$105,"Player",'Access Codes'!$D$6:$D$105,"Active")),IF(INDEX(Events!$I$5:$I$204,MATCH(Transactions!$G28,Events!$A$5:$A$204,0))="Attendance",Transactions!$F28/MAX(1,COUNTIF(W$7:W$206,"1")),0)),0))} | X4: {=IF(X3="","",IFERROR(IF(INDEX(Events!$I$5:$I$204,MATCH(Transactions!$G29,Events!$A$5:$A$204,0))="Equal Split",Transactions!$F29/MAX(1,COUNTIFS('Access Codes'!$C$6:$C$105,"Player",'Access Codes'!$D$6:$D$105,"Active")),IF(INDEX(Events!$I$5:$I$204,MATCH(Transactions!$G29,Events!$A$5:$A$204,0))="Attendance",Transactions!$F29/MAX(1,COUNTIF(X$7:X$206,"1")),0)),0))} | Y4: {=IF(Y3="","",IFERROR(IF(INDEX(Events!$I$5:$I$204,MATCH(Transactions!$G30,Events!$A$5:$A$204,0))="Equal Split",Transactions!$F30/MAX(1,COUNTIFS('Access Codes'!$C$6:$C$105,"Player",'Access Codes'!$D$6:$D$105,"Active")),IF(INDEX(Events!$I$5:$I$204,MATCH(Transactions!$G30,Events!$A$5:$A$204,0))="Attendance",Transactions!$F30/MAX(1,COUNTIF(Y$7:Y$206,"1")),0)),0))} | Z4: {=IF(Z3="","",IFERROR(IF(INDEX(Events!$I$5:$I$204,MATCH(Transactions!$G31,Events!$A$5:$A$204,0))="Equal Split",Transactions!$F31/MAX(1,COUNTIFS('Access Codes'!$C$6:$C$105,"Player",'Access Codes'!$D$6:$D$105,"Active")),IF(INDEX(Events!$I$5:$I$204,MATCH(Transactions!$G31,Events!$A$5:$A$204,0))="Attendance",Transactions!$F31/MAX(1,COUNTIF(Z$7:Z$206,"1")),0)),0))} | AA4: {=IF(AA3="","",IFERROR(IF(INDEX(Events!$I$5:$I$204,MATCH(Transactions!$G32,Events!$A$5:$A$204,0))="Equal Split",Transactions!$F32/MAX(1,COUNTIFS('Access Codes'!$C$6:$C$105,"Player",'Access Codes'!$D$6:$D$105,"Active")),IF(INDEX(Events!$I$5:$I$204,MATCH(Transactions!$G32,Events!$A$5:$A$204,0))="Attendance",Transactions!$F32/MAX(1,COUNTIF(AA$7:AA$206,"1")),0)),0))} | AB4: {=IF(AB3="","",IFERROR(IF(INDEX(Events!$I$5:$I$204,MATCH(Transactions!$G33,Events!$A$5:$A$204,0))="Equal Split",Transactions!$F33/MAX(1,COUNTIFS('Access Codes'!$C$6:$C$105,"Player",'Access Codes'!$D$6:$D$105,"Active")),IF(INDEX(Events!$I$5:$I$204,MATCH(Transactions!$G33,Events!$A$5:$A$204,0))="Attendance",Transactions!$F33/MAX(1,COUNTIF(AB$7:AB$206,"1")),0)),0))} -> 7.2442857 | AC4: {=IF(AC3="","",IFERROR(IF(INDEX(Events!$I$5:$I$204,MATCH(Transactions!$G34,Events!$A$5:$A$204,0))="Equal Split",Transactions!$F34/MAX(1,COUNTIFS('Access Codes'!$C$6:$C$105,"Player",'Access Codes'!$D$6:$D$105,"Active")),IF(INDEX(Events!$I$5:$I$204,MATCH(Transactions!$G34,Events!$A$5:$A$204,0))="Attendance",Transactions!$F34/MAX(1,COUNTIF(AC$7:AC$206,"1")),0)),0))} | AD4: {=IF(AD3="","",IFERROR(IF(INDEX(Events!$I$5:$I$204,MATCH(Transactions!$G35,Events!$A$5:$A$204,0))="Equal Split",Transactions!$F35/MAX(1,COUNTIFS('Access Codes'!$C$6:$C$105,"Player",'Access Codes'!$D$6:$D$105,"Active")),IF(INDEX(Events!$I$5:$I$204,MATCH(Transactions!$G35,Events!$A$5:$A$204,0))="Attendance",Transactions!$F35/MAX(1,COUNTIF(AD$7:AD$206,"1")),0)),0))} -> 41.666667 | AE4: {=IF(AE3="","",IFERROR(IF(INDEX(Events!$I$5:$I$204,MATCH(Transactions!$G36,Events!$A$5:$A$204,0))="Equal Split",Transactions!$F36/MAX(1,COUNTIFS('Access Codes'!$C$6:$C$105,"Player",'Access Codes'!$D$6:$D$105,"Active")),IF(INDEX(Events!$I$5:$I$204,MATCH(Transactions!$G36,Events!$A$5:$A$204,0))="Attendance",Transactions!$F36/MAX(1,COUNTIF(AE$7:AE$206,"1")),0)),0))} | AF4: {=IF(AF3="","",IFERROR(IF(INDEX(Events!$I$5:$I$204,MATCH(Transactions!$G37,Events!$A$5:$A$204,0))="Equal Split",Transactions!$F37/MAX(1,COUNTIFS('Access Codes'!$C$6:$C$105,"Player",'Access Codes'!$D$6:$D$105,"Active")),IF(INDEX(Events!$I$5:$I$204,MATCH(Transactions!$G37,Events!$A$5:$A$204,0))="Attendance",Transactions!$F37/MAX(1,COUNTIF(AF$7:AF$206,"1")),0)),0))} | AG4: {=IF(AG3="","",IFERROR(IF(INDEX(Events!$I$5:$I$204,MATCH(Transactions!$G38,Events!$A$5:$A$204,0))="Equal Split",Transactions!$F38/MAX(1,COUNTIFS('Access Codes'!$C$6:$C$105,"Player",'Access Codes'!$D$6:$D$105,"Active")),IF(INDEX(Events!$I$5:$I$204,MATCH(Transactions!$G38,Events!$A$5:$A$204,0))="Attendance",Transactions!$F38/MAX(1,COUNTIF(AG$7:AG$206,"1")),0)),0))} | AH4: {=IF(AH3="","",IFERROR(IF(INDEX(Events!$I$5:$I$204,MATCH(Transactions!$G39,Events!$A$5:$A$204,0))="Equal Split",Transactions!$F39/MAX(1,COUNTIFS('Access Codes'!$C$6:$C$105,"Player",'Access Codes'!$D$6:$D$105,"Active")),IF(INDEX(Events!$I$5:$I$204,MATCH(Transactions!$G39,Events!$A$5:$A$204,0))="Attendance",Transactions!$F39/MAX(1,COUNTIF(AH$7:AH$206,"1")),0)),0))} | AI4: {=IF(AI3="","",IFERROR(IF(INDEX(Events!$I$5:$I$204,MATCH(Transactions!$G40,Events!$A$5:$A$204,0))="Equal Split",Transactions!$F40/MAX(1,COUNTIFS('Access Codes'!$C$6:$C$105,"Player",'Access Codes'!$D$6:$D$105,"Active")),IF(INDEX(Events!$I$5:$I$204,MATCH(Transactions!$G40,Events!$A$5:$A$204,0))="Attendance",Transactions!$F40/MAX(1,COUNTIF(AI$7:AI$206,"1")),0)),0))} -> 12.64125 | AJ4: {=IF(AJ3="","",IFERROR(IF(INDEX(Events!$I$5:$I$204,MATCH(Transactions!$G41,Events!$A$5:$A$204,0))="Equal Split",Transactions!$F41/MAX(1,COUNTIFS('Access Codes'!$C$6:$C$105,"Player",'Access Codes'!$D$6:$D$105,"Active")),IF(INDEX(Events!$I$5:$I$204,MATCH(Transactions!$G41,Events!$A$5:$A$204,0))="Attendance",Transactions!$F41/MAX(1,COUNTIF(AJ$7:AJ$206,"1")),0)),0))} -> 99.55 | AK4: {=IF(AK3="","",IFERROR(IF(INDEX(Events!$I$5:$I$204,MATCH(Transactions!$G42,Events!$A$5:$A$204,0))="Equal Split",Transactions!$F42/MAX(1,COUNTIFS('Access Codes'!$C$6:$C$105,"Player",'Access Codes'!$D$6:$D$105,"Active")),IF(INDEX(Events!$I$5:$I$204,MATCH(Transactions!$G42,Events!$A$5:$A$204,0))="Attendance",Transactions!$F42/MAX(1,COUNTIF(AK$7:AK$206,"1")),0)),0))} -> 2.4927273 | AL4: {=IF(AL3="","",IFERROR(IF(INDEX(Events!$I$5:$I$204,MATCH(INDEX(Transactions!$G:$G, COLUMN()+5),Events!$A$5:$A$204,0))="Equal Split",INDEX(Transactions!$F:$F, COLUMN()+5)/MAX(1,COUNTIFS('Access Codes'!$C$6:$C$105,"Player",'Access Codes'!$D$6:$D$105,"Active")),IF(INDEX(Events!$I$5:$I$204,MATCH(INDEX(Transactions!$G:$G, COLUMN()+5),Events!$A$5:$A$204,0))="Attendance",INDEX(Transactions!$F:$F, COLUMN()+5)/MAX(1,COUNTIF(INDIRECT(SUBSTITUTE(ADDRESS(1, COLUMN(), 4), "1", "") & "7:" & SUBSTITUTE(ADDRESS(1, COLUMN(), 4), "1", "") & "206"),"1")),0)),0))} -> 75.233333 | AM4: {=IF(AM3="","",IFERROR(IF(INDEX(Events!$I$5:$I$204,MATCH(INDEX(Transactions!$G:$G, COLUMN()+5),Events!$A$5:$A$204,0))="Equal Split",INDEX(Transactions!$F:$F, COLUMN()+5)/MAX(1,COUNTIFS('Access Codes'!$C$6:$C$105,"Player",'Access Codes'!$D$6:$D$105,"Active")),IF(INDEX(Events!$I$5:$I$204,MATCH(INDEX(Transactions!$G:$G, COLUMN()+5),Events!$A$5:$A$204,0))="Attendance",INDEX(Transactions!$F:$F, COLUMN()+5)/MAX(1,COUNTIF(INDIRECT(SUBSTITUTE(ADDRESS(1, COLUMN(), 4), "1", "") & "7:" & SUBSTITUTE(ADDRESS(1, COLUMN(), 4), "1", "") & "206"),"1")),0)),0))} | AN4: {=IF(AN3="","",IFERROR(IF(INDEX(Events!$I$5:$I$204,MATCH(INDEX(Transactions!$G:$G, COLUMN()+5),Events!$A$5:$A$204,0))="Equal Split",INDEX(Transactions!$F:$F, COLUMN()+5)/MAX(1,COUNTIFS('Access Codes'!$C$6:$C$105,"Player",'Access Codes'!$D$6:$D$105,"Active")),IF(INDEX(Events!$I$5:$I$204,MATCH(INDEX(Transactions!$G:$G, COLUMN()+5),Events!$A$5:$A$204,0))="Attendance",INDEX(Transactions!$F:$F, COLUMN()+5)/MAX(1,COUNTIF(INDIRECT(SUBSTITUTE(ADDRESS(1, COLUMN(), 4), "1", "") & "7:" & SUBSTITUTE(ADDRESS(1, COLUMN(), 4), "1", "") & "206"),"1")),0)),0))} | AO4: {=IF(AO3="","",IFERROR(IF(INDEX(Events!$I$5:$I$204,MATCH(INDEX(Transactions!$G:$G, COLUMN()+5),Events!$A$5:$A$204,0))="Equal Split",INDEX(Transactions!$F:$F, COLUMN()+5)/MAX(1,COUNTIFS('Access Codes'!$C$6:$C$105,"Player",'Access Codes'!$D$6:$D$105,"Active")),IF(INDEX(Events!$I$5:$I$204,MATCH(INDEX(Transactions!$G:$G, COLUMN()+5),Events!$A$5:$A$204,0))="Attendance",INDEX(Transactions!$F:$F, COLUMN()+5)/MAX(1,COUNTIF(INDIRECT(SUBSTITUTE(ADDRESS(1, COLUMN(), 4), "1", "") & "7:" & SUBSTITUTE(ADDRESS(1, COLUMN(), 4), "1", "") & "206"),"1")),0)),0))} | AP4: {=IF(AP3="","",IFERROR(IF(INDEX(Events!$I$5:$I$204,MATCH(INDEX(Transactions!$G:$G, COLUMN()+5),Events!$A$5:$A$204,0))="Equal Split",INDEX(Transactions!$F:$F, COLUMN()+5)/MAX(1,COUNTIFS('Access Codes'!$C$6:$C$105,"Player",'Access Codes'!$D$6:$D$105,"Active")),IF(INDEX(Events!$I$5:$I$204,MATCH(INDEX(Transactions!$G:$G, COLUMN()+5),Events!$A$5:$A$204,0))="Attendance",INDEX(Transactions!$F:$F, COLUMN()+5)/MAX(1,COUNTIF(INDIRECT(SUBSTITUTE(ADDRESS(1, COLUMN(), 4), "1", "") & "7:" & SUBSTITUTE(ADDRESS(1, COLUMN(), 4), "1", "") & "206"),"1")),0)),0))} | AQ4: {=IF(AQ3="","",IFERROR(IF(INDEX(Events!$I$5:$I$204,MATCH(INDEX(Transactions!$G:$G, COLUMN()+5),Events!$A$5:$A$204,0))="Equal Split",INDEX(Transactions!$F:$F, COLUMN()+5)/MAX(1,COUNTIFS('Access Codes'!$C$6:$C$105,"Player",'Access Codes'!$D$6:$D$105,"Active")),IF(INDEX(Events!$I$5:$I$204,MATCH(INDEX(Transactions!$G:$G, COLUMN()+5),Events!$A$5:$A$204,0))="Attendance",INDEX(Transactions!$F:$F, COLUMN()+5)/MAX(1,COUNTIF(INDIRECT(SUBSTITUTE(ADDRESS(1, COLUMN(), 4), "1", "") & "7:" & SUBSTITUTE(ADDRESS(1, COLUMN(), 4), "1", "") & "206"),"1")),0)),0))} | AR4: {=IF(AR3="","",IFERROR(IF(INDEX(Events!$I$5:$I$204,MATCH(INDEX(Transactions!$G:$G, COLUMN()+5),Events!$A$5:$A$204,0))="Equal Split",INDEX(Transactions!$F:$F, COLUMN()+5)/MAX(1,COUNTIFS('Access Codes'!$C$6:$C$105,"Player",'Access Codes'!$D$6:$D$105,"Active")),IF(INDEX(Events!$I$5:$I$204,MATCH(INDEX(Transactions!$G:$G, COLUMN()+5),Events!$A$5:$A$204,0))="Attendance",INDEX(Transactions!$F:$F, COLUMN()+5)/MAX(1,COUNTIF(INDIRECT(SUBSTITUTE(ADDRESS(1, COLUMN(), 4), "1", "") & "7:" & SUBSTITUTE(ADDRESS(1, COLUMN(), 4), "1", "") & "206"),"1")),0)),0))} -> 22 | AS4: {=IF(AS3="","",IFERROR(IF(INDEX(Events!$I$5:$I$204,MATCH(INDEX(Transactions!$G:$G, COLUMN()+5),Events!$A$5:$A$204,0))="Equal Split",INDEX(Transactions!$F:$F, COLUMN()+5)/MAX(1,COUNTIFS('Access Codes'!$C$6:$C$105,"Player",'Access Codes'!$D$6:$D$105,"Active")),IF(INDEX(Events!$I$5:$I$204,MATCH(INDEX(Transactions!$G:$G, COLUMN()+5),Events!$A$5:$A$204,0))="Attendance",INDEX(Transactions!$F:$F, COLUMN()+5)/MAX(1,COUNTIF(INDIRECT(SUBSTITUTE(ADDRESS(1, COLUMN(), 4), "1", "") & "7:" & SUBSTITUTE(ADDRESS(1, COLUMN(), 4), "1", "") & "206"),"1")),0)),0))} -> 121.0848 | ... EE4: {=IF(EE3="","",IFERROR(IF(INDEX(Events!$I$5:$I$204,MATCH(INDEX(Transactions!$G:$G, COLUMN()+5),Events!$A$5:$A$204,0))="Equal Split",INDEX(Transactions!$F:$F, COLUMN()+5)/MAX(1,COUNTIFS('Access Codes'!$C$6:$C$105,"Player",'Access Codes'!$D$6:$D$105,"Active")),IF(INDEX(Events!$I$5:$I$204,MATCH(INDEX(Transactions!$G:$G, COLUMN()+5),Events!$A$5:$A$204,0))="Attendance",INDEX(Transactions!$F:$F, COLUMN()+5)/MAX(1,COUNTIF(INDIRECT(SUBSTITUTE(ADDRESS(1, COLUMN(), 4), "1", "") & "7:" & SUBSTITUTE(ADDRESS(1, COLUMN(), 4), "1", "") & "206"),"1")),0)),0))}
A5: Total Attendees | B5: =COUNTIF(B7:B206,"1") -> 25 | C5: =COUNTIF(C7:C206,"1") -> 23 | D5: =COUNTIF(D7:D206,"1") -> 0 | E5: =COUNTIF(E7:E206,"1") -> 0 | F5: =COUNTIF(F7:F206,"1") -> 0 | G5: =COUNTIF(G7:G206,"1") -> 30 | H5: =COUNTIF(H7:H206,"1") -> 26 | I5: =COUNTIF(I7:I206,"1") -> 6 | ... EE5: =COUNTIF(EE7:EE206,"1") -> 0
A6: Total Cost ($) | B6: =B4*B5 -> 920 | C6: =C4*C5 -> 1150 | D6: =D4*D5 -> 0 | E6: =E4*E5 -> 0 | F6: =F4*F5 -> 0 | G6: =G4*G5 -> 69 | H6: =H4*H5 -> 185.69 | I6: =I4*I5 -> 228.44 | ... EE6: =EE4*EE5 -> 0
A7: =IF(Roster!$A$5<>"",Roster!$A$5,"") -> At | B7: 1 | C7: 1 | G7: 1 | H7: 1 | I7: 1 | J7: 1 | L7: 0 | M7: 1 | O7: 1 | P7: 1 | AB7: 1 | AD7: 1 | AI7: 1 | AJ7: 1 | AK7: 0 | AL7: 1 | AR7: 1 | AS7: 1 | AV7: 1 | BC7: 0 | BD7: 1 | BE7: 1 | BW7: 1 | BX7: 0 | BY7: 0 | BZ7: 0 | CA7: 0 | CI7: 1 | CJ7: 1 | CK7: 1 | CL7: 0 | CQ7: 1 | CY7: 1
A8: =IF(Roster!$A$6<>"",Roster!$A$6,"") -> Alex Warrington | B8: 1 | C8: 1 | G8: 1 | H8: 1 | I8: 0 | J8: 1 | L8: 0 | M8: 1 | O8: 0 | P8: 0 | AB8: 0 | AD8: 1 | AI8: 0 | AJ8: 1 | AK8: 0 | AL8: 1 | AR8: 1 | AS8: 1 | AV8: 0 | BC8: 1 | BD8: 1 | BE8: 1 | BW8: 1 | BX8: 0 | BY8: 0 | BZ8: 0 | CA8: 0 | CI8: 1 | CJ8: 0 | CK8: 1 | CL8: 0 | CQ8: 1 | CY8: 1
A9: =IF(Roster!$A$7<>"",Roster!$A$7,"") -> Chris Wohl | B9: 1 | C9: 1 | G9: 1 | H9: 1 | I9: 0 | J9: 1 | L9: 1 | M9: 1 | O9: 0 | P9: 0 | AB9: 1 | AD9: 1 | AI9: 1 | AJ9: 1 | AK9: 1 | AL9: 1 | AR9: 1 | AS9: 1 | AV9: 1 | BC9: 0 | BD9: 1 | BE9: 1 | BW9: 1 | BX9: 0 | BY9: 0 | BZ9: 0 | CA9: 0 | CI9: 1 | CJ9: 1 | CK9: 1 | CL9: 1 | CQ9: 1 | CY9: 1
A10: =IF(Roster!$A$8<>"",Roster!$A$8,"") -> Darra Reppermund | B10: 1 | C10: 1 | G10: 1 | H10: 1 | I10: 0 | J10: 1 | L10: 0 | M10: 1 | O10: 0 | P10: 0 | AB10: 1 | AD10: 1 | AI10: 1 | AJ10: 0 | AK10: 0 | AL10: 1 | AR10: 1 | AS10: 1 | AV10: 1 | BC10: 1 | BD10: 0 | BE10: 1 | BW10: 1 | BX10: 0 | BY10: 0 | BZ10: 0 | CA10: 0 | CI10: 1 | CJ10: 1 | CK10: 1 | CL10: 0 | CQ10: 1 | CY10: 1
A11: =IF(Roster!$A$9<>"",Roster!$A$9,"") -> Dylan Best | B11: 1 | C11: 1 | G11: 1 | H11: 1 | I11: 1 | J11: 1 | L11: 0 | M11: 1 | O11: 1 | P11: 1 | AB11: 1 | AD11: 1 | AI11: 1 | AJ11: 1 | AK11: 0 | AL11: 1 | AR11: 1 | AS11: 1 | AV11: 1 | BC11: 0 | BD11: 1 | BE11: X | BW11: 1 | BX11: 0 | BY11: 0 | BZ11: 0 | CA11: 0 | CI11: 1 | CJ11: 1 | CK11: 1 | CL11: 0 | CQ11: 1 | CY11: 1
A12: =IF(Roster!$A$10<>"",Roster!$A$10,"") -> Griffin O'Neal-Freeman | B12: 1 | C12: 1 | G12: 1 | H12: 1 | I12: 0 | J12: 1 | L12: 1 | M12: 1 | O12: 0 | P12: 0 | AB12: 1 | AD12: 1 | AI12: 1 | AJ12: 1 | AK12: 1 | AL12: 1 | AR12: 1 | AS12: 1 | AV12: 1 | BC12: 0 | BD12: X | BE12: 1 | BW12: 0 | BX12: 1 | BY12: 0 | BZ12: 0 | CA12: 0 | CI12: 1 | CJ12: 1 | CK12: 1 | CL12: 1 | CQ12: 1 | CY12: 1
A13: =IF(Roster!$A$11<>"",Roster!$A$11,"") -> Haley Young | B13: 1 | C13: 1 | G13: 1 | H13: 1 | I13: 0 | J13: 1 | L13: 0 | M13: 1 | O13: 0 | P13: 0 | AB13: 0 | AD13: 1 | AI13: 0 | AJ13: 1 | AK13: 0 | AL13: 1 | AR13: 1 | AS13: 1 | AV13: 1 | BC13: 1 | BD13: X | BE13: 1 | BW13: 0 | BX13: 1 | BY13: 0 | BZ13: 0 | CA13: 0 | CI13: 1 | CJ13: 0 | CK13: 1 | CL13: 0 | CQ13: 1 | CY13: 1
A14: =IF(Roster!$A$12<>"",Roster!$A$12,"") -> Harry Park | B14: 1 | C14: 1 | G14: 1 | H14: 1 | I14: 0 | J14: 1 | L14: 1 | M14: 1 | O14: 0 | P14: 0 | AB14: 1 | AD14: 1 | AI14: 1 | AJ14: 1 | AK14: 1 | AL14: 1 | AR14: 1 | AS14: 1 | AV14: 1 | BC14: 0 | BD14: 1 | BE14: X | BW14: 0 | BX14: 0 | BY14: 0 | BZ14: 0 | CA14: 0 | CI14: 1 | CJ14: 1 | CK14: 1 | CL14: 1 | CQ14: 1 | CY14: 1
A15: =IF(Roster!$A$13<>"",Roster!$A$13,"") -> Ian Piper | B15: X | C15: 1 | G15: 1 | H15: 1 | I15: 0 | J15: 1 | L15: 1 | M15: 1 | O15: 0 | P15: 0 | AB15: 1 | AD15: 1 | AI15: 1 | AJ15: 1 | AK15: 1 | AL15: 1 | AR15: 1 | AS15: 1 | AV15: 1 | BC15: 0 | BD15: 1 | BE15: 1 | BW15: 0 | BX15: 1 | BY15: 0 | BZ15: 0 | CA15: 0 | CI15: 1 | CJ15: 1 | CK15: 1 | CL15: 1 | CQ15: 1 | CY15: 1
A16: =IF(Roster!$A$14<>"",Roster!$A$14,"") -> Jake Murray | B16: 1 | C16: 1 | G16: 1 | H16: 1 | I16: 1 | J16: 1 | L16: 0 | M16: 1 | O16: 1 | P16: 1 | AB16: 1 | AD16: 1 | AI16: 1 | AJ16: 1 | AK16: 0 | AL16: 1 | AR16: 1 | AS16: 1 | AV16: 1 | BC16: 0 | BD16: X | BE16: 1 | BW16: 1 | BX16: 0 | BY16: 0 | BZ16: 0 | CA16: 0 | CI16: 1 | CJ16: 1 | CK16: 1 | CL16: 1 | CQ16: 1 | CY16: 1
A17: =IF(Roster!$A$15<>"",Roster!$A$15,"") -> Jenna Nold | B17: 1 | C17: 1 | G17: 1 | H17: 1 | I17: 0 | J17: 1 | L17: 1 | M17: 1 | O17: 0 | P17: 0 | AB17: 1 | AD17: 1 | AI17: 1 | AJ17: 1 | AK17: 1 | AL17: 1 | AR17: 1 | AS17: 1 | AV17: 1 | BC17: 0 | BD17: 1 | BE17: 1 | BW17: 0 | BX17: 0 | BY17: 0 | BZ17: 0 | CA17: 0 | CI17: 1 | CJ17: 1 | CK17: 1 | CL17: 1 | CQ17: 1 | CY17: 1
A18: =IF(Roster!$A$16<>"",Roster!$A$16,"") -> Jimmy Towle | B18: 0 | C18: 0 | G18: 1 | H18: 0 | I18: 0 | J18: 1 | L18: 0 | M18: 0 | O18: 0 | P18: 0 | AB18: 0 | AD18: 1 | AI18: 0 | AJ18: 0 | AK18: 0 | AL18: 1 | AR18: 1 | AS18: 1 | AV18: 1 | BC18: 0 | BD18: 0 | BE18: 1 | BW18: 1 | BX18: 0 | BY18: 0 | BZ18: 0 | CA18: 0 | CI18: 1 | CJ18: 1 | CK18: 1 | CL18: 0 | CQ18: 1 | CY18: 1
A19: =IF(Roster!$A$17<>"",Roster!$A$17,"") -> Kailey Rugani | B19: 1 | C19: 1 | G19: 1 | H19: 1 | I19: 0 | J19: 1 | L19: 1 | M19: 1 | O19: 0 | P19: 0 | AB19: 1 | AD19: 1 | AI19: 1 | AJ19: 1 | AK19: 1 | AL19: 1 | AR19: 1 | AS19: 1 | AV19: 1 | BC19: 0 | BD19: 1 | BE19: 1 | BW19: 0 | BX19: 0 | BY19: 0 | BZ19: 1 | CA19: 0 | CI19: 1 | CJ19: 1 | CK19: 1 | CL19: 0 | CQ19: 1 | CY19: 1
A20: =IF(Roster!$A$18<>"",Roster!$A$18,"") -> Kasey Schock | B20: 1 | C20: 1 | G20: 1 | H20: 1 | I20: 0 | J20: 1 | L20: 1 | M20: 1 | O20: 0 | P20: 0 | AB20: 1 | AD20: 1 | AI20: 0 | AJ20: 1 | AK20: 1 | AL20: 1 | AR20: 1 | AS20: 1 | AV20: 1 | BC20: 0 | BD20: X | BE20: 1 | BW20: 0 | BX20: 0 | BY20: 0 | BZ20: 0 | CA20: 0 | CI20: 1 | CJ20: 1 | CK20: 1 | CL20: 0 | CQ20: 1 | CY20: 1
A21: =IF(Roster!$A$19<>"",Roster!$A$19,"") -> Kevin Nicholl | B21: 1 | C21: 1 | G21: 1 | H21: 1 | I21: 0 | J21: 1 | L21: 0 | M21: 1 | O21: 0 | P21: 0 | AB21: 1 | AD21: 1 | AI21: 1 | AJ21: 1 | AK21: 0 | AL21: 1 | AR21: 1 | AS21: 1 | AV21: 1 | BC21: X | BD21: X | BE21: 1 | BW21: 0 | BX21: 0 | BY21: 0 | BZ21: 0 | CA21: 0 | CI21: 1 | CJ21: 1 | CK21: 1 | CL21: 0 | CQ21: 1 | CY21: 1
A22: =IF(Roster!$A$20<>"",Roster!$A$20,"") -> Kit Asterin | B22: 1 | C22: 1 | G22: 1 | H22: 1 | I22: 0 | J22: 1 | L22: 1 | M22: 1 | O22: 0 | P22: 0 | AB22: 0 | AD22: 1 | AI22: 0 | AJ22: 1 | AK22: 1 | AL22: 1 | AR22: 1 | AS22: 1 | AV22: 0 | BC22: 0 | BD22: 1 | BE22: 1 | BW22: 1 | BX22: 0 | BY22: 0 | BZ22: 0 | CA22: 0 | CI22: 1 | CJ22: 0 | CK22: 1 | CL22: 1 | CQ22: 1 | CY22: 1
A23: =IF(Roster!$A$21<>"",Roster!$A$21,"") -> Kristin Dudley | B23: 1 | C23: 1 | G23: 1 | H23: 1 | I23: 1 | J23: 1 | L23: 0 | M23: 1 | O23: 1 | P23: 0 | AB23: 0 | AD23: 1 | AI23: 0 | AJ23: 1 | AK23: 0 | AL23: 1 | AR23: 1 | AS23: 1 | AV23: 0 | BC23: 0 | BD23: 1 | BE23: 0 | BW23: 1 | BX23: 0 | BY23: 0 | BZ23: 0 | CA23: 0 | CI23: 1 | CJ23: 0 | CK23: 1 | CL23: 0 | CQ23: 1 | CY23: 1
A24: =IF(Roster!$A$22<>"",Roster!$A$22,"") -> Lexie Thomas | B24: 1 | C24: 1 | G24: 1 | H24: 1 | I24: 0 | J24: 1 | L24: 0 | M24: 1 | O24: 0 | P24: 0 | AB24: 1 | AD24: 1 | AI24: 0 | AJ24: 1 | AK24: 0 | AL24: 1 | AR24: 1 | AS24: 1 | AV24: 0 | BC24: 1 | BD24: 1 | BE24: 1 | BW24: 1 | BX24: 0 | BY24: 0 | BZ24: 0 | CA24: 0 | CI24: 1 | CJ24: 0 | CK24: 1 | CL24: 0 | CQ24: 1 | CY24: 1
A25: =IF(Roster!$A$23<>"",Roster!$A$23,"") -> Lucas Jones | B25: 0 | C25: 0 | G25: 1 | H25: 0 | I25: 0 | J25: 1 | L25: 0 | M25: 0 | O25: 0 | P25: 0 | AB25: 0 | AD25: 0 | AI25: 0 | AJ25: 0 | AK25: 0 | AL25: 1 | AR25: X | AS25: 0 | AV25: 0 | BC25: 0 | BD25: 0 | BE25: 0 | BW25: 1 | BX25: 0 | BY25: 0 | BZ25: 0 | CA25: 0 | CI25: X | CJ25: X | CK25: X | CL25: 0 | CQ25: X | CY25: X
A26: =IF(Roster!$A$24<>"",Roster!$A$24,"") -> Max Sheppard | B26: 1 | C26: 0 | G26: X | H26: 1 | I26: 0 | J26: X | L26: 0 | M26: 1 | O26: 0 | P26: 0 | AB26: 1 | AD26: 0 | AI26: 0 | AJ26: 0 | AK26: 0 | AL26: X | AR26: 0 | AS26: 0 | AV26: 0 | BC26: X | BD26: 0 | BE26: 0 | BW26: 0 | BX26: 0 | BY26: 0 | BZ26: 0 | CA26: 0 | CI26: 0 | CJ26: 0 | CK26: 1 | CL26: 1 | CQ26: 1 | CY26: 1
A27: =IF(Roster!$A$25<>"",Roster!$A$25,"") -> Lucius Christie | B27: 1 | C27: 1 | G27: 1 | H27: 1 | I27: 0 | J27: 1 | L27: 0 | M27: 1 | O27: 0 | P27: 0 | AB27: 1 | AD27: 1 | AI27: 1 | AJ27: 1 | AK27: 0 | AL27: 1 | AR27: 1 | AS27: 1 | AV27: 1 | BC27: 1 | BD27: 1 | BE27: 1 | BW27: 1 | BX27: 0 | BY27: 0 | BZ27: 0 | CA27: 0 | CI27: 1 | CJ27: 1 | CK27: 1 | CL27: 1 | CQ27: 1 | CY27: 1
A28: =IF(Roster!$A$26<>"",Roster!$A$26,"") -> Patrick McMullen | B28: 1 | C28: 1 | G28: 1 | H28: 1 | I28: 0 | J28: 1 | L28: 1 | M28: 1 | O28: 0 | P28: 0 | AB28: 1 | AD28: 1 | AI28: 1 | AJ28: 1 | AK28: 1 | AL28: 1 | AR28: 1 | AS28: 1 | AV28: 1 | BC28: 0 | BD28: 1 | BE28: 1 | BW28: 1 | BX28: 0 | BY28: 0 | BZ28: 0 | CA28: 0 | CI28: 1 | CJ28: 1 | CK28: 1 | CL28: 0 | CQ28: 1 | CY28: 1
A29: =IF(Roster!$A$27<>"",Roster!$A$27,"") -> Rachel Graber | B29: 1 | C29: 1 | G29: 1 | H29: 1 | I29: 0 | J29: 1 | L29: 0 | M29: 1 | O29: 0 | P29: 0 | AB29: 0 | AD29: 1 | AI29: 0 | AJ29: 1 | AK29: 0 | AL29: 1 | AR29: 1 | AS29: 1 | AV29: 0 | BC29: 1 | BD29: 1 | BE29: 1 | BW29: 0 | BX29: 0 | BY29: 1 | BZ29: 0 | CA29: 0 | CI29: 1 | CJ29: 1 | CK29: 1 | CL29: 0 | CQ29: 1 | CY29: 1
A30: =IF(Roster!$A$28<>"",Roster!$A$28,"") -> Ryan Kindell | B30: 1 | C30: 1 | G30: 1 | H30: 1 | I30: 0 | J30: 1 | L30: 0 | M30: 1 | O30: 0 | P30: 0 | AB30: 1 | AD30: 1 | AI30: 1 | AJ30: 1 | AK30: 0 | AL30: 1 | AR30: 1 | AS30: 1 | AV30: 1 | BC30: X | BD30: 1 | BE30: 1 | BW30: 0 | BX30: 0 | BY30: 0 | BZ30: 0 | CA30: 0 | CI30: 1 | CJ30: 1 | CK30: 1 | CL30: 0 | CQ30: 1 | CY30: 1
A31: =IF(Roster!$A$29<>"",Roster!$A$29,"") -> Ryan Ward | B31: 1 | C31: 1 | G31: 1 | H31: 1 | I31: 0 | J31: 1 | L31: 0 | M31: 1 | O31: 0 | P31: 0 | AB31: 1 | AD31: 0 | AI31: 1 | AJ31: 1 | AK31: 0 | AL31: 1 | AR31: 1 | AS31: 0 | AV31: 0 | BC31: 1 | BD31: 1 | BE31: 0 | BW31: 0 | BX31: 0 | BY31: 0 | BZ31: 0 | CA31: 0 | CI31: 1 | CJ31: 1 | CK31: 1 | CL31: 0 | CQ31: 1 | CY31: 1
A32: =IF(Roster!$A$30<>"",Roster!$A$30,"") -> Sam Gombiner | B32: 0 | C32: 0 | G32: 1 | H32: 0 | I32: 0 | J32: 1 | L32: 0 | M32: 0 | O32: 0 | P32: 0 | AB32: 0 | AD32: 0 | AI32: 0 | AJ32: 0 | AK32: 0 | AL32: 1 | AR32: X | AS32: 0 | AV32: 0 | BC32: 0 | BD32: 0 | BE32: 0 | BW32: 0 | BX32: 0 | BY32: 0 | BZ32: 0 | CA32: 0 | CI32: X | CJ32: X | CK32: X | CL32: 0 | CQ32: X | CY32: X
A33: =IF(Roster!$A$31<>"",Roster!$A$31,"") -> Sarah Kingsley-Hart | B33: 1 | C33: 0 | G33: 1 | H33: 1 | I33: 0 | J33: 1 | L33: 0 | M33: 1 | O33: 0 | P33: 0 | AB33: 1 | AD33: 0 | AI33: 0 | AJ33: 0 | AK33: 0 | AL33: 1 | AR33: X | AS33: 0 | AV33: 0 | BC33: X | BD33: 0 | BE33: 0 | BW33: 0 | BX33: 0 | BY33: 0 | BZ33: 0 | CA33: 1 | CI33: X | CJ33: X | CK33: X | CL33: 0 | CQ33: X | CY33: X
A34: =IF(Roster!$A$32<>"",Roster!$A$32,"") -> Sarah Lynch | B34: 0 | C34: 0 | G34: 1 | H34: 0 | I34: 0 | J34: 1 | L34: 0 | M34: 0 | O34: 0 | P34: 0 | AB34: 0 | AD34: 1 | AI34: 0 | AJ34: 0 | AK34: 0 | AL34: 1 | AR34: X | AS34: 1 | AV34: 1 | BC34: 0 | BD34: 0 | BE34: X | BW34: 1 | BX34: 0 | BY34: 0 | BZ34: 0 | CA34: 0 | CI34: X | CJ34: X | CK34: X | CL34: 0 | CQ34: X | CY34: X
A35: =IF(Roster!$A$33<>"",Roster!$A$33,"") -> Shani Rosenthal | B35: 1 | C35: 1 | G35: 1 | H35: 1 | I35: 1 | J35: 1 | L35: 0 | M35: 1 | O35: 1 | P35: 0 | AB35: 0 | AD35: 1 | AI35: 0 | AJ35: 1 | AK35: 0 | AL35: 1 | AR35: 1 | AS35: 1 | AV35: 0 | BC35: 0 | BD35: 1 | BE35: 1 | BW35: 0 | BX35: 0 | BY35: 0 | BZ35: 1 | CA35: 0 | CI35: 1 | CJ35: 0 | CK35: 1 | CL35: 0 | CQ35: 1 | CY35: 1
A36: =IF(Roster!$A$34<>"",Roster!$A$34,"") -> Vivian Shen | B36: 1 | C36: X | G36: 1 | H36: 1 | I36: 1 | J36: 1 | L36: 0 | M36: 1 | O36: 1 | P36: 1 | AB36: 1 | AD36: 0 | AI36: 1 | AJ36: 1 | AK36: 0 | AL36: 1 | AR36: 1 | AS36: 0 | AV36: 0 | BC36: 0 | BD36: 1 | BE36: 0 | BW36: 1 | BX36: 0 | BY36: 0 | BZ36: 0 | CA36: 0 | CI36: 1 | CJ36: 1 | CK36: 1 | CL36: 0 | CQ36: 1 | CY36: 1
A37: =IF(Roster!$A$35<>"",Roster!$A$35,"") -> Zach Esakof | B37: X | C37: 0 | G37: 1 | H37: 0 | I37: 0 | J37: 1 | L37: 0 | M37: 1 | O37: 0 | P37: 0 | AB37: 1 | AD37: X | AI37: 0 | AJ37: 0 | AK37: 0 | AL37: 1 | AR37: X | AS37: 1 | AV37: 1 | BC37: X | BD37: 0 | BE37: 1 | BW37: 1 | BX37: 0 | BY37: 0 | BZ37: 0 | CA37: 0 | CI37: X | CJ37: X | CK37: X | CL37: X | CQ37: X | CY37: X
A38: =IF(Roster!$A$36<>"",Roster!$A$36,"") -> Annette Kukunas-Piper | B38: X | C38: X | G38: X | H38: X | I38: 0 | J38: 1 | L38: X | M38: X | O38: 0 | P38: 0 | AB38: X | AD38: X | AI38: X | AJ38: X | AK38: 1 | AL38: X | AR38: X | AS38: X | AV38: X | BC38: X | BD38: 1 | BE38: 1 | BW38: 0 | BX38: 1 | BY38: 0 | BZ38: 0 | CA38: 0 | CI38: X | CJ38: X | CK38: X | CQ38: X | CY38: X
A39: =IF(Roster!$A$37<>"",Roster!$A$37,"") -> Matt Duffy | B39: X | C39: X | G39: X | H39: X | I39: 0 | J39: 1 | L39: X | M39: X | O39: 0 | P39: 0 | AB39: X | AD39: X | AI39: X | AJ39: X | AK39: 1 | AL39: X | AR39: X | AS39: X | AV39: X | BC39: X | BD39: 1 | BE39: 1 | BW39: 1 | BX39: 0 | BY39: 0 | BZ39: 0 | CA39: 0 | CI39: X | CJ39: X | CK39: X | CQ39: X | CY39: X
A40: =IF(Roster!$A$38<>"",Roster!$A$38,"") -> Ryan Birchard | B40: X | C40: X | G40: X | H40: X | I40: 0 | J40: 1 | L40: X | M40: X | O40: 0 | P40: 0 | AB40: X | AD40: X | AI40: X | AJ40: X | AK40: X | AL40: X | AR40: X | AS40: X | AV40: 0 | BC40: X | BD40: 1 | BE40: X | BW40: 0 | BX40: 0 | BY40: 0 | BZ40: 0 | CA40: 0 | CI40: X | CJ40: X | CK40: X | CQ40: X | CY40: X
A41: =IF(Roster!$A$39<>"",Roster!$A$39,"") -> Nick Blair | B41: X | C41: X | G41: X | H41: X | I41: 0 | J41: X | L41: X | M41: X | O41: 0 | P41: 0 | AB41: X | AD41: 0 | AI41: X | AJ41: X | AK41: X | AL41: X | AS41: 0 | AV41: 0 | BC41: X | BD41: X | BE41: 0 | BW41: 1 | BX41: 0 | BY41: 0 | BZ41: 0 | CA41: 0
A42: =IF(Roster!$A$40<>"",Roster!$A$40,"") -> Lily Nguyen | B42: 0 | C42: X | G42: 0 | H42: 0 | I42: 0 | J42: 0 | L42: 0 | M42: 0 | O42: 0 | P42: 0 | AB42: 0 | AD42: 0 | AI42: X | AJ42: 1 | AK42: 0 | AL42: 0 | AS42: 0 | AV42: 0 | BC42: 0 | BD42: 1 | BE42: 0 | BW42: 0 | BX42: 0 | BY42: 0 | BZ42: 0 | CA42: 0 | CK42: 1
A43: =IF(Roster!$A$41<>"",Roster!$A$41,"") -> Griff Soren | B43: 0 | C43: 0 | D43: 0 | E43: 0 | F43: 0 | G43: 0 | H43: 0 | I43: 0 | J43: 0 | K43: 0 | L43: 0 | M43: 0 | N43: 0 | O43: 0 | P43: 0 | Q43: 0 | R43: 0 | S43: 0 | T43: 0 | U43: 0 | V43: 0 | W43: 0 | X43: 0 | Y43: 0 | Z43: 0 | AA43: 0 | AB43: 0 | AC43: 0 | AD43: 0 | AE43: 0 | AF43: 0 | AG43: 0 | AH43: 0 | AI43: 0 | AJ43: 0 | AK43: 0 | AL43: 0 | AS43: 0 | AV43: 0 | BC43: 0 | BD43: 0 | BE43: 0 | BW43: 0 | BX43: 1 | BY43: 0 | BZ43: 0 | CA43: 0
A44: =IF(Roster!$A$42<>"",Roster!$A$42,"") -> Griff Alice | BW44: 1 | BX44: 0 | BY44: 0 | BZ44: 0 | CA44: 0
A45: =IF(Roster!$A$43<>"",Roster!$A$43,"")
A46: =IF(Roster!$A$44<>"",Roster!$A$44,"")
A47: =IF(Roster!$A$45<>"",Roster!$A$45,"")
A48: =IF(Roster!$A$46<>"",Roster!$A$46,"")
A49: =IF(Roster!$A$47<>"",Roster!$A$47,"")
A50: =IF(Roster!$A$48<>"",Roster!$A$48,"")
A51: =IF(Roster!$A$49<>"",Roster!$A$49,"")
A52: =IF(Roster!$A$50<>"",Roster!$A$50,"")
A53: =IF(Roster!$A$51<>"",Roster!$A$51,"")
A54: =IF(Roster!$A$52<>"",Roster!$A$52,"")
A55: =IF(Roster!$A$53<>"",Roster!$A$53,"")
A56: =IF(Roster!$A$54<>"",Roster!$A$54,"")
A57: =IF(Roster!$A$55<>"",Roster!$A$55,"")
A58: =IF(Roster!$A$56<>"",Roster!$A$56,"")
A59: =IF(Roster!$A$57<>"",Roster!$A$57,"")
A60: =IF(Roster!$A$58<>"",Roster!$A$58,"")
A61: =IF(Roster!$A$59<>"",Roster!$A$59,"")
A62: =IF(Roster!$A$60<>"",Roster!$A$60,"")
A63: =IF(Roster!$A$61<>"",Roster!$A$61,"")
A64: =IF(Roster!$A$62<>"",Roster!$A$62,"")
A65: =IF(Roster!$A$63<>"",Roster!$A$63,"")
A66: =IF(Roster!$A$64<>"",Roster!$A$64,"")
A67: =IF(Roster!$A$65<>"",Roster!$A$65,"")
A68: =IF(Roster!$A$66<>"",Roster!$A$66,"")
A69: =IF(Roster!$A$67<>"",Roster!$A$67,"")
A70: =IF(Roster!$A$68<>"",Roster!$A$68,"")
A71: =IF(Roster!$A$69<>"",Roster!$A$69,"")
A72: =IF(Roster!$A$70<>"",Roster!$A$70,"")
A73: =IF(Roster!$A$71<>"",Roster!$A$71,"")
A74: =IF(Roster!$A$72<>"",Roster!$A$72,"")
A75: =IF(Roster!$A$73<>"",Roster!$A$73,"")
A76: =IF(Roster!$A$74<>"",Roster!$A$74,"")
A77: =IF(Roster!$A$75<>"",Roster!$A$75,"")
A78: =IF(Roster!$A$76<>"",Roster!$A$76,"")
A79: =IF(Roster!$A$77<>"",Roster!$A$77,"")
A80: =IF(Roster!$A$78<>"",Roster!$A$78,"")
A81: =IF(Roster!$A$79<>"",Roster!$A$79,"")
A82: =IF(Roster!$A$80<>"",Roster!$A$80,"")
A83: =IF(Roster!$A$81<>"",Roster!$A$81,"")
A84: =IF(Roster!$A$82<>"",Roster!$A$82,"")
A85: =IF(Roster!$A$83<>"",Roster!$A$83,"")
A86: =IF(Roster!$A$84<>"",Roster!$A$84,"")
A87: =IF(Roster!$A$85<>"",Roster!$A$85,"")
A88: =IF(Roster!$A$86<>"",Roster!$A$86,"")
A89: =IF(Roster!$A$87<>"",Roster!$A$87,"")
A90: =IF(Roster!$A$88<>"",Roster!$A$88,"")
A91: =IF(Roster!$A$89<>"",Roster!$A$89,"")
A92: =IF(Roster!$A$90<>"",Roster!$A$90,"")
A93: =IF(Roster!$A$91<>"",Roster!$A$91,"")
A94: =IF(Roster!$A$92<>"",Roster!$A$92,"")
A95: =IF(Roster!$A$93<>"",Roster!$A$93,"")
A96: =IF(Roster!$A$94<>"",Roster!$A$94,"")
A97: =IF(Roster!$A$95<>"",Roster!$A$95,"")
A98: =IF(Roster!$A$96<>"",Roster!$A$96,"")
A99: =IF(Roster!$A$97<>"",Roster!$A$97,"")
A100: =IF(Roster!$A$98<>"",Roster!$A$98,"")
...

Sheet Transactions
A1: TRANSACTIONS â€” All Money In & Out
A3: Total In | B3: Total Out | C3: Net Balance | D3: Avg Transaction | E3: Pending
A4: =SUMIF(D7:D989,"Income",F7:F989)+SUMIF(D7:D989,"Fundraiser",F7:F989) -> 22487.2 | B4: =SUMIF(D7:D989,"Expense",F7:F989) -> 40876.53 | C4: =A4-B4 -> -18389.33 | D4: =IFERROR(AVERAGE(F7:F989),0) -> 613.49935 | E4: =COUNTIF(I7:I989,"Pending") -> 0
A6: Date | B6: Description | C6: Category | D6: Type | E6: Paid By | F6: Amount ($) | G6: Linked Event | H6: Reimbursed To | I6: Status | J6: Cost per Attendee ($)
B7: PEC Bid Fee | C7: Tournament Fee | D7: Expense | E7: Jake Murray | F7: 920 | G7: PEC | I7: Cleared | J7: {=IF(G7="","",IFERROR(LET(ev_cost,INDEX(Events!$G$5:$G$505,MATCH(G7,Events!$A$5:$A$505,0)),ev_split,INDEX(Events!$I$5:$I$505,MATCH(G7,Events!$A$5:$A$505,0)),att_offset,MATCH(G7,Attendance!$B$3:$AV$3,0),attendees,COUNTIF(INDEX(Attendance!$B$7:$AV$206,0,att_offset),"1"),IF(ev_split="Equal Split",ev_cost/MAX(1,COUNTA(Roster!$A$5:$A$204)),ev_cost/MAX(1,attendees))),"N/A"))} -> 1310
B8: SFI Bid Fee | C8: Tournament Fee | D8: Expense | E8: Jake Murray | F8: 1150 | G8: SFI | I8: Cleared | J8: {=IF(G8="","",IFERROR(LET(ev_cost,INDEX(Events!$G$5:$G$505,MATCH(G8,Events!$A$5:$A$505,0)),ev_split,INDEX(Events!$I$5:$I$505,MATCH(G8,Events!$A$5:$A$505,0)),att_offset,MATCH(G8,Attendance!$B$3:$AV$3,0),attendees,COUNTIF(INDEX(Attendance!$B$7:$AV$206,0,att_offset),"1"),IF(ev_split="Equal Split",ev_cost/MAX(1,COUNTA(Roster!$A$5:$A$204)),ev_cost/MAX(1,attendees))),"N/A"))} -> 1050
B9: Fantapalooza | C9: Fundraiser Income | D9: Fundraiser | E9: Jake Murray | F9: 956 | G9: Fantapalooza | I9: Cleared | J9: {=IF(G9="","",IFERROR(LET(ev_cost,INDEX(Events!$G$5:$G$505,MATCH(G9,Events!$A$5:$A$505,0)),ev_split,INDEX(Events!$I$5:$I$505,MATCH(G9,Events!$A$5:$A$505,0)),att_offset,MATCH(G9,Attendance!$B$3:$AV$3,0),attendees,COUNTIF(INDEX(Attendance!$B$7:$AV$206,0,att_offset),"1"),IF(ev_split="Equal Split",ev_cost/MAX(1,COUNTA(Roster!$A$5:$A$204)),ev_cost/MAX(1,attendees))),"N/A"))} -> -956
B10: Natties Watch Party | C10: Fundraiser Income | D10: Fundraiser | E10: Jake Murray | F10: 123 | G10: Natties Watch Party | I10: Cleared | J10: {=IF(G10="","",IFERROR(LET(ev_cost,INDEX(Events!$G$5:$G$505,MATCH(G10,Events!$A$5:$A$505,0)),ev_split,INDEX(Events!$I$5:$I$505,MATCH(G10,Events!$A$5:$A$505,0)),att_offset,MATCH(G10,Attendance!$B$3:$AV$3,0),attendees,COUNTIF(INDEX(Attendance!$B$7:$AV$206,0,att_offset),"1"),IF(ev_split="Equal Split",ev_cost/MAX(1,COUNTA(Roster!$A$5:$A$204)),ev_cost/MAX(1,attendees))),"N/A"))} -> -123
B11: Outstanding 2025 Funds | C11: Fundraiser Income | D11: Fundraiser | E11: Jake Murray | F11: 1030 | G11: 2025 Fundraising | I11: Cleared | J11: {=IF(G11="","",IFERROR(LET(ev_cost,INDEX(Events!$G$5:$G$505,MATCH(G11,Events!$A$5:$A$505,0)),ev_split,INDEX(Events!$I$5:$I$505,MATCH(G11,Events!$A$5:$A$505,0)),att_offset,MATCH(G11,Attendance!$B$3:$AV$3,0),attendees,COUNTIF(INDEX(Attendance!$B$7:$AV$206,0,att_offset),"1"),IF(ev_split="Equal Split",ev_cost/MAX(1,COUNTA(Roster!$A$5:$A$204)),ev_cost/MAX(1,attendees))),"N/A"))} -> 1030
B12: Wednesday Tryout Field | C12: Field Fee | D12: Expense | E12: Jake Murray | F12: 69 | G12: May-July Fields | I12: Cleared | J12: {=IF(G12="","",IFERROR(LET(ev_cost,INDEX(Events!$G$5:$G$505,MATCH(G12,Events!$A$5:$A$505,0)),ev_split,INDEX(Events!$I$5:$I$505,MATCH(G12,Events!$A$5:$A$505,0)),att_offset,MATCH(G12,Attendance!$B$3:$AV$3,0),attendees,COUNTIF(INDEX(Attendance!$B$7:$AV$206,0,att_offset),"1"),IF(ev_split="Equal Split",ev_cost/MAX(1,COUNTA(Roster!$A$5:$A$204)),ev_cost/MAX(1,attendees))),"N/A"))} -> 2326
A13: 46192 | B13: tshirts and spray paint | C13: Equipment | D13: Expense | E13: Jenna Nold | F13: 185.69 | G13: PEC | I13: Cleared | J13: {=IF(G13="","",IFERROR(LET(ev_cost,INDEX(Events!$G$5:$G$505,MATCH(G13,Events!$A$5:$A$505,0)),ev_split,INDEX(Events!$I$5:$I$505,MATCH(G13,Events!$A$5:$A$505,0)),att_offset,MATCH(G13,Attendance!$B$3:$AV$3,0),attendees,COUNTIF(INDEX(Attendance!$B$7:$AV$206,0,att_offset),"1"),IF(ev_split="Equal Split",ev_cost/MAX(1,COUNTA(Roster!$A$5:$A$204)),ev_cost/MAX(1,attendees))),"N/A"))} -> 1310
A14: 46195 | B14: gso airport minivan | C14: Travel | D14: Expense | E14: Jake Murray | F14: 228.44 | G14: PEC | I14: Cleared | J14: {=IF(G14="","",IFERROR(LET(ev_cost,INDEX(Events!$G$5:$G$505,MATCH(G14,Events!$A$5:$A$505,0)),ev_split,INDEX(Events!$I$5:$I$505,MATCH(G14,Events!$A$5:$A$505,0)),att_offset,MATCH(G14,Attendance!$B$3:$AV$3,0),attendees,COUNTIF(INDEX(Attendance!$B$7:$AV$206,0,att_offset),"1"),IF(ev_split="Equal Split",ev_cost/MAX(1,COUNTA(Roster!$A$5:$A$204)),ev_cost/MAX(1,attendees))),"N/A"))} -> 1310
B15: City Practice Fields | C15: Field Fee | D15: Income | F15: 0 | I15: Cleared | J15: {=IF(G15="","",IFERROR(LET(ev_cost,INDEX(Events!$G$5:$G$505,MATCH(G15,Events!$A$5:$A$505,0)),ev_split,INDEX(Events!$I$5:$I$505,MATCH(G15,Events!$A$5:$A$505,0)),att_offset,MATCH(G15,Attendance!$B$3:$AV$3,0),attendees,COUNTIF(INDEX(Attendance!$B$7:$AV$206,0,att_offset),"1"),IF(ev_split="Equal Split",ev_cost/MAX(1,COUNTA(Roster!$A$5:$A$204)),ev_cost/MAX(1,attendees))),"N/A"))}
A16: 46196 | B16: Chris Wohl Dues | C16: Dues | D16: Income | E16: Chris Wohl | F16: 68.75 | H16: Jake Murray | I16: Cleared | J16: {=IF(G16="","",IFERROR(LET(ev_cost,INDEX(Events!$G$5:$G$505,MATCH(G16,Events!$A$5:$A$505,0)),ev_split,INDEX(Events!$I$5:$I$505,MATCH(G16,Events!$A$5:$A$505,0)),att_offset,MATCH(G16,Attendance!$B$3:$AV$3,0),attendees,COUNTIF(INDEX(Attendance!$B$7:$AV$206,0,att_offset),"1"),IF(ev_split="Equal Split",ev_cost/MAX(1,COUNTA(Roster!$A$5:$A$204)),ev_cost/MAX(1,attendees))),"N/A"))}
A17: 46195 | B17: pec megavan | C17: Travel | D17: Expense | E17: Harry Park | G17: PEC | I17: Cleared | J17: {=IF(G17="","",IFERROR(LET(ev_cost,INDEX(Events!$G$5:$G$505,MATCH(G17,Events!$A$5:$A$505,0)),ev_split,INDEX(Events!$I$5:$I$505,MATCH(G17,Events!$A$5:$A$505,0)),att_offset,MATCH(G17,Attendance!$B$3:$AV$3,0),attendees,COUNTIF(INDEX(Attendance!$B$7:$AV$206,0,att_offset),"1"),IF(ev_split="Equal Split",ev_cost/MAX(1,COUNTA(Roster!$A$5:$A$204)),ev_cost/MAX(1,attendees))),"N/A"))} -> 1310 | K17: Will sort it out amongst passengers once final costs are finalized
A18: 46201 | B18: PEC Hotel | C18: Hotel | D18: Expense | E18: Shani Rosenthal | F18: 3487.59 | G18: PEC | I18: Cleared | J18: {=IF(G18="","",IFERROR(LET(ev_cost,INDEX(Events!$G$5:$G$505,MATCH(G18,Events!$A$5:$A$505,0)),ev_split,INDEX(Events!$I$5:$I$505,MATCH(G18,Events!$A$5:$A$505,0)),att_offset,MATCH(G18,Attendance!$B$3:$AV$3,0),attendees,COUNTIF(INDEX(Attendance!$B$7:$AV$206,0,att_offset),"1"),IF(ev_split="Equal Split",ev_cost/MAX(1,COUNTA(Roster!$A$5:$A$204)),ev_cost/MAX(1,attendees))),"N/A"))} -> 1310
B19: Nick Van Team Comp | C19: Travel | D19: Credit | E19: Jake Murray | F19: 59.99 | G19: PEC | H19: Nick Blair | I19: Cleared | J19: {=IF(G19="","",IFERROR(LET(ev_cost,INDEX(Events!$G$5:$G$505,MATCH(G19,Events!$A$5:$A$505,0)),ev_split,INDEX(Events!$I$5:$I$505,MATCH(G19,Events!$A$5:$A$505,0)),att_offset,MATCH(G19,Attendance!$B$3:$AV$3,0),attendees,COUNTIF(INDEX(Attendance!$B$7:$AV$206,0,att_offset),"1"),IF(ev_split="Equal Split",ev_cost/MAX(1,COUNTA(Roster!$A$5:$A$204)),ev_cost/MAX(1,attendees))),"N/A"))} -> 1310 | K19: Not sure if this amount is correct
A20: 46201 | B20: gso minivan gas | C20: Travel | D20: Expense | E20: jake murray | F20: 15.26 | G20: PEC | I20: Cleared | J20: {=IF(G20="","",IFERROR(LET(ev_cost,INDEX(Events!$G$5:$G$505,MATCH(G20,Events!$A$5:$A$505,0)),ev_split,INDEX(Events!$I$5:$I$505,MATCH(G20,Events!$A$5:$A$505,0)),att_offset,MATCH(G20,Attendance!$B$3:$AV$3,0),attendees,COUNTIF(INDEX(Attendance!$B$7:$AV$206,0,att_offset),"1"),IF(ev_split="Equal Split",ev_cost/MAX(1,COUNTA(Roster!$A$5:$A$204)),ev_cost/MAX(1,attendees))),"N/A"))} -> 1310
A21: 46201 | B21: Jake's Car Airport Parking | C21: Travel | D21: Expense | E21: jake murray | F21: 83.64 | G21: PEC | I21: Cleared | J21: {=IF(G21="","",IFERROR(LET(ev_cost,INDEX(Events!$G$5:$G$505,MATCH(G21,Events!$A$5:$A$505,0)),ev_split,INDEX(Events!$I$5:$I$505,MATCH(G21,Events!$A$5:$A$505,0)),att_offset,MATCH(G21,Attendance!$B$3:$AV$3,0),attendees,COUNTIF(INDEX(Attendance!$B$7:$AV$206,0,att_offset),"1"),IF(ev_split="Equal Split",ev_cost/MAX(1,COUNTA(Roster!$A$5:$A$204)),ev_cost/MAX(1,attendees))),"N/A"))} -> 1310
A22: 46930 | B22: Lexie dues | C22: Dues | D22: Income | E22: Lexie Thomas | F22: 68.75 | H22: Jake Murray | I22: Cleared | J22: {=IF(G22="","",IFERROR(LET(ev_cost,INDEX(Events!$G$5:$G$505,MATCH(G22,Events!$A$5:$A$505,0)),ev_split,INDEX(Events!$I$5:$I$505,MATCH(G22,Events!$A$5:$A$505,0)),att_offset,MATCH(G22,Attendance!$B$3:$AV$3,0),attendees,COUNTIF(INDEX(Attendance!$B$7:$AV$206,0,att_offset),"1"),IF(ev_split="Equal Split",ev_cost/MAX(1,COUNTA(Roster!$A$5:$A$204)),ev_cost/MAX(1,attendees))),"N/A"))}
A23: 46201 | B23: Vivian dues | C23: Dues | D23: Income | E23: Vivian Shen | F23: 400 | H23: Jake Murray | I23: Cleared | J23: {=IF(G23="","",IFERROR(LET(ev_cost,INDEX(Events!$G$5:$G$505,MATCH(G23,Events!$A$5:$A$505,0)),ev_split,INDEX(Events!$I$5:$I$505,MATCH(G23,Events!$A$5:$A$505,0)),att_offset,MATCH(G23,Attendance!$B$3:$AV$3,0),attendees,COUNTIF(INDEX(Attendance!$B$7:$AV$206,0,att_offset),"1"),IF(ev_split="Equal Split",ev_cost/MAX(1,COUNTA(Roster!$A$5:$A$204)),ev_cost/MAX(1,attendees))),"N/A"))}
A24: 46201 | B24: Dudley dues | C24: Dues | D24: Income | E24: Kristin Dudley | F24: 400 | H24: Jake Murray | I24: Cleared | J24: {=IF(G24="","",IFERROR(LET(ev_cost,INDEX(Events!$G$5:$G$505,MATCH(G24,Events!$A$5:$A$505,0)),ev_split,INDEX(Events!$I$5:$I$505,MATCH(G24,Events!$A$5:$A$505,0)),att_offset,MATCH(G24,Attendance!$B$3:$AV$3,0),attendees,COUNTIF(INDEX(Attendance!$B$7:$AV$206,0,att_offset),"1"),IF(ev_split="Equal Split",ev_cost/MAX(1,COUNTA(Roster!$A$5:$A$204)),ev_cost/MAX(1,attendees))),"N/A"))}
A25: 46203 | B25: Graber dues | C25: Dues | D25: Income | E25: Rachel Graber | F25: 202.89 | H25: Jake Murray | I25: Cleared | J25: {=IF(G25="","",IFERROR(LET(ev_cost,INDEX(Events!$G$5:$G$505,MATCH(G25,Events!$A$5:$A$505,0)),ev_split,INDEX(Events!$I$5:$I$505,MATCH(G25,Events!$A$5:$A$505,0)),att_offset,MATCH(G25,Attendance!$B$3:$AV$3,0),attendees,COUNTIF(INDEX(Attendance!$B$7:$AV$206,0,att_offset),"1"),IF(ev_split="Equal Split",ev_cost/MAX(1,COUNTA(Roster!$A$5:$A$204)),ev_cost/MAX(1,attendees))),"N/A"))}
A26: 46203 | B26: Kasey dues | C26: Dues | D26: Income | E26: Kasey Schock | F26: 202.89 | H26: Jake Murray | I26: Cleared | J26: {=IF(G26="","",IFERROR(LET(ev_cost,INDEX(Events!$G$5:$G$505,MATCH(G26,Events!$A$5:$A$505,0)),ev_split,INDEX(Events!$I$5:$I$505,MATCH(G26,Events!$A$5:$A$505,0)),att_offset,MATCH(G26,Attendance!$B$3:$AV$3,0),attendees,COUNTIF(INDEX(Attendance!$B$7:$AV$206,0,att_offset),"1"),IF(ev_split="Equal Split",ev_cost/MAX(1,COUNTA(Roster!$A$5:$A$204)),ev_cost/MAX(1,attendees))),"N/A"))}
A27: 46203 | B27: Haleydues | C27: Dues | D27: Income | E27: Haley Young | F27: 202.89 | H27: Jake Murray | I27: Cleared | J27: {=IF(G27="","",IFERROR(LET(ev_cost,INDEX(Events!$G$5:$G$505,MATCH(G27,Events!$A$5:$A$505,0)),ev_split,INDEX(Events!$I$5:$I$505,MATCH(G27,Events!$A$5:$A$505,0)),att_offset,MATCH(G27,Attendance!$B$3:$AV$3,0),attendees,COUNTIF(INDEX(Attendance!$B$7:$AV$206,0,att_offset),"1"),IF(ev_split="Equal Split",ev_cost/MAX(1,COUNTA(Roster!$A$5:$A$204)),ev_cost/MAX(1,attendees))),"N/A"))}
A28: 46203 | B28: Sarah kh dues | C28: Dues | D28: Income | E28: Sarah Kingsley-Hart | F28: 202.89 | H28: Jake Murray | I28: Cleared | J28: {=IF(G28="","",IFERROR(LET(ev_cost,INDEX(Events!$G$5:$G$505,MATCH(G28,Events!$A$5:$A$505,0)),ev_split,INDEX(Events!$I$5:$I$505,MATCH(G28,Events!$A$5:$A$505,0)),att_offset,MATCH(G28,Attendance!$B$3:$AV$3,0),attendees,COUNTIF(INDEX(Attendance!$B$7:$AV$206,0,att_offset),"1"),IF(ev_split="Equal Split",ev_cost/MAX(1,COUNTA(Roster!$A$5:$A$204)),ev_cost/MAX(1,attendees))),"N/A"))}
A29: 46204 | B29: Jimmy dues | C29: Dues | D29: Income | E29: Jimmy Towle | F29: 28.75 | H29: Jake Murray | I29: Cleared | J29: {=IF(G29="","",IFERROR(LET(ev_cost,INDEX(Events!$G$5:$G$505,MATCH(G29,Events!$A$5:$A$505,0)),ev_split,INDEX(Events!$I$5:$I$505,MATCH(G29,Events!$A$5:$A$505,0)),att_offset,MATCH(G29,Attendance!$B$3:$AV$3,0),attendees,COUNTIF(INDEX(Attendance!$B$7:$AV$206,0,att_offset),"1"),IF(ev_split="Equal Split",ev_cost/MAX(1,COUNTA(Roster!$A$5:$A$204)),ev_cost/MAX(1,attendees))),"N/A"))}
A30: 46206 | B30: Kevin Nicholl | C30: Dues | D30: Income | E30: Kevin Nicholl | F30: 202.89 | H30: Jake Murray | I30: Cleared | J30: {=IF(G30="","",IFERROR(LET(ev_cost,INDEX(Events!$G$5:$G$505,MATCH(G30,Events!$A$5:$A$505,0)),ev_split,INDEX(Events!$I$5:$I$505,MATCH(G30,Events!$A$5:$A$505,0)),att_offset,MATCH(G30,Attendance!$B$3:$AV$3,0),attendees,COUNTIF(INDEX(Attendance!$B$7:$AV$206,0,att_offset),"1"),IF(ev_split="Equal Split",ev_cost/MAX(1,COUNTA(Roster!$A$5:$A$204)),ev_cost/MAX(1,attendees))),"N/A"))}
A31: 46206 | B31: Pat dues | C31: Dues | D31: Income | E31: Patrick McMullen | F31: 202.89 | H31: Jake Murray | I31: Cleared | J31: {=IF(G31="","",IFERROR(LET(ev_cost,INDEX(Events!$G$5:$G$505,MATCH(G31,Events!$A$5:$A$505,0)),ev_split,INDEX(Events!$I$5:$I$505,MATCH(G31,Events!$A$5:$A$505,0)),att_offset,MATCH(G31,Attendance!$B$3:$AV$3,0),attendees,COUNTIF(INDEX(Attendance!$B$7:$AV$206,0,att_offset),"1"),IF(ev_split="Equal Split",ev_cost/MAX(1,COUNTA(Roster!$A$5:$A$204)),ev_cost/MAX(1,attendees))),"N/A"))}
A32: 46203 | B32: Ward dues | C32: Dues | D32: Income | E32: Ryan Ward | F32: 202.89 | H32: Jake Murray | I32: Cleared | J32: {=IF(G32="","",IFERROR(LET(ev_cost,INDEX(Events!$G$5:$G$505,MATCH(G32,Events!$A$5:$A$505,0)),ev_split,INDEX(Events!$I$5:$I$505,MATCH(G32,Events!$A$5:$A$505,0)),att_offset,MATCH(G32,Attendance!$B$3:$AV$3,0),attendees,COUNTIF(INDEX(Attendance!$B$7:$AV$206,0,att_offset),"1"),IF(ev_split="Equal Split",ev_cost/MAX(1,COUNTA(Roster!$A$5:$A$204)),ev_cost/MAX(1,attendees))),"N/A"))}
A33: 46198 | B33: PEC Team Snacks | C33: Equipment | D33: Expense | E33: Darra Reppermund | F33: 152.13 | G33: PEC | I33: Cleared | J33: {=IF(G33="","",IFERROR(LET(ev_cost,INDEX(Events!$G$5:$G$505,MATCH(G33,Events!$A$5:$A$505,0)),ev_split,INDEX(Events!$I$5:$I$505,MATCH(G33,Events!$A$5:$A$505,0)),att_offset,MATCH(G33,Attendance!$B$3:$AV$3,0),attendees,COUNTIF(INDEX(Attendance!$B$7:$AV$206,0,att_offset),"1"),IF(ev_split="Equal Split",ev_cost/MAX(1,COUNTA(Roster!$A$5:$A$204)),ev_cost/MAX(1,attendees))),"N/A"))} -> 1310
A34: 46209 | B34: Toll Credit | C34: Travel | D34: Credit | E34: Jake murray | F34: =17.1+19.7 -> 36.8 | H34: Lexie Thomas | I34: Cleared | J34: {=IF(G34="","",IFERROR(LET(ev_cost,INDEX(Events!$G$5:$G$505,MATCH(G34,Events!$A$5:$A$505,0)),ev_split,INDEX(Events!$I$5:$I$505,MATCH(G34,Events!$A$5:$A$505,0)),att_offset,MATCH(G34,Attendance!$B$3:$AV$3,0),attendees,COUNTIF(INDEX(Attendance!$B$7:$AV$206,0,att_offset),"1"),IF(ev_split="Equal Split",ev_cost/MAX(1,COUNTA(Roster!$A$5:$A$204)),ev_cost/MAX(1,attendees))),"N/A"))}
A35: 46209 | B35: ESC Bid Fee | C35: Tournament Fee | D35: Expense | E35: Jake murray | F35: 1000 | G35: ESC | I35: Cleared | J35: {=IF(G35="","",IFERROR(LET(ev_cost,INDEX(Events!$G$5:$G$505,MATCH(G35,Events!$A$5:$A$505,0)),ev_split,INDEX(Events!$I$5:$I$505,MATCH(G35,Events!$A$5:$A$505,0)),att_offset,MATCH(G35,Attendance!$B$3:$AV$3,0),attendees,COUNTIF(INDEX(Attendance!$B$7:$AV$206,0,att_offset),"1"),IF(ev_split="Equal Split",ev_cost/MAX(1,COUNTA(Roster!$A$5:$A$204)),ev_cost/MAX(1,attendees))),"N/A"))} -> 5345.86
A36: 46208 | B36: Kindell Dues | C36: Dues | D36: Income | E36: Ryan Kindell | F36: 500 | H36: Jake Murray | I36: Cleared | J36: {=IF(G36="","",IFERROR(LET(ev_cost,INDEX(Events!$G$5:$G$505,MATCH(G36,Events!$A$5:$A$505,0)),ev_split,INDEX(Events!$I$5:$I$505,MATCH(G36,Events!$A$5:$A$505,0)),att_offset,MATCH(G36,Attendance!$B$3:$AV$3,0),attendees,COUNTIF(INDEX(Attendance!$B$7:$AV$206,0,att_offset),"1"),IF(ev_split="Equal Split",ev_cost/MAX(1,COUNTA(Roster!$A$5:$A$204)),ev_cost/MAX(1,attendees))),"N/A"))}
A37: 46209 | B37: Darra Dues | C37: Dues | D37: Income | E37: Darra Reppermund | F37: 56.24 | H37: Jake Murray | I37: Cleared | J37: {=IF(G37="","",IFERROR(LET(ev_cost,INDEX(Events!$G$5:$G$505,MATCH(G37,Events!$A$5:$A$505,0)),ev_split,INDEX(Events!$I$5:$I$505,MATCH(G37,Events!$A$5:$A$505,0)),att_offset,MATCH(G37,Attendance!$B$3:$AV$3,0),attendees,COUNTIF(INDEX(Attendance!$B$7:$AV$206,0,att_offset),"1"),IF(ev_split="Equal Split",ev_cost/MAX(1,COUNTA(Roster!$A$5:$A$204)),ev_cost/MAX(1,attendees))),"N/A"))}
A38: 46218 | B38: SD Card | C38: Equipment | D38: Credit | E38: Jake murray | F38: 58.84 | H38: Jake Murray | I38: Cleared | J38: {=IF(G38="","",IFERROR(LET(ev_cost,INDEX(Events!$G$5:$G$505,MATCH(G38,Events!$A$5:$A$505,0)),ev_split,INDEX(Events!$I$5:$I$505,MATCH(G38,Events!$A$5:$A$505,0)),att_offset,MATCH(G38,Attendance!$B$3:$AV$3,0),attendees,COUNTIF(INDEX(Attendance!$B$7:$AV$206,0,att_offset),"1"),IF(ev_split="Equal Split",ev_cost/MAX(1,COUNTA(Roster!$A$5:$A$204)),ev_cost/MAX(1,attendees))),"N/A"))}
A39: 46230 | B39: Chris wohl Dues | C39: Dues | D39: Income | E39: Chris Wohl | F39: 139.61 | H39: Jake Murray | I39: Cleared | J39: {=IF(G39="","",IFERROR(LET(ev_cost,INDEX(Events!$G$5:$G$505,MATCH(G39,Events!$A$5:$A$505,0)),ev_split,INDEX(Events!$I$5:$I$505,MATCH(G39,Events!$A$5:$A$505,0)),att_offset,MATCH(G39,Attendance!$B$3:$AV$3,0),attendees,COUNTIF(INDEX(Attendance!$B$7:$AV$206,0,att_offset),"1"),IF(ev_split="Equal Split",ev_cost/MAX(1,COUNTA(Roster!$A$5:$A$204)),ev_cost/MAX(1,attendees))),"N/A"))}
A40: 46227 | B40: SFI Team snacks | C40: Equipment | D40: Expense | E40: Ryan Ward | F40: 202.26 | G40: SFI | I40: Cleared | J40: {=IF(G40="","",IFERROR(LET(ev_cost,INDEX(Events!$G$5:$G$505,MATCH(G40,Events!$A$5:$A$505,0)),ev_split,INDEX(Events!$I$5:$I$505,MATCH(G40,Events!$A$5:$A$505,0)),att_offset,MATCH(G40,Attendance!$B$3:$AV$3,0),attendees,COUNTIF(INDEX(Attendance!$B$7:$AV$206,0,att_offset),"1"),IF(ev_split="Equal Split",ev_cost/MAX(1,COUNTA(Roster!$A$5:$A$204)),ev_cost/MAX(1,attendees))),"N/A"))} -> 1050
A41: 46227 | B41: SFI Hotels | C41: Hotel | D41: Expense | E41: Harry Park | F41: 2389.2 | G41: SFI | I41: Cleared | J41: {=IF(G41="","",IFERROR(LET(ev_cost,INDEX(Events!$G$5:$G$505,MATCH(G41,Events!$A$5:$A$505,0)),ev_split,INDEX(Events!$I$5:$I$505,MATCH(G41,Events!$A$5:$A$505,0)),att_offset,MATCH(G41,Attendance!$B$3:$AV$3,0),attendees,COUNTIF(INDEX(Attendance!$B$7:$AV$206,0,att_offset),"1"),IF(ev_split="Equal Split",ev_cost/MAX(1,COUNTA(Roster!$A$5:$A$204)),ev_cost/MAX(1,attendees))),"N/A"))} -> 1050
A42: 46201 | B42: Mega Van Tolls | C42: Travel | D42: Expense | E42: Harry Park | F42: 27.42 | G42: PEC | I42: Cleared | J42: {=IF(G42="","",IFERROR(LET(ev_cost,INDEX(Events!$G$5:$G$505,MATCH(G42,Events!$A$5:$A$505,0)),ev_split,INDEX(Events!$I$5:$I$505,MATCH(G42,Events!$A$5:$A$505,0)),att_offset,MATCH(G42,Attendance!$B$3:$AV$3,0),attendees,COUNTIF(INDEX(Attendance!$B$7:$AV$206,0,att_offset),"1"),IF(ev_split="Equal Split",ev_cost/MAX(1,COUNTA(Roster!$A$5:$A$204)),ev_cost/MAX(1,attendees))),"N/A"))} -> 1310
A43: 46238 | B43: Practice Fields thru July | C43: Field Fee | D43: Expense | E43: Jake Murray | F43: 2257 | G43: May-July Fields | I43: Cleared | J43: {=IF(G43="","",IFERROR(LET(ev_cost,INDEX(Events!$G$5:$G$505,MATCH(G43,Events!$A$5:$A$505,0)),ev_split,INDEX(Events!$I$5:$I$505,MATCH(G43,Events!$A$5:$A$505,0)),att_offset,MATCH(G43,Attendance!$B$3:$AV$3,0),attendees,COUNTIF(INDEX(Attendance!$B$7:$AV$206,0,att_offset),"1"),IF(ev_split="Equal Split",ev_cost/MAX(1,COUNTA(Roster!$A$5:$A$204)),ev_cost/MAX(1,attendees))),"N/A"))} -> 2326
A44: 46238 | B44: Post-SFI Reimbursement | C44: Dues | D44: Reimbursement | E44: Jake Murray | F44: 2005.28 | H44: Harry Park | I44: Cleared | J44: {=IF(G44="","",IFERROR(LET(ev_cost,INDEX(Events!$G$5:$G$505,MATCH(G44,Events!$A$5:$A$505,0)),ev_split,INDEX(Events!$I$5:$I$505,MATCH(G44,Events!$A$5:$A$505,0)),att_offset,MATCH(G44,Attendance!$B$3:$AV$3,0),attendees,COUNTIF(INDEX(Attendance!$B$7:$AV$206,0,att_offset),"1"),IF(ev_split="Equal Split",ev_cost/MAX(1,COUNTA(Roster!$A$5:$A$204)),ev_cost/MAX(1,attendees))),"N/A"))}
A45: 46239 | B45: Griffin Dues | C45: Dues | D45: Income | E45: Griffin O'Neal-Freeman | F45: 411.34 | H45: Jake Murray | I45: Cleared | J45: {=IF(G45="","",IFERROR(LET(ev_cost,INDEX(Events!$G$5:$G$505,MATCH(G45,Events!$A$5:$A$505,0)),ev_split,INDEX(Events!$I$5:$I$505,MATCH(G45,Events!$A$5:$A$505,0)),att_offset,MATCH(G45,Attendance!$B$3:$AV$3,0),attendees,COUNTIF(INDEX(Attendance!$B$7:$AV$206,0,att_offset),"1"),IF(ev_split="Equal Split",ev_cost/MAX(1,COUNTA(Roster!$A$5:$A$204)),ev_cost/MAX(1,attendees))),"N/A"))}
A46: 46244 | B46: Graber dues | C46: Dues | D46: Income | E46: Rachel Graber | F46: 200 | H46: Jake Murray | I46: Cleared | J46: {=IF(G46="","",IFERROR(LET(ev_cost,INDEX(Events!$G$5:$G$505,MATCH(G46,Events!$A$5:$A$505,0)),ev_split,INDEX(Events!$I$5:$I$505,MATCH(G46,Events!$A$5:$A$505,0)),att_offset,MATCH(G46,Attendance!$B$3:$AV$3,0),attendees,COUNTIF(INDEX(Attendance!$B$7:$AV$206,0,att_offset),"1"),IF(ev_split="Equal Split",ev_cost/MAX(1,COUNTA(Roster!$A$5:$A$204)),ev_cost/MAX(1,attendees))),"N/A"))}
A47: 46246 | B47: AT Dues | C47: Dues | D47: Income | E47: At | F47: 470.58 | H47: Jake Murray | I47: Cleared | J47: {=IF(G47="","",IFERROR(LET(ev_cost,INDEX(Events!$G$5:$G$505,MATCH(G47,Events!$A$5:$A$505,0)),ev_split,INDEX(Events!$I$5:$I$505,MATCH(G47,Events!$A$5:$A$505,0)),att_offset,MATCH(G47,Attendance!$B$3:$AV$3,0),attendees,COUNTIF(INDEX(Attendance!$B$7:$AV$206,0,att_offset),"1"),IF(ev_split="Equal Split",ev_cost/MAX(1,COUNTA(Roster!$A$5:$A$204)),ev_cost/MAX(1,attendees))),"N/A"))}
A48: 46247 | B48: Kev Dues | C48: Dues | D48: Income | E48: Kevin Nicholl | F48: 206.16 | H48: Jake Murray | I48: Cleared | J48: {=IF(G48="","",IFERROR(LET(ev_cost,INDEX(Events!$G$5:$G$505,MATCH(G48,Events!$A$5:$A$505,0)),ev_split,INDEX(Events!$I$5:$I$505,MATCH(G48,Events!$A$5:$A$505,0)),att_offset,MATCH(G48,Attendance!$B$3:$AV$3,0),attendees,COUNTIF(INDEX(Attendance!$B$7:$AV$206,0,att_offset),"1"),IF(ev_split="Equal Split",ev_cost/MAX(1,COUNTA(Roster!$A$5:$A$204)),ev_cost/MAX(1,attendees))),"N/A"))}
A49: 46266 | B49: Sectionals Bid Fee | C49: Tournament Fee | D49: Expense | E49: Jake Murray | F49: 550 | G49: Sectionals | I49: Cleared | J49: {=IF(G49="","",IFERROR(LET(ev_cost,INDEX(Events!$G$5:$G$505,MATCH(G49,Events!$A$5:$A$505,0)),ev_split,INDEX(Events!$I$5:$I$505,MATCH(G49,Events!$A$5:$A$505,0)),att_offset,MATCH(G49,Attendance!$B$3:$AV$3,0),attendees,COUNTIF(INDEX(Attendance!$B$7:$AV$206,0,att_offset),"1"),IF(ev_split="Equal Split",ev_cost/MAX(1,COUNTA(Roster!$A$5:$A$204)),ev_cost/MAX(1,attendees))),"N/A"))} -> 560.85
A50: 46255 | B50: ESC Hotel | C50: Hotel | D50: Expense | E50: Harry Park | F50: 3027.12 | G50: ESC | I50: Cleared | J50: {=IF(G50="","",IFERROR(LET(ev_cost,INDEX(Events!$G$5:$G$505,MATCH(G50,Events!$A$5:$A$505,0)),ev_split,INDEX(Events!$I$5:$I$505,MATCH(G50,Events!$A$5:$A$505,0)),att_offset,MATCH(G50,Attendance!$B$3:$AV$3,0),attendees,COUNTIF(INDEX(Attendance!$B$7:$AV$206,0,att_offset),"1"),IF(ev_split="Equal Split",ev_cost/MAX(1,COUNTA(Roster!$A$5:$A$204)),ev_cost/MAX(1,attendees))),"N/A"))} -> 5345.86
A51: 46255 | B51: Camera Gear | C51: Equipment | D51: Credit | E51: Jake Murray | F51: 20.12 | H51: Harry Park | I51: Cleared | J51: {=IF(G51="","",IFERROR(LET(ev_cost,INDEX(Events!$G$5:$G$505,MATCH(G51,Events!$A$5:$A$505,0)),ev_split,INDEX(Events!$I$5:$I$505,MATCH(G51,Events!$A$5:$A$505,0)),att_offset,MATCH(G51,Attendance!$B$3:$AV$3,0),attendees,COUNTIF(INDEX(Attendance!$B$7:$AV$206,0,att_offset),"1"),IF(ev_split="Equal Split",ev_cost/MAX(1,COUNTA(Roster!$A$5:$A$204)),ev_cost/MAX(1,attendees))),"N/A"))}
A53: 46253 | B53: ESC Team Snacks | C53: Equipment | D53: Expense | E53: Darra Reppermund | F53: 170.28 | G53: ESC | I53: Cleared | J53: {=IF(G53="","",IFERROR(LET(ev_cost,INDEX(Events!$G$5:$G$505,MATCH(G53,Events!$A$5:$A$505,0)),ev_split,INDEX(Events!$I$5:$I$505,MATCH(G53,Events!$A$5:$A$505,0)),att_offset,MATCH(G53,Attendance!$B$3:$AV$3,0),attendees,COUNTIF(INDEX(Attendance!$B$7:$AV$206,0,att_offset),"1"),IF(ev_split="Equal Split",ev_cost/MAX(1,COUNTA(Roster!$A$5:$A$204)),ev_cost/MAX(1,attendees))),"N/A"))} -> 5345.86
A54: 46259 | B54: BBQ Food | C54: Refund | D54: Credit | E54: Jake Murray | F54: 28 | H54: Dylan Best | I54: Cleared | J54: {=IF(G54="","",IFERROR(LET(ev_cost,INDEX(Events!$G$5:$G$505,MATCH(G54,Events!$A$5:$A$505,0)),ev_split,INDEX(Events!$I$5:$I$505,MATCH(G54,Events!$A$5:$A$505,0)),att_offset,MATCH(G54,Attendance!$B$3:$AV$3,0),attendees,COUNTIF(INDEX(Attendance!$B$7:$AV$206,0,att_offset),"1"),IF(ev_split="Equal Split",ev_cost/MAX(1,COUNTA(Roster!$A$5:$A$204)),ev_cost/MAX(1,attendees))),"N/A"))}
A55: 46260 | B55: August Fan Store | C55: Fundraiser Income | D55: Fundraiser | E55: Jake Murray | F55: 359.25 | G55: Fan Stores | I55: Cleared | J55: {=IF(G55="","",IFERROR(LET(ev_cost,INDEX(Events!$G$5:$G$505,MATCH(G55,Events!$A$5:$A$505,0)),ev_split,INDEX(Events!$I$5:$I$505,MATCH(G55,Events!$A$5:$A$505,0)),att_offset,MATCH(G55,Attendance!$B$3:$AV$3,0),attendees,COUNTIF(INDEX(Attendance!$B$7:$AV$206,0,att_offset),"1"),IF(ev_split="Equal Split",ev_cost/MAX(1,COUNTA(Roster!$A$5:$A$204)),ev_cost/MAX(1,attendees))),"N/A"))} -> 0
A56: 46236 | B56: Sarah KH Car Credit | C56: Travel | D56: Expense | E56: Sarah Kingsley-Hart | F56: 21 | G56: PEC | I56: Cleared | J56: {=IF(G56="","",IFERROR(LET(ev_cost,INDEX(Events!$G$5:$G$505,MATCH(G56,Events!$A$5:$A$505,0)),ev_split,INDEX(Events!$I$5:$I$505,MATCH(G56,Events!$A$5:$A$505,0)),att_offset,MATCH(G56,Attendance!$B$3:$AV$3,0),attendees,COUNTIF(INDEX(Attendance!$B$7:$AV$206,0,att_offset),"1"),IF(ev_split="Equal Split",ev_cost/MAX(1,COUNTA(Roster!$A$5:$A$204)),ev_cost/MAX(1,attendees))),"N/A"))} -> 1310
A57: 46236 | B57: Sarah KH Car Credit | C57: Travel | D57: Expense | E57: Lucius Christie | F57: 21 | G57: PEC | I57: Cleared | J57: {=IF(G57="","",IFERROR(LET(ev_cost,INDEX(Events!$G$5:$G$505,MATCH(G57,Events!$A$5:$A$505,0)),ev_split,INDEX(Events!$I$5:$I$505,MATCH(G57,Events!$A$5:$A$505,0)),att_offset,MATCH(G57,Attendance!$B$3:$AV$3,0),attendees,COUNTIF(INDEX(Attendance!$B$7:$AV$206,0,att_offset),"1"),IF(ev_split="Equal Split",ev_cost/MAX(1,COUNTA(Roster!$A$5:$A$204)),ev_cost/MAX(1,attendees))),"N/A"))} -> 1310
A58: 46236 | B58: Sarah KH Car Credit | C58: Travel | D58: Expense | E58: Haley Young | F58: 21 | G58: PEC | I58: Cleared | J58: {=IF(G58="","",IFERROR(LET(ev_cost,INDEX(Events!$G$5:$G$505,MATCH(G58,Events!$A$5:$A$505,0)),ev_split,INDEX(Events!$I$5:$I$505,MATCH(G58,Events!$A$5:$A$505,0)),att_offset,MATCH(G58,Attendance!$B$3:$AV$3,0),attendees,COUNTIF(INDEX(Attendance!$B$7:$AV$206,0,att_offset),"1"),IF(ev_split="Equal Split",ev_cost/MAX(1,COUNTA(Roster!$A$5:$A$204)),ev_cost/MAX(1,attendees))),"N/A"))} -> 1310
A59: 46236 | B59: Sarah KH Car Credit | C59: Travel | D59: Expense | E59: Darra Reppermund | F59: 21 | G59: PEC | I59: Cleared | J59: {=IF(G59="","",IFERROR(LET(ev_cost,INDEX(Events!$G$5:$G$505,MATCH(G59,Events!$A$5:$A$505,0)),ev_split,INDEX(Events!$I$5:$I$505,MATCH(G59,Events!$A$5:$A$505,0)),att_offset,MATCH(G59,Attendance!$B$3:$AV$3,0),attendees,COUNTIF(INDEX(Attendance!$B$7:$AV$206,0,att_offset),"1"),IF(ev_split="Equal Split",ev_cost/MAX(1,COUNTA(Roster!$A$5:$A$204)),ev_cost/MAX(1,attendees))),"N/A"))} -> 1310
A60: 46267 | B60: PEC Pooled Car Fees | C60: Travel | D60: Expense | F60: 293.02 | G60: PEC | I60: Cleared | J60: {=IF(G60="","",IFERROR(LET(ev_cost,INDEX(Events!$G$5:$G$505,MATCH(G60,Events!$A$5:$A$505,0)),ev_split,INDEX(Events!$I$5:$I$505,MATCH(G60,Events!$A$5:$A$505,0)),att_offset,MATCH(G60,Attendance!$B$3:$AV$3,0),attendees,COUNTIF(INDEX(Attendance!$B$7:$AV$206,0,att_offset),"1"),IF(ev_split="Equal Split",ev_cost/MAX(1,COUNTA(Roster!$A$5:$A$204)),ev_cost/MAX(1,attendees))),"N/A"))} -> 1310
A61: 46267 | B61: SFI Pooled Car Fees | C61: Travel | D61: Expense | F61: 523.2 | G61: SFI | I61: Cleared | J61: {=IF(G61="","",IFERROR(LET(ev_cost,INDEX(Events!$G$5:$G$505,MATCH(G61,Events!$A$5:$A$505,0)),ev_split,INDEX(Events!$I$5:$I$505,MATCH(G61,Events!$A$5:$A$505,0)),att_offset,MATCH(G61,Attendance!$B$3:$AV$3,0),attendees,COUNTIF(INDEX(Attendance!$B$7:$AV$206,0,att_offset),"1"),IF(ev_split="Equal Split",ev_cost/MAX(1,COUNTA(Roster!$A$5:$A$204)),ev_cost/MAX(1,attendees))),"N/A"))} -> 1050
A62: 46267 | B62: ESC Pooled Car Fees | C62: Travel | D62: Expense | F62: 574.23 | G62: ESC | I62: Cleared | J62: {=IF(G62="","",IFERROR(LET(ev_cost,INDEX(Events!$G$5:$G$505,MATCH(G62,Events!$A$5:$A$505,0)),ev_split,INDEX(Events!$I$5:$I$505,MATCH(G62,Events!$A$5:$A$505,0)),att_offset,MATCH(G62,Attendance!$B$3:$AV$3,0),attendees,COUNTIF(INDEX(Attendance!$B$7:$AV$206,0,att_offset),"1"),IF(ev_split="Equal Split",ev_cost/MAX(1,COUNTA(Roster!$A$5:$A$204)),ev_cost/MAX(1,attendees))),"N/A"))} -> 5345.86
A63: 46199 | B63: Kindell gas + tolls | C63: Travel | D63: Expense | E63: Ryan Kindell | F63: 100.8 | G63: PEC | I63: Cleared | J63: {=IF(G63="","",IFERROR(LET(ev_cost,INDEX(Events!$G$5:$G$505,MATCH(G63,Events!$A$5:$A$505,0)),ev_split,INDEX(Events!$I$5:$I$505,MATCH(G63,Events!$A$5:$A$505,0)),att_offset,MATCH(G63,Attendance!$B$3:$AV$3,0),attendees,COUNTIF(INDEX(Attendance!$B$7:$AV$206,0,att_offset),"1"),IF(ev_split="Equal Split",ev_cost/MAX(1,COUNTA(Roster!$A$5:$A$204)),ev_cost/MAX(1,attendees))),"N/A"))} -> 1310
A64: 46228 | B64: Jake's Car Gas & Tolls | C64: Travel | D64: Expense | E64: Jake Murray | F64: 116.63 | G64: SFI | I64: Cleared | J64: {=IF(G64="","",IFERROR(LET(ev_cost,INDEX(Events!$G$5:$G$505,MATCH(G64,Events!$A$5:$A$505,0)),ev_split,INDEX(Events!$I$5:$I$505,MATCH(G64,Events!$A$5:$A$505,0)),att_offset,MATCH(G64,Attendance!$B$3:$AV$3,0),attendees,COUNTIF(INDEX(Attendance!$B$7:$AV$206,0,att_offset),"1"),IF(ev_split="Equal Split",ev_cost/MAX(1,COUNTA(Roster!$A$5:$A$204)),ev_cost/MAX(1,attendees))),"N/A"))} -> 1050
A65: 46228 | B65: Haley Car Gas & tolls | C65: Travel | D65: Expense | E65: Haley Young | F65: 106.02 | G65: SFI | I65: Cleared | J65: {=IF(G65="","",IFERROR(LET(ev_cost,INDEX(Events!$G$5:$G$505,MATCH(G65,Events!$A$5:$A$505,0)),ev_split,INDEX(Events!$I$5:$I$505,MATCH(G65,Events!$A$5:$A$505,0)),att_offset,MATCH(G65,Attendance!$B$3:$AV$3,0),attendees,COUNTIF(INDEX(Attendance!$B$7:$AV$206,0,att_offset),"1"),IF(ev_split="Equal Split",ev_cost/MAX(1,COUNTA(Roster!$A$5:$A$204)),ev_cost/MAX(1,attendees))),"N/A"))} -> 1050
A66: 46227 | B66: Kasey's car fri only gas & tolls | C66: Travel | D66: Expense | E66: Kasey Schock | F66: 55.5 | G66: SFI | I66: Cleared | J66: {=IF(G66="","",IFERROR(LET(ev_cost,INDEX(Events!$G$5:$G$505,MATCH(G66,Events!$A$5:$A$505,0)),ev_split,INDEX(Events!$I$5:$I$505,MATCH(G66,Events!$A$5:$A$505,0)),att_offset,MATCH(G66,Attendance!$B$3:$AV$3,0),attendees,COUNTIF(INDEX(Attendance!$B$7:$AV$206,0,att_offset),"1"),IF(ev_split="Equal Split",ev_cost/MAX(1,COUNTA(Roster!$A$5:$A$204)),ev_cost/MAX(1,attendees))),"N/A"))} -> 1050
A67: 46239 | B67: Griffin Car SFI Gas | C67: Travel | D67: Expense | E67: Griffin O'Neal-Freeman | F67: 80 | G67: SFI | I67: Cleared | J67: {=IF(G67="","",IFERROR(LET(ev_cost,INDEX(Events!$G$5:$G$505,MATCH(G67,Events!$A$5:$A$505,0)),ev_split,INDEX(Events!$I$5:$I$505,MATCH(G67,Events!$A$5:$A$505,0)),att_offset,MATCH(G67,Attendance!$B$3:$AV$3,0),attendees,COUNTIF(INDEX(Attendance!$B$7:$AV$206,0,att_offset),"1"),IF(ev_split="Equal Split",ev_cost/MAX(1,COUNTA(Roster!$A$5:$A$204)),ev_cost/MAX(1,attendees))),"N/A"))} -> 1050
A68: 46258 | B68: DB Car ESC Gas | C68: Travel | D68: Expense | E68: Dylan Best | F68: 90 | G68: ESC | I68: Cleared | J68: {=IF(G68="","",IFERROR(LET(ev_cost,INDEX(Events!$G$5:$G$505,MATCH(G68,Events!$A$5:$A$505,0)),ev_split,INDEX(Events!$I$5:$I$505,MATCH(G68,Events!$A$5:$A$505,0)),att_offset,MATCH(G68,Attendance!$B$3:$AV$3,0),attendees,COUNTIF(INDEX(Attendance!$B$7:$AV$206,0,att_offset),"1"),IF(ev_split="Equal Split",ev_cost/MAX(1,COUNTA(Roster!$A$5:$A$204)),ev_cost/MAX(1,attendees))),"N/A"))} -> 5345.86
A69: 46258 | B69: Dick car ESC gas | C69: Travel | D69: Expense | E69: Ryan Birchard | F69: 95.83 | G69: ESC | I69: Cleared | J69: {=IF(G69="","",IFERROR(LET(ev_cost,INDEX(Events!$G$5:$G$505,MATCH(G69,Events!$A$5:$A$505,0)),ev_split,INDEX(Events!$I$5:$I$505,MATCH(G69,Events!$A$5:$A$505,0)),att_offset,MATCH(G69,Attendance!$B$3:$AV$3,0),attendees,COUNTIF(INDEX(Attendance!$B$7:$AV$206,0,att_offset),"1"),IF(ev_split="Equal Split",ev_cost/MAX(1,COUNTA(Roster!$A$5:$A$204)),ev_cost/MAX(1,attendees))),"N/A"))} -> 5345.86
A70: 46255 | B70: Harry Gas | C70: Travel | D70: Expense | E70: Harry Park | F70: 133.19 | G70: ESC | I70: Cleared | J70: {=IF(G70="","",IFERROR(LET(ev_cost,INDEX(Events!$G$5:$G$505,MATCH(G70,Events!$A$5:$A$505,0)),ev_split,INDEX(Events!$I$5:$I$505,MATCH(G70,Events!$A$5:$A$505,0)),att_offset,MATCH(G70,Attendance!$B$3:$AV$3,0),attendees,COUNTIF(INDEX(Attendance!$B$7:$AV$206,0,att_offset),"1"),IF(ev_split="Equal Split",ev_cost/MAX(1,COUNTA(Roster!$A$5:$A$204)),ev_cost/MAX(1,attendees))),"N/A"))} -> 5345.86
A71: 46260 | B71: Annette car gas ESC | C71: Travel | D71: Expense | E71: Annette Kukunas-Piper | F71: 96.57 | G71: ESC | I71: Cleared | J71: {=IF(G71="","",IFERROR(LET(ev_cost,INDEX(Events!$G$5:$G$505,MATCH(G71,Events!$A$5:$A$505,0)),ev_split,INDEX(Events!$I$5:$I$505,MATCH(G71,Events!$A$5:$A$505,0)),att_offset,MATCH(G71,Attendance!$B$3:$AV$3,0),attendees,COUNTIF(INDEX(Attendance!$B$7:$AV$206,0,att_offset),"1"),IF(ev_split="Equal Split",ev_cost/MAX(1,COUNTA(Roster!$A$5:$A$204)),ev_cost/MAX(1,attendees))),"N/A"))} -> 5345.86
A72: 46267 | B72: Retreat - AirBNB | C72: Other | D72: Expense | E72: Vivian Shen | F72: 3780 | G72: Retreat | I72: Cleared | J72: {=IF(G72="","",IFERROR(LET(ev_cost,INDEX(Events!$G$5:$G$505,MATCH(G72,Events!$A$5:$A$505,0)),ev_split,INDEX(Events!$I$5:$I$505,MATCH(G72,Events!$A$5:$A$505,0)),att_offset,MATCH(G72,Attendance!$B$3:$AV$3,0),attendees,COUNTIF(INDEX(Attendance!$B$7:$AV$206,0,att_offset),"1"),IF(ev_split="Equal Split",ev_cost/MAX(1,COUNTA(Roster!$A$5:$A$204)),ev_cost/MAX(1,attendees))),"N/A"))} -> 9054.59
A73: 46267 | B73: Retreat - Duffy | C73: Other | D73: Expense | E73: Matt Duffy | F73: 51 | G73: Retreat | I73: Cleared | J73: {=IF(G73="","",IFERROR(LET(ev_cost,INDEX(Events!$G$5:$G$505,MATCH(G73,Events!$A$5:$A$505,0)),ev_split,INDEX(Events!$I$5:$I$505,MATCH(G73,Events!$A$5:$A$505,0)),att_offset,MATCH(G73,Attendance!$B$3:$AV$3,0),attendees,COUNTIF(INDEX(Attendance!$B$7:$AV$206,0,att_offset),"1"),IF(ev_split="Equal Split",ev_cost/MAX(1,COUNTA(Roster!$A$5:$A$204)),ev_cost/MAX(1,attendees))),"N/A"))} -> 9054.59
A74: 46267 | B74: Retreat - Slynch | C74: Other | D74: Expense | E74: Sarah Lynch | F74: 92.39 | G74: Retreat | I74: Cleared | J74: {=IF(G74="","",IFERROR(LET(ev_cost,INDEX(Events!$G$5:$G$505,MATCH(G74,Events!$A$5:$A$505,0)),ev_split,INDEX(Events!$I$5:$I$505,MATCH(G74,Events!$A$5:$A$505,0)),att_offset,MATCH(G74,Attendance!$B$3:$AV$3,0),attendees,COUNTIF(INDEX(Attendance!$B$7:$AV$206,0,att_offset),"1"),IF(ev_split="Equal Split",ev_cost/MAX(1,COUNTA(Roster!$A$5:$A$204)),ev_cost/MAX(1,attendees))),"N/A"))} -> 9054.59
A75: 46267 | B75: Retreat - Annette | C75: Other | D75: Expense | E75: Annette Kukunas-Piper | F75: 43.75 | G75: Retreat | I75: Cleared | J75: {=IF(G75="","",IFERROR(LET(ev_cost,INDEX(Events!$G$5:$G$505,MATCH(G75,Events!$A$5:$A$505,0)),ev_split,INDEX(Events!$I$5:$I$505,MATCH(G75,Events!$A$5:$A$505,0)),att_offset,MATCH(G75,Attendance!$B$3:$AV$3,0),attendees,COUNTIF(INDEX(Attendance!$B$7:$AV$206,0,att_offset),"1"),IF(ev_split="Equal Split",ev_cost/MAX(1,COUNTA(Roster!$A$5:$A$204)),ev_cost/MAX(1,attendees))),"N/A"))} -> 9054.59
A76: 46267 | B76: Retreat - Dudley | C76: Other | D76: Expense | E76: Kristin Dudley | F76: =38.41+198.54 -> 236.95 | G76: Retreat | I76: Cleared | J76: {=IF(G76="","",IFERROR(LET(ev_cost,INDEX(Events!$G$5:$G$505,MATCH(G76,Events!$A$5:$A$505,0)),ev_split,INDEX(Events!$I$5:$I$505,MATCH(G76,Events!$A$5:$A$505,0)),att_offset,MATCH(G76,Attendance!$B$3:$AV$3,0),attendees,COUNTIF(INDEX(Attendance!$B$7:$AV$206,0,att_offset),"1"),IF(ev_split="Equal Split",ev_cost/MAX(1,COUNTA(Roster!$A$5:$A$204)),ev_cost/MAX(1,attendees))),"N/A"))} -> 9054.59
A77: 46267 | B77: Retreat - Ian | C77: Other | D77: Expense | E77: Ian Piper | F77: 23.87 | G77: Retreat | I77: Cleared | J77: {=IF(G77="","",IFERROR(LET(ev_cost,INDEX(Events!$G$5:$G$505,MATCH(G77,Events!$A$5:$A$505,0)),ev_split,INDEX(Events!$I$5:$I$505,MATCH(G77,Events!$A$5:$A$505,0)),att_offset,MATCH(G77,Attendance!$B$3:$AV$3,0),attendees,COUNTIF(INDEX(Attendance!$B$7:$AV$206,0,att_offset),"1"),IF(ev_split="Equal Split",ev_cost/MAX(1,COUNTA(Roster!$A$5:$A$204)),ev_cost/MAX(1,attendees))),"N/A"))} -> 9054.59
A78: 46267 | B78: Retreat - Tofu | C78: Other | D78: Expense | E78: Alex Warrington | F78: 180 | G78: Retreat | I78: Cleared | J78: {=IF(G78="","",IFERROR(LET(ev_cost,INDEX(Events!$G$5:$G$505,MATCH(G78,Events!$A$5:$A$505,0)),ev_split,INDEX(Events!$I$5:$I$505,MATCH(G78,Events!$A$5:$A$505,0)),att_offset,MATCH(G78,Attendance!$B$3:$AV$3,0),attendees,COUNTIF(INDEX(Attendance!$B$7:$AV$206,0,att_offset),"1"),IF(ev_split="Equal Split",ev_cost/MAX(1,COUNTA(Roster!$A$5:$A$204)),ev_cost/MAX(1,attendees))),"N/A"))} -> 9054.59
A79: 46267 | B79: Retreat - Griff | C79: Other | D79: Expense | E79: Griffin O'Neal-Freeman | F79: 121.45 | G79: Retreat | I79: Cleared | J79: {=IF(G79="","",IFERROR(LET(ev_cost,INDEX(Events!$G$5:$G$505,MATCH(G79,Events!$A$5:$A$505,0)),ev_split,INDEX(Events!$I$5:$I$505,MATCH(G79,Events!$A$5:$A$505,0)),att_offset,MATCH(G79,Attendance!$B$3:$AV$3,0),attendees,COUNTIF(INDEX(Attendance!$B$7:$AV$206,0,att_offset),"1"),IF(ev_split="Equal Split",ev_cost/MAX(1,COUNTA(Roster!$A$5:$A$204)),ev_cost/MAX(1,attendees))),"N/A"))} -> 9054.59
A80: 46267 | B80: Retreat - Full Cost | C80: Other | D80: Expense | F80: 3417.82 | G80: Retreat | I80: Cleared | J80: {=IF(G80="","",IFERROR(LET(ev_cost,INDEX(Events!$G$5:$G$505,MATCH(G80,Events!$A$5:$A$505,0)),ev_split,INDEX(Events!$I$5:$I$505,MATCH(G80,Events!$A$5:$A$505,0)),att_offset,MATCH(G80,Attendance!$B$3:$AV$3,0),attendees,COUNTIF(INDEX(Attendance!$B$7:$AV$206,0,att_offset),"1"),IF(ev_split="Equal Split",ev_cost/MAX(1,COUNTA(Roster!$A$5:$A$204)),ev_cost/MAX(1,attendees))),"N/A"))} -> 9054.59
A81: 46267 | B81: Retreat - Air Mattress | C81: Other | D81: Expense | F81: 834.42 | G81: Retreat | I81: Cleared | J81: {=IF(G81="","",IFERROR(LET(ev_cost,INDEX(Events!$G$5:$G$505,MATCH(G81,Events!$A$5:$A$505,0)),ev_split,INDEX(Events!$I$5:$I$505,MATCH(G81,Events!$A$5:$A$505,0)),att_offset,MATCH(G81,Attendance!$B$3:$AV$3,0),attendees,COUNTIF(INDEX(Attendance!$B$7:$AV$206,0,att_offset),"1"),IF(ev_split="Equal Split",ev_cost/MAX(1,COUNTA(Roster!$A$5:$A$204)),ev_cost/MAX(1,attendees))),"N/A"))} -> 9054.59
A82: 46267 | B82: Retreat - One Night | C82: Other | D82: Expense | F82: 107.94 | G82: Retreat | I82: Cleared | J82: {=IF(G82="","",IFERROR(LET(ev_cost,INDEX(Events!$G$5:$G$505,MATCH(G82,Events!$A$5:$A$505,0)),ev_split,INDEX(Events!$I$5:$I$505,MATCH(G82,Events!$A$5:$A$505,0)),att_offset,MATCH(G82,Attendance!$B$3:$AV$3,0),attendees,COUNTIF(INDEX(Attendance!$B$7:$AV$206,0,att_offset),"1"),IF(ev_split="Equal Split",ev_cost/MAX(1,COUNTA(Roster!$A$5:$A$204)),ev_cost/MAX(1,attendees))),"N/A"))} -> 9054.59
A83: 46267 | B83: Retreat - Last Minute Drop | C83: Other | D83: Expense | F83: 140 | G83: Retreat | I83: Cleared | J83: {=IF(G83="","",IFERROR(LET(ev_cost,INDEX(Events!$G$5:$G$505,MATCH(G83,Events!$A$5:$A$505,0)),ev_split,INDEX(Events!$I$5:$I$505,MATCH(G83,Events!$A$5:$A$505,0)),att_offset,MATCH(G83,Attendance!$B$3:$AV$3,0),attendees,COUNTIF(INDEX(Attendance!$B$7:$AV$206,0,att_offset),"1"),IF(ev_split="Equal Split",ev_cost/MAX(1,COUNTA(Roster!$A$5:$A$204)),ev_cost/MAX(1,attendees))),"N/A"))} -> 9054.59
A84: 46267 | B84: Retreat - Drop | C84: Other | D84: Expense | F84: 25 | G84: Retreat | I84: Cleared | J84: {=IF(G84="","",IFERROR(LET(ev_cost,INDEX(Events!$G$5:$G$505,MATCH(G84,Events!$A$5:$A$505,0)),ev_split,INDEX(Events!$I$5:$I$505,MATCH(G84,Events!$A$5:$A$505,0)),att_offset,MATCH(G84,Attendance!$B$3:$AV$3,0),attendees,COUNTIF(INDEX(Attendance!$B$7:$AV$206,0,att_offset),"1"),IF(ev_split="Equal Split",ev_cost/MAX(1,COUNTA(Roster!$A$5:$A$204)),ev_cost/MAX(1,attendees))),"N/A"))} -> 9054.59
A85: 46267 | B85: Jenna Dues | C85: Dues | D85: Income | E85: Jenna Nold | F85: 300 | H85: Jake Murray | I85: Cleared | J85: {=IF(G85="","",IFERROR(LET(ev_cost,INDEX(Events!$G$5:$G$505,MATCH(G85,Events!$A$5:$A$505,0)),ev_split,INDEX(Events!$I$5:$I$505,MATCH(G85,Events!$A$5:$A$505,0)),att_offset,MATCH(G85,Attendance!$B$3:$AV$3,0),attendees,COUNTIF(INDEX(Attendance!$B$7:$AV$206,0,att_offset),"1"),IF(ev_split="Equal Split",ev_cost/MAX(1,COUNTA(Roster!$A$5:$A$204)),ev_cost/MAX(1,attendees))),"N/A"))}
A86: 46267 | B86: Post-ESC Reimbursement | C86: Dues | D86: Reimbursement | E86: Jake Murray | F86: 3027.12 | H86: Harry Park | I86: Cleared | J86: {=IF(G86="","",IFERROR(LET(ev_cost,INDEX(Events!$G$5:$G$505,MATCH(G86,Events!$A$5:$A$505,0)),ev_split,INDEX(Events!$I$5:$I$505,MATCH(G86,Events!$A$5:$A$505,0)),att_offset,MATCH(G86,Attendance!$B$3:$AV$3,0),attendees,COUNTIF(INDEX(Attendance!$B$7:$AV$206,0,att_offset),"1"),IF(ev_split="Equal Split",ev_cost/MAX(1,COUNTA(Roster!$A$5:$A$204)),ev_cost/MAX(1,attendees))),"N/A"))}
A87: 46201 | B87: Kevin car gas | C87: Travel | D87: Expense | E87: Kevin Nicholl | F87: 108.22 | G87: PEC | I87: Cleared | J87: {=IF(G87="","",IFERROR(LET(ev_cost,INDEX(Events!$G$5:$G$505,MATCH(G87,Events!$A$5:$A$505,0)),ev_split,INDEX(Events!$I$5:$I$505,MATCH(G87,Events!$A$5:$A$505,0)),att_offset,MATCH(G87,Attendance!$B$3:$AV$3,0),attendees,COUNTIF(INDEX(Attendance!$B$7:$AV$206,0,att_offset),"1"),IF(ev_split="Equal Split",ev_cost/MAX(1,COUNTA(Roster!$A$5:$A$204)),ev_cost/MAX(1,attendees))),"N/A"))} -> 1310
A88: 46227 | B88: Kevin car gas | C88: Travel | D88: Expense | E88: Kevin Nicholl | F88: 37.22 | G88: SFI | I88: Cleared | J88: {=IF(G88="","",IFERROR(LET(ev_cost,INDEX(Events!$G$5:$G$505,MATCH(G88,Events!$A$5:$A$505,0)),ev_split,INDEX(Events!$I$5:$I$505,MATCH(G88,Events!$A$5:$A$505,0)),att_offset,MATCH(G88,Attendance!$B$3:$AV$3,0),attendees,COUNTIF(INDEX(Attendance!$B$7:$AV$206,0,att_offset),"1"),IF(ev_split="Equal Split",ev_cost/MAX(1,COUNTA(Roster!$A$5:$A$204)),ev_cost/MAX(1,attendees))),"N/A"))} -> 1050
A89: 46228 | B89: Kindell car gas + tolls | C89: Travel | D89: Expense | E89: Ryan Kindell | F89: 127.83 | G89: SFI | I89: Cleared | J89: {=IF(G89="","",IFERROR(LET(ev_cost,INDEX(Events!$G$5:$G$505,MATCH(G89,Events!$A$5:$A$505,0)),ev_split,INDEX(Events!$I$5:$I$505,MATCH(G89,Events!$A$5:$A$505,0)),att_offset,MATCH(G89,Attendance!$B$3:$AV$3,0),attendees,COUNTIF(INDEX(Attendance!$B$7:$AV$206,0,att_offset),"1"),IF(ev_split="Equal Split",ev_cost/MAX(1,COUNTA(Roster!$A$5:$A$204)),ev_cost/MAX(1,attendees))),"N/A"))} -> 1050
A90: 46257 | B90: Kindell car gas (return trip) | C90: Travel | D90: Expense | E90: Ryan Kindell | F90: 43.52 | G90: ESC | I90: Cleared | J90: {=IF(G90="","",IFERROR(LET(ev_cost,INDEX(Events!$G$5:$G$505,MATCH(G90,Events!$A$5:$A$505,0)),ev_split,INDEX(Events!$I$5:$I$505,MATCH(G90,Events!$A$5:$A$505,0)),att_offset,MATCH(G90,Attendance!$B$3:$AV$3,0),attendees,COUNTIF(INDEX(Attendance!$B$7:$AV$206,0,att_offset),"1"),IF(ev_split="Equal Split",ev_cost/MAX(1,COUNTA(Roster!$A$5:$A$204)),ev_cost/MAX(1,attendees))),"N/A"))} -> 5345.86
A91: 46278 | B91: Pool Party Pizza | C91: Other | D91: Credit | E91: Jake Murray | F91: 185.53 | G91: Misc | H91: Darra Reppermund | I91: Cleared | J91: {=IF(G91="","",IFERROR(LET(ev_cost,INDEX(Events!$G$5:$G$505,MATCH(G91,Events!$A$5:$A$505,0)),ev_split,INDEX(Events!$I$5:$I$505,MATCH(G91,Events!$A$5:$A$505,0)),att_offset,MATCH(G91,Attendance!$B$3:$AV$3,0),attendees,COUNTIF(INDEX(Attendance!$B$7:$AV$206,0,att_offset),"1"),IF(ev_split="Equal Split",ev_cost/MAX(1,COUNTA(Roster!$A$5:$A$204)),ev_cost/MAX(1,attendees))),"N/A"))} -> 0
A92: 46277 | B92: Sectionals team snacks | C92: Equipment | D92: Expense | E92: Darra Reppermund | F92: 10.85 | G92: Sectionals | J92: {=IF(G92="","",IFERROR(LET(ev_cost,INDEX(Events!$G$5:$G$505,MATCH(G92,Events!$A$5:$A$505,0)),ev_split,INDEX(Events!$I$5:$I$505,MATCH(G92,Events!$A$5:$A$505,0)),att_offset,MATCH(G92,Attendance!$B$3:$AV$3,0),attendees,COUNTIF(INDEX(Attendance!$B$7:$AV$206,0,att_offset),"1"),IF(ev_split="Equal Split",ev_cost/MAX(1,COUNTA(Roster!$A$5:$A$204)),ev_cost/MAX(1,attendees))),"N/A"))} -> 560.85
A93: 46288 | B93: Regionals team snacks | C93: Equipment | D93: Expense | E93: Darra Reppermund | F93: 84.36 | G93: Regionals | J93: {=IF(G93="","",IFERROR(LET(ev_cost,INDEX(Events!$G$5:$G$505,MATCH(G93,Events!$A$5:$A$505,0)),ev_split,INDEX(Events!$I$5:$I$505,MATCH(G93,Events!$A$5:$A$505,0)),att_offset,MATCH(G93,Attendance!$B$3:$AV$3,0),attendees,COUNTIF(INDEX(Attendance!$B$7:$AV$206,0,att_offset),"1"),IF(ev_split="Equal Split",ev_cost/MAX(1,COUNTA(Roster!$A$5:$A$204)),ev_cost/MAX(1,attendees))),"N/A"))} -> 5965.16
B94: Regionals Hotels | C94: Hotel | D94: Expense | E94: Shani Rosenthal | F94: 4741.06 | G94: Regionals | J94: {=IF(G94="","",IFERROR(LET(ev_cost,INDEX(Events!$G$5:$G$505,MATCH(G94,Events!$A$5:$A$505,0)),ev_split,INDEX(Events!$I$5:$I$505,MATCH(G94,Events!$A$5:$A$505,0)),att_offset,MATCH(G94,Attendance!$B$3:$AV$3,0),attendees,COUNTIF(INDEX(Attendance!$B$7:$AV$206,0,att_offset),"1"),IF(ev_split="Equal Split",ev_cost/MAX(1,COUNTA(Roster!$A$5:$A$204)),ev_cost/MAX(1,attendees))),"N/A"))} -> 5965.16
A95: 46295 | B95: Regionals laundry | C95: Other | D95: Expense | E95: Annette Kukunas-Piper | F95: 8.5 | G95: Regionals | J95: {=IF(G95="","",IFERROR(LET(ev_cost,INDEX(Events!$G$5:$G$505,MATCH(G95,Events!$A$5:$A$505,0)),ev_split,INDEX(Events!$I$5:$I$505,MATCH(G95,Events!$A$5:$A$505,0)),att_offset,MATCH(G95,Attendance!$B$3:$AV$3,0),attendees,COUNTIF(INDEX(Attendance!$B$7:$AV$206,0,att_offset),"1"),IF(ev_split="Equal Split",ev_cost/MAX(1,COUNTA(Roster!$A$5:$A$204)),ev_cost/MAX(1,attendees))),"N/A"))} -> 5965.16
B96: Shani Car Gas | C96: Travel | D96: Expense | E96: Shani Rosenthal | F96: 117.91 | G96: Regionals | J96: {=IF(G96="","",IFERROR(LET(ev_cost,INDEX(Events!$G$5:$G$505,MATCH(G96,Events!$A$5:$A$505,0)),ev_split,INDEX(Events!$I$5:$I$505,MATCH(G96,Events!$A$5:$A$505,0)),att_offset,MATCH(G96,Attendance!$B$3:$AV$3,0),attendees,COUNTIF(INDEX(Attendance!$B$7:$AV$206,0,att_offset),"1"),IF(ev_split="Equal Split",ev_cost/MAX(1,COUNTA(Roster!$A$5:$A$204)),ev_cost/MAX(1,attendees))),"N/A"))} -> 5965.16
B97: Shani Car Tolls | C97: Travel | D97: Expense | E97: Shani Rosenthal | F97: 32.78 | G97: Regionals | J97: {=IF(G97="","",IFERROR(LET(ev_cost,INDEX(Events!$G$5:$G$505,MATCH(G97,Events!$A$5:$A$505,0)),ev_split,INDEX(Events!$I$5:$I$505,MATCH(G97,Events!$A$5:$A$505,0)),att_offset,MATCH(G97,Attendance!$B$3:$AV$3,0),attendees,COUNTIF(INDEX(Attendance!$B$7:$AV$206,0,att_offset),"1"),IF(ev_split="Equal Split",ev_cost/MAX(1,COUNTA(Roster!$A$5:$A$204)),ev_cost/MAX(1,attendees))),"N/A"))} -> 5965.16
B98: Shani Car Parking | C98: Travel | D98: Expense | E98: Shani Rosenthal | F98: 30.55 | G98: Regionals | J98: {=IF(G98="","",IFERROR(LET(ev_cost,INDEX(Events!$G$5:$G$505,MATCH(G98,Events!$A$5:$A$505,0)),ev_split,INDEX(Events!$I$5:$I$505,MATCH(G98,Events!$A$5:$A$505,0)),att_offset,MATCH(G98,Attendance!$B$3:$AV$3,0),attendees,COUNTIF(INDEX(Attendance!$B$7:$AV$206,0,att_offset),"1"),IF(ev_split="Equal Split",ev_cost/MAX(1,COUNTA(Roster!$A$5:$A$204)),ev_cost/MAX(1,attendees))),"N/A"))} -> 5965.16
B99: Kasey SFI & ESC Hotel Credit | C99: Hotel | D99: Adjustment | F99: =(121 + 100) / 2 -> 110.5 | G99: ESC | H99: Kasey Schock | J99: {=IF(G99="","",IFERROR(LET(ev_cost,INDEX(Events!$G$5:$G$505,MATCH(G99,Events!$A$5:$A$505,0)),ev_split,INDEX(Events!$I$5:$I$505,MATCH(G99,Events!$A$5:$A$505,0)),att_offset,MATCH(G99,Attendance!$B$3:$AV$3,0),attendees,COUNTIF(INDEX(Attendance!$B$7:$AV$206,0,att_offset),"1"),IF(ev_split="Equal Split",ev_cost/MAX(1,COUNTA(Roster!$A$5:$A$204)),ev_cost/MAX(1,attendees))),"N/A"))} -> 5345.86
A100: 46303 | B100: Nationals Bid Fee | C100: Tournament Fee | D100: Expense | E100: Jake Murray | F100: 7150 | G100: Nationals | J100: {=IF(G100="","",IFERROR(LET(ev_cost,INDEX(Events!$G$5:$G$505,MATCH(G100,Events!$A$5:$A$505,0)),ev_split,INDEX(Events!$I$5:$I$505,MATCH(G100,Events!$A$5:$A$505,0)),att_offset,MATCH(G100,Attendance!$B$3:$AV$3,0),attendees,COUNTIF(INDEX(Attendance!$B$7:$AV$206,0,att_offset),"1"),IF(ev_split="Equal Split",ev_cost/MAX(1,COUNTA(Roster!$A$5:$A$204)),ev_cost/MAX(1,attendees))),"N/A"))} -> 7150
A101: 46267 | B101: Kit Dues | C101: Dues | D101: Income | E101: Kit Asterin | F101: 781.37 | H101: Jake Murray | J101: {=IF(G101="","",IFERROR(LET(ev_cost,INDEX(Events!$G$5:$G$505,MATCH(G101,Events!$A$5:$A$505,0)),ev_split,INDEX(Events!$I$5:$I$505,MATCH(G101,Events!$A$5:$A$505,0)),att_offset,MATCH(G101,Attendance!$B$3:$AV$3,0),attendees,COUNTIF(INDEX(Attendance!$B$7:$AV$206,0,att_offset),"1"),IF(ev_split="Equal Split",ev_cost/MAX(1,COUNTA(Roster!$A$5:$A$204)),ev_cost/MAX(1,attendees))),"N/A"))}
A102: 46268 | B102: Darra Dues | C102: Dues | D102: Income | E102: Darra Reppermund | F102: 327.18 | H102: Jake Murray | J102: {=IF(G102="","",IFERROR(LET(ev_cost,INDEX(Events!$G$5:$G$505,MATCH(G102,Events!$A$5:$A$505,0)),ev_split,INDEX(Events!$I$5:$I$505,MATCH(G102,Events!$A$5:$A$505,0)),att_offset,MATCH(G102,Attendance!$B$3:$AV$3,0),attendees,COUNTIF(INDEX(Attendance!$B$7:$AV$206,0,att_offset),"1"),IF(ev_split="Equal Split",ev_cost/MAX(1,COUNTA(Roster!$A$5:$A$204)),ev_cost/MAX(1,attendees))),"N/A"))}
A103: 46269 | B103: Graber Dues | C103: Dues | D103: Income | E103: Rachel Graber | F103: 200 | H103: Jake Murray | J103: {=IF(G103="","",IFERROR(LET(ev_cost,INDEX(Events!$G$5:$G$505,MATCH(G103,Events!$A$5:$A$505,0)),ev_split,INDEX(Events!$I$5:$I$505,MATCH(G103,Events!$A$5:$A$505,0)),att_offset,MATCH(G103,Attendance!$B$3:$AV$3,0),attendees,COUNTIF(INDEX(Attendance!$B$7:$AV$206,0,att_offset),"1"),IF(ev_split="Equal Split",ev_cost/MAX(1,COUNTA(Roster!$A$5:$A$204)),ev_cost/MAX(1,attendees))),"N/A"))}
...

Sheet Nationals Fundraising
A1: Random Venmo Donations | D1: Total | F1: Cork Harbor Event
A2: Mike Y | B2: =8.88+11.11 -> 19.99 | D2: =SUM(B:B) -> 3792.99 | F2: Note | G2: From | H2: To | I2: Amount (total) | K2: Total Venmo From Cork Harbor
A3: Justin Murray | B3: 50 | F3: Kira and taha anime pig shirt | G3: Kira Udyawar | H3: Jacob Murray | I3: + $40.00 | J3: =INT(I3) -> 40 | K3: =sum(J:J)-sum(N:N) -> 735
A4: Jeannine Opie | B4: 25 | F4: Oink oink San Diego | G4: Charles Forster | H4: Jacob Murray | I4: + $20.00 | J4: =INT(I4) -> 20
A5: Lily Nong | B5: 10 | F5: 馃 | G5: Jesse Puglin | H5: Jacob Murray | I5: + $20.00 | J5: =INT(I5) -> 20
A6: Drew Rose | B6: 20 | F6: Port sticker | G6: Sophie Smith | H6: Jacob Murray | I6: + $1.00 | J6: =INT(I6) -> 1
F7: raffle! | G7: Jenna Nold | H7: Jacob Murray | I7: + $20.00 | J7: =INT(I7) -> 20
F8: Raffle | G8: Shannon Haupt | H8: Jacob Murray | I8: + $10.00 | J8: =INT(I8) -> 10
F9: Ticket | G9: Quincy Washington | H9: Jacob Murray | I9: + $10.00 | J9: =INT(I9) -> 10 | M9: Taha | N9: 20
F10: T shirt 2 | G10: Lily Nguyen | H10: Jacob Murray | I10: + $20.00 | J10: =INT(I10) -> 20 | M10: Kira | N10: 20
A11: GoFundMe | F11: Tshirt | G11: Lily Nguyen | H11: Jacob Murray | I11: + $20.00 | J11: =INT(I11) -> 20 | M11: Lily | N11: 20
A12: Griffin | B12: 3668 | F12: 馃惙馃惙 | G12: Harrison Findley | H12: Jacob Murray | I12: + $25.00 | J12: =INT(I12) -> 25 | M12: Kindell | N12: 20
F13: Earrings and sticker | G13: Katie Spence | H13: Jacob Murray | I13: + $6.00 | J13: =INT(I13) -> 6 | M13: Ben | N13: 20
F14: Port Fundraiser | G14: Daniel McGann | H14: Jacob Murray | I14: + $10.00 | J14: =INT(I14) -> 10 | M14: Madi | N14: 20
F15: Raffle | G15: Ryan Ward | H15: Jacob Murray | I15: + $10.00 | J15: =INT(I15) -> 10 | M15: Harrison | N15: 20
F16: 馃殞 | G16: Nayana Suvarna | H16: Jacob Murray | I16: + $10.00 | J16: =INT(I16) -> 10 | M16: Jesse | N16: 20
F17: Frisbe | G17: Swapnil Pande | H17: Jacob Murray | I17: + $10.00 | J17: =INT(I17) -> 10 | M17: Josh | N17: 20
F18: T-shirt and sticker | G18: Ben Meyers | H18: Jacob Murray | I18: + $21.00 | J18: =INT(I18) -> 21
F19: Ticket | G19: Henry Braun | H19: Jacob Murray | I19: + $5.00 | J19: =INT(I19) -> 5
F20: 馃惙 | G20: Harrison Findley | H20: Jacob Murray | I20: + $2.00 | J20: =INT(I20) -> 2
F21: Stickers | G21: Kira Udyawar | H21: Jacob Murray | I21: + $3.00 | J21: =INT(I21) -> 3
F22: Stickerrr | G22: Griffin O'Neal-Freeman | H22: Jacob Murray | I22: + $2.00 | J22: =INT(I22) -> 2
F23: Stickers | G23: Taha Udyawar | H23: Jacob Murray | I23: + $2.00 | J23: =INT(I23) -> 2
F24: Port raffle | G24: Taha Udyawar | H24: Jacob Murray | I24: + $20.00 | J24: =INT(I24) -> 20
F25: Tickets! | G25: Sarah Lynch | H25: Jacob Murray | I25: + $20.00 | J25: =INT(I25) -> 20
F26: Pork | G26: Kara Mariani | H26: Jacob Murray | I26: + $20.00 | J26: =INT(I26) -> 20
F27: Armspan | G27: Joseph Merante | H27: Jacob Murray | I27: + $20.00 | J27: =INT(I27) -> 20
F28: Raffle | G28: Priyanka Tewani | H28: Jacob Murray | I28: + $5.00 | J28: =INT(I28) -> 5
F29: Pig earring and raffle tickets | G29: Makenzie Priest | H29: Jacob Murray | I29: + $23.00 | J29: =INT(I29) -> 23
... F37: Port raffle and things | G37: Jeannine Opie | H37: Jacob Murray | I37: + $24.00 | J37: =INT(I37) -> 24
F38: Cash from Kasey | G38: Kasey Schock | H38: Jacob Murray | J38: 96
F39: Venmo | G39: Tanner Fitzgerald | H39: Jacob Murray | I39: + $280.00 | J39: =INT(I39) -> 280

Sheet Player Balances
A1: PLAYER BALANCES - Individual Ledger
A3: Total Owed TO Team | B3: Total Owed BY Team | C3: Net | D3: Settled | E3: Unsettled
A4: =SUMIF(E7:E206,">0",E7:E206) -> 0 | B4: =SUMIF(E7:E206,"<0",E7:E206) -> -50663.78 | C4: =SUM(E7:E206) -> -50663.78 | D4: =COUNTIF(F7:F206,"Settled") -> 8 | E4: =COUNTIF(F7:F206,"Unsettled") -> 30
A6: Player Name | B6: Total Charged ($) | C6: Total Paid ($) | D6: Paid Upfront For Team ($) | E6: Net Balance ($) | F6: Status | G6: Credits Applied ($)
A7: =IF(Roster!$A$5<>"",Roster!$A$5,"") -> At | B7: {=IF(A7<>"",IFERROR(SUMPRODUCT((INDEX(Attendance!$B$7:$EE$206,MATCH(A7,Attendance!$A$7:$A$206,0),0)=1)*Attendance!$B$4:$EE$4),0),"")} -> 0 | C7: =IF(A7<>"",SUMIFS(Transactions!$F$7:$F$989,Transactions!$D$7:$D$989,"Income",Transactions!$E$7:$E$989,A7),"") -> 470.58 | D7: =IF(A7<>"",SUMIFS(Transactions!$F$7:$F$989,Transactions!$D$7:$D$989,"Expense",Transactions!$E$7:$E$989,A7),"") -> 0 | E7: =IF(A7<>"",B7-C7-D7-G7,"") -> -470.58 | F7: =IF(A7<>"",IF(E7=0,"Settled","Unsettled"),"") -> Unsettled | G7: =IF(A7<>"",SUMIFS(Transactions!$F$7:$F$989,Transactions!$D$7:$D$989,"Credit",Transactions!$H$7:$H$989,A7),"") -> 0
A8: =IF(Roster!$A$6<>"",Roster!$A$6,"") -> Alex Warrington | B8: {=IF(A8<>"",IFERROR(SUMPRODUCT((INDEX(Attendance!$B$7:$EE$206,MATCH(A8,Attendance!$A$7:$A$206,0),0)=1)*Attendance!$B$4:$EE$4),0),"")} -> 0 | C8: =IF(A8<>"",SUMIFS(Transactions!$F$7:$F$989,Transactions!$D$7:$D$989,"Income",Transactions!$E$7:$E$989,A8),"") -> 0 | D8: =IF(A8<>"",SUMIFS(Transactions!$F$7:$F$989,Transactions!$D$7:$D$989,"Expense",Transactions!$E$7:$E$989,A8),"") -> 180 | E8: =IF(A8<>"",B8-C8-D8-G8,"") -> -180 | F8: =IF(A8<>"",IF(E8=0,"Settled","Unsettled"),"") -> Unsettled | G8: =IF(A8<>"",SUMIFS(Transactions!$F$7:$F$989,Transactions!$D$7:$D$989,"Credit",Transactions!$H$7:$H$989,A8),"") -> 0
A9: =IF(Roster!$A$7<>"",Roster!$A$7,"") -> Chris Wohl | B9: {=IF(A9<>"",IFERROR(SUMPRODUCT((INDEX(Attendance!$B$7:$EE$206,MATCH(A9,Attendance!$A$7:$A$206,0),0)=1)*Attendance!$B$4:$EE$4),0),"")} -> 0 | C9: =IF(A9<>"",SUMIFS(Transactions!$F$7:$F$989,Transactions!$D$7:$D$989,"Income",Transactions!$E$7:$E$989,A9),"") -> 608.36 | D9: =IF(A9<>"",SUMIFS(Transactions!$F$7:$F$989,Transactions!$D$7:$D$989,"Expense",Transactions!$E$7:$E$989,A9),"") -> 0 | E9: =IF(A9<>"",B9-C9-D9-G9,"") -> -608.36 | F9: =IF(A9<>"",IF(E9=0,"Settled","Unsettled"),"") -> Unsettled | G9: =IF(A9<>"",SUMIFS(Transactions!$F$7:$F$989,Transactions!$D$7:$D$989,"Credit",Transactions!$H$7:$H$989,A9),"") -> 0
A10: =IF(Roster!$A$8<>"",Roster!$A$8,"") -> Darra Reppermund | B10: {=IF(A10<>"",IFERROR(SUMPRODUCT((INDEX(Attendance!$B$7:$EE$206,MATCH(A10,Attendance!$A$7:$A$206,0),0)=1)*Attendance!$B$4:$EE$4),0),"")} -> 0 | C10: =IF(A10<>"",SUMIFS(Transactions!$F$7:$F$989,Transactions!$D$7:$D$989,"Income",Transactions!$E$7:$E$989,A10),"") -> 628.81 | D10: =IF(A10<>"",SUMIFS(Transactions!$F$7:$F$989,Transactions!$D$7:$D$989,"Expense",Transactions!$E$7:$E$989,A10),"") -> 438.62 | E10: =IF(A10<>"",B10-C10-D10-G10,"") -> -1252.96 | F10: =IF(A10<>"",IF(E10=0,"Settled","Unsettled"),"") -> Unsettled | G10: =IF(A10<>"",SUMIFS(Transactions!$F$7:$F$989,Transactions!$D$7:$D$989,"Credit",Transactions!$H$7:$H$989,A10),"") -> 185.53
A11: =IF(Roster!$A$9<>"",Roster!$A$9,"") -> Dylan Best | B11: {=IF(A11<>"",IFERROR(SUMPRODUCT((INDEX(Attendance!$B$7:$EE$206,MATCH(A11,Attendance!$A$7:$A$206,0),0)=1)*Attendance!$B$4:$EE$4),0),"")} -> 0 | C11: =IF(A11<>"",SUMIFS(Transactions!$F$7:$F$989,Transactions!$D$7:$D$989,"Income",Transactions!$E$7:$E$989,A11),"") -> 0 | D11: =IF(A11<>"",SUMIFS(Transactions!$F$7:$F$989,Transactions!$D$7:$D$989,"Expense",Transactions!$E$7:$E$989,A11),"") -> 90 | E11: =IF(A11<>"",B11-C11-D11-G11,"") -> -118 | F11: =IF(A11<>"",IF(E11=0,"Settled","Unsettled"),"") -> Unsettled | G11: =IF(A11<>"",SUMIFS(Transactions!$F$7:$F$989,Transactions!$D$7:$D$989,"Credit",Transactions!$H$7:$H$989,A11),"") -> 28
A12: =IF(Roster!$A$10<>"",Roster!$A$10,"") -> Griffin O'Neal-Freeman | B12: {=IF(A12<>"",IFERROR(SUMPRODUCT((INDEX(Attendance!$B$7:$EE$206,MATCH(A12,Attendance!$A$7:$A$206,0),0)=1)*Attendance!$B$4:$EE$4),0),"")} -> 0 | C12: =IF(A12<>"",SUMIFS(Transactions!$F$7:$F$989,Transactions!$D$7:$D$989,"Income",Transactions!$E$7:$E$989,A12),"") -> 1447.04 | D12: =IF(A12<>"",SUMIFS(Transactions!$F$7:$F$989,Transactions!$D$7:$D$989,"Expense",Transactions!$E$7:$E$989,A12),"") -> 201.45 | E12: =IF(A12<>"",B12-C12-D12-G12,"") -> -1648.49 | F12: =IF(A12<>"",IF(E12=0,"Settled","Unsettled"),"") -> Unsettled | G12: =IF(A12<>"",SUMIFS(Transactions!$F$7:$F$989,Transactions!$D$7:$D$989,"Credit",Transactions!$H$7:$H$989,A12),"") -> 0
A13: =IF(Roster!$A$11<>"",Roster!$A$11,"") -> Haley Young | B13: {=IF(A13<>"",IFERROR(SUMPRODUCT((INDEX(Attendance!$B$7:$EE$206,MATCH(A13,Attendance!$A$7:$A$206,0),0)=1)*Attendance!$B$4:$EE$4),0),"")} -> 0 | C13: =IF(A13<>"",SUMIFS(Transactions!$F$7:$F$989,Transactions!$D$7:$D$989,"Income",Transactions!$E$7:$E$989,A13),"") -> 1188.17 | D13: =IF(A13<>"",SUMIFS(Transactions!$F$7:$F$989,Transactions!$D$7:$D$989,"Expense",Transactions!$E$7:$E$989,A13),"") -> 127.02 | E13: =IF(A13<>"",B13-C13-D13-G13,"") -> -1315.19 | F13: =IF(A13<>"",IF(E13=0,"Settled","Unsettled"),"") -> Unsettled | G13: =IF(A13<>"",SUMIFS(Transactions!$F$7:$F$989,Transactions!$D$7:$D$989,"Credit",Transactions!$H$7:$H$989,A13),"") -> 0
A14: =IF(Roster!$A$12<>"",Roster!$A$12,"") -> Harry Park | B14: {=IF(A14<>"",IFERROR(SUMPRODUCT((INDEX(Attendance!$B$7:$EE$206,MATCH(A14,Attendance!$A$7:$A$206,0),0)=1)*Attendance!$B$4:$EE$4),0),"")} -> 0 | C14: =IF(A14<>"",SUMIFS(Transactions!$F$7:$F$989,Transactions!$D$7:$D$989,"Income",Transactions!$E$7:$E$989,A14),"") -> 568.37 | D14: =IF(A14<>"",SUMIFS(Transactions!$F$7:$F$989,Transactions!$D$7:$D$989,"Expense",Transactions!$E$7:$E$989,A14),"") -> 5576.93 | E14: =IF(A14<>"",B14-C14-D14-G14,"") -> -6165.42 | F14: =IF(A14<>"",IF(E14=0,"Settled","Unsettled"),"") -> Unsettled | G14: =IF(A14<>"",SUMIFS(Transactions!$F$7:$F$989,Transactions!$D$7:$D$989,"Credit",Transactions!$H$7:$H$989,A14),"") -> 20.12
A15: =IF(Roster!$A$13<>"",Roster!$A$13,"") -> Ian Piper | B15: {=IF(A15<>"",IFERROR(SUMPRODUCT((INDEX(Attendance!$B$7:$EE$206,MATCH(A15,Attendance!$A$7:$A$206,0),0)=1)*Attendance!$B$4:$EE$4),0),"")} -> 0 | C15: =IF(A15<>"",SUMIFS(Transactions!$F$7:$F$989,Transactions!$D$7:$D$989,"Income",Transactions!$E$7:$E$989,A15),"") -> 1264.2 | D15: =IF(A15<>"",SUMIFS(Transactions!$F$7:$F$989,Transactions!$D$7:$D$989,"Expense",Transactions!$E$7:$E$989,A15),"") -> 23.87 | E15: =IF(A15<>"",B15-C15-D15-G15,"") -> -1288.07 | F15: =IF(A15<>"",IF(E15=0,"Settled","Unsettled"),"") -> Unsettled | G15: =IF(A15<>"",SUMIFS(Transactions!$F$7:$F$989,Transactions!$D$7:$D$989,"Credit",Transactions!$H$7:$H$989,A15),"") -> 0
A16: =IF(Roster!$A$14<>"",Roster!$A$14,"") -> Jake Murray | B16: {=IF(A16<>"",IFERROR(SUMPRODUCT((INDEX(Attendance!$B$7:$EE$206,MATCH(A16,Attendance!$A$7:$A$206,0),0)=1)*Attendance!$B$4:$EE$4),0),"")} -> 0 | C16: =IF(A16<>"",SUMIFS(Transactions!$F$7:$F$989,Transactions!$D$7:$D$989,"Income",Transactions!$E$7:$E$989,A16),"") -> 0 | D16: =IF(A16<>"",SUMIFS(Transactions!$F$7:$F$989,Transactions!$D$7:$D$989,"Expense",Transactions!$E$7:$E$989,A16),"") -> 14489.97 | E16: =IF(A16<>"",B16-C16-D16-G16,"") -> -14548.81 | F16: =IF(A16<>"",IF(E16=0,"Settled","Unsettled"),"") -> Unsettled | G16: =IF(A16<>"",SUMIFS(Transactions!$F$7:$F$989,Transactions!$D$7:$D$989,"Credit",Transactions!$H$7:$H$989,A16),"") -> 58.84
A17: =IF(Roster!$A$15<>"",Roster!$A$15,"") -> Jenna Nold | B17: {=IF(A17<>"",IFERROR(SUMPRODUCT((INDEX(Attendance!$B$7:$EE$206,MATCH(A17,Attendance!$A$7:$A$206,0),0)=1)*Attendance!$B$4:$EE$4),0),"")} -> 0 | C17: =IF(A17<>"",SUMIFS(Transactions!$F$7:$F$989,Transactions!$D$7:$D$989,"Income",Transactions!$E$7:$E$989,A17),"") -> 900 | D17: =IF(A17<>"",SUMIFS(Transactions!$F$7:$F$989,Transactions!$D$7:$D$989,"Expense",Transactions!$E$7:$E$989,A17),"") -> 185.69 | E17: =IF(A17<>"",B17-C17-D17-G17,"") -> -1085.69 | F17: =IF(A17<>"",IF(E17=0,"Settled","Unsettled"),"") -> Unsettled | G17: =IF(A17<>"",SUMIFS(Transactions!$F$7:$F$989,Transactions!$D$7:$D$989,"Credit",Transactions!$H$7:$H$989,A17),"") -> 0
A18: =IF(Roster!$A$16<>"",Roster!$A$16,"") -> Jimmy Towle | B18: {=IF(A18<>"",IFERROR(SUMPRODUCT((INDEX(Attendance!$B$7:$EE$206,MATCH(A18,Attendance!$A$7:$A$206,0),0)=1)*Attendance!$B$4:$EE$4),0),"")} -> 0 | C18: =IF(A18<>"",SUMIFS(Transactions!$F$7:$F$989,Transactions!$D$7:$D$989,"Income",Transactions!$E$7:$E$989,A18),"") -> 28.75 | D18: =IF(A18<>"",SUMIFS(Transactions!$F$7:$F$989,Transactions!$D$7:$D$989,"Expense",Transactions!$E$7:$E$989,A18),"") -> 0 | E18: =IF(A18<>"",B18-C18-D18-G18,"") -> -28.75 | F18: =IF(A18<>"",IF(E18=0,"Settled","Unsettled"),"") -> Unsettled | G18: =IF(A18<>"",SUMIFS(Transactions!$F$7:$F$989,Transactions!$D$7:$D$989,"Credit",Transactions!$H$7:$H$989,A18),"") -> 0
A19: =IF(Roster!$A$17<>"",Roster!$A$17,"") -> Kailey Rugani | B19: {=IF(A19<>"",IFERROR(SUMPRODUCT((INDEX(Attendance!$B$7:$EE$206,MATCH(A19,Attendance!$A$7:$A$206,0),0)=1)*Attendance!$B$4:$EE$4),0),"")} -> 0 | C19: =IF(A19<>"",SUMIFS(Transactions!$F$7:$F$989,Transactions!$D$7:$D$989,"Income",Transactions!$E$7:$E$989,A19),"") -> 0 | D19: =IF(A19<>"",SUMIFS(Transactions!$F$7:$F$989,Transactions!$D$7:$D$989,"Expense",Transactions!$E$7:$E$989,A19),"") -> 0 | E19: =IF(A19<>"",B19-C19-D19-G19,"") -> 0 | F19: =IF(A19<>"",IF(E19=0,"Settled","Unsettled"),"") -> Settled | G19: =IF(A19<>"",SUMIFS(Transactions!$F$7:$F$989,Transactions!$D$7:$D$989,"Credit",Transactions!$H$7:$H$989,A19),"") -> 0
A20: =IF(Roster!$A$18<>"",Roster!$A$18,"") -> Kasey Schock | B20: {=IF(A20<>"",IFERROR(SUMPRODUCT((INDEX(Attendance!$B$7:$EE$206,MATCH(A20,Attendance!$A$7:$A$206,0),0)=1)*Attendance!$B$4:$EE$4),0),"")} -> 0 | C20: =IF(A20<>"",SUMIFS(Transactions!$F$7:$F$989,Transactions!$D$7:$D$989,"Income",Transactions!$E$7:$E$989,A20),"") -> 954.62 | D20: =IF(A20<>"",SUMIFS(Transactions!$F$7:$F$989,Transactions!$D$7:$D$989,"Expense",Transactions!$E$7:$E$989,A20),"") -> 55.5 | E20: =IF(A20<>"",B20-C20-D20-G20,"") -> -1010.12 | F20: =IF(A20<>"",IF(E20=0,"Settled","Unsettled"),"") -> Unsettled | G20: =IF(A20<>"",SUMIFS(Transactions!$F$7:$F$989,Transactions!$D$7:$D$989,"Credit",Transactions!$H$7:$H$989,A20),"") -> 0
A21: =IF(Roster!$A$19<>"",Roster!$A$19,"") -> Kevin Nicholl | B21: {=IF(A21<>"",IFERROR(SUMPRODUCT((INDEX(Attendance!$B$7:$EE$206,MATCH(A21,Attendance!$A$7:$A$206,0),0)=1)*Attendance!$B$4:$EE$4),0),"")} -> 0 | C21: =IF(A21<>"",SUMIFS(Transactions!$F$7:$F$989,Transactions!$D$7:$D$989,"Income",Transactions!$E$7:$E$989,A21),"") -> 710.33 | D21: =IF(A21<>"",SUMIFS(Transactions!$F$7:$F$989,Transactions!$D$7:$D$989,"Expense",Transactions!$E$7:$E$989,A21),"") -> 145.44 | E21: =IF(A21<>"",B21-C21-D21-G21,"") -> -855.77 | F21: =IF(A21<>"",IF(E21=0,"Settled","Unsettled"),"") -> Unsettled | G21: =IF(A21<>"",SUMIFS(Transactions!$F$7:$F$989,Transactions!$D$7:$D$989,"Credit",Transactions!$H$7:$H$989,A21),"") -> 0
A22: =IF(Roster!$A$20<>"",Roster!$A$20,"") -> Kit Asterin | B22: {=IF(A22<>"",IFERROR(SUMPRODUCT((INDEX(Attendance!$B$7:$EE$206,MATCH(A22,Attendance!$A$7:$A$206,0),0)=1)*Attendance!$B$4:$EE$4),0),"")} -> 0 | C22: =IF(A22<>"",SUMIFS(Transactions!$F$7:$F$989,Transactions!$D$7:$D$989,"Income",Transactions!$E$7:$E$989,A22),"") -> 781.37 | D22: =IF(A22<>"",SUMIFS(Transactions!$F$7:$F$989,Transactions!$D$7:$D$989,"Expense",Transactions!$E$7:$E$989,A22),"") -> 0 | E22: =IF(A22<>"",B22-C22-D22-G22,"") -> -781.37 | F22: =IF(A22<>"",IF(E22=0,"Settled","Unsettled"),"") -> Unsettled | G22: =IF(A22<>"",SUMIFS(Transactions!$F$7:$F$989,Transactions!$D$7:$D$989,"Credit",Transactions!$H$7:$H$989,A22),"") -> 0
A23: =IF(Roster!$A$21<>"",Roster!$A$21,"") -> Kristin Dudley | B23: {=IF(A23<>"",IFERROR(SUMPRODUCT((INDEX(Attendance!$B$7:$EE$206,MATCH(A23,Attendance!$A$7:$A$206,0),0)=1)*Attendance!$B$4:$EE$4),0),"")} -> 0 | C23: =IF(A23<>"",SUMIFS(Transactions!$F$7:$F$989,Transactions!$D$7:$D$989,"Income",Transactions!$E$7:$E$989,A23),"") -> 1079.85 | D23: =IF(A23<>"",SUMIFS(Transactions!$F$7:$F$989,Transactions!$D$7:$D$989,"Expense",Transactions!$E$7:$E$989,A23),"") -> 236.95 | E23: =IF(A23<>"",B23-C23-D23-G23,"") -> -1316.8 | F23: =IF(A23<>"",IF(E23=0,"Settled","Unsettled"),"") -> Unsettled | G23: =IF(A23<>"",SUMIFS(Transactions!$F$7:$F$989,Transactions!$D$7:$D$989,"Credit",Transactions!$H$7:$H$989,A23),"") -> 0
A24: =IF(Roster!$A$22<>"",Roster!$A$22,"") -> Lexie Thomas | B24: {=IF(A24<>"",IFERROR(SUMPRODUCT((INDEX(Attendance!$B$7:$EE$206,MATCH(A24,Attendance!$A$7:$A$206,0),0)=1)*Attendance!$B$4:$EE$4),0),"")} -> 0 | C24: =IF(A24<>"",SUMIFS(Transactions!$F$7:$F$989,Transactions!$D$7:$D$989,"Income",Transactions!$E$7:$E$989,A24),"") -> 218.75 | D24: =IF(A24<>"",SUMIFS(Transactions!$F$7:$F$989,Transactions!$D$7:$D$989,"Expense",Transactions!$E$7:$E$989,A24),"") -> 0 | E24: =IF(A24<>"",B24-C24-D24-G24,"") -> -255.55 | F24: =IF(A24<>"",IF(E24=0,"Settled","Unsettled"),"") -> Unsettled | G24: =IF(A24<>"",SUMIFS(Transactions!$F$7:$F$989,Transactions!$D$7:$D$989,"Credit",Transactions!$H$7:$H$989,A24),"") -> 36.8
A25: =IF(Roster!$A$23<>"",Roster!$A$23,"") -> Lucas Jones | B25: {=IF(A25<>"",IFERROR(SUMPRODUCT((INDEX(Attendance!$B$7:$EE$206,MATCH(A25,Attendance!$A$7:$A$206,0),0)=1)*Attendance!$B$4:$EE$4),0),"")} -> 0 | C25: =IF(A25<>"",SUMIFS(Transactions!$F$7:$F$989,Transactions!$D$7:$D$989,"Income",Transactions!$E$7:$E$989,A25),"") -> 0 | D25: =IF(A25<>"",SUMIFS(Transactions!$F$7:$F$989,Transactions!$D$7:$D$989,"Expense",Transactions!$E$7:$E$989,A25),"") -> 0 | E25: =IF(A25<>"",B25-C25-D25-G25,"") -> 0 | F25: =IF(A25<>"",IF(E25=0,"Settled","Unsettled"),"") -> Settled | G25: =IF(A25<>"",SUMIFS(Transactions!$F$7:$F$989,Transactions!$D$7:$D$989,"Credit",Transactions!$H$7:$H$989,A25),"") -> 0
A26: =IF(Roster!$A$24<>"",Roster!$A$24,"") -> Max Sheppard | B26: {=IF(A26<>"",IFERROR(SUMPRODUCT((INDEX(Attendance!$B$7:$EE$206,MATCH(A26,Attendance!$A$7:$A$206,0),0)=1)*Attendance!$B$4:$EE$4),0),"")} -> 0 | C26: =IF(A26<>"",SUMIFS(Transactions!$F$7:$F$989,Transactions!$D$7:$D$989,"Income",Transactions!$E$7:$E$989,A26),"") -> 0 | D26: =IF(A26<>"",SUMIFS(Transactions!$F$7:$F$989,Transactions!$D$7:$D$989,"Expense",Transactions!$E$7:$E$989,A26),"") -> 0 | E26: =IF(A26<>"",B26-C26-D26-G26,"") -> 0 | F26: =IF(A26<>"",IF(E26=0,"Settled","Unsettled"),"") -> Settled | G26: =IF(A26<>"",SUMIFS(Transactions!$F$7:$F$989,Transactions!$D$7:$D$989,"Credit",Transactions!$H$7:$H$989,A26),"") -> 0
A27: =IF(Roster!$A$25<>"",Roster!$A$25,"") -> Lucius Christie | B27: {=IF(A27<>"",IFERROR(SUMPRODUCT((INDEX(Attendance!$B$7:$EE$206,MATCH(A27,Attendance!$A$7:$A$206,0),0)=1)*Attendance!$B$4:$EE$4),0),"")} -> 0 | C27: =IF(A27<>"",SUMIFS(Transactions!$F$7:$F$989,Transactions!$D$7:$D$989,"Income",Transactions!$E$7:$E$989,A27),"") -> 0 | D27: =IF(A27<>"",SUMIFS(Transactions!$F$7:$F$989,Transactions!$D$7:$D$989,"Expense",Transactions!$E$7:$E$989,A27),"") -> 21 | E27: =IF(A27<>"",B27-C27-D27-G27,"") -> -21 | F27: =IF(A27<>"",IF(E27=0,"Settled","Unsettled"),"") -> Unsettled | G27: =IF(A27<>"",SUMIFS(Transactions!$F$7:$F$989,Transactions!$D$7:$D$989,"Credit",Transactions!$H$7:$H$989,A27),"") -> 0
A28: =IF(Roster!$A$26<>"",Roster!$A$26,"") -> Patrick McMullen | B28: {=IF(A28<>"",IFERROR(SUMPRODUCT((INDEX(Attendance!$B$7:$EE$206,MATCH(A28,Attendance!$A$7:$A$206,0),0)=1)*Attendance!$B$4:$EE$4),0),"")} -> 0 | C28: =IF(A28<>"",SUMIFS(Transactions!$F$7:$F$989,Transactions!$D$7:$D$989,"Income",Transactions!$E$7:$E$989,A28),"") -> 1336.93 | D28: =IF(A28<>"",SUMIFS(Transactions!$F$7:$F$989,Transactions!$D$7:$D$989,"Expense",Transactions!$E$7:$E$989,A28),"") -> 0 | E28: =IF(A28<>"",B28-C28-D28-G28,"") -> -1336.93 | F28: =IF(A28<>"",IF(E28=0,"Settled","Unsettled"),"") -> Unsettled | G28: =IF(A28<>"",SUMIFS(Transactions!$F$7:$F$989,Transactions!$D$7:$D$989,"Credit",Transactions!$H$7:$H$989,A28),"") -> 0
A29: =IF(Roster!$A$27<>"",Roster!$A$27,"") -> Rachel Graber | B29: {=IF(A29<>"",IFERROR(SUMPRODUCT((INDEX(Attendance!$B$7:$EE$206,MATCH(A29,Attendance!$A$7:$A$206,0),0)=1)*Attendance!$B$4:$EE$4),0),"")} -> 0 | C29: =IF(A29<>"",SUMIFS(Transactions!$F$7:$F$989,Transactions!$D$7:$D$989,"Income",Transactions!$E$7:$E$989,A29),"") -> 602.89 | D29: =IF(A29<>"",SUMIFS(Transactions!$F$7:$F$989,Transactions!$D$7:$D$989,"Expense",Transactions!$E$7:$E$989,A29),"") -> 0 | E29: =IF(A29<>"",B29-C29-D29-G29,"") -> -602.89 | F29: =IF(A29<>"",IF(E29=0,"Settled","Unsettled"),"") -> Unsettled | G29: =IF(A29<>"",SUMIFS(Transactions!$F$7:$F$989,Transactions!$D$7:$D$989,"Credit",Transactions!$H$7:$H$989,A29),"") -> 0
A30: =IF(Roster!$A$28<>"",Roster!$A$28,"") -> Ryan Kindell | B30: {=IF(A30<>"",IFERROR(SUMPRODUCT((INDEX(Attendance!$B$7:$EE$206,MATCH(A30,Attendance!$A$7:$A$206,0),0)=1)*Attendance!$B$4:$EE$4),0),"")} -> 0 | C30: =IF(A30<>"",SUMIFS(Transactions!$F$7:$F$989,Transactions!$D$7:$D$989,"Income",Transactions!$E$7:$E$989,A30),"") -> 500 | D30: =IF(A30<>"",SUMIFS(Transactions!$F$7:$F$989,Transactions!$D$7:$D$989,"Expense",Transactions!$E$7:$E$989,A30),"") -> 272.15 | E30: =IF(A30<>"",B30-C30-D30-G30,"") -> -772.15 | F30: =IF(A30<>"",IF(E30=0,"Settled","Unsettled"),"") -> Unsettled | G30: =IF(A30<>"",SUMIFS(Transactions!$F$7:$F$989,Transactions!$D$7:$D$989,"Credit",Transactions!$H$7:$H$989,A30),"") -> 0
A31: =IF(Roster!$A$29<>"",Roster!$A$29,"") -> Ryan Ward | B31: {=IF(A31<>"",IFERROR(SUMPRODUCT((INDEX(Attendance!$B$7:$EE$206,MATCH(A31,Attendance!$A$7:$A$206,0),0)=1)*Attendance!$B$4:$EE$4),0),"")} -> 0 | C31: =IF(A31<>"",SUMIFS(Transactions!$F$7:$F$989,Transactions!$D$7:$D$989,"Income",Transactions!$E$7:$E$989,A31),"") -> 673.89 | D31: =IF(A31<>"",SUMIFS(Transactions!$F$7:$F$989,Transactions!$D$7:$D$989,"Expense",Transactions!$E$7:$E$989,A31),"") -> 202.26 | E31: =IF(A31<>"",B31-C31-D31-G31,"") -> -876.15 | F31: =IF(A31<>"",IF(E31=0,"Settled","Unsettled"),"") -> Unsettled | G31: =IF(A31<>"",SUMIFS(Transactions!$F$7:$F$989,Transactions!$D$7:$D$989,"Credit",Transactions!$H$7:$H$989,A31),"") -> 0
A32: =IF(Roster!$A$30<>"",Roster!$A$30,"") -> Sam Gombiner | B32: {=IF(A32<>"",IFERROR(SUMPRODUCT((INDEX(Attendance!$B$7:$EE$206,MATCH(A32,Attendance!$A$7:$A$206,0),0)=1)*Attendance!$B$4:$EE$4),0),"")} -> 0 | C32: =IF(A32<>"",SUMIFS(Transactions!$F$7:$F$989,Transactions!$D$7:$D$989,"Income",Transactions!$E$7:$E$989,A32),"") -> 0 | D32: =IF(A32<>"",SUMIFS(Transactions!$F$7:$F$989,Transactions!$D$7:$D$989,"Expense",Transactions!$E$7:$E$989,A32),"") -> 0 | E32: =IF(A32<>"",B32-C32-D32-G32,"") -> 0 | F32: =IF(A32<>"",IF(E32=0,"Settled","Unsettled"),"") -> Settled | G32: =IF(A32<>"",SUMIFS(Transactions!$F$7:$F$989,Transactions!$D$7:$D$989,"Credit",Transactions!$H$7:$H$989,A32),"") -> 0
A33: =IF(Roster!$A$31<>"",Roster!$A$31,"") -> Sarah Kingsley-Hart | B33: {=IF(A33<>"",IFERROR(SUMPRODUCT((INDEX(Attendance!$B$7:$EE$206,MATCH(A33,Attendance!$A$7:$A$206,0),0)=1)*Attendance!$B$4:$EE$4),0),"")} -> 0 | C33: =IF(A33<>"",SUMIFS(Transactions!$F$7:$F$989,Transactions!$D$7:$D$989,"Income",Transactions!$E$7:$E$989,A33),"") -> 249.39 | D33: =IF(A33<>"",SUMIFS(Transactions!$F$7:$F$989,Transactions!$D$7:$D$989,"Expense",Transactions!$E$7:$E$989,A33),"") -> 21 | E33: =IF(A33<>"",B33-C33-D33-G33,"") -> -270.39 | F33: =IF(A33<>"",IF(E33=0,"Settled","Unsettled"),"") -> Unsettled | G33: =IF(A33<>"",SUMIFS(Transactions!$F$7:$F$989,Transactions!$D$7:$D$989,"Credit",Transactions!$H$7:$H$989,A33),"") -> 0
A34: =IF(Roster!$A$32<>"",Roster!$A$32,"") -> Sarah Lynch | B34: {=IF(A34<>"",IFERROR(SUMPRODUCT((INDEX(Attendance!$B$7:$EE$206,MATCH(A34,Attendance!$A$7:$A$206,0),0)=1)*Attendance!$B$4:$EE$4),0),"")} -> 0 | C34: =IF(A34<>"",SUMIFS(Transactions!$F$7:$F$989,Transactions!$D$7:$D$989,"Income",Transactions!$E$7:$E$989,A34),"") -> 451.86 | D34: =IF(A34<>"",SUMIFS(Transactions!$F$7:$F$989,Transactions!$D$7:$D$989,"Expense",Transactions!$E$7:$E$989,A34),"") -> 207.51 | E34: =IF(A34<>"",B34-C34-D34-G34,"") -> -659.37 | F34: =IF(A34<>"",IF(E34=0,"Settled","Unsettled"),"") -> Unsettled | G34: =IF(A34<>"",SUMIFS(Transactions!$F$7:$F$989,Transactions!$D$7:$D$989,"Credit",Transactions!$H$7:$H$989,A34),"") -> 0
A35: =IF(Roster!$A$33<>"",Roster!$A$33,"") -> Shani Rosenthal | B35: {=IF(A35<>"",IFERROR(SUMPRODUCT((INDEX(Attendance!$B$7:$EE$206,MATCH(A35,Attendance!$A$7:$A$206,0),0)=1)*Attendance!$B$4:$EE$4),0),"")} -> 0 | C35: =IF(A35<>"",SUMIFS(Transactions!$F$7:$F$989,Transactions!$D$7:$D$989,"Income",Transactions!$E$7:$E$989,A35),"") -> 0 | D35: =IF(A35<>"",SUMIFS(Transactions!$F$7:$F$989,Transactions!$D$7:$D$989,"Expense",Transactions!$E$7:$E$989,A35),"") -> 8409.89 | E35: =IF(A35<>"",B35-C35-D35-G35,"") -> -8409.89 | F35: =IF(A35<>"",IF(E35=0,"Settled","Unsettled"),"") -> Unsettled | G35: =IF(A35<>"",SUMIFS(Transactions!$F$7:$F$989,Transactions!$D$7:$D$989,"Credit",Transactions!$H$7:$H$989,A35),"") -> 0
A36: =IF(Roster!$A$34<>"",Roster!$A$34,"") -> Vivian Shen | B36: {=IF(A36<>"",IFERROR(SUMPRODUCT((INDEX(Attendance!$B$7:$EE$206,MATCH(A36,Attendance!$A$7:$A$206,0),0)=1)*Attendance!$B$4:$EE$4),0),"")} -> 0 | C36: =IF(A36<>"",SUMIFS(Transactions!$F$7:$F$989,Transactions!$D$7:$D$989,"Income",Transactions!$E$7:$E$989,A36),"") -> 400 | D36: =IF(A36<>"",SUMIFS(Transactions!$F$7:$F$989,Transactions!$D$7:$D$989,"Expense",Transactions!$E$7:$E$989,A36),"") -> 3780 | E36: =IF(A36<>"",B36-C36-D36-G36,"") -> -4180 | F36: =IF(A36<>"",IF(E36=0,"Settled","Unsettled"),"") -> Unsettled | G36: =IF(A36<>"",SUMIFS(Transactions!$F$7:$F$989,Transactions!$D$7:$D$989,"Credit",Transactions!$H$7:$H$989,A36),"") -> 0
A37: =IF(Roster!$A$35<>"",Roster!$A$35,"") -> Zach Esakof | B37: {=IF(A37<>"",IFERROR(SUMPRODUCT((INDEX(Attendance!$B$7:$EE$206,MATCH(A37,Attendance!$A$7:$A$206,0),0)=1)*Attendance!$B$4:$EE$4),0),"")} -> 0 | C37: =IF(A37<>"",SUMIFS(Transactions!$F$7:$F$989,Transactions!$D$7:$D$989,"Income",Transactions!$E$7:$E$989,A37),"") -> 0 | D37: =IF(A37<>"",SUMIFS(Transactions!$F$7:$F$989,Transactions!$D$7:$D$989,"Expense",Transactions!$E$7:$E$989,A37),"") -> 0 | E37: =IF(A37<>"",B37-C37-D37-G37,"") -> 0 | F37: =IF(A37<>"",IF(E37=0,"Settled","Unsettled"),"") -> Settled | G37: =IF(A37<>"",SUMIFS(Transactions!$F$7:$F$989,Transactions!$D$7:$D$989,"Credit",Transactions!$H$7:$H$989,A37),"") -> 0
A38: =IF(Roster!$A$36<>"",Roster!$A$36,"") -> Annette Kukunas-Piper | B38: {=IF(A38<>"",IFERROR(SUMPRODUCT((INDEX(Attendance!$B$7:$EE$206,MATCH(A38,Attendance!$A$7:$A$206,0),0)=1)*Attendance!$B$4:$EE$4),0),"")} -> 0 | C38: =IF(A38<>"",SUMIFS(Transactions!$F$7:$F$989,Transactions!$D$7:$D$989,"Income",Transactions!$E$7:$E$989,A38),"") -> 69.31 | D38: =IF(A38<>"",SUMIFS(Transactions!$F$7:$F$989,Transactions!$D$7:$D$989,"Expense",Transactions!$E$7:$E$989,A38),"") -> 148.82 | E38: =IF(A38<>"",B38-C38-D38-G38,"") -> -218.13 | F38: =IF(A38<>"",IF(E38=0,"Settled","Unsettled"),"") -> Unsettled | G38: =IF(A38<>"",SUMIFS(Transactions!$F$7:$F$989,Transactions!$D$7:$D$989,"Credit",Transactions!$H$7:$H$989,A38),"") -> 0
A39: =IF(Roster!$A$37<>"",Roster!$A$37,"") -> Matt Duffy | B39: {=IF(A39<>"",IFERROR(SUMPRODUCT((INDEX(Attendance!$B$7:$EE$206,MATCH(A39,Attendance!$A$7:$A$206,0),0)=1)*Attendance!$B$4:$EE$4),0),"")} -> 0 | C39: =IF(A39<>"",SUMIFS(Transactions!$F$7:$F$989,Transactions!$D$7:$D$989,"Income",Transactions!$E$7:$E$989,A39),"") -> 180.13 | D39: =IF(A39<>"",SUMIFS(Transactions!$F$7:$F$989,Transactions!$D$7:$D$989,"Expense",Transactions!$E$7:$E$989,A39),"") -> 51 | E39: =IF(A39<>"",B39-C39-D39-G39,"") -> -231.13 | F39: =IF(A39<>"",IF(E39=0,"Settled","Unsettled"),"") -> Unsettled | G39: =IF(A39<>"",SUMIFS(Transactions!$F$7:$F$989,Transactions!$D$7:$D$989,"Credit",Transactions!$H$7:$H$989,A39),"") -> 0
A40: =IF(Roster!$A$38<>"",Roster!$A$38,"") -> Ryan Birchard | B40: {=IF(A40<>"",IFERROR(SUMPRODUCT((INDEX(Attendance!$B$7:$EE$206,MATCH(A40,Attendance!$A$7:$A$206,0),0)=1)*Attendance!$B$4:$EE$4),0),"")} -> 0 | C40: =IF(A40<>"",SUMIFS(Transactions!$F$7:$F$989,Transactions!$D$7:$D$989,"Income",Transactions!$E$7:$E$989,A40),"") -> 0 | D40: =IF(A40<>"",SUMIFS(Transactions!$F$7:$F$989,Transactions!$D$7:$D$989,"Expense",Transactions!$E$7:$E$989,A40),"") -> 95.83 | E40: =IF(A40<>"",B40-C40-D40-G40,"") -> -95.83 | F40: =IF(A40<>"",IF(E40=0,"Settled","Unsettled"),"") -> Unsettled | G40: =IF(A40<>"",SUMIFS(Transactions!$F$7:$F$989,Transactions!$D$7:$D$989,"Credit",Transactions!$H$7:$H$989,A40),"") -> 0
A41: =IF(Roster!$A$39<>"",Roster!$A$39,"") -> Nick Blair | B41: {=IF(A41<>"",IFERROR(SUMPRODUCT((INDEX(Attendance!$B$7:$EE$206,MATCH(A41,Attendance!$A$7:$A$206,0),0)=1)*Attendance!$B$4:$EE$4),0),"")} -> 0 | C41: =IF(A41<>"",SUMIFS(Transactions!$F$7:$F$989,Transactions!$D$7:$D$989,"Income",Transactions!$E$7:$E$989,A41),"") -> 0 | D41: =IF(A41<>"",SUMIFS(Transactions!$F$7:$F$989,Transactions!$D$7:$D$989,"Expense",Transactions!$E$7:$E$989,A41),"") -> 0 | E41: =IF(A41<>"",B41-C41-D41-G41,"") -> -59.99 | F41: =IF(A41<>"",IF(E41=0,"Settled","Unsettled"),"") -> Unsettled | G41: =IF(A41<>"",SUMIFS(Transactions!$F$7:$F$989,Transactions!$D$7:$D$989,"Credit",Transactions!$H$7:$H$989,A41),"") -> 59.99
A42: =IF(Roster!$A$40<>"",Roster!$A$40,"") -> Lily Nguyen | B42: {=IF(A42<>"",IFERROR(SUMPRODUCT((INDEX(Attendance!$B$7:$EE$206,MATCH(A42,Attendance!$A$7:$A$206,0),0)=1)*Attendance!$B$4:$EE$4),0),"")} -> 0 | C42: =IF(A42<>"",SUMIFS(Transactions!$F$7:$F$989,Transactions!$D$7:$D$989,"Income",Transactions!$E$7:$E$989,A42),"") -> 0 | D42: =IF(A42<>"",SUMIFS(Transactions!$F$7:$F$989,Transactions!$D$7:$D$989,"Expense",Transactions!$E$7:$E$989,A42),"") -> 0 | E42: =IF(A42<>"",B42-C42-D42-G42,"") -> 0 | F42: =IF(A42<>"",IF(E42=0,"Settled","Unsettled"),"") -> Settled | G42: =IF(A42<>"",SUMIFS(Transactions!$F$7:$F$989,Transactions!$D$7:$D$989,"Credit",Transactions!$H$7:$H$989,A42),"") -> 0
A43: =IF(Roster!$A$41<>"",Roster!$A$41,"") -> Griff Soren | B43: {=IF(A43<>"",IFERROR(SUMPRODUCT((INDEX(Attendance!$B$7:$EE$206,MATCH(A43,Attendance!$A$7:$A$206,0),0)=1)*Attendance!$B$4:$EE$4),0),"")} -> 0 | C43: =IF(A43<>"",SUMIFS(Transactions!$F$7:$F$989,Transactions!$D$7:$D$989,"Income",Transactions!$E$7:$E$989,A43),"") -> 0 | D43: =IF(A43<>"",SUMIFS(Transactions!$F$7:$F$989,Transactions!$D$7:$D$989,"Expense",Transactions!$E$7:$E$989,A43),"") -> 0 | E43: =IF(A43<>"",B43-C43-D43-G43,"") -> 0 | F43: =IF(A43<>"",IF(E43=0,"Settled","Unsettled"),"") -> Settled | G43: =IF(A43<>"",SUMIFS(Transactions!$F$7:$F$989,Transactions!$D$7:$D$989,"Credit",Transactions!$H$7:$H$989,A43),"") -> 0
A44: =IF(Roster!$A$42<>"",Roster!$A$42,"") -> Griff Alice | B44: {=IF(A44<>"",IFERROR(SUMPRODUCT((INDEX(Attendance!$B$7:$EE$206,MATCH(A44,Attendance!$A$7:$A$206,0),0)=1)*Attendance!$B$4:$EE$4),0),"")} -> 0 | C44: =IF(A44<>"",SUMIFS(Transactions!$F$7:$F$989,Transactions!$D$7:$D$989,"Income",Transactions!$E$7:$E$989,A44),"") -> 0 | D44: =IF(A44<>"",SUMIFS(Transactions!$F$7:$F$989,Transactions!$D$7:$D$989,"Expense",Transactions!$E$7:$E$989,A44),"") -> 0 | E44: =IF(A44<>"",B44-C44-D44-G44,"") -> 0 | F44: =IF(A44<>"",IF(E44=0,"Settled","Unsettled"),"") -> Settled | G44: =IF(A44<>"",SUMIFS(Transactions!$F$7:$F$989,Transactions!$D$7:$D$989,"Credit",Transactions!$H$7:$H$989,A44),"") -> 0
A45: =IF(Roster!$A$43<>"",Roster!$A$43,"") | B45: {=IF(A45<>"",IFERROR(SUMPRODUCT((INDEX(Attendance!$B$7:$AV$206,MATCH(A45,Attendance!$A$7:$A$206,0),0)=1)*Attendance!$B$4:$AV$4),0),"")} | C45: =IF(A45<>"",SUMIFS(Transactions!$F$7:$F$989,Transactions!$D$7:$D$989,"Income",Transactions!$E$7:$E$989,A45),"") | D45: =IF(A45<>"",SUMIFS(Transactions!$F$7:$F$989,Transactions!$D$7:$D$989,"Expense",Transactions!$E$7:$E$989,A45),"") | E45: =IF(A45<>"",B45-C45-D45-G45,"") | F45: =IF(A45<>"",IF(E45=0,"Settled","Unsettled"),"") | G45: =IF(A45<>"",SUMIFS(Transactions!$F$7:$F$989,Transactions!$D$7:$D$989,"Credit",Transactions!$H$7:$H$989,A45),"")
A46: =IF(Roster!$A$44<>"",Roster!$A$44,"") | B46: {=IF(A46<>"",IFERROR(SUMPRODUCT((INDEX(Attendance!$B$7:$AV$206,MATCH(A46,Attendance!$A$7:$A$206,0),0)=1)*Attendance!$B$4:$AV$4),0),"")} | C46: =IF(A46<>"",SUMIFS(Transactions!$F$7:$F$989,Transactions!$D$7:$D$989,"Income",Transactions!$E$7:$E$989,A46),"") | D46: =IF(A46<>"",SUMIFS(Transactions!$F$7:$F$989,Transactions!$D$7:$D$989,"Expense",Transactions!$E$7:$E$989,A46),"") | E46: =IF(A46<>"",B46-C46-D46-G46,"") | F46: =IF(A46<>"",IF(E46=0,"Settled","Unsettled"),"") | G46: =IF(A46<>"",SUMIFS(Transactions!$F$7:$F$989,Transactions!$D$7:$D$989,"Credit",Transactions!$H$7:$H$989,A46),"")
A47: =IF(Roster!$A$45<>"",Roster!$A$45,"") | B47: {=IF(A47<>"",IFERROR(SUMPRODUCT((INDEX(Attendance!$B$7:$AV$206,MATCH(A47,Attendance!$A$7:$A$206,0),0)=1)*Attendance!$B$4:$AV$4),0),"")} | C47: =IF(A47<>"",SUMIFS(Transactions!$F$7:$F$989,Transactions!$D$7:$D$989,"Income",Transactions!$E$7:$E$989,A47),"") | D47: =IF(A47<>"",SUMIFS(Transactions!$F$7:$F$989,Transactions!$D$7:$D$989,"Expense",Transactions!$E$7:$E$989,A47),"") | E47: =IF(A47<>"",B47-C47-D47-G47,"") | F47: =IF(A47<>"",IF(E47=0,"Settled","Unsettled"),"") | G47: =IF(A47<>"",SUMIFS(Transactions!$F$7:$F$989,Transactions!$D$7:$D$989,"Credit",Transactions!$H$7:$H$989,A47),"")
A48: =IF(Roster!$A$46<>"",Roster!$A$46,"") | B48: {=IF(A48<>"",IFERROR(SUMPRODUCT((INDEX(Attendance!$B$7:$AV$206,MATCH(A48,Attendance!$A$7:$A$206,0),0)=1)*Attendance!$B$4:$AV$4),0),"")} | C48: =IF(A48<>"",SUMIFS(Transactions!$F$7:$F$989,Transactions!$D$7:$D$989,"Income",Transactions!$E$7:$E$989,A48),"") | D48: =IF(A48<>"",SUMIFS(Transactions!$F$7:$F$989,Transactions!$D$7:$D$989,"Expense",Transactions!$E$7:$E$989,A48),"") | E48: =IF(A48<>"",B48-C48-D48-G48,"") | F48: =IF(A48<>"",IF(E48=0,"Settled","Unsettled"),"") | G48: =IF(A48<>"",SUMIFS(Transactions!$F$7:$F$989,Transactions!$D$7:$D$989,"Credit",Transactions!$H$7:$H$989,A48),"")
A49: =IF(Roster!$A$47<>"",Roster!$A$47,"") | B49: {=IF(A49<>"",IFERROR(SUMPRODUCT((INDEX(Attendance!$B$7:$AV$206,MATCH(A49,Attendance!$A$7:$A$206,0),0)=1)*Attendance!$B$4:$AV$4),0),"")} | C49: =IF(A49<>"",SUMIFS(Transactions!$F$7:$F$989,Transactions!$D$7:$D$989,"Income",Transactions!$E$7:$E$989,A49),"") | D49: =IF(A49<>"",SUMIFS(Transactions!$F$7:$F$989,Transactions!$D$7:$D$989,"Expense",Transactions!$E$7:$E$989,A49),"") | E49: =IF(A49<>"",B49-C49-D49-G49,"") | F49: =IF(A49<>"",IF(E49=0,"Settled","Unsettled"),"") | G49: =IF(A49<>"",SUMIFS(Transactions!$F$7:$F$989,Transactions!$D$7:$D$989,"Credit",Transactions!$H$7:$H$989,A49),"")
A50: =IF(Roster!$A$48<>"",Roster!$A$48,"") | B50: {=IF(A50<>"",IFERROR(SUMPRODUCT((INDEX(Attendance!$B$7:$AV$206,MATCH(A50,Attendance!$A$7:$A$206,0),0)=1)*Attendance!$B$4:$AV$4),0),"")} | C50: =IF(A50<>"",SUMIFS(Transactions!$F$7:$F$989,Transactions!$D$7:$D$989,"Income",Transactions!$E$7:$E$989,A50),"") | D50: =IF(A50<>"",SUMIFS(Transactions!$F$7:$F$989,Transactions!$D$7:$D$989,"Expense",Transactions!$E$7:$E$989,A50),"") | E50: =IF(A50<>"",B50-C50-D50-G50,"") | F50: =IF(A50<>"",IF(E50=0,"Settled","Unsettled"),"") | G50: =IF(A50<>"",SUMIFS(Transactions!$F$7:$F$989,Transactions!$D$7:$D$989,"Credit",Transactions!$H$7:$H$989,A50),"")
A51: =IF(Roster!$A$49<>"",Roster!$A$49,"") | B51: {=IF(A51<>"",IFERROR(SUMPRODUCT((INDEX(Attendance!$B$7:$AV$206,MATCH(A51,Attendance!$A$7:$A$206,0),0)=1)*Attendance!$B$4:$AV$4),0),"")} | C51: =IF(A51<>"",SUMIFS(Transactions!$F$7:$F$989,Transactions!$D$7:$D$989,"Income",Transactions!$E$7:$E$989,A51),"") | D51: =IF(A51<>"",SUMIFS(Transactions!$F$7:$F$989,Transactions!$D$7:$D$989,"Expense",Transactions!$E$7:$E$989,A51),"") | E51: =IF(A51<>"",B51-C51-D51-G51,"") | F51: =IF(A51<>"",IF(E51=0,"Settled","Unsettled"),"") | G51: =IF(A51<>"",SUMIFS(Transactions!$F$7:$F$989,Transactions!$D$7:$D$989,"Credit",Transactions!$H$7:$H$989,A51),"")
A52: =IF(Roster!$A$50<>"",Roster!$A$50,"") | B52: {=IF(A52<>"",IFERROR(SUMPRODUCT((INDEX(Attendance!$B$7:$AV$206,MATCH(A52,Attendance!$A$7:$A$206,0),0)=1)*Attendance!$B$4:$AV$4),0),"")} | C52: =IF(A52<>"",SUMIFS(Transactions!$F$7:$F$989,Transactions!$D$7:$D$989,"Income",Transactions!$E$7:$E$989,A52),"") | D52: =IF(A52<>"",SUMIFS(Transactions!$F$7:$F$989,Transactions!$D$7:$D$989,"Expense",Transactions!$E$7:$E$989,A52),"") | E52: =IF(A52<>"",B52-C52-D52-G52,"") | F52: =IF(A52<>"",IF(E52=0,"Settled","Unsettled"),"") | G52: =IF(A52<>"",SUMIFS(Transactions!$F$7:$F$989,Transactions!$D$7:$D$989,"Credit",Transactions!$H$7:$H$989,A52),"")
A53: =IF(Roster!$A$51<>"",Roster!$A$51,"") | B53: {=IF(A53<>"",IFERROR(SUMPRODUCT((INDEX(Attendance!$B$7:$AV$206,MATCH(A53,Attendance!$A$7:$A$206,0),0)=1)*Attendance!$B$4:$AV$4),0),"")} | C53: =IF(A53<>"",SUMIFS(Transactions!$F$7:$F$989,Transactions!$D$7:$D$989,"Income",Transactions!$E$7:$E$989,A53),"") | D53: =IF(A53<>"",SUMIFS(Transactions!$F$7:$F$989,Transactions!$D$7:$D$989,"Expense",Transactions!$E$7:$E$989,A53),"") | E53: =IF(A53<>"",B53-C53-D53-G53,"") | F53: =IF(A53<>"",IF(E53=0,"Settled","Unsettled"),"") | G53: =IF(A53<>"",SUMIFS(Transactions!$F$7:$F$989,Transactions!$D$7:$D$989,"Credit",Transactions!$H$7:$H$989,A53),"")
A54: =IF(Roster!$A$52<>"",Roster!$A$52,"") | B54: {=IF(A54<>"",IFERROR(SUMPRODUCT((INDEX(Attendance!$B$7:$AV$206,MATCH(A54,Attendance!$A$7:$A$206,0),0)=1)*Attendance!$B$4:$AV$4),0),"")} | C54: =IF(A54<>"",SUMIFS(Transactions!$F$7:$F$989,Transactions!$D$7:$D$989,"Income",Transactions!$E$7:$E$989,A54),"") | D54: =IF(A54<>"",SUMIFS(Transactions!$F$7:$F$989,Transactions!$D$7:$D$989,"Expense",Transactions!$E$7:$E$989,A54),"") | E54: =IF(A54<>"",B54-C54-D54-G54,"") | F54: =IF(A54<>"",IF(E54=0,"Settled","Unsettled"),"") | G54: =IF(A54<>"",SUMIFS(Transactions!$F$7:$F$989,Transactions!$D$7:$D$989,"Credit",Transactions!$H$7:$H$989,A54),"")
A55: =IF(Roster!$A$53<>"",Roster!$A$53,"") | B55: {=IF(A55<>"",IFERROR(SUMPRODUCT((INDEX(Attendance!$B$7:$AV$206,MATCH(A55,Attendance!$A$7:$A$206,0),0)=1)*Attendance!$B$4:$AV$4),0),"")} | C55: =IF(A55<>"",SUMIFS(Transactions!$F$7:$F$989,Transactions!$D$7:$D$989,"Income",Transactions!$E$7:$E$989,A55),"") | D55: =IF(A55<>"",SUMIFS(Transactions!$F$7:$F$989,Transactions!$D$7:$D$989,"Expense",Transactions!$E$7:$E$989,A55),"") | E55: =IF(A55<>"",B55-C55-D55-G55,"") | F55: =IF(A55<>"",IF(E55=0,"Settled","Unsettled"),"") | G55: =IF(A55<>"",SUMIFS(Transactions!$F$7:$F$989,Transactions!$D$7:$D$989,"Credit",Transactions!$H$7:$H$989,A55),"")
A56: =IF(Roster!$A$54<>"",Roster!$A$54,"") | B56: {=IF(A56<>"",IFERROR(SUMPRODUCT((INDEX(Attendance!$B$7:$AV$206,MATCH(A56,Attendance!$A$7:$A$206,0),0)=1)*Attendance!$B$4:$AV$4),0),"")} | C56: =IF(A56<>"",SUMIFS(Transactions!$F$7:$F$989,Transactions!$D$7:$D$989,"Income",Transactions!$E$7:$E$989,A56),"") | D56: =IF(A56<>"",SUMIFS(Transactions!$F$7:$F$989,Transactions!$D$7:$D$989,"Expense",Transactions!$E$7:$E$989,A56),"") | E56: =IF(A56<>"",B56-C56-D56-G56,"") | F56: =IF(A56<>"",IF(E56=0,"Settled","Unsettled"),"") | G56: =IF(A56<>"",SUMIFS(Transactions!$F$7:$F$989,Transactions!$D$7:$D$989,"Credit",Transactions!$H$7:$H$989,A56),"")
A57: =IF(Roster!$A$55<>"",Roster!$A$55,"") | B57: {=IF(A57<>"",IFERROR(SUMPRODUCT((INDEX(Attendance!$B$7:$AV$206,MATCH(A57,Attendance!$A$7:$A$206,0),0)=1)*Attendance!$B$4:$AV$4),0),"")} | C57: =IF(A57<>"",SUMIFS(Transactions!$F$7:$F$989,Transactions!$D$7:$D$989,"Income",Transactions!$E$7:$E$989,A57),"") | D57: =IF(A57<>"",SUMIFS(Transactions!$F$7:$F$989,Transactions!$D$7:$D$989,"Expense",Transactions!$E$7:$E$989,A57),"") | E57: =IF(A57<>"",B57-C57-D57-G57,"") | F57: =IF(A57<>"",IF(E57=0,"Settled","Unsettled"),"") | G57: =IF(A57<>"",SUMIFS(Transactions!$F$7:$F$989,Transactions!$D$7:$D$989,"Credit",Transactions!$H$7:$H$989,A57),"")
A58: =IF(Roster!$A$56<>"",Roster!$A$56,"") | B58: {=IF(A58<>"",IFERROR(SUMPRODUCT((INDEX(Attendance!$B$7:$AV$206,MATCH(A58,Attendance!$A$7:$A$206,0),0)=1)*Attendance!$B$4:$AV$4),0),"")} | C58: =IF(A58<>"",SUMIFS(Transactions!$F$7:$F$989,Transactions!$D$7:$D$989,"Income",Transactions!$E$7:$E$989,A58),"") | D58: =IF(A58<>"",SUMIFS(Transactions!$F$7:$F$989,Transactions!$D$7:$D$989,"Expense",Transactions!$E$7:$E$989,A58),"") | E58: =IF(A58<>"",B58-C58-D58-G58,"") | F58: =IF(A58<>"",IF(E58=0,"Settled","Unsettled"),"") | G58: =IF(A58<>"",SUMIFS(Transactions!$F$7:$F$989,Transactions!$D$7:$D$989,"Credit",Transactions!$H$7:$H$989,A58),"")
A59: =IF(Roster!$A$57<>"",Roster!$A$57,"") | B59: {=IF(A59<>"",IFERROR(SUMPRODUCT((INDEX(Attendance!$B$7:$AV$206,MATCH(A59,Attendance!$A$7:$A$206,0),0)=1)*Attendance!$B$4:$AV$4),0),"")} | C59: =IF(A59<>"",SUMIFS(Transactions!$F$7:$F$989,Transactions!$D$7:$D$989,"Income",Transactions!$E$7:$E$989,A59),"") | D59: =IF(A59<>"",SUMIFS(Transactions!$F$7:$F$989,Transactions!$D$7:$D$989,"Expense",Transactions!$E$7:$E$989,A59),"") | E59: =IF(A59<>"",B59-C59-D59-G59,"") | F59: =IF(A59<>"",IF(E59=0,"Settled","Unsettled"),"") | G59: =IF(A59<>"",SUMIFS(Transactions!$F$7:$F$989,Transactions!$D$7:$D$989,"Credit",Transactions!$H$7:$H$989,A59),"")
A60: =IF(Roster!$A$58<>"",Roster!$A$58,"") | B60: {=IF(A60<>"",IFERROR(SUMPRODUCT((INDEX(Attendance!$B$7:$AV$206,MATCH(A60,Attendance!$A$7:$A$206,0),0)=1)*Attendance!$B$4:$AV$4),0),"")} | C60: =IF(A60<>"",SUMIFS(Transactions!$F$7:$F$989,Transactions!$D$7:$D$989,"Income",Transactions!$E$7:$E$989,A60),"") | D60: =IF(A60<>"",SUMIFS(Transactions!$F$7:$F$989,Transactions!$D$7:$D$989,"Expense",Transactions!$E$7:$E$989,A60),"") | E60: =IF(A60<>"",B60-C60-D60-G60,"") | F60: =IF(A60<>"",IF(E60=0,"Settled","Unsettled"),"") | G60: =IF(A60<>"",SUMIFS(Transactions!$F$7:$F$989,Transactions!$D$7:$D$989,"Credit",Transactions!$H$7:$H$989,A60),"")
A61: =IF(Roster!$A$59<>"",Roster!$A$59,"") | B61: {=IF(A61<>"",IFERROR(SUMPRODUCT((INDEX(Attendance!$B$7:$AV$206,MATCH(A61,Attendance!$A$7:$A$206,0),0)=1)*Attendance!$B$4:$AV$4),0),"")} | C61: =IF(A61<>"",SUMIFS(Transactions!$F$7:$F$989,Transactions!$D$7:$D$989,"Income",Transactions!$E$7:$E$989,A61),"") | D61: =IF(A61<>"",SUMIFS(Transactions!$F$7:$F$989,Transactions!$D$7:$D$989,"Expense",Transactions!$E$7:$E$989,A61),"") | E61: =IF(A61<>"",B61-C61-D61-G61,"") | F61: =IF(A61<>"",IF(E61=0,"Settled","Unsettled"),"") | G61: =IF(A61<>"",SUMIFS(Transactions!$F$7:$F$989,Transactions!$D$7:$D$989,"Credit",Transactions!$H$7:$H$989,A61),"")
A62: =IF(Roster!$A$60<>"",Roster!$A$60,"") | B62: {=IF(A62<>"",IFERROR(SUMPRODUCT((INDEX(Attendance!$B$7:$AV$206,MATCH(A62,Attendance!$A$7:$A$206,0),0)=1)*Attendance!$B$4:$AV$4),0),"")} | C62: =IF(A62<>"",SUMIFS(Transactions!$F$7:$F$989,Transactions!$D$7:$D$989,"Income",Transactions!$E$7:$E$989,A62),"") | D62: =IF(A62<>"",SUMIFS(Transactions!$F$7:$F$989,Transactions!$D$7:$D$989,"Expense",Transactions!$E$7:$E$989,A62),"") | E62: =IF(A62<>"",B62-C62-D62-G62,"") | F62: =IF(A62<>"",IF(E62=0,"Settled","Unsettled"),"") | G62: =IF(A62<>"",SUMIFS(Transactions!$F$7:$F$989,Transactions!$D$7:$D$989,"Credit",Transactions!$H$7:$H$989,A62),"")
A63: =IF(Roster!$A$61<>"",Roster!$A$61,"") | B63: {=IF(A63<>"",IFERROR(SUMPRODUCT((INDEX(Attendance!$B$7:$AV$206,MATCH(A63,Attendance!$A$7:$A$206,0),0)=1)*Attendance!$B$4:$AV$4),0),"")} | C63: =IF(A63<>"",SUMIFS(Transactions!$F$7:$F$989,Transactions!$D$7:$D$989,"Income",Transactions!$E$7:$E$989,A63),"") | D63: =IF(A63<>"",SUMIFS(Transactions!$F$7:$F$989,Transactions!$D$7:$D$989,"Expense",Transactions!$E$7:$E$989,A63),"") | E63: =IF(A63<>"",B63-C63-D63-G63,"") | F63: =IF(A63<>"",IF(E63=0,"Settled","Unsettled"),"") | G63: =IF(A63<>"",SUMIFS(Transactions!$F$7:$F$989,Transactions!$D$7:$D$989,"Credit",Transactions!$H$7:$H$989,A63),"")
A64: =IF(Roster!$A$62<>"",Roster!$A$62,"") | B64: {=IF(A64<>"",IFERROR(SUMPRODUCT((INDEX(Attendance!$B$7:$AV$206,MATCH(A64,Attendance!$A$7:$A$206,0),0)=1)*Attendance!$B$4:$AV$4),0),"")} | C64: =IF(A64<>"",SUMIFS(Transactions!$F$7:$F$989,Transactions!$D$7:$D$989,"Income",Transactions!$E$7:$E$989,A64),"") | D64: =IF(A64<>"",SUMIFS(Transactions!$F$7:$F$989,Transactions!$D$7:$D$989,"Expense",Transactions!$E$7:$E$989,A64),"") | E64: =IF(A64<>"",B64-C64-D64-G64,"") | F64: =IF(A64<>"",IF(E64=0,"Settled","Unsettled"),"") | G64: =IF(A64<>"",SUMIFS(Transactions!$F$7:$F$989,Transactions!$D$7:$D$989,"Credit",Transactions!$H$7:$H$989,A64),"")
A65: =IF(Roster!$A$63<>"",Roster!$A$63,"") | B65: {=IF(A65<>"",IFERROR(SUMPRODUCT((INDEX(Attendance!$B$7:$AV$206,MATCH(A65,Attendance!$A$7:$A$206,0),0)=1)*Attendance!$B$4:$AV$4),0),"")} | C65: =IF(A65<>"",SUMIFS(Transactions!$F$7:$F$989,Transactions!$D$7:$D$989,"Income",Transactions!$E$7:$E$989,A65),"") | D65: =IF(A65<>"",SUMIFS(Transactions!$F$7:$F$989,Transactions!$D$7:$D$989,"Expense",Transactions!$E$7:$E$989,A65),"") | E65: =IF(A65<>"",B65-C65-D65-G65,"") | F65: =IF(A65<>"",IF(E65=0,"Settled","Unsettled"),"") | G65: =IF(A65<>"",SUMIFS(Transactions!$F$7:$F$989,Transactions!$D$7:$D$989,"Credit",Transactions!$H$7:$H$989,A65),"")
A66: =IF(Roster!$A$64<>"",Roster!$A$64,"") | B66: {=IF(A66<>"",IFERROR(SUMPRODUCT((INDEX(Attendance!$B$7:$AV$206,MATCH(A66,Attendance!$A$7:$A$206,0),0)=1)*Attendance!$B$4:$AV$4),0),"")} | C66: =IF(A66<>"",SUMIFS(Transactions!$F$7:$F$989,Transactions!$D$7:$D$989,"Income",Transactions!$E$7:$E$989,A66),"") | D66: =IF(A66<>"",SUMIFS(Transactions!$F$7:$F$989,Transactions!$D$7:$D$989,"Expense",Transactions!$E$7:$E$989,A66),"") | E66: =IF(A66<>"",B66-C66-D66-G66,"") | F66: =IF(A66<>"",IF(E66=0,"Settled","Unsettled"),"") | G66: =IF(A66<>"",SUMIFS(Transactions!$F$7:$F$989,Transactions!$D$7:$D$989,"Credit",Transactions!$H$7:$H$989,A66),"")
A67: =IF(Roster!$A$65<>"",Roster!$A$65,"") | B67: {=IF(A67<>"",IFERROR(SUMPRODUCT((INDEX(Attendance!$B$7:$AV$206,MATCH(A67,Attendance!$A$7:$A$206,0),0)=1)*Attendance!$B$4:$AV$4),0),"")} | C67: =IF(A67<>"",SUMIFS(Transactions!$F$7:$F$989,Transactions!$D$7:$D$989,"Income",Transactions!$E$7:$E$989,A67),"") | D67: =IF(A67<>"",SUMIFS(Transactions!$F$7:$F$989,Transactions!$D$7:$D$989,"Expense",Transactions!$E$7:$E$989,A67),"") | E67: =IF(A67<>"",B67-C67-D67-G67,"") | F67: =IF(A67<>"",IF(E67=0,"Settled","Unsettled"),"") | G67: =IF(A67<>"",SUMIFS(Transactions!$F$7:$F$989,Transactions!$D$7:$D$989,"Credit",Transactions!$H$7:$H$989,A67),"")
A68: =IF(Roster!$A$66<>"",Roster!$A$66,"") | B68: {=IF(A68<>"",IFERROR(SUMPRODUCT((INDEX(Attendance!$B$7:$AV$206,MATCH(A68,Attendance!$A$7:$A$206,0),0)=1)*Attendance!$B$4:$AV$4),0),"")} | C68: =IF(A68<>"",SUMIFS(Transactions!$F$7:$F$989,Transactions!$D$7:$D$989,"Income",Transactions!$E$7:$E$989,A68),"") | D68: =IF(A68<>"",SUMIFS(Transactions!$F$7:$F$989,Transactions!$D$7:$D$989,"Expense",Transactions!$E$7:$E$989,A68),"") | E68: =IF(A68<>"",B68-C68-D68-G68,"") | F68: =IF(A68<>"",IF(E68=0,"Settled","Unsettled"),"") | G68: =IF(A68<>"",SUMIFS(Transactions!$F$7:$F$989,Transactions!$D$7:$D$989,"Credit",Transactions!$H$7:$H$989,A68),"")
A69: =IF(Roster!$A$67<>"",Roster!$A$67,"") | B69: {=IF(A69<>"",IFERROR(SUMPRODUCT((INDEX(Attendance!$B$7:$AV$206,MATCH(A69,Attendance!$A$7:$A$206,0),0)=1)*Attendance!$B$4:$AV$4),0),"")} | C69: =IF(A69<>"",SUMIFS(Transactions!$F$7:$F$989,Transactions!$D$7:$D$989,"Income",Transactions!$E$7:$E$989,A69),"") | D69: =IF(A69<>"",SUMIFS(Transactions!$F$7:$F$989,Transactions!$D$7:$D$989,"Expense",Transactions!$E$7:$E$989,A69),"") | E69: =IF(A69<>"",B69-C69-D69-G69,"") | F69: =IF(A69<>"",IF(E69=0,"Settled","Unsettled"),"") | G69: =IF(A69<>"",SUMIFS(Transactions!$F$7:$F$989,Transactions!$D$7:$D$989,"Credit",Transactions!$H$7:$H$989,A69),"")
A70: =IF(Roster!$A$68<>"",Roster!$A$68,"") | B70: {=IF(A70<>"",IFERROR(SUMPRODUCT((INDEX(Attendance!$B$7:$AV$206,MATCH(A70,Attendance!$A$7:$A$206,0),0)=1)*Attendance!$B$4:$AV$4),0),"")} | C70: =IF(A70<>"",SUMIFS(Transactions!$F$7:$F$989,Transactions!$D$7:$D$989,"Income",Transactions!$E$7:$E$989,A70),"") | D70: =IF(A70<>"",SUMIFS(Transactions!$F$7:$F$989,Transactions!$D$7:$D$989,"Expense",Transactions!$E$7:$E$989,A70),"") | E70: =IF(A70<>"",B70-C70-D70-G70,"") | F70: =IF(A70<>"",IF(E70=0,"Settled","Unsettled"),"") | G70: =IF(A70<>"",SUMIFS(Transactions!$F$7:$F$989,Transactions!$D$7:$D$989,"Credit",Transactions!$H$7:$H$989,A70),"")
A71: =IF(Roster!$A$69<>"",Roster!$A$69,"") | B71: {=IF(A71<>"",IFERROR(SUMPRODUCT((INDEX(Attendance!$B$7:$AV$206,MATCH(A71,Attendance!$A$7:$A$206,0),0)=1)*Attendance!$B$4:$AV$4),0),"")} | C71: =IF(A71<>"",SUMIFS(Transactions!$F$7:$F$989,Transactions!$D$7:$D$989,"Income",Transactions!$E$7:$E$989,A71),"") | D71: =IF(A71<>"",SUMIFS(Transactions!$F$7:$F$989,Transactions!$D$7:$D$989,"Expense",Transactions!$E$7:$E$989,A71),"") | E71: =IF(A71<>"",B71-C71-D71-G71,"") | F71: =IF(A71<>"",IF(E71=0,"Settled","Unsettled"),"") | G71: =IF(A71<>"",SUMIFS(Transactions!$F$7:$F$989,Transactions!$D$7:$D$989,"Credit",Transactions!$H$7:$H$989,A71),"")
A72: =IF(Roster!$A$70<>"",Roster!$A$70,"") | B72: {=IF(A72<>"",IFERROR(SUMPRODUCT((INDEX(Attendance!$B$7:$AV$206,MATCH(A72,Attendance!$A$7:$A$206,0),0)=1)*Attendance!$B$4:$AV$4),0),"")} | C72: =IF(A72<>"",SUMIFS(Transactions!$F$7:$F$989,Transactions!$D$7:$D$989,"Income",Transactions!$E$7:$E$989,A72),"") | D72: =IF(A72<>"",SUMIFS(Transactions!$F$7:$F$989,Transactions!$D$7:$D$989,"Expense",Transactions!$E$7:$E$989,A72),"") | E72: =IF(A72<>"",B72-C72-D72-G72,"") | F72: =IF(A72<>"",IF(E72=0,"Settled","Unsettled"),"") | G72: =IF(A72<>"",SUMIFS(Transactions!$F$7:$F$989,Transactions!$D$7:$D$989,"Credit",Transactions!$H$7:$H$989,A72),"")
A73: =IF(Roster!$A$71<>"",Roster!$A$71,"") | B73: {=IF(A73<>"",IFERROR(SUMPRODUCT((INDEX(Attendance!$B$7:$AV$206,MATCH(A73,Attendance!$A$7:$A$206,0),0)=1)*Attendance!$B$4:$AV$4),0),"")} | C73: =IF(A73<>"",SUMIFS(Transactions!$F$7:$F$989,Transactions!$D$7:$D$989,"Income",Transactions!$E$7:$E$989,A73),"") | D73: =IF(A73<>"",SUMIFS(Transactions!$F$7:$F$989,Transactions!$D$7:$D$989,"Expense",Transactions!$E$7:$E$989,A73),"") | E73: =IF(A73<>"",B73-C73-D73-G73,"") | F73: =IF(A73<>"",IF(E73=0,"Settled","Unsettled"),"") | G73: =IF(A73<>"",SUMIFS(Transactions!$F$7:$F$989,Transactions!$D$7:$D$989,"Credit",Transactions!$H$7:$H$989,A73),"")
A74: =IF(Roster!$A$72<>"",Roster!$A$72,"") | B74: {=IF(A74<>"",IFERROR(SUMPRODUCT((INDEX(Attendance!$B$7:$AV$206,MATCH(A74,Attendance!$A$7:$A$206,0),0)=1)*Attendance!$B$4:$AV$4),0),"")} | C74: =IF(A74<>"",SUMIFS(Transactions!$F$7:$F$989,Transactions!$D$7:$D$989,"Income",Transactions!$E$7:$E$989,A74),"") | D74: =IF(A74<>"",SUMIFS(Transactions!$F$7:$F$989,Transactions!$D$7:$D$989,"Expense",Transactions!$E$7:$E$989,A74),"") | E74: =IF(A74<>"",B74-C74-D74-G74,"") | F74: =IF(A74<>"",IF(E74=0,"Settled","Unsettled"),"") | G74: =IF(A74<>"",SUMIFS(Transactions!$F$7:$F$989,Transactions!$D$7:$D$989,"Credit",Transactions!$H$7:$H$989,A74),"")
A75: =IF(Roster!$A$73<>"",Roster!$A$73,"") | B75: {=IF(A75<>"",IFERROR(SUMPRODUCT((INDEX(Attendance!$B$7:$AV$206,MATCH(A75,Attendance!$A$7:$A$206,0),0)=1)*Attendance!$B$4:$AV$4),0),"")} | C75: =IF(A75<>"",SUMIFS(Transactions!$F$7:$F$989,Transactions!$D$7:$D$989,"Income",Transactions!$E$7:$E$989,A75),"") | D75: =IF(A75<>"",SUMIFS(Transactions!$F$7:$F$989,Transactions!$D$7:$D$989,"Expense",Transactions!$E$7:$E$989,A75),"") | E75: =IF(A75<>"",B75-C75-D75-G75,"") | F75: =IF(A75<>"",IF(E75=0,"Settled","Unsettled"),"") | G75: =IF(A75<>"",SUMIFS(Transactions!$F$7:$F$989,Transactions!$D$7:$D$989,"Credit",Transactions!$H$7:$H$989,A75),"")
A76: =IF(Roster!$A$74<>"",Roster!$A$74,"") | B76: {=IF(A76<>"",IFERROR(SUMPRODUCT((INDEX(Attendance!$B$7:$AV$206,MATCH(A76,Attendance!$A$7:$A$206,0),0)=1)*Attendance!$B$4:$AV$4),0),"")} | C76: =IF(A76<>"",SUMIFS(Transactions!$F$7:$F$989,Transactions!$D$7:$D$989,"Income",Transactions!$E$7:$E$989,A76),"") | D76: =IF(A76<>"",SUMIFS(Transactions!$F$7:$F$989,Transactions!$D$7:$D$989,"Expense",Transactions!$E$7:$E$989,A76),"") | E76: =IF(A76<>"",B76-C76-D76-G76,"") | F76: =IF(A76<>"",IF(E76=0,"Settled","Unsettled"),"") | G76: =IF(A76<>"",SUMIFS(Transactions!$F$7:$F$989,Transactions!$D$7:$D$989,"Credit",Transactions!$H$7:$H$989,A76),"")
A77: =IF(Roster!$A$75<>"",Roster!$A$75,"") | B77: {=IF(A77<>"",IFERROR(SUMPRODUCT((INDEX(Attendance!$B$7:$AV$206,MATCH(A77,Attendance!$A$7:$A$206,0),0)=1)*Attendance!$B$4:$AV$4),0),"")} | C77: =IF(A77<>"",SUMIFS(Transactions!$F$7:$F$989,Transactions!$D$7:$D$989,"Income",Transactions!$E$7:$E$989,A77),"") | D77: =IF(A77<>"",SUMIFS(Transactions!$F$7:$F$989,Transactions!$D$7:$D$989,"Expense",Transactions!$E$7:$E$989,A77),"") | E77: =IF(A77<>"",B77-C77-D77-G77,"") | F77: =IF(A77<>"",IF(E77=0,"Settled","Unsettled"),"") | G77: =IF(A77<>"",SUMIFS(Transactions!$F$7:$F$989,Transactions!$D$7:$D$989,"Credit",Transactions!$H$7:$H$989,A77),"")
A78: =IF(Roster!$A$76<>"",Roster!$A$76,"") | B78: {=IF(A78<>"",IFERROR(SUMPRODUCT((INDEX(Attendance!$B$7:$AV$206,MATCH(A78,Attendance!$A$7:$A$206,0),0)=1)*Attendance!$B$4:$AV$4),0),"")} | C78: =IF(A78<>"",SUMIFS(Transactions!$F$7:$F$989,Transactions!$D$7:$D$989,"Income",Transactions!$E$7:$E$989,A78),"") | D78: =IF(A78<>"",SUMIFS(Transactions!$F$7:$F$989,Transactions!$D$7:$D$989,"Expense",Transactions!$E$7:$E$989,A78),"") | E78: =IF(A78<>"",B78-C78-D78-G78,"") | F78: =IF(A78<>"",IF(E78=0,"Settled","Unsettled"),"") | G78: =IF(A78<>"",SUMIFS(Transactions!$F$7:$F$989,Transactions!$D$7:$D$989,"Credit",Transactions!$H$7:$H$989,A78),"")
A79: =IF(Roster!$A$77<>"",Roster!$A$77,"") | B79: {=IF(A79<>"",IFERROR(SUMPRODUCT((INDEX(Attendance!$B$7:$AV$206,MATCH(A79,Attendance!$A$7:$A$206,0),0)=1)*Attendance!$B$4:$AV$4),0),"")} | C79: =IF(A79<>"",SUMIFS(Transactions!$F$7:$F$989,Transactions!$D$7:$D$989,"Income",Transactions!$E$7:$E$989,A79),"") | D79: =IF(A79<>"",SUMIFS(Transactions!$F$7:$F$989,Transactions!$D$7:$D$989,"Expense",Transactions!$E$7:$E$989,A79),"") | E79: =IF(A79<>"",B79-C79-D79-G79,"") | F79: =IF(A79<>"",IF(E79=0,"Settled","Unsettled"),"") | G79: =IF(A79<>"",SUMIFS(Transactions!$F$7:$F$989,Transactions!$D$7:$D$989,"Credit",Transactions!$H$7:$H$989,A79),"")
A80: =IF(Roster!$A$78<>"",Roster!$A$78,"") | B80: {=IF(A80<>"",IFERROR(SUMPRODUCT((INDEX(Attendance!$B$7:$AV$206,MATCH(A80,Attendance!$A$7:$A$206,0),0)=1)*Attendance!$B$4:$AV$4),0),"")} | C80: =IF(A80<>"",SUMIFS(Transactions!$F$7:$F$989,Transactions!$D$7:$D$989,"Income",Transactions!$E$7:$E$989,A80),"") | D80: =IF(A80<>"",SUMIFS(Transactions!$F$7:$F$989,Transactions!$D$7:$D$989,"Expense",Transactions!$E$7:$E$989,A80),"") | E80: =IF(A80<>"",B80-C80-D80-G80,"") | F80: =IF(A80<>"",IF(E80=0,"Settled","Unsettled"),"") | G80: =IF(A80<>"",SUMIFS(Transactions!$F$7:$F$989,Transactions!$D$7:$D$989,"Credit",Transactions!$H$7:$H$989,A80),"")
A81: =IF(Roster!$A$79<>"",Roster!$A$79,"") | B81: {=IF(A81<>"",IFERROR(SUMPRODUCT((INDEX(Attendance!$B$7:$AV$206,MATCH(A81,Attendance!$A$7:$A$206,0),0)=1)*Attendance!$B$4:$AV$4),0),"")} | C81: =IF(A81<>"",SUMIFS(Transactions!$F$7:$F$989,Transactions!$D$7:$D$989,"Income",Transactions!$E$7:$E$989,A81),"") | D81: =IF(A81<>"",SUMIFS(Transactions!$F$7:$F$989,Transactions!$D$7:$D$989,"Expense",Transactions!$E$7:$E$989,A81),"") | E81: =IF(A81<>"",B81-C81-D81-G81,"") | F81: =IF(A81<>"",IF(E81=0,"Settled","Unsettled"),"") | G81: =IF(A81<>"",SUMIFS(Transactions!$F$7:$F$989,Transactions!$D$7:$D$989,"Credit",Transactions!$H$7:$H$989,A81),"")
A82: =IF(Roster!$A$80<>"",Roster!$A$80,"") | B82: {=IF(A82<>"",IFERROR(SUMPRODUCT((INDEX(Attendance!$B$7:$AV$206,MATCH(A82,Attendance!$A$7:$A$206,0),0)=1)*Attendance!$B$4:$AV$4),0),"")} | C82: =IF(A82<>"",SUMIFS(Transactions!$F$7:$F$989,Transactions!$D$7:$D$989,"Income",Transactions!$E$7:$E$989,A82),"") | D82: =IF(A82<>"",SUMIFS(Transactions!$F$7:$F$989,Transactions!$D$7:$D$989,"Expense",Transactions!$E$7:$E$989,A82),"") | E82: =IF(A82<>"",B82-C82-D82-G82,"") | F82: =IF(A82<>"",IF(E82=0,"Settled","Unsettled"),"") | G82: =IF(A82<>"",SUMIFS(Transactions!$F$7:$F$989,Transactions!$D$7:$D$989,"Credit",Transactions!$H$7:$H$989,A82),"")
A83: =IF(Roster!$A$81<>"",Roster!$A$81,"") | B83: {=IF(A83<>"",IFERROR(SUMPRODUCT((INDEX(Attendance!$B$7:$AV$206,MATCH(A83,Attendance!$A$7:$A$206,0),0)=1)*Attendance!$B$4:$AV$4),0),"")} | C83: =IF(A83<>"",SUMIFS(Transactions!$F$7:$F$989,Transactions!$D$7:$D$989,"Income",Transactions!$E$7:$E$989,A83),"") | D83: =IF(A83<>"",SUMIFS(Transactions!$F$7:$F$989,Transactions!$D$7:$D$989,"Expense",Transactions!$E$7:$E$989,A83),"") | E83: =IF(A83<>"",B83-C83-D83-G83,"") | F83: =IF(A83<>"",IF(E83=0,"Settled","Unsettled"),"") | G83: =IF(A83<>"",SUMIFS(Transactions!$F$7:$F$989,Transactions!$D$7:$D$989,"Credit",Transactions!$H$7:$H$989,A83),"")
A84: =IF(Roster!$A$82<>"",Roster!$A$82,"") | B84: {=IF(A84<>"",IFERROR(SUMPRODUCT((INDEX(Attendance!$B$7:$AV$206,MATCH(A84,Attendance!$A$7:$A$206,0),0)=1)*Attendance!$B$4:$AV$4),0),"")} | C84: =IF(A84<>"",SUMIFS(Transactions!$F$7:$F$989,Transactions!$D$7:$D$989,"Income",Transactions!$E$7:$E$989,A84),"") | D84: =IF(A84<>"",SUMIFS(Transactions!$F$7:$F$989,Transactions!$D$7:$D$989,"Expense",Transactions!$E$7:$E$989,A84),"") | E84: =IF(A84<>"",B84-C84-D84-G84,"") | F84: =IF(A84<>"",IF(E84=0,"Settled","Unsettled"),"") | G84: =IF(A84<>"",SUMIFS(Transactions!$F$7:$F$989,Transactions!$D$7:$D$989,"Credit",Transactions!$H$7:$H$989,A84),"")
A85: =IF(Roster!$A$83<>"",Roster!$A$83,"") | B85: {=IF(A85<>"",IFERROR(SUMPRODUCT((INDEX(Attendance!$B$7:$AV$206,MATCH(A85,Attendance!$A$7:$A$206,0),0)=1)*Attendance!$B$4:$AV$4),0),"")} | C85: =IF(A85<>"",SUMIFS(Transactions!$F$7:$F$989,Transactions!$D$7:$D$989,"Income",Transactions!$E$7:$E$989,A85),"") | D85: =IF(A85<>"",SUMIFS(Transactions!$F$7:$F$989,Transactions!$D$7:$D$989,"Expense",Transactions!$E$7:$E$989,A85),"") | E85: =IF(A85<>"",B85-C85-D85-G85,"") | F85: =IF(A85<>"",IF(E85=0,"Settled","Unsettled"),"") | G85: =IF(A85<>"",SUMIFS(Transactions!$F$7:$F$989,Transactions!$D$7:$D$989,"Credit",Transactions!$H$7:$H$989,A85),"")
A86: =IF(Roster!$A$84<>"",Roster!$A$84,"") | B86: {=IF(A86<>"",IFERROR(SUMPRODUCT((INDEX(Attendance!$B$7:$AV$206,MATCH(A86,Attendance!$A$7:$A$206,0),0)=1)*Attendance!$B$4:$AV$4),0),"")} | C86: =IF(A86<>"",SUMIFS(Transactions!$F$7:$F$989,Transactions!$D$7:$D$989,"Income",Transactions!$E$7:$E$989,A86),"") | D86: =IF(A86<>"",SUMIFS(Transactions!$F$7:$F$989,Transactions!$D$7:$D$989,"Expense",Transactions!$E$7:$E$989,A86),"") | E86: =IF(A86<>"",B86-C86-D86-G86,"") | F86: =IF(A86<>"",IF(E86=0,"Settled","Unsettled"),"") | G86: =IF(A86<>"",SUMIFS(Transactions!$F$7:$F$989,Transactions!$D$7:$D$989,"Credit",Transactions!$H$7:$H$989,A86),"")
A87: =IF(Roster!$A$85<>"",Roster!$A$85,"") | B87: {=IF(A87<>"",IFERROR(SUMPRODUCT((INDEX(Attendance!$B$7:$AV$206,MATCH(A87,Attendance!$A$7:$A$206,0),0)=1)*Attendance!$B$4:$AV$4),0),"")} | C87: =IF(A87<>"",SUMIFS(Transactions!$F$7:$F$989,Transactions!$D$7:$D$989,"Income",Transactions!$E$7:$E$989,A87),"") | D87: =IF(A87<>"",SUMIFS(Transactions!$F$7:$F$989,Transactions!$D$7:$D$989,"Expense",Transactions!$E$7:$E$989,A87),"") | E87: =IF(A87<>"",B87-C87-D87-G87,"") | F87: =IF(A87<>"",IF(E87=0,"Settled","Unsettled"),"") | G87: =IF(A87<>"",SUMIFS(Transactions!$F$7:$F$989,Transactions!$D$7:$D$989,"Credit",Transactions!$H$7:$H$989,A87),"")
A88: =IF(Roster!$A$86<>"",Roster!$A$86,"") | B88: {=IF(A88<>"",IFERROR(SUMPRODUCT((INDEX(Attendance!$B$7:$AV$206,MATCH(A88,Attendance!$A$7:$A$206,0),0)=1)*Attendance!$B$4:$AV$4),0),"")} | C88: =IF(A88<>"",SUMIFS(Transactions!$F$7:$F$989,Transactions!$D$7:$D$989,"Income",Transactions!$E$7:$E$989,A88),"") | D88: =IF(A88<>"",SUMIFS(Transactions!$F$7:$F$989,Transactions!$D$7:$D$989,"Expense",Transactions!$E$7:$E$989,A88),"") | E88: =IF(A88<>"",B88-C88-D88-G88,"") | F88: =IF(A88<>"",IF(E88=0,"Settled","Unsettled"),"") | G88: =IF(A88<>"",SUMIFS(Transactions!$F$7:$F$989,Transactions!$D$7:$D$989,"Credit",Transactions!$H$7:$H$989,A88),"")
A89: =IF(Roster!$A$87<>"",Roster!$A$87,"") | B89: {=IF(A89<>"",IFERROR(SUMPRODUCT((INDEX(Attendance!$B$7:$AV$206,MATCH(A89,Attendance!$A$7:$A$206,0),0)=1)*Attendance!$B$4:$AV$4),0),"")} | C89: =IF(A89<>"",SUMIFS(Transactions!$F$7:$F$989,Transactions!$D$7:$D$989,"Income",Transactions!$E$7:$E$989,A89),"") | D89: =IF(A89<>"",SUMIFS(Transactions!$F$7:$F$989,Transactions!$D$7:$D$989,"Expense",Transactions!$E$7:$E$989,A89),"") | E89: =IF(A89<>"",B89-C89-D89-G89,"") | F89: =IF(A89<>"",IF(E89=0,"Settled","Unsettled"),"") | G89: =IF(A89<>"",SUMIFS(Transactions!$F$7:$F$989,Transactions!$D$7:$D$989,"Credit",Transactions!$H$7:$H$989,A89),"")
A90: =IF(Roster!$A$88<>"",Roster!$A$88,"") | B90: {=IF(A90<>"",IFERROR(SUMPRODUCT((INDEX(Attendance!$B$7:$AV$206,MATCH(A90,Attendance!$A$7:$A$206,0),0)=1)*Attendance!$B$4:$AV$4),0),"")} | C90: =IF(A90<>"",SUMIFS(Transactions!$F$7:$F$989,Transactions!$D$7:$D$989,"Income",Transactions!$E$7:$E$989,A90),"") | D90: =IF(A90<>"",SUMIFS(Transactions!$F$7:$F$989,Transactions!$D$7:$D$989,"Expense",Transactions!$E$7:$E$989,A90),"") | E90: =IF(A90<>"",B90-C90-D90-G90,"") | F90: =IF(A90<>"",IF(E90=0,"Settled","Unsettled"),"") | G90: =IF(A90<>"",SUMIFS(Transactions!$F$7:$F$989,Transactions!$D$7:$D$989,"Credit",Transactions!$H$7:$H$989,A90),"")
A91: =IF(Roster!$A$89<>"",Roster!$A$89,"") | B91: {=IF(A91<>"",IFERROR(SUMPRODUCT((INDEX(Attendance!$B$7:$AV$206,MATCH(A91,Attendance!$A$7:$A$206,0),0)=1)*Attendance!$B$4:$AV$4),0),"")} | C91: =IF(A91<>"",SUMIFS(Transactions!$F$7:$F$989,Transactions!$D$7:$D$989,"Income",Transactions!$E$7:$E$989,A91),"") | D91: =IF(A91<>"",SUMIFS(Transactions!$F$7:$F$989,Transactions!$D$7:$D$989,"Expense",Transactions!$E$7:$E$989,A91),"") | E91: =IF(A91<>"",B91-C91-D91-G91,"") | F91: =IF(A91<>"",IF(E91=0,"Settled","Unsettled"),"") | G91: =IF(A91<>"",SUMIFS(Transactions!$F$7:$F$989,Transactions!$D$7:$D$989,"Credit",Transactions!$H$7:$H$989,A91),"")
A92: =IF(Roster!$A$90<>"",Roster!$A$90,"") | B92: {=IF(A92<>"",IFERROR(SUMPRODUCT((INDEX(Attendance!$B$7:$AV$206,MATCH(A92,Attendance!$A$7:$A$206,0),0)=1)*Attendance!$B$4:$AV$4),0),"")} | C92: =IF(A92<>"",SUMIFS(Transactions!$F$7:$F$989,Transactions!$D$7:$D$989,"Income",Transactions!$E$7:$E$989,A92),"") | D92: =IF(A92<>"",SUMIFS(Transactions!$F$7:$F$989,Transactions!$D$7:$D$989,"Expense",Transactions!$E$7:$E$989,A92),"") | E92: =IF(A92<>"",B92-C92-D92-G92,"") | F92: =IF(A92<>"",IF(E92=0,"Settled","Unsettled"),"") | G92: =IF(A92<>"",SUMIFS(Transactions!$F$7:$F$989,Transactions!$D$7:$D$989,"Credit",Transactions!$H$7:$H$989,A92),"")
A93: =IF(Roster!$A$91<>"",Roster!$A$91,"") | B93: {=IF(A93<>"",IFERROR(SUMPRODUCT((INDEX(Attendance!$B$7:$AV$206,MATCH(A93,Attendance!$A$7:$A$206,0),0)=1)*Attendance!$B$4:$AV$4),0),"")} | C93: =IF(A93<>"",SUMIFS(Transactions!$F$7:$F$989,Transactions!$D$7:$D$989,"Income",Transactions!$E$7:$E$989,A93),"") | D93: =IF(A93<>"",SUMIFS(Transactions!$F$7:$F$989,Transactions!$D$7:$D$989,"Expense",Transactions!$E$7:$E$989,A93),"") | E93: =IF(A93<>"",B93-C93-D93-G93,"") | F93: =IF(A93<>"",IF(E93=0,"Settled","Unsettled"),"") | G93: =IF(A93<>"",SUMIFS(Transactions!$F$7:$F$989,Transactions!$D$7:$D$989,"Credit",Transactions!$H$7:$H$989,A93),"")
A94: =IF(Roster!$A$92<>"",Roster!$A$92,"") | B94: {=IF(A94<>"",IFERROR(SUMPRODUCT((INDEX(Attendance!$B$7:$AV$206,MATCH(A94,Attendance!$A$7:$A$206,0),0)=1)*Attendance!$B$4:$AV$4),0),"")} | C94: =IF(A94<>"",SUMIFS(Transactions!$F$7:$F$989,Transactions!$D$7:$D$989,"Income",Transactions!$E$7:$E$989,A94),"") | D94: =IF(A94<>"",SUMIFS(Transactions!$F$7:$F$989,Transactions!$D$7:$D$989,"Expense",Transactions!$E$7:$E$989,A94),"") | E94: =IF(A94<>"",B94-C94-D94-G94,"") | F94: =IF(A94<>"",IF(E94=0,"Settled","Unsettled"),"") | G94: =IF(A94<>"",SUMIFS(Transactions!$F$7:$F$989,Transactions!$D$7:$D$989,"Credit",Transactions!$H$7:$H$989,A94),"")
A95: =IF(Roster!$A$93<>"",Roster!$A$93,"") | B95: {=IF(A95<>"",IFERROR(SUMPRODUCT((INDEX(Attendance!$B$7:$AV$206,MATCH(A95,Attendance!$A$7:$A$206,0),0)=1)*Attendance!$B$4:$AV$4),0),"")} | C95: =IF(A95<>"",SUMIFS(Transactions!$F$7:$F$989,Transactions!$D$7:$D$989,"Income",Transactions!$E$7:$E$989,A95),"") | D95: =IF(A95<>"",SUMIFS(Transactions!$F$7:$F$989,Transactions!$D$7:$D$989,"Expense",Transactions!$E$7:$E$989,A95),"") | E95: =IF(A95<>"",B95-C95-D95-G95,"") | F95: =IF(A95<>"",IF(E95=0,"Settled","Unsettled"),"") | G95: =IF(A95<>"",SUMIFS(Transactions!$F$7:$F$989,Transactions!$D$7:$D$989,"Credit",Transactions!$H$7:$H$989,A95),"")
A96: =IF(Roster!$A$94<>"",Roster!$A$94,"") | B96: {=IF(A96<>"",IFERROR(SUMPRODUCT((INDEX(Attendance!$B$7:$AV$206,MATCH(A96,Attendance!$A$7:$A$206,0),0)=1)*Attendance!$B$4:$AV$4),0),"")} | C96: =IF(A96<>"",SUMIFS(Transactions!$F$7:$F$989,Transactions!$D$7:$D$989,"Income",Transactions!$E$7:$E$989,A96),"") | D96: =IF(A96<>"",SUMIFS(Transactions!$F$7:$F$989,Transactions!$D$7:$D$989,"Expense",Transactions!$E$7:$E$989,A96),"") | E96: =IF(A96<>"",B96-C96-D96-G96,"") | F96: =IF(A96<>"",IF(E96=0,"Settled","Unsettled"),"") | G96: =IF(A96<>"",SUMIFS(Transactions!$F$7:$F$989,Transactions!$D$7:$D$989,"Credit",Transactions!$H$7:$H$989,A96),"")
A97: =IF(Roster!$A$95<>"",Roster!$A$95,"") | B97: {=IF(A97<>"",IFERROR(SUMPRODUCT((INDEX(Attendance!$B$7:$AV$206,MATCH(A97,Attendance!$A$7:$A$206,0),0)=1)*Attendance!$B$4:$AV$4),0),"")} | C97: =IF(A97<>"",SUMIFS(Transactions!$F$7:$F$989,Transactions!$D$7:$D$989,"Income",Transactions!$E$7:$E$989,A97),"") | D97: =IF(A97<>"",SUMIFS(Transactions!$F$7:$F$989,Transactions!$D$7:$D$989,"Expense",Transactions!$E$7:$E$989,A97),"") | E97: =IF(A97<>"",B97-C97-D97-G97,"") | F97: =IF(A97<>"",IF(E97=0,"Settled","Unsettled"),"") | G97: =IF(A97<>"",SUMIFS(Transactions!$F$7:$F$989,Transactions!$D$7:$D$989,"Credit",Transactions!$H$7:$H$989,A97),"")
A98: =IF(Roster!$A$96<>"",Roster!$A$96,"") | B98: {=IF(A98<>"",IFERROR(SUMPRODUCT((INDEX(Attendance!$B$7:$AV$206,MATCH(A98,Attendance!$A$7:$A$206,0),0)=1)*Attendance!$B$4:$AV$4),0),"")} | C98: =IF(A98<>"",SUMIFS(Transactions!$F$7:$F$989,Transactions!$D$7:$D$989,"Income",Transactions!$E$7:$E$989,A98),"") | D98: =IF(A98<>"",SUMIFS(Transactions!$F$7:$F$989,Transactions!$D$7:$D$989,"Expense",Transactions!$E$7:$E$989,A98),"") | E98: =IF(A98<>"",B98-C98-D98-G98,"") | F98: =IF(A98<>"",IF(E98=0,"Settled","Unsettled"),"") | G98: =IF(A98<>"",SUMIFS(Transactions!$F$7:$F$989,Transactions!$D$7:$D$989,"Credit",Transactions!$H$7:$H$989,A98),"")
A99: =IF(Roster!$A$97<>"",Roster!$A$97,"") | B99: {=IF(A99<>"",IFERROR(SUMPRODUCT((INDEX(Attendance!$B$7:$AV$206,MATCH(A99,Attendance!$A$7:$A$206,0),0)=1)*Attendance!$B$4:$AV$4),0),"")} | C99: =IF(A99<>"",SUMIFS(Transactions!$F$7:$F$989,Transactions!$D$7:$D$989,"Income",Transactions!$E$7:$E$989,A99),"") | D99: =IF(A99<>"",SUMIFS(Transactions!$F$7:$F$989,Transactions!$D$7:$D$989,"Expense",Transactions!$E$7:$E$989,A99),"") | E99: =IF(A99<>"",B99-C99-D99-G99,"") | F99: =IF(A99<>"",IF(E99=0,"Settled","Unsettled"),"") | G99: =IF(A99<>"",SUMIFS(Transactions!$F$7:$F$989,Transactions!$D$7:$D$989,"Credit",Transactions!$H$7:$H$989,A99),"")
A100: =IF(Roster!$A$98<>"",Roster!$A$98,"") | B100: {=IF(A100<>"",IFERROR(SUMPRODUCT((INDEX(Attendance!$B$7:$AV$206,MATCH(A100,Attendance!$A$7:$A$206,0),0)=1)*Attendance!$B$4:$AV$4),0),"")} | C100: =IF(A100<>"",SUMIFS(Transactions!$F$7:$F$989,Transactions!$D$7:$D$989,"Income",Transactions!$E$7:$E$989,A100),"") | D100: =IF(A100<>"",SUMIFS(Transactions!$F$7:$F$989,Transactions!$D$7:$D$989,"Expense",Transactions!$E$7:$E$989,A100),"") | E100: =IF(A100<>"",B100-C100-D100-G100,"") | F100: =IF(A100<>"",IF(E100=0,"Settled","Unsettled"),"") | G100: =IF(A100<>"",SUMIFS(Transactions!$F$7:$F$989,Transactions!$D$7:$D$989,"Credit",Transactions!$H$7:$H$989,A100),"")
A101: =IF(Roster!$A$99<>"",Roster!$A$99,"") | B101: {=IF(A101<>"",IFERROR(SUMPRODUCT((INDEX(Attendance!$B$7:$AV$206,MATCH(A101,Attendance!$A$7:$A$206,0),0)=1)*Attendance!$B$4:$AV$4),0),"")} | C101: =IF(A101<>"",SUMIFS(Transactions!$F$7:$F$989,Transactions!$D$7:$D$989,"Income",Transactions!$E$7:$E$989,A101),"") | D101: =IF(A101<>"",SUMIFS(Transactions!$F$7:$F$989,Transactions!$D$7:$D$989,"Expense",Transactions!$E$7:$E$989,A101),"") | E101: =IF(A101<>"",B101-C101-D101-G101,"") | F101: =IF(A101<>"",IF(E101=0,"Settled","Unsettled"),"") | G101: =IF(A101<>"",SUMIFS(Transactions!$F$7:$F$989,Transactions!$D$7:$D$989,"Credit",Transactions!$H$7:$H$989,A101),"")
A102: =IF(Roster!$A$100<>"",Roster!$A$100,"") | B102: {=IF(A102<>"",IFERROR(SUMPRODUCT((INDEX(Attendance!$B$7:$AV$206,MATCH(A102,Attendance!$A$7:$A$206,0),0)=1)*Attendance!$B$4:$AV$4),0),"")} | C102: =IF(A102<>"",SUMIFS(Transactions!$F$7:$F$989,Transactions!$D$7:$D$989,"Income",Transactions!$E$7:$E$989,A102),"") | D102: =IF(A102<>"",SUMIFS(Transactions!$F$7:$F$989,Transactions!$D$7:$D$989,"Expense",Transactions!$E$7:$E$989,A102),"") | E102: =IF(A102<>"",B102-C102-D102-G102,"") | F102: =IF(A102<>"",IF(E102=0,"Settled","Unsettled"),"") | G102: =IF(A102<>"",SUMIFS(Transactions!$F$7:$F$989,Transactions!$D$7:$D$989,"Credit",Transactions!$H$7:$H$989,A102),"")
...

Sheet Pending Approval
A1: PORT AUTHORITY - PENDING EXPENSE APPROVAL
A2: Fill in rows below for expenses you paid out of pocket. Do NOT edit the Approved? column.
A3: Date | B3: Description | C3: Category | D3: Type | E3: Paid By | F3: Amount ($) | G3: Linked Event | H3: Reimbursed To | I3: Notes | J3: Approved?
A4: 46236 | B4: Sarah KH PEC Car | C4: Travel | D4: Car Fee | E4: Sarah Kingsley-Hart | F4: 84 | G4: PEC | I4: Cleared
A5: 46199 | B5: Kindell gas + tolls | C5: Travel | D5: Expense | E5: Kindell | F5: 100.8 | G5: PEC | I5: Waiting till all car costs are in to add. Credit will be applied against dues. | M5: PEC Total Car fees
A6: 46228 | B6: Jake's Car Gas & Tolls | C6: Travel | D6: Expense | E6: Jake Murray | F6: =51.04+48.84+5.5+11.25 -> 116.63 | G6: SFI | M6: =sumif(G:G,"PEC",F:F) -> 293.02
A7: 46228 | B7: Haley Car Gas & tolls | C7: Travel | D7: Expense | E7: Haley | F7: 106.02 | G7: SFI
A8: 46227 | B8: Kasey's car fri only gas & tolls | C8: Travel | D8: Expense | E8: Kasey | F8: 55.5 | G8: SFI | M8: SFI Total Car fees
A9: 46239 | B9: Griffin Car SFI Gas | C9: Travel | D9: Expense | E9: Griffin | F9: 80 | G9: SFI | M9: =sumif(G:G,"SFI",F:F) -> 523.2
A10: 46258 | B10: DB Car ESC Gas | C10: Travel | D10: Expense | E10: DB | F10: 90 | G10: ESC
A11: 46258 | B11: Dick car ESC gas | C11: Travel | D11: Expense | E11: Dick | F11: 95.83 | G11: ESC | M11: ESC Total Car fees
A12: 46255 | B12: Harry Gas | C12: Travel | D12: Expense | E12: Harry Park | F12: 133.19 | G12: ESC | M12: =sumif(G:G,"ESC",F:F) -> 574.23
A13: 46260 | B13: Annette car gas ESC | C13: Travel | D13: Expense | E13: Annette | F13: 96.57 | G13: ESC
A14: 46201 | B14: Kevin car gas | C14: Travel | D14: Expense | E14: Kevin Nicholl | F14: 108.22 | G14: PEC
A15: 46227 | B15: Kevin car gas | C15: Travel | D15: Expense | E15: Kevin Nicholl | F15: 37.22 | G15: SFI
A16: 46228 | B16: Kindell car gas + tolls | C16: Travel | D16: Expense | E16: Kindell | F16: 127.83 | G16: SFI
A17: 46257 | B17: Kindell car gas (return trip) | C17: Travel | D17: Expense | E17: Kindell | F17: 43.52 | G17: ESC
B18: Shani Car Gas | C18: Travel | D18: Expense | E18: Shani Rosenthal | F18: 117.91 | G18: Regionals
B19: Shani Car Tolls | C19: Travel | D19: Expense | E19: Shani Rosenthal | F19: 32.78 | G19: Regionals
B20: Shani Car Parking | C20: Travel | D20: Expense | E20: Shani Rosenthal | F20: 30.55 | G20: Regionals
A21: 46257 | B21: Slynch Car Gas | C21: Travel | D21: Expense | E21: Slynch | F21: 115.12 | G21: ESC

Sheet Dashboard
A1: DASHBOARD â€” Auto-calculated Summary (Website reads this)
A3: TEAM OVERVIEW
A4: Total Players | B4: =COUNTA(Roster!A5:A204) -> 38
A5: Active Players | B5: =COUNTIF(Roster!E5:E204,"Active") -> 38
A6: Coaches/Staff | B6: =COUNTIF(Roster!D5:D204,"Coach")+COUNTIF(Roster!D5:D204,"Treasurer") -> 4
A7: Captains | B7: =COUNTIF(Roster!D5:D204,"Captain") -> 3
A9: FINANCES
A10: Total Dues Owed | B10: =SUMIF(Roster!E5:E204,"Active",Roster!B5:B204) -> 0
A11: Total Dues Collected | B11: =SUMIFS(Transactions!F7:F989,Transactions!D7:D989,"Income",Transactions!C7:C989,"Dues") -> 15313.6
A12: Dues Outstanding | B12: =B10-B11 -> -15313.6
A13: Total Income | B13: =Transactions!A4 -> 22487.2
A14: Total Expenses | B14: =Transactions!B4 -> 40876.53
A15: Net Balance | B15: =Transactions!C4 -> -18389.33
A16: Pending Transactions | B16: =Transactions!E4 -> 0
A18: EVENTS
A19: Total Events | B19: =COUNTA(Events!A5:A505) -> 14
A20: Practices | B20: =COUNTIF(Events!D5:D505,"Practice") -> 1
A21: Tournaments | B21: =Events!D4 -> Category
A22: Fundraisers | B22: =Events!D4 -> Category
A23: Total Budgeted | B23: =Events!H4
A24: Total Actual Spend | B24: =Events!I4 -> Split Method
A25: Budget Variance | B25: =Events!J4 -> Season Group

Sheet Key & Instructions
A1: KEY & INSTRUCTIONS
A3: COLOR CODING
A4: Blue text | B4: Enter data here â€” these are your inputs
A5: Black text (formula) | B5: Auto-calculated â€” do not edit
A6: Green text | B6: Pulls from another sheet â€” do not edit
A8: ACCESS CODES
A9: Access codes | B9: Set unique codes in the 'Access Codes' tab. Share each player's code only with them.
A10: Player view | B10: Players enter their code â†’ see only their own dues, balance, attendance
A11: Captain view | B11: Captains enter their code â†’ see full roster balances, event attendance summary
A12: Coach/Treasurer | B12: Full dashboard: all finances, all player balances, all transactions
A14: ATTENDANCE
A15: 1 = Attended | 0 = Absent | X = Exempt | B15: Player was present
A16: N = Absent | B16: Player did not attend
A17: X = Exempt â€” absent but excused/exempt from cost | B17: Absent but excused â€” may waive cost
A18: Row 4 in Attendance is auto-calculated from Events (Actual Cost Ã· attendees for "Attendance" events; Ã· roster size for "Equal Split" events) | B18: Row 6 in Attendance sheet â€” enter per-event cost, auto-calculates totals
A20: WORKFLOW
A21: 1. Roster | B21: Add all players/coaches, set unique access codes, set dues amounts
A22: 2. Events | B22: Log every event with budget and actual cost
A23: 3. Attendance | B23: Mark Y/N/E for each player per event; set cost per person in row 6
A24: 4. Transactions | B24: Log all money in/out; link to events where possible
A25: 5. Player Balances | B25: Update dues paid, event costs owed, upfront payments â€” net auto-calculates
A26: 6. Dashboard | B26: Auto-updates â€” this is what the website displays
A27: 7. Commit to GitHub | B27: Save file â†’ git add â†’ git commit â†’ git push â†’ website updates!
A29: SPLIT METHODS
A30: Equal Split | B30: Total cost Ã· all active players
A31: Attendance | B31: Total cost Ã· attendees only
A32: Custom | B32: Manual â€” enter individual amounts in Player Balances
A33: Team Pays | B33: Covered by team funds, no individual charge
A34: Individual Pays | B34: Person pays their own way, no reimbursement

Sheet Access Codes
A1: ðŸ”’ ACCESS CODES â€” TREASURER ONLY ðŸ”’
A2: âš ï¸_x008f_ HIDE THIS SHEET BEFORE SHARING THE FILE WITH PLAYERS âš ï¸_x008f_
A3: To hide: right-click this sheet tab â†’ 'Hide'. To unhide: right-click any tab â†’ 'Unhide'.
A5: Player Name | B5: Access Code | C5: Role | D5: Status | E5: Notes / Share Method
A6: At | B6: TA | C6: Captain | D6: Active
A7: Alex Warrington | B7: AW | C7: Player | D7: Active
A8: Chris Wohl | B8: CW | C8: Player | D8: Active
A9: Darra Reppermund | B9: DR | C9: Player | D9: Active
A10: Dylan Best | B10: DB | C10: Player | D10: Active
A11: Griffin O'Neal-Freeman | B11: GOF | C11: Player | D11: Active
A12: Haley Young | B12: HY | C12: Player | D12: Active
A13: Harry Park | B13: HP | C13: Player | D13: Active
A14: Ian Piper | B14: IP | C14: Player | D14: Active
A15: Jake Murray | B15: 1762 | C15: Treasurer | D15: Active
A16: Jenna Nold | B16: NJ | C16: Captain | D16: Active
A17: Jimmy Towle | B17: JT | C17: Player | D17: Active
A18: Kailey Rugani | B18: KR | C18: Player | D18: Active
A19: Kasey Schock | B19: KS | C19: Player | D19: Active
A20: Kevin Nicholl | B20: KN | C20: Player | D20: Active
A21: Kit Asterin | B21: AK | C21: Captain | D21: Active
A22: Kristin Dudley | B22: KD | C22: Player | D22: Active
A23: Lexie Thomas | B23: LT | C23: Player | D23: Active
A24: Lucas Jones | B24: LJ | C24: Player | D24: Active
A25: Max Sheppard | B25: MS | C25: Player | D25: Active
A26: Lucius Christie | B26: LC | C26: Player | D26: Active
A27: Patrick McMullen | B27: PM | C27: Player | D27: Active
... A43: Griff Alice | B43: GA | C43: Support | D43: Active
A107: ðŸ’¡ Tip: Codes can be anything â€” e.g. initials + jersey # + year. Make them easy to remember but hard to guess.

Sheet Settings
A1: PORT AUTHORITY - VIEW SETTINGS (TREASURER ONLY)
A2: Set "Show in Player View?" to Yes/No to control which events appear in the player My Balance breakdown.
A4: Season Group | B4: Show in Player View? | C4: Notes
A5: Pre-Season 2026 | B5: No | C5: Tryouts, scrimmages, early practices
A6: In-Season 2026 | B6: Yes | C6: Tournaments and regular season events

Sheet Retreat Expenses
C1: Airbnb costs | D1: Duffy beer | E1: Slynch Beer | F1: Annette Beer | G1: Dudley Beer | H1: Ian Beer | I1: Tofu Beer | J1: Griff food | K1: Dudley Food | L1: Total pp | N1: Tier 1 - Full | O1: Tier 2 - Air Mattress | P1: Tier 3 - One Night | Q1: Tier 4 - Last Minute Drop | R1: Tier 5 - Drop | T1: Total Tier 1: | U1: Total Tier 2: | V1: Total Tier 3: | W1: Total Tier 4: | X1: Total Tier 5:
A2: Alex Warrington | C2: 149 | D2: =D31/D32 -> 2.125 | E2: =E31/D32 -> 3.8495833 | F2: =F31/D32 -> 1.8229167 | G2: =G31/D32 -> 1.6004167 | H2: =H31/D32 -> 0.99458333 | I2: =180/24 -> 7.5 | J2: =J31/D32 -> 5.0604167 | K2: =K31/J32 -> 7.9416 | L2: =SUM(C2:K2) -> 179.89452 | M2: =round(L2,0) -> 180 | N2: =IF(M2=180, 1, 0) -> 1 | O2: =IF(M2=167, 1, 0) -> 0 | P2: =IF(M2=108, 1, 0) -> 0 | Q2: =IF(M2=70, 1, 0) -> 0 | R2: =IF(M2=25, 1, 0) -> 0 | T2: {=sum(N2:N29*L2:L29)} -> 3417.8245 | U2: {=sum(O2:O29*L2:L29)} -> 834.425 | V2: {=sum(P2:P29*L2:L29)} -> 107.94 | W2: {=sum(Q2:Q29*L2:L29)} -> 140 | X2: {=sum(R2:R29*L2:L29)} -> 25
A3: Annette | B3: air mattress | C3: 136 | D3: =D31/D32 -> 2.125 | E3: 3.85 | F3: 1.82 | G3: 1.6 | H3: 0.99 | I3: 7.5 | J3: 5.06 | K3: 7.94 | L3: =SUM(C3:K3) -> 166.885 | M3: =round(L3,0) -> 167 | N3: =IF(M3=180, 1, 0) -> 0 | O3: =IF(M3=167, 1, 0) -> 1 | P3: =IF(M3=108, 1, 0) -> 0 | Q3: =IF(M3=70, 1, 0) -> 0 | R3: =IF(M3=25, 1, 0) -> 0
A4: AT | C4: 149 | D4: 2.125 | E4: 3.85 | F4: 1.82 | G4: 1.6 | H4: 0.99 | I4: 7.5 | J4: 5.06 | K4: 7.94 | L4: =SUM(C4:K4) -> 179.885 | M4: =round(L4,0) -> 180 | N4: =IF(M4=180, 1, 0) -> 1 | O4: =IF(M4=167, 1, 0) -> 0 | P4: =IF(M4=108, 1, 0) -> 0 | Q4: =IF(M4=70, 1, 0) -> 0 | R4: =IF(M4=25, 1, 0) -> 0
A5: Chris Wohl | C5: 149 | D5: 2.125 | E5: 3.85 | F5: 1.82 | G5: 1.6 | H5: 0.99 | I5: 7.5 | J5: 5.06 | K5: 7.94 | L5: =SUM(C5:K5) -> 179.885 | M5: =round(L5,0) -> 180 | N5: =IF(M5=180, 1, 0) -> 1 | O5: =IF(M5=167, 1, 0) -> 0 | P5: =IF(M5=108, 1, 0) -> 0 | Q5: =IF(M5=70, 1, 0) -> 0 | R5: =IF(M5=25, 1, 0) -> 0
A6: Darra Reppermund | C6: 149 | D6: 2.125 | E6: 3.85 | F6: 1.82 | G6: 1.6 | H6: 0.99 | I6: 7.5 | J6: 5.06 | K6: 7.94 | L6: =SUM(C6:K6) -> 179.885 | M6: =round(L6,0) -> 180 | N6: =IF(M6=180, 1, 0) -> 1 | O6: =IF(M6=167, 1, 0) -> 0 | P6: =IF(M6=108, 1, 0) -> 0 | Q6: =IF(M6=70, 1, 0) -> 0 | R6: =IF(M6=25, 1, 0) -> 0
A7: Db | C7: 149 | D7: =51/24 -> 2.125 | E7: 3.85 | F7: 1.82 | G7: 1.6 | H7: 0.99 | I7: 7.5 | J7: 5.06 | K7: 7.94 | L7: =SUM(C7:K7) -> 179.885 | M7: =round(L7,0) -> 180 | N7: =IF(M7=180, 1, 0) -> 1 | O7: =IF(M7=167, 1, 0) -> 0 | P7: =IF(M7=108, 1, 0) -> 0 | Q7: =IF(M7=70, 1, 0) -> 0 | R7: =IF(M7=25, 1, 0) -> 0
A8: Dudley | C8: 149 | D8: =51/24 -> 2.125 | E8: 3.85 | F8: 1.82 | G8: 1.6 | H8: 0.99 | I8: 7.5 | J8: 5.06 | K8: 7.94 | L8: =SUM(C8:K8) -> 179.885 | M8: =round(L8,0) -> 180 | N8: =IF(M8=180, 1, 0) -> 1 | O8: =IF(M8=167, 1, 0) -> 0 | P8: =IF(M8=108, 1, 0) -> 0 | Q8: =IF(M8=70, 1, 0) -> 0 | R8: =IF(M8=25, 1, 0) -> 0
A9: Duffy | C9: 149 | D9: =51/24 -> 2.125 | E9: 3.85 | F9: 1.82 | G9: 1.6 | H9: 0.99 | I9: 7.5 | J9: 5.06 | K9: 7.94 | L9: =SUM(C9:K9) -> 179.885 | M9: =round(L9,0) -> 180 | N9: =IF(M9=180, 1, 0) -> 1 | O9: =IF(M9=167, 1, 0) -> 0 | P9: =IF(M9=108, 1, 0) -> 0 | Q9: =IF(M9=70, 1, 0) -> 0 | R9: =IF(M9=25, 1, 0) -> 0
A10: Griff Alice | C10: 149 | D10: =51/24 -> 2.125 | E10: 3.85 | F10: 1.82 | G10: 1.6 | H10: 0.99 | I10: 7.5 | J10: 5.06 | K10: 7.94 | L10: =SUM(C10:K10) -> 179.885 | M10: =round(L10,0) -> 180 | N10: =IF(M10=180, 1, 0) -> 1 | O10: =IF(M10=167, 1, 0) -> 0 | P10: =IF(M10=108, 1, 0) -> 0 | Q10: =IF(M10=70, 1, 0) -> 0 | R10: =IF(M10=25, 1, 0) -> 0
A11: Griff Soren | B11: air mattress | C11: 136 | D11: =51/24 -> 2.125 | E11: 3.85 | F11: 1.82 | G11: 1.6 | H11: 0.99 | I11: 7.5 | J11: 5.06 | K11: 7.94 | L11: =SUM(C11:K11) -> 166.885 | M11: =round(L11,0) -> 167 | N11: =IF(M11=180, 1, 0) -> 0 | O11: =IF(M11=167, 1, 0) -> 1 | P11: =IF(M11=108, 1, 0) -> 0 | Q11: =IF(M11=70, 1, 0) -> 0 | R11: =IF(M11=25, 1, 0) -> 0
A12: Griffin | B12: air mattress | C12: 136 | D12: =51/24 -> 2.125 | E12: 3.85 | F12: 1.82 | G12: 1.6 | H12: 0.99 | I12: 7.5 | J12: 5.06 | K12: 7.94 | L12: =SUM(C12:K12) -> 166.885 | M12: =round(L12,0) -> 167 | N12: =IF(M12=180, 1, 0) -> 0 | O12: =IF(M12=167, 1, 0) -> 1 | P12: =IF(M12=108, 1, 0) -> 0 | Q12: =IF(M12=70, 1, 0) -> 0 | R12: =IF(M12=25, 1, 0) -> 0
A13: Haley | B13: air mattress | C13: 136 | D13: =51/24 -> 2.125 | E13: 3.85 | F13: 1.82 | G13: 1.6 | H13: 0.99 | I13: 7.5 | J13: 5.06 | K13: 7.94 | L13: =SUM(C13:K13) -> 166.885 | M13: =round(L13,0) -> 167 | N13: =IF(M13=180, 1, 0) -> 0 | O13: =IF(M13=167, 1, 0) -> 1 | P13: =IF(M13=108, 1, 0) -> 0 | Q13: =IF(M13=70, 1, 0) -> 0 | R13: =IF(M13=25, 1, 0) -> 0
A14: Ian | B14: air mattress | C14: 136 | D14: =51/24 -> 2.125 | E14: 3.85 | F14: 1.82 | G14: 1.6 | H14: 0.99 | I14: 7.5 | J14: 5.06 | K14: 7.94 | L14: =SUM(C14:K14) -> 166.885 | M14: =round(L14,0) -> 167 | N14: =IF(M14=180, 1, 0) -> 0 | O14: =IF(M14=167, 1, 0) -> 1 | P14: =IF(M14=108, 1, 0) -> 0 | Q14: =IF(M14=70, 1, 0) -> 0 | R14: =IF(M14=25, 1, 0) -> 0
A15: Jake | C15: 149 | D15: =51/24 -> 2.125 | E15: 3.85 | F15: 1.82 | G15: 1.6 | H15: 0.99 | I15: 7.5 | J15: 5.06 | K15: 7.94 | L15: =SUM(C15:K15) -> 179.885 | M15: =round(L15,0) -> 180 | N15: =IF(M15=180, 1, 0) -> 1 | O15: =IF(M15=167, 1, 0) -> 0 | P15: =IF(M15=108, 1, 0) -> 0 | Q15: =IF(M15=70, 1, 0) -> 0 | R15: =IF(M15=25, 1, 0) -> 0
A16: Jimmy | C16: 149 | D16: =51/24 -> 2.125 | E16: 3.85 | F16: 1.82 | G16: 1.6 | H16: 0.99 | I16: 7.5 | J16: 5.06 | K16: 7.94 | L16: =SUM(C16:K16) -> 179.885 | M16: =round(L16,0) -> 180 | N16: =IF(M16=180, 1, 0) -> 1 | O16: =IF(M16=167, 1, 0) -> 0 | P16: =IF(M16=108, 1, 0) -> 0 | Q16: =IF(M16=70, 1, 0) -> 0 | R16: =IF(M16=25, 1, 0) -> 0
A17: Kit | C17: 149 | D17: =51/24 -> 2.125 | E17: 3.85 | F17: 1.82 | G17: 1.6 | H17: 0.99 | I17: 7.5 | J17: 5.06 | K17: 7.94 | L17: =SUM(C17:K17) -> 179.885 | M17: =round(L17,0) -> 180 | N17: =IF(M17=180, 1, 0) -> 1 | O17: =IF(M17=167, 1, 0) -> 0 | P17: =IF(M17=108, 1, 0) -> 0 | Q17: =IF(M17=70, 1, 0) -> 0 | R17: =IF(M17=25, 1, 0) -> 0
A18: Lexie | C18: 149 | D18: =51/24 -> 2.125 | E18: 3.85 | F18: 1.82 | G18: 1.6 | H18: 0.99 | I18: 7.5 | J18: 5.06 | K18: 7.94 | L18: =SUM(C18:K18) -> 179.885 | M18: =round(L18,0) -> 180 | N18: =IF(M18=180, 1, 0) -> 1 | O18: =IF(M18=167, 1, 0) -> 0 | P18: =IF(M18=108, 1, 0) -> 0 | Q18: =IF(M18=70, 1, 0) -> 0 | R18: =IF(M18=25, 1, 0) -> 0
A19: Lucas | C19: 149 | D19: =51/24 -> 2.125 | E19: 3.85 | F19: 1.82 | G19: 1.6 | H19: 0.99 | I19: 7.5 | J19: 5.06 | K19: 7.94 | L19: =SUM(C19:K19) -> 179.885 | M19: =round(L19,0) -> 180 | N19: =IF(M19=180, 1, 0) -> 1 | O19: =IF(M19=167, 1, 0) -> 0 | P19: =IF(M19=108, 1, 0) -> 0 | Q19: =IF(M19=70, 1, 0) -> 0 | R19: =IF(M19=25, 1, 0) -> 0
A20: lucius christie | C20: 149 | D20: =51/24 -> 2.125 | E20: 3.85 | F20: 1.82 | G20: 1.6 | H20: 0.99 | I20: 7.5 | J20: 5.06 | K20: 7.94 | L20: =SUM(C20:K20) -> 179.885 | M20: =round(L20,0) -> 180 | N20: =IF(M20=180, 1, 0) -> 1 | O20: =IF(M20=167, 1, 0) -> 0 | P20: =IF(M20=108, 1, 0) -> 0 | Q20: =IF(M20=70, 1, 0) -> 0 | R20: =IF(M20=25, 1, 0) -> 0
A21: Nick | C21: 149 | D21: =51/24 -> 2.125 | E21: 3.85 | F21: 1.82 | G21: 1.6 | H21: 0.99 | I21: 7.5 | J21: 5.06 | K21: 7.94 | L21: =SUM(C21:K21) -> 179.885 | M21: =round(L21,0) -> 180 | N21: =IF(M21=180, 1, 0) -> 1 | O21: =IF(M21=167, 1, 0) -> 0 | P21: =IF(M21=108, 1, 0) -> 0 | Q21: =IF(M21=70, 1, 0) -> 0 | R21: =IF(M21=25, 1, 0) -> 0
A22: PatMac! | C22: 149 | D22: =51/24 -> 2.125 | E22: 3.85 | F22: 1.82 | G22: 1.6 | H22: 0.99 | I22: 7.5 | J22: 5.06 | K22: 7.94 | L22: =SUM(C22:K22) -> 179.885 | M22: =round(L22,0) -> 180 | N22: =IF(M22=180, 1, 0) -> 1 | O22: =IF(M22=167, 1, 0) -> 0 | P22: =IF(M22=108, 1, 0) -> 0 | Q22: =IF(M22=70, 1, 0) -> 0 | R22: =IF(M22=25, 1, 0) -> 0
A23: Ringo | C23: 149 | D23: =51/24 -> 2.125 | E23: 3.85 | F23: 1.82 | G23: 1.6 | H23: 0.99 | I23: 7.5 | J23: 5.06 | K23: 7.94 | L23: =SUM(C23:K23) -> 179.885 | M23: =round(L23,0) -> 180 | N23: =IF(M23=180, 1, 0) -> 1 | O23: =IF(M23=167, 1, 0) -> 0 | P23: =IF(M23=108, 1, 0) -> 0 | Q23: =IF(M23=70, 1, 0) -> 0 | R23: =IF(M23=25, 1, 0) -> 0
A24: Slynch | C24: 149 | D24: =51/24 -> 2.125 | E24: 3.85 | F24: 1.82 | G24: 1.6 | H24: 0.99 | I24: 7.5 | J24: 5.06 | K24: 7.94 | L24: =SUM(C24:K24) -> 179.885 | M24: =round(L24,0) -> 180 | N24: =IF(M24=180, 1, 0) -> 1 | O24: =IF(M24=167, 1, 0) -> 0 | P24: =IF(M24=108, 1, 0) -> 0 | Q24: =IF(M24=70, 1, 0) -> 0 | R24: =IF(M24=25, 1, 0) -> 0
A25: Vivian | C25: 149 | D25: =51/24 -> 2.125 | E25: 3.85 | F25: 1.82 | G25: 1.6 | H25: 0.99 | I25: 7.5 | J25: 5.06 | K25: 7.94 | L25: =SUM(C25:K25) -> 179.885 | M25: =round(L25,0) -> 180 | N25: =IF(M25=180, 1, 0) -> 1 | O25: =IF(M25=167, 1, 0) -> 0 | P25: =IF(M25=108, 1, 0) -> 0 | Q25: =IF(M25=70, 1, 0) -> 0 | R25: =IF(M25=25, 1, 0) -> 0
A26: Rachel Graber | C26: 100 | K26: 7.94 | L26: =SUM(C26:K26) -> 107.94 | M26: =round(L26,0) -> 108 | N26: =IF(M26=180, 1, 0) -> 0 | O26: =IF(M26=167, 1, 0) -> 0 | P26: =IF(M26=108, 1, 0) -> 1 | Q26: =IF(M26=70, 1, 0) -> 0 | R26: =IF(M26=25, 1, 0) -> 0
A27: Kailey | C27: 70 | L27: =SUM(C27:K27) -> 70 | M27: =round(L27,0) -> 70 | N27: =IF(M27=180, 1, 0) -> 0 | O27: =IF(M27=167, 1, 0) -> 0 | P27: =IF(M27=108, 1, 0) -> 0 | Q27: =IF(M27=70, 1, 0) -> 1 | R27: =IF(M27=25, 1, 0) -> 0
A28: Shani | C28: 70 | L28: =SUM(C28:K28) -> 70 | M28: =round(L28,0) -> 70 | N28: =IF(M28=180, 1, 0) -> 0 | O28: =IF(M28=167, 1, 0) -> 0 | P28: =IF(M28=108, 1, 0) -> 0 | Q28: =IF(M28=70, 1, 0) -> 1 | R28: =IF(M28=25, 1, 0) -> 0
A29: Sarah | C29: 25 | L29: =SUM(C29:K29) -> 25 | M29: =round(L29,0) -> 25 | N29: =IF(M29=180, 1, 0) -> 0 | O29: =IF(M29=167, 1, 0) -> 0 | P29: =IF(M29=108, 1, 0) -> 0 | Q29: =IF(M29=70, 1, 0) -> 0 | R29: =IF(M29=25, 1, 0) -> 1
C30: =SUM(C2:C29) -> 3776 | N30: =SUM(N2:N29) -> 19
B31: Total | C31: 3780 | D31: 51 | E31: 92.39 | F31: 43.75 | G31: 38.41 | H31: 23.87 | I31: 180 | J31: 121.45 | K31: 198.54
D32: =COUNT(C2:C25) -> 24 | J32: =COUNTA(A2:A26) -> 25

Sheet Documentation
A1: Donations
A2: Annette | B2: 0.74097222 | C2: 46307 | D2: Jake, we’d like to use all the fundraising money for nationals except for $1,000 so there’s something to start next season. For fundraising, after it’s allocated for people who need assistance, we want that money to go directly split across the individual player bid fees
