Workbook

Sheet Roster
A1: ROSTER - Ultimate Frisbee Team
A4: Full Name | B4: Dues Amount ($) | C4: Dues Paid? | D4: Role | E4: Status | F4: Notes
A5: At | C5: Paid | D5: Captain | E5: Active
A6: Alex Warrington | C6: Unpaid | D6: Player | E6: Active
A7: Chris Wohl | C7: Partial | D7: Player | E7: Active | F7: Paid $75
A8: Darra Reppermund | C8: Waived | D8: Player | E8: Active
A9: Dylan Best | C9: Paid | D9: Player | E9: Active
A10: Griffin O'Neal-Freeman | D10: Player
A11: Haley Young | D11: Player
A12: Harry Park | D12: Player
A13: Ian Piper | D13: Player
A14: Jake Murray | D14: Treasurer
A15: Jenna Nold | D15: Captain
A16: Jimmy Towle | D16: Player
A17: Kailey Rugani | D17: Player
A18: Kasey Schock | D18: Player
A19: Kevin Nicholl | D19: Player
A20: Kit Asterin | D20: Captain
A21: Kristin Dudley | D21: Player
... A38: Nick Blair | D38: Player

Sheet Events
A1: EVENTS MASTER - All Team Events & Costs
A4: Event Name | B4: Start Date | C4: End Date | D4: Category | E4: Location | F4: Budgeted Cost ($) | G4: Actual Cost ($) | H4: Who Paid Upfront | I4: Split Method | J4: Notes
A5: May-July Fields | B5: 03/15/2025 | D5: Practice | E5: Dan Marino | F5: 850 | G5: =IFERROR(SUMIFS(Transactions!$F$7:$F$996,Transactions!$G$7:$G$996,A5,Transactions!$D$7:$D$996,"Expense"),0) -> 0 | H5: Jake Murray | I5: Equal Split
A6: Wednedsay Tryout Field | B6: 03/15/2025 | D6: Practice | E6: Dan Marino | F6: 69 | G6: =IFERROR(SUMIFS(Transactions!$F$7:$F$996,Transactions!$G$7:$G$996,A6,Transactions!$D$7:$D$996,"Expense"),0) -> 0 | H6: Jake Murray | I6: Equal Split | J6: One time payment
A7: PEC | B7: 03/18/2025 | D7: Tournament | E7: Browns Summit | F7: 1310 | G7: 1310 | H7: Jake Murray | I7: Attendance
A8: SFI | B8: 03/14/2025 | D8: Tournament | E8: Holiday Inn Downtown | F8: 1050 | G8: 1050 | H8: Jake Murray | I8: Attendance
A9: Natties Watch Party | D9: Fundraiser | E9: Goodlander | F9: 0 | G9: -123 | H9: Jake Murray
A10: Fantapalooza | B10: 45706 | D10: Fundraiser | E10: Goodlander | F10: 0 | G10: -956 | H10: Jake Murray
A11: 2025 Fundraising | B11: 45706 | D11: Fundraiser | E11: Mult. | F11: 0 | G11: 1030 | H11: Jake Murray
A12: GHP Sessions | D12: Event | E12: GHP | F12: 600 | G12: =IFERROR(SUMIFS(Transactions!$F$7:$F$996,Transactions!$G$7:$G$996,A12,Transactions!$D$7:$D$996,"Expense"),0) -> 0 | H12: Jake Murray | I12: Attendance
G13: =IFERROR(SUMIFS(Transactions!$F$7:$F$996,Transactions!$G$7:$G$996,A13,Transactions!$D$7:$D$996,"Expense"),0) -> 0
G14: =IFERROR(SUMIFS(Transactions!$F$7:$F$996,Transactions!$G$7:$G$996,A14,Transactions!$D$7:$D$996,"Expense"),0) -> 0
G15: =IFERROR(SUMIFS(Transactions!$F$7:$F$996,Transactions!$G$7:$G$996,A15,Transactions!$D$7:$D$996,"Expense"),0) -> 0
G16: =IFERROR(SUMIFS(Transactions!$F$7:$F$996,Transactions!$G$7:$G$996,A16,Transactions!$D$7:$D$996,"Expense"),0) -> 0
G17: =IFERROR(SUMIFS(Transactions!$F$7:$F$996,Transactions!$G$7:$G$996,A17,Transactions!$D$7:$D$996,"Expense"),0) -> 0
G18: =IFERROR(SUMIFS(Transactions!$F$7:$F$996,Transactions!$G$7:$G$996,A18,Transactions!$D$7:$D$996,"Expense"),0) -> 0
G19: =IFERROR(SUMIFS(Transactions!$F$7:$F$996,Transactions!$G$7:$G$996,A19,Transactions!$D$7:$D$996,"Expense"),0) -> 0
G20: =IFERROR(SUMIFS(Transactions!$F$7:$F$996,Transactions!$G$7:$G$996,A20,Transactions!$D$7:$D$996,"Expense"),0) -> 0
G21: =IFERROR(SUMIFS(Transactions!$F$7:$F$996,Transactions!$G$7:$G$996,A21,Transactions!$D$7:$D$996,"Expense"),0) -> 0
G22: =IFERROR(SUMIFS(Transactions!$F$7:$F$996,Transactions!$G$7:$G$996,A22,Transactions!$D$7:$D$996,"Expense"),0) -> 0
G23: =IFERROR(SUMIFS(Transactions!$F$7:$F$996,Transactions!$G$7:$G$996,A23,Transactions!$D$7:$D$996,"Expense"),0) -> 0
G24: =IFERROR(SUMIFS(Transactions!$F$7:$F$996,Transactions!$G$7:$G$996,A24,Transactions!$D$7:$D$996,"Expense"),0) -> 0
... G505: =IFERROR(SUMIFS(Transactions!$F$7:$F$996,Transactions!$G$7:$G$996,A505,Transactions!$D$7:$D$996,"Expense"),0) -> 0

Sheet Attendance
B1: ATTENDANCE TRACKER
A3: Player Name | B3: =IF(Events!$A$5<>"",Events!$A$5,"") -> May-July Fields | C3: =IF(Events!$A$7<>"",Events!$A$7,"") -> PEC | D3: =IF(Events!$A$8<>"",Events!$A$8,"") -> SFI | E3: =IF(#REF!<>"",#REF!,"") -> #REF! | F3: =IF(Events!$A$10<>"",Events!$A$10,"") -> Fantapalooza | G3: =IF(Events!$A$12<>"",Events!$A$12,"") -> GHP Sessions | H3: =IF(#REF!<>"",#REF!,"") -> #REF! | I3: =IF(Events!$A$13<>"",Events!$A$13,"") | J3: =IF(Events!$A$14<>"",Events!$A$14,"") | K3: =IF(Events!$A$15<>"",Events!$A$15,"") | L3: =IF(Events!$A$16<>"",Events!$A$16,"") | M3: =IF(Events!$A$17<>"",Events!$A$17,"") | N3: =IF(Events!$A$18<>"",Events!$A$18,"") | O3: =IF(Events!$A$19<>"",Events!$A$19,"") | P3: =IF(Events!$A$20<>"",Events!$A$20,"") | Q3: =IF(Events!$A$21<>"",Events!$A$21,"") | R3: =IF(Events!$A$22<>"",Events!$A$22,"") | S3: =IF(Events!$A$23<>"",Events!$A$23,"") | T3: =IF(Events!$A$24<>"",Events!$A$24,"") | U3: =IF(Events!$A$25<>"",Events!$A$25,"") | V3: =IF(Events!$A$26<>"",Events!$A$26,"") | W3: =IF(Events!$A$27<>"",Events!$A$27,"") | X3: =IF(Events!$A$28<>"",Events!$A$28,"") | Y3: =IF(Events!$A$29<>"",Events!$A$29,"") | Z3: =IF(Events!$A$30<>"",Events!$A$30,"") | AA3: =IF(Events!$A$31<>"",Events!$A$31,"") | AB3: =IF(Events!$A$32<>"",Events!$A$32,"") | AC3: =IF(Events!$A$33<>"",Events!$A$33,"") | AD3: =IF(Events!$A$34<>"",Events!$A$34,"") | AE3: =IF(Events!$A$35<>"",Events!$A$35,"") | AF3: =IF(Events!$A$36<>"",Events!$A$36,"") | AG3: =IF(Events!$A$37<>"",Events!$A$37,"") | AH3: =IF(Events!$A$38<>"",Events!$A$38,"") | AI3: =IF(Events!$A$39<>"",Events!$A$39,"") | AJ3: =IF(Events!$A$40<>"",Events!$A$40,"") | AK3: =IF(Events!$A$41<>"",Events!$A$41,"") | AL3: =IF(Events!$A$42<>"",Events!$A$42,"") | AM3: =IF(Events!$A$43<>"",Events!$A$43,"") | AN3: =IF(Events!$A$44<>"",Events!$A$44,"") | AO3: =IF(Events!$A$45<>"",Events!$A$45,"") | AP3: =IF(Events!$A$46<>"",Events!$A$46,"") | AQ3: =IF(Events!$A$47<>"",Events!$A$47,"") | AR3: =IF(Events!$A$48<>"",Events!$A$48,"") | AS3: =IF(Events!$A$49<>"",Events!$A$49,"") | AT3: =IF(Events!$A$50<>"",Events!$A$50,"") | AU3: =IF(Events!$A$51<>"",Events!$A$51,"") | AV3: =IF(Events!$A$52<>"",Events!$A$52,"") | AW3: =IF(Events!$A$53<>"",Events!$A$53,"") | AX3: =IF(Events!$A$54<>"",Events!$A$54,"") | AY3: =IF(Events!$A$55<>"",Events!$A$55,"")
A4: Cost per Person ($) [auto] | B4: =IFERROR(IF(Events!$A$5<>"",IF(Events!$I$5="Equal Split",Events!$G$5/MAX(1,COUNTA(Roster!$A$5:$A$204)),Events!$G$5/MAX(1,COUNTIF(B$7:B$206,"1"))),0),0) -> 0 | C4: =IFERROR(IF(Events!$A$7<>"",IF(Events!$I$7="Equal Split",Events!$G$7/MAX(1,COUNTA(Roster!$A$5:$A$204)),Events!$G$7/MAX(1,COUNTIF(C$7:C$206,"1"))),0),0) -> 50.384615 | D4: =IFERROR(IF(Events!$A$8<>"",IF(Events!$I$8="Equal Split",Events!$G$8/MAX(1,COUNTA(Roster!$A$5:$A$204)),Events!$G$8/MAX(1,COUNTIF(D$7:D$206,"1"))),0),0) -> 40.384615 | E4: =IFERROR(IF(#REF!<>"",IF(#REF!="Equal Split",#REF!/MAX(1,COUNTA(Roster!$A$5:$A$204)),#REF!/MAX(1,COUNTIF(E$7:E$206,"1"))),0),0) -> 0 | F4: =IFERROR(IF(Events!$A$10<>"",IF(Events!$I$10="Equal Split",Events!$G$10/MAX(1,COUNTA(Roster!$A$5:$A$204)),Events!$G$10/MAX(1,COUNTIF(F$7:F$206,"1"))),0),0) -> -956 | G4: =IFERROR(IF(Events!$A$12<>"",IF(Events!$I$12="Equal Split",Events!$G$12/MAX(1,COUNTA(Roster!$A$5:$A$204)),Events!$G$12/MAX(1,COUNTIF(G$7:G$206,"1"))),0),0) -> 0 | H4: =IFERROR(IF(#REF!<>"",IF(#REF!="Equal Split",#REF!/MAX(1,COUNTA(Roster!$A$5:$A$204)),#REF!/MAX(1,COUNTIF(H$7:H$206,"1"))),0),0) -> 0 | I4: =IFERROR(IF(Events!$A$13<>"",IF(Events!$I$13="Equal Split",Events!$G$13/MAX(1,COUNTA(Roster!$A$5:$A$204)),Events!$G$13/MAX(1,COUNTIF(I$7:I$206,"1"))),0),0) -> 0 | J4: =IFERROR(IF(Events!$A$14<>"",IF(Events!$I$14="Equal Split",Events!$G$14/MAX(1,COUNTA(Roster!$A$5:$A$204)),Events!$G$14/MAX(1,COUNTIF(J$7:J$206,"1"))),0),0) -> 0 | K4: =IFERROR(IF(Events!$A$15<>"",IF(Events!$I$15="Equal Split",Events!$G$15/MAX(1,COUNTA(Roster!$A$5:$A$204)),Events!$G$15/MAX(1,COUNTIF(K$7:K$206,"1"))),0),0) -> 0 | L4: =IFERROR(IF(Events!$A$16<>"",IF(Events!$I$16="Equal Split",Events!$G$16/MAX(1,COUNTA(Roster!$A$5:$A$204)),Events!$G$16/MAX(1,COUNTIF(L$7:L$206,"1"))),0),0) -> 0 | M4: =IFERROR(IF(Events!$A$17<>"",IF(Events!$I$17="Equal Split",Events!$G$17/MAX(1,COUNTA(Roster!$A$5:$A$204)),Events!$G$17/MAX(1,COUNTIF(M$7:M$206,"1"))),0),0) -> 0 | N4: =IFERROR(IF(Events!$A$18<>"",IF(Events!$I$18="Equal Split",Events!$G$18/MAX(1,COUNTA(Roster!$A$5:$A$204)),Events!$G$18/MAX(1,COUNTIF(N$7:N$206,"1"))),0),0) -> 0 | O4: =IFERROR(IF(Events!$A$19<>"",IF(Events!$I$19="Equal Split",Events!$G$19/MAX(1,COUNTA(Roster!$A$5:$A$204)),Events!$G$19/MAX(1,COUNTIF(O$7:O$206,"1"))),0),0) -> 0 | P4: =IFERROR(IF(Events!$A$20<>"",IF(Events!$I$20="Equal Split",Events!$G$20/MAX(1,COUNTA(Roster!$A$5:$A$204)),Events!$G$20/MAX(1,COUNTIF(P$7:P$206,"1"))),0),0) -> 0 | Q4: =IFERROR(IF(Events!$A$21<>"",IF(Events!$I$21="Equal Split",Events!$G$21/MAX(1,COUNTA(Roster!$A$5:$A$204)),Events!$G$21/MAX(1,COUNTIF(Q$7:Q$206,"1"))),0),0) -> 0 | R4: =IFERROR(IF(Events!$A$22<>"",IF(Events!$I$22="Equal Split",Events!$G$22/MAX(1,COUNTA(Roster!$A$5:$A$204)),Events!$G$22/MAX(1,COUNTIF(R$7:R$206,"1"))),0),0) -> 0 | S4: =IFERROR(IF(Events!$A$23<>"",IF(Events!$I$23="Equal Split",Events!$G$23/MAX(1,COUNTA(Roster!$A$5:$A$204)),Events!$G$23/MAX(1,COUNTIF(S$7:S$206,"1"))),0),0) -> 0 | T4: =IFERROR(IF(Events!$A$24<>"",IF(Events!$I$24="Equal Split",Events!$G$24/MAX(1,COUNTA(Roster!$A$5:$A$204)),Events!$G$24/MAX(1,COUNTIF(T$7:T$206,"1"))),0),0) -> 0 | U4: =IFERROR(IF(Events!$A$25<>"",IF(Events!$I$25="Equal Split",Events!$G$25/MAX(1,COUNTA(Roster!$A$5:$A$204)),Events!$G$25/MAX(1,COUNTIF(U$7:U$206,"1"))),0),0) -> 0 | V4: =IFERROR(IF(Events!$A$26<>"",IF(Events!$I$26="Equal Split",Events!$G$26/MAX(1,COUNTA(Roster!$A$5:$A$204)),Events!$G$26/MAX(1,COUNTIF(V$7:V$206,"1"))),0),0) -> 0 | W4: =IFERROR(IF(Events!$A$27<>"",IF(Events!$I$27="Equal Split",Events!$G$27/MAX(1,COUNTA(Roster!$A$5:$A$204)),Events!$G$27/MAX(1,COUNTIF(W$7:W$206,"1"))),0),0) -> 0 | X4: =IFERROR(IF(Events!$A$28<>"",IF(Events!$I$28="Equal Split",Events!$G$28/MAX(1,COUNTA(Roster!$A$5:$A$204)),Events!$G$28/MAX(1,COUNTIF(X$7:X$206,"1"))),0),0) -> 0 | Y4: =IFERROR(IF(Events!$A$29<>"",IF(Events!$I$29="Equal Split",Events!$G$29/MAX(1,COUNTA(Roster!$A$5:$A$204)),Events!$G$29/MAX(1,COUNTIF(Y$7:Y$206,"1"))),0),0) -> 0 | Z4: =IFERROR(IF(Events!$A$30<>"",IF(Events!$I$30="Equal Split",Events!$G$30/MAX(1,COUNTA(Roster!$A$5:$A$204)),Events!$G$30/MAX(1,COUNTIF(Z$7:Z$206,"1"))),0),0) -> 0 | AA4: =IFERROR(IF(Events!$A$31<>"",IF(Events!$I$31="Equal Split",Events!$G$31/MAX(1,COUNTA(Roster!$A$5:$A$204)),Events!$G$31/MAX(1,COUNTIF(AA$7:AA$206,"1"))),0),0) -> 0 | AB4: =IFERROR(IF(Events!$A$32<>"",IF(Events!$I$32="Equal Split",Events!$G$32/MAX(1,COUNTA(Roster!$A$5:$A$204)),Events!$G$32/MAX(1,COUNTIF(AB$7:AB$206,"1"))),0),0) -> 0 | AC4: =IFERROR(IF(Events!$A$33<>"",IF(Events!$I$33="Equal Split",Events!$G$33/MAX(1,COUNTA(Roster!$A$5:$A$204)),Events!$G$33/MAX(1,COUNTIF(AC$7:AC$206,"1"))),0),0) -> 0 | AD4: =IFERROR(IF(Events!$A$34<>"",IF(Events!$I$34="Equal Split",Events!$G$34/MAX(1,COUNTA(Roster!$A$5:$A$204)),Events!$G$34/MAX(1,COUNTIF(AD$7:AD$206,"1"))),0),0) -> 0 | AE4: =IFERROR(IF(Events!$A$35<>"",IF(Events!$I$35="Equal Split",Events!$G$35/MAX(1,COUNTA(Roster!$A$5:$A$204)),Events!$G$35/MAX(1,COUNTIF(AE$7:AE$206,"1"))),0),0) -> 0 | AF4: =IFERROR(IF(Events!$A$36<>"",IF(Events!$I$36="Equal Split",Events!$G$36/MAX(1,COUNTA(Roster!$A$5:$A$204)),Events!$G$36/MAX(1,COUNTIF(AF$7:AF$206,"1"))),0),0) -> 0 | AG4: =IFERROR(IF(Events!$A$37<>"",IF(Events!$I$37="Equal Split",Events!$G$37/MAX(1,COUNTA(Roster!$A$5:$A$204)),Events!$G$37/MAX(1,COUNTIF(AG$7:AG$206,"1"))),0),0) -> 0 | AH4: =IFERROR(IF(Events!$A$38<>"",IF(Events!$I$38="Equal Split",Events!$G$38/MAX(1,COUNTA(Roster!$A$5:$A$204)),Events!$G$38/MAX(1,COUNTIF(AH$7:AH$206,"1"))),0),0) -> 0 | AI4: =IFERROR(IF(Events!$A$39<>"",IF(Events!$I$39="Equal Split",Events!$G$39/MAX(1,COUNTA(Roster!$A$5:$A$204)),Events!$G$39/MAX(1,COUNTIF(AI$7:AI$206,"1"))),0),0) -> 0 | AJ4: =IFERROR(IF(Events!$A$40<>"",IF(Events!$I$40="Equal Split",Events!$G$40/MAX(1,COUNTA(Roster!$A$5:$A$204)),Events!$G$40/MAX(1,COUNTIF(AJ$7:AJ$206,"1"))),0),0) -> 0 | AK4: =IFERROR(IF(Events!$A$41<>"",IF(Events!$I$41="Equal Split",Events!$G$41/MAX(1,COUNTA(Roster!$A$5:$A$204)),Events!$G$41/MAX(1,COUNTIF(AK$7:AK$206,"1"))),0),0) -> 0 | AL4: =IFERROR(IF(Events!$A$42<>"",IF(Events!$I$42="Equal Split",Events!$G$42/MAX(1,COUNTA(Roster!$A$5:$A$204)),Events!$G$42/MAX(1,COUNTIF(AL$7:AL$206,"1"))),0),0) -> 0 | AM4: =IFERROR(IF(Events!$A$43<>"",IF(Events!$I$43="Equal Split",Events!$G$43/MAX(1,COUNTA(Roster!$A$5:$A$204)),Events!$G$43/MAX(1,COUNTIF(AM$7:AM$206,"1"))),0),0) -> 0 | AN4: =IFERROR(IF(Events!$A$44<>"",IF(Events!$I$44="Equal Split",Events!$G$44/MAX(1,COUNTA(Roster!$A$5:$A$204)),Events!$G$44/MAX(1,COUNTIF(AN$7:AN$206,"1"))),0),0) -> 0 | AO4: =IFERROR(IF(Events!$A$45<>"",IF(Events!$I$45="Equal Split",Events!$G$45/MAX(1,COUNTA(Roster!$A$5:$A$204)),Events!$G$45/MAX(1,COUNTIF(AO$7:AO$206,"1"))),0),0) -> 0 | AP4: =IFERROR(IF(Events!$A$46<>"",IF(Events!$I$46="Equal Split",Events!$G$46/MAX(1,COUNTA(Roster!$A$5:$A$204)),Events!$G$46/MAX(1,COUNTIF(AP$7:AP$206,"1"))),0),0) -> 0 | AQ4: =IFERROR(IF(Events!$A$47<>"",IF(Events!$I$47="Equal Split",Events!$G$47/MAX(1,COUNTA(Roster!$A$5:$A$204)),Events!$G$47/MAX(1,COUNTIF(AQ$7:AQ$206,"1"))),0),0) -> 0 | AR4: =IFERROR(IF(Events!$A$48<>"",IF(Events!$I$48="Equal Split",Events!$G$48/MAX(1,COUNTA(Roster!$A$5:$A$204)),Events!$G$48/MAX(1,COUNTIF(AR$7:AR$206,"1"))),0),0) -> 0 | AS4: =IFERROR(IF(Events!$A$49<>"",IF(Events!$I$49="Equal Split",Events!$G$49/MAX(1,COUNTA(Roster!$A$5:$A$204)),Events!$G$49/MAX(1,COUNTIF(AS$7:AS$206,"1"))),0),0) -> 0 | AT4: =IFERROR(IF(Events!$A$50<>"",IF(Events!$I$50="Equal Split",Events!$G$50/MAX(1,COUNTA(Roster!$A$5:$A$204)),Events!$G$50/MAX(1,COUNTIF(AT$7:AT$206,"1"))),0),0) -> 0 | AU4: =IFERROR(IF(Events!$A$51<>"",IF(Events!$I$51="Equal Split",Events!$G$51/MAX(1,COUNTA(Roster!$A$5:$A$204)),Events!$G$51/MAX(1,COUNTIF(AU$7:AU$206,"1"))),0),0) -> 0 | AV4: =IFERROR(IF(Events!$A$52<>"",IF(Events!$I$52="Equal Split",Events!$G$52/MAX(1,COUNTA(Roster!$A$5:$A$204)),Events!$G$52/MAX(1,COUNTIF(AV$7:AV$206,"1"))),0),0) -> 0 | AW4: =IFERROR(IF(Events!$A$53<>"",IF(Events!$I$53="Equal Split",Events!$G$53/MAX(1,COUNTA(Roster!$A$5:$A$204)),Events!$G$53/MAX(1,COUNTIF(AW$7:AW$206,"1"))),0),0) -> 0 | AX4: =IFERROR(IF(Events!$A$54<>"",IF(Events!$I$54="Equal Split",Events!$G$54/MAX(1,COUNTA(Roster!$A$5:$A$204)),Events!$G$54/MAX(1,COUNTIF(AX$7:AX$206,"1"))),0),0) -> 0 | AY4: =IFERROR(IF(Events!$A$55<>"",IF(Events!$I$55="Equal Split",Events!$G$55/MAX(1,COUNTA(Roster!$A$5:$A$204)),Events!$G$55/MAX(1,COUNTIF(AY$7:AY$206,"1"))),0),0) -> 0
A5: Total Attendees | B5: =COUNTIF(B7:B206,"1") -> 0 | C5: =COUNTIF(C7:C206,"1") -> 26 | D5: =COUNTIF(D7:D206,"1") -> 26 | E5: =COUNTIF(E7:E206,"1") -> 0 | F5: =COUNTIF(F7:F206,"1") -> 0 | G5: =COUNTIF(G7:G206,"1") -> 0 | H5: =COUNTIF(H7:H206,"1") -> 0 | I5: =COUNTIF(I7:I206,"1") -> 0 | ... AY5: =COUNTIF(AY7:AY206,"1") -> 0
A6: Total Cost ($) | B6: =B4*B5 -> 0 | C6: =C4*C5 -> 1310 | D6: =D4*D5 -> 1050 | E6: =E4*E5 -> 0 | F6: =F4*F5 -> 0 | G6: =G4*G5 -> 0 | H6: =H4*H5 -> 0 | I6: =I4*I5 -> 0 | ... AY6: =AY4*AY5 -> 0
A7: =IF(Roster!$A$5<>"",Roster!$A$5,"") -> At | C7: 1 | D7: 1
A8: =IF(Roster!$A$6<>"",Roster!$A$6,"") -> Alex Warrington | C8: 1 | D8: 1
A9: =IF(Roster!$A$7<>"",Roster!$A$7,"") -> Chris Wohl | C9: 1 | D9: 1
A10: =IF(Roster!$A$8<>"",Roster!$A$8,"") -> Darra Reppermund | C10: 1 | D10: 1
A11: =IF(Roster!$A$9<>"",Roster!$A$9,"") -> Dylan Best | C11: 1 | D11: 1
A12: =IF(Roster!$A$10<>"",Roster!$A$10,"") -> Griffin O'Neal-Freeman | C12: 1 | D12: 1
A13: =IF(Roster!$A$11<>"",Roster!$A$11,"") -> Haley Young | C13: 1 | D13: 1
A14: =IF(Roster!$A$12<>"",Roster!$A$12,"") -> Harry Park | C14: 1 | D14: 1
A15: =IF(Roster!$A$13<>"",Roster!$A$13,"") -> Ian Piper | C15: 1 | D15: 1
A16: =IF(Roster!$A$14<>"",Roster!$A$14,"") -> Jake Murray | C16: 1 | D16: 1
A17: =IF(Roster!$A$15<>"",Roster!$A$15,"") -> Jenna Nold | C17: 1 | D17: 1
A18: =IF(Roster!$A$16<>"",Roster!$A$16,"") -> Jimmy Towle | C18: 0 | D18: 0
A19: =IF(Roster!$A$17<>"",Roster!$A$17,"") -> Kailey Rugani | C19: 1 | D19: 1
A20: =IF(Roster!$A$18<>"",Roster!$A$18,"") -> Kasey Schock | C20: 1 | D20: 1
A21: =IF(Roster!$A$19<>"",Roster!$A$19,"") -> Kevin Nicholl | C21: 1 | D21: 1
A22: =IF(Roster!$A$20<>"",Roster!$A$20,"") -> Kit Asterin | C22: 1 | D22: 1
A23: =IF(Roster!$A$21<>"",Roster!$A$21,"") -> Kristin Dudley | C23: 1 | D23: 1
A24: =IF(Roster!$A$22<>"",Roster!$A$22,"") -> Lexie Thomas | C24: 1 | D24: 1
A25: =IF(Roster!$A$23<>"",Roster!$A$23,"") -> Lucas Jones | C25: 0 | D25: 0
A26: =IF(Roster!$A$24<>"",Roster!$A$24,"") -> Lucius Christie | C26: 1 | D26: 1
A27: =IF(Roster!$A$25<>"",Roster!$A$25,"") -> Patrick McMullen | C27: 1 | D27: 1
A28: =IF(Roster!$A$26<>"",Roster!$A$26,"") -> Rachel Graber | C28: 1 | D28: 1
A29: =IF(Roster!$A$27<>"",Roster!$A$27,"") -> Ryan Kindell | C29: 1 | D29: 1
A30: =IF(Roster!$A$28<>"",Roster!$A$28,"") -> Ryan Ward | C30: 1 | D30: 1
A31: =IF(Roster!$A$29<>"",Roster!$A$29,"") -> Sam Gombiner | C31: 0 | D31: 0
A32: =IF(Roster!$A$30<>"",Roster!$A$30,"") -> Sarah Kingsley-Hart | C32: 1 | D32: 1
A33: =IF(Roster!$A$31<>"",Roster!$A$31,"") -> Sarah Lynch | C33: 1 | D33: 1
A34: =IF(Roster!$A$32<>"",Roster!$A$32,"") -> Shani Rosenthal | C34: 1 | D34: 1
A35: =IF(Roster!$A$33<>"",Roster!$A$33,"") -> Vivian Shen | C35: 1 | D35: 1
A36: =IF(Roster!$A$34<>"",Roster!$A$34,"") -> Zach Esakof | C36: 0 | D36: 0
A37: =IF(Roster!$A$35<>"",Roster!$A$35,"") -> Annette Kukunas-Piper | C37: X | D37: X
A38: =IF(Roster!$A$36<>"",Roster!$A$36,"") -> Matt Duffy | C38: X | D38: X
A39: =IF(Roster!$A$37<>"",Roster!$A$37,"") -> Ryan Birchard | C39: X | D39: X
A40: =IF(Roster!$A$38<>"",Roster!$A$38,"") -> Nick Blair | C40: X | D40: X
A41: =IF(Roster!$A$39<>"",Roster!$A$39,"")
A42: =IF(Roster!$A$40<>"",Roster!$A$40,"")
A43: =IF(Roster!$A$41<>"",Roster!$A$41,"")
A44: =IF(Roster!$A$42<>"",Roster!$A$42,"")
A45: =IF(Roster!$A$43<>"",Roster!$A$43,"")
A46: =IF(Roster!$A$44<>"",Roster!$A$44,"")
A47: =IF(Roster!$A$45<>"",Roster!$A$45,"")
A48: =IF(Roster!$A$46<>"",Roster!$A$46,"")
A49: =IF(Roster!$A$47<>"",Roster!$A$47,"")
A50: =IF(Roster!$A$48<>"",Roster!$A$48,"")
A51: =IF(Roster!$A$49<>"",Roster!$A$49,"")
A52: =IF(Roster!$A$50<>"",Roster!$A$50,"")
A53: =IF(Roster!$A$51<>"",Roster!$A$51,"")
A54: =IF(Roster!$A$52<>"",Roster!$A$52,"")
A55: =IF(Roster!$A$53<>"",Roster!$A$53,"")
A56: =IF(Roster!$A$54<>"",Roster!$A$54,"")
A57: =IF(Roster!$A$55<>"",Roster!$A$55,"")
A58: =IF(Roster!$A$56<>"",Roster!$A$56,"")
A59: =IF(Roster!$A$57<>"",Roster!$A$57,"")
A60: =IF(Roster!$A$58<>"",Roster!$A$58,"")
A61: =IF(Roster!$A$59<>"",Roster!$A$59,"")
A62: =IF(Roster!$A$60<>"",Roster!$A$60,"")
A63: =IF(Roster!$A$61<>"",Roster!$A$61,"")
A64: =IF(Roster!$A$62<>"",Roster!$A$62,"")
A65: =IF(Roster!$A$63<>"",Roster!$A$63,"")
A66: =IF(Roster!$A$64<>"",Roster!$A$64,"")
A67: =IF(Roster!$A$65<>"",Roster!$A$65,"")
A68: =IF(Roster!$A$66<>"",Roster!$A$66,"")
A69: =IF(Roster!$A$67<>"",Roster!$A$67,"")
A70: =IF(Roster!$A$68<>"",Roster!$A$68,"")
A71: =IF(Roster!$A$69<>"",Roster!$A$69,"")
A72: =IF(Roster!$A$70<>"",Roster!$A$70,"")
A73: =IF(Roster!$A$71<>"",Roster!$A$71,"")
A74: =IF(Roster!$A$72<>"",Roster!$A$72,"")
A75: =IF(Roster!$A$73<>"",Roster!$A$73,"")
A76: =IF(Roster!$A$74<>"",Roster!$A$74,"")
A77: =IF(Roster!$A$75<>"",Roster!$A$75,"")
A78: =IF(Roster!$A$76<>"",Roster!$A$76,"")
A79: =IF(Roster!$A$77<>"",Roster!$A$77,"")
A80: =IF(Roster!$A$78<>"",Roster!$A$78,"")
A81: =IF(Roster!$A$79<>"",Roster!$A$79,"")
A82: =IF(Roster!$A$80<>"",Roster!$A$80,"")
A83: =IF(Roster!$A$81<>"",Roster!$A$81,"")
A84: =IF(Roster!$A$82<>"",Roster!$A$82,"")
A85: =IF(Roster!$A$83<>"",Roster!$A$83,"")
A86: =IF(Roster!$A$84<>"",Roster!$A$84,"")
A87: =IF(Roster!$A$85<>"",Roster!$A$85,"")
A88: =IF(Roster!$A$86<>"",Roster!$A$86,"")
A89: =IF(Roster!$A$87<>"",Roster!$A$87,"")
A90: =IF(Roster!$A$88<>"",Roster!$A$88,"")
A91: =IF(Roster!$A$89<>"",Roster!$A$89,"")
A92: =IF(Roster!$A$90<>"",Roster!$A$90,"")
A93: =IF(Roster!$A$91<>"",Roster!$A$91,"")
A94: =IF(Roster!$A$92<>"",Roster!$A$92,"")
A95: =IF(Roster!$A$93<>"",Roster!$A$93,"")
A96: =IF(Roster!$A$94<>"",Roster!$A$94,"")
A97: =IF(Roster!$A$95<>"",Roster!$A$95,"")
A98: =IF(Roster!$A$96<>"",Roster!$A$96,"")
A99: =IF(Roster!$A$97<>"",Roster!$A$97,"")
A100: =IF(Roster!$A$98<>"",Roster!$A$98,"")
A101: =IF(Roster!$A$99<>"",Roster!$A$99,"")
...

Sheet Transactions
A1: TRANSACTIONS — All Money In & Out
A3: Total In | B3: Total Out | C3: Net Balance | D3: Avg Transaction | E3: Pending
A4: =SUMIF(D7:D996,"Income",F7:F996)+SUMIF(D7:D996,"Fundraiser",F7:F996) -> 2109 | B4: =SUMIF(D7:D996,"Expense",F7:F996) -> 2070 | C4: =A4-B4 -> 39 | D4: =IFERROR(AVERAGE(F7:F996),0) -> 835.8 | E4: =COUNTIF(I7:I996,"Pending") -> 0
A6: Date | B6: Description | C6: Category | D6: Type | E6: Paid By | F6: Amount ($) | G6: Linked Event | H6: Reimbursed To | I6: Status | J6: Cost per Attendee ($)
A7: 03/15/2025 | B7: PEC Bid Fee | C7: Tournament Fee | D7: Expense | E7: Jake Murray | F7: 920 | G7: PEC | I7: Cleared | J7: {=IF(G7="","",IFERROR(LET(ev_cost,INDEX(Events!$G$5:$G$506,MATCH(G7,Events!$A$5:$A$506,0)),ev_split,INDEX(Events!$I$5:$I$506,MATCH(G7,Events!$A$5:$A$506,0)),att_offset,MATCH(G7,Attendance!$B$3:$AY$3,0),attendees,COUNTIF(INDEX(Attendance!$B$7:$AY$206,0,att_offset),"1"),IF(ev_split="Equal Split",ev_cost/MAX(1,COUNTA(Roster!$A$5:$A$204)),ev_cost/MAX(1,attendees))),"N/A"))} -> 50.384615
A8: 03/14/2025 | B8: SFI Bid Fee | C8: Hotel | D8: Expense | E8: Jake Murray | F8: 1150 | G8: SFI | I8: Cleared | J8: {=IF(G8="","",IFERROR(LET(ev_cost,INDEX(Events!$G$5:$G$506,MATCH(G8,Events!$A$5:$A$506,0)),ev_split,INDEX(Events!$I$5:$I$506,MATCH(G8,Events!$A$5:$A$506,0)),att_offset,MATCH(G8,Attendance!$B$3:$AY$3,0),attendees,COUNTIF(INDEX(Attendance!$B$7:$AY$206,0,att_offset),"1"),IF(ev_split="Equal Split",ev_cost/MAX(1,COUNTA(Roster!$A$5:$A$204)),ev_cost/MAX(1,attendees))),"N/A"))} -> 40.384615
A9: 03/22/2025 | B9: Fantapalooza | C9: Fundraiser Income | D9: Fundraiser | E9: Jake Murray | F9: 956 | G9: Fantapalooza | I9: Cleared | J9: {=IF(G9="","",IFERROR(LET(ev_cost,INDEX(Events!$G$5:$G$506,MATCH(G9,Events!$A$5:$A$506,0)),ev_split,INDEX(Events!$I$5:$I$506,MATCH(G9,Events!$A$5:$A$506,0)),att_offset,MATCH(G9,Attendance!$B$3:$AY$3,0),attendees,COUNTIF(INDEX(Attendance!$B$7:$AY$206,0,att_offset),"1"),IF(ev_split="Equal Split",ev_cost/MAX(1,COUNTA(Roster!$A$5:$A$204)),ev_cost/MAX(1,attendees))),"N/A"))} -> -956
B10: Natties Watch Party | C10: Fundraiser Income | D10: Fundraiser | E10: Jake Murray | F10: 123 | G10: Natties Watch Party | I10: Cleared | J10: {=IF(G10="","",IFERROR(LET(ev_cost,INDEX(Events!$G$5:$G$506,MATCH(G10,Events!$A$5:$A$506,0)),ev_split,INDEX(Events!$I$5:$I$506,MATCH(G10,Events!$A$5:$A$506,0)),att_offset,MATCH(G10,Attendance!$B$3:$AY$3,0),attendees,COUNTIF(INDEX(Attendance!$B$7:$AY$206,0,att_offset),"1"),IF(ev_split="Equal Split",ev_cost/MAX(1,COUNTA(Roster!$A$5:$A$204)),ev_cost/MAX(1,attendees))),"N/A"))} -> -123
B11: Outstanding 2025 Funds | C11: Fundraiser Income | D11: Fundraiser | E11: Jake Murray | F11: 1030 | G11: 2025 Fundraising | I11: Cleared | J11: {=IF(G11="","",IFERROR(LET(ev_cost,INDEX(Events!$G$5:$G$506,MATCH(G11,Events!$A$5:$A$506,0)),ev_split,INDEX(Events!$I$5:$I$506,MATCH(G11,Events!$A$5:$A$506,0)),att_offset,MATCH(G11,Attendance!$B$3:$AY$3,0),attendees,COUNTIF(INDEX(Attendance!$B$7:$AY$206,0,att_offset),"1"),IF(ev_split="Equal Split",ev_cost/MAX(1,COUNTA(Roster!$A$5:$A$204)),ev_cost/MAX(1,attendees))),"N/A"))} -> 1030
J12: {=IF(G12="","",IFERROR(LET(ev_cost,INDEX(Events!$G$5:$G$506,MATCH(G12,Events!$A$5:$A$506,0)),ev_split,INDEX(Events!$I$5:$I$506,MATCH(G12,Events!$A$5:$A$506,0)),att_offset,MATCH(G12,Attendance!$B$3:$AY$3,0),attendees,COUNTIF(INDEX(Attendance!$B$7:$AY$206,0,att_offset),"1"),IF(ev_split="Equal Split",ev_cost/MAX(1,COUNTA(Roster!$A$5:$A$204)),ev_cost/MAX(1,attendees))),"N/A"))}
J13: {=IF(G13="","",IFERROR(LET(ev_cost,INDEX(Events!$G$5:$G$506,MATCH(G13,Events!$A$5:$A$506,0)),ev_split,INDEX(Events!$I$5:$I$506,MATCH(G13,Events!$A$5:$A$506,0)),att_offset,MATCH(G13,Attendance!$B$3:$AY$3,0),attendees,COUNTIF(INDEX(Attendance!$B$7:$AY$206,0,att_offset),"1"),IF(ev_split="Equal Split",ev_cost/MAX(1,COUNTA(Roster!$A$5:$A$204)),ev_cost/MAX(1,attendees))),"N/A"))}
J14: {=IF(G14="","",IFERROR(LET(ev_cost,INDEX(Events!$G$5:$G$506,MATCH(G14,Events!$A$5:$A$506,0)),ev_split,INDEX(Events!$I$5:$I$506,MATCH(G14,Events!$A$5:$A$506,0)),att_offset,MATCH(G14,Attendance!$B$3:$AY$3,0),attendees,COUNTIF(INDEX(Attendance!$B$7:$AY$206,0,att_offset),"1"),IF(ev_split="Equal Split",ev_cost/MAX(1,COUNTA(Roster!$A$5:$A$204)),ev_cost/MAX(1,attendees))),"N/A"))}
J15: {=IF(G15="","",IFERROR(LET(ev_cost,INDEX(Events!$G$5:$G$506,MATCH(G15,Events!$A$5:$A$506,0)),ev_split,INDEX(Events!$I$5:$I$506,MATCH(G15,Events!$A$5:$A$506,0)),att_offset,MATCH(G15,Attendance!$B$3:$AY$3,0),attendees,COUNTIF(INDEX(Attendance!$B$7:$AY$206,0,att_offset),"1"),IF(ev_split="Equal Split",ev_cost/MAX(1,COUNTA(Roster!$A$5:$A$204)),ev_cost/MAX(1,attendees))),"N/A"))}
J16: {=IF(G16="","",IFERROR(LET(ev_cost,INDEX(Events!$G$5:$G$506,MATCH(G16,Events!$A$5:$A$506,0)),ev_split,INDEX(Events!$I$5:$I$506,MATCH(G16,Events!$A$5:$A$506,0)),att_offset,MATCH(G16,Attendance!$B$3:$AY$3,0),attendees,COUNTIF(INDEX(Attendance!$B$7:$AY$206,0,att_offset),"1"),IF(ev_split="Equal Split",ev_cost/MAX(1,COUNTA(Roster!$A$5:$A$204)),ev_cost/MAX(1,attendees))),"N/A"))}
J17: {=IF(G17="","",IFERROR(LET(ev_cost,INDEX(Events!$G$5:$G$506,MATCH(G17,Events!$A$5:$A$506,0)),ev_split,INDEX(Events!$I$5:$I$506,MATCH(G17,Events!$A$5:$A$506,0)),att_offset,MATCH(G17,Attendance!$B$3:$AY$3,0),attendees,COUNTIF(INDEX(Attendance!$B$7:$AY$206,0,att_offset),"1"),IF(ev_split="Equal Split",ev_cost/MAX(1,COUNTA(Roster!$A$5:$A$204)),ev_cost/MAX(1,attendees))),"N/A"))}
J18: {=IF(G18="","",IFERROR(LET(ev_cost,INDEX(Events!$G$5:$G$506,MATCH(G18,Events!$A$5:$A$506,0)),ev_split,INDEX(Events!$I$5:$I$506,MATCH(G18,Events!$A$5:$A$506,0)),att_offset,MATCH(G18,Attendance!$B$3:$AY$3,0),attendees,COUNTIF(INDEX(Attendance!$B$7:$AY$206,0,att_offset),"1"),IF(ev_split="Equal Split",ev_cost/MAX(1,COUNTA(Roster!$A$5:$A$204)),ev_cost/MAX(1,attendees))),"N/A"))}
J19: {=IF(G19="","",IFERROR(LET(ev_cost,INDEX(Events!$G$5:$G$506,MATCH(G19,Events!$A$5:$A$506,0)),ev_split,INDEX(Events!$I$5:$I$506,MATCH(G19,Events!$A$5:$A$506,0)),att_offset,MATCH(G19,Attendance!$B$3:$AY$3,0),attendees,COUNTIF(INDEX(Attendance!$B$7:$AY$206,0,att_offset),"1"),IF(ev_split="Equal Split",ev_cost/MAX(1,COUNTA(Roster!$A$5:$A$204)),ev_cost/MAX(1,attendees))),"N/A"))}
J20: {=IF(G20="","",IFERROR(LET(ev_cost,INDEX(Events!$G$5:$G$506,MATCH(G20,Events!$A$5:$A$506,0)),ev_split,INDEX(Events!$I$5:$I$506,MATCH(G20,Events!$A$5:$A$506,0)),att_offset,MATCH(G20,Attendance!$B$3:$AY$3,0),attendees,COUNTIF(INDEX(Attendance!$B$7:$AY$206,0,att_offset),"1"),IF(ev_split="Equal Split",ev_cost/MAX(1,COUNTA(Roster!$A$5:$A$204)),ev_cost/MAX(1,attendees))),"N/A"))}
J21: {=IF(G21="","",IFERROR(LET(ev_cost,INDEX(Events!$G$5:$G$506,MATCH(G21,Events!$A$5:$A$506,0)),ev_split,INDEX(Events!$I$5:$I$506,MATCH(G21,Events!$A$5:$A$506,0)),att_offset,MATCH(G21,Attendance!$B$3:$AY$3,0),attendees,COUNTIF(INDEX(Attendance!$B$7:$AY$206,0,att_offset),"1"),IF(ev_split="Equal Split",ev_cost/MAX(1,COUNTA(Roster!$A$5:$A$204)),ev_cost/MAX(1,attendees))),"N/A"))}
J22: {=IF(G22="","",IFERROR(LET(ev_cost,INDEX(Events!$G$5:$G$506,MATCH(G22,Events!$A$5:$A$506,0)),ev_split,INDEX(Events!$I$5:$I$506,MATCH(G22,Events!$A$5:$A$506,0)),att_offset,MATCH(G22,Attendance!$B$3:$AY$3,0),attendees,COUNTIF(INDEX(Attendance!$B$7:$AY$206,0,att_offset),"1"),IF(ev_split="Equal Split",ev_cost/MAX(1,COUNTA(Roster!$A$5:$A$204)),ev_cost/MAX(1,attendees))),"N/A"))}
J23: {=IF(G23="","",IFERROR(LET(ev_cost,INDEX(Events!$G$5:$G$506,MATCH(G23,Events!$A$5:$A$506,0)),ev_split,INDEX(Events!$I$5:$I$506,MATCH(G23,Events!$A$5:$A$506,0)),att_offset,MATCH(G23,Attendance!$B$3:$AY$3,0),attendees,COUNTIF(INDEX(Attendance!$B$7:$AY$206,0,att_offset),"1"),IF(ev_split="Equal Split",ev_cost/MAX(1,COUNTA(Roster!$A$5:$A$204)),ev_cost/MAX(1,attendees))),"N/A"))}
... J996: {=IF(G996="","",IFERROR(LET(ev_cost,INDEX(Events!$G$5:$G$506,MATCH(G996,Events!$A$5:$A$506,0)),ev_split,INDEX(Events!$I$5:$I$506,MATCH(G996,Events!$A$5:$A$506,0)),att_offset,MATCH(G996,Attendance!$B$3:$AY$3,0),attendees,COUNTIF(INDEX(Attendance!$B$7:$AY$206,0,att_offset),"1"),IF(ev_split="Equal Split",ev_cost/MAX(1,COUNTA(Roster!$A$5:$A$204)),ev_cost/MAX(1,attendees))),"N/A"))}

Sheet Player Balances
A1: PLAYER BALANCES - Individual Ledger
A3: Total Owed TO Team | B3: Total Owed BY Team | C3: Net | D3: Settled | E3: Unsettled
A4: =SUMIF(E7:E206,">0",E7:E206) -> 2269.2308 | B4: =SUMIF(E7:E206,"<0",E7:E206) -> -1979.2308 | C4: =SUM(E7:E206) -> 290 | D4: =COUNTIF(F7:F206,"Settled") -> 8 | E4: =COUNTIF(F7:F206,"Unsettled") -> 26
A6: Player Name | B6: Total Charged ($) | C6: Total Paid ($) | D6: Paid Upfront For Team ($) | E6: Net Balance ($) | F6: Status
A7: =IF(Roster!$A$5<>"",Roster!$A$5,"") -> At | B7: {=IF(A7<>"",IFERROR(INDEX(Roster!$B$5:$B$204,MATCH(A7,Roster!$A$5:$A$204,0)),0)+IFERROR(SUMPRODUCT((INDEX(Attendance!$B$7:$AY$206,MATCH(A7,Attendance!$A$7:$A$206,0),0)=1)*Attendance!$B$4:$AY$4),0),"")} -> 90.769231 | C7: =IF(A7<>"",SUMIFS(Transactions!$F$7:$F$996,Transactions!$D$7:$D$996,"Income",Transactions!$E$7:$E$996,A7),"") -> 0 | D7: =IF(A7<>"",SUMIFS(Transactions!$F$7:$F$996,Transactions!$D$7:$D$996,"Expense",Transactions!$E$7:$E$996,A7),"") -> 0 | E7: =IF(A7<>"",B7-C7-D7,"") -> 90.769231 | F7: =IF(A7<>"",IF(E7=0,"Settled","Unsettled"),"") -> Unsettled
A8: =IF(Roster!$A$6<>"",Roster!$A$6,"") -> Alex Warrington | B8: {=IF(A8<>"",IFERROR(INDEX(Roster!$B$5:$B$204,MATCH(A8,Roster!$A$5:$A$204,0)),0)+IFERROR(SUMPRODUCT((INDEX(Attendance!$B$7:$AY$206,MATCH(A8,Attendance!$A$7:$A$206,0),0)=1)*Attendance!$B$4:$AY$4),0),"")} -> 90.769231 | C8: =IF(A8<>"",SUMIFS(Transactions!$F$7:$F$996,Transactions!$D$7:$D$996,"Income",Transactions!$E$7:$E$996,A8),"") -> 0 | D8: =IF(A8<>"",SUMIFS(Transactions!$F$7:$F$996,Transactions!$D$7:$D$996,"Expense",Transactions!$E$7:$E$996,A8),"") -> 0 | E8: =IF(A8<>"",B8-C8-D8,"") -> 90.769231 | F8: =IF(A8<>"",IF(E8=0,"Settled","Unsettled"),"") -> Unsettled
A9: =IF(Roster!$A$7<>"",Roster!$A$7,"") -> Chris Wohl | B9: {=IF(A9<>"",IFERROR(INDEX(Roster!$B$5:$B$204,MATCH(A9,Roster!$A$5:$A$204,0)),0)+IFERROR(SUMPRODUCT((INDEX(Attendance!$B$7:$AY$206,MATCH(A9,Attendance!$A$7:$A$206,0),0)=1)*Attendance!$B$4:$AY$4),0),"")} -> 90.769231 | C9: =IF(A9<>"",SUMIFS(Transactions!$F$7:$F$996,Transactions!$D$7:$D$996,"Income",Transactions!$E$7:$E$996,A9),"") -> 0 | D9: =IF(A9<>"",SUMIFS(Transactions!$F$7:$F$996,Transactions!$D$7:$D$996,"Expense",Transactions!$E$7:$E$996,A9),"") -> 0 | E9: =IF(A9<>"",B9-C9-D9,"") -> 90.769231 | F9: =IF(A9<>"",IF(E9=0,"Settled","Unsettled"),"") -> Unsettled
A10: =IF(Roster!$A$8<>"",Roster!$A$8,"") -> Darra Reppermund | B10: {=IF(A10<>"",IFERROR(INDEX(Roster!$B$5:$B$204,MATCH(A10,Roster!$A$5:$A$204,0)),0)+IFERROR(SUMPRODUCT((INDEX(Attendance!$B$7:$AY$206,MATCH(A10,Attendance!$A$7:$A$206,0),0)=1)*Attendance!$B$4:$AY$4),0),"")} -> 90.769231 | C10: =IF(A10<>"",SUMIFS(Transactions!$F$7:$F$996,Transactions!$D$7:$D$996,"Income",Transactions!$E$7:$E$996,A10),"") -> 0 | D10: =IF(A10<>"",SUMIFS(Transactions!$F$7:$F$996,Transactions!$D$7:$D$996,"Expense",Transactions!$E$7:$E$996,A10),"") -> 0 | E10: =IF(A10<>"",B10-C10-D10,"") -> 90.769231 | F10: =IF(A10<>"",IF(E10=0,"Settled","Unsettled"),"") -> Unsettled
A11: =IF(Roster!$A$9<>"",Roster!$A$9,"") -> Dylan Best | B11: {=IF(A11<>"",IFERROR(INDEX(Roster!$B$5:$B$204,MATCH(A11,Roster!$A$5:$A$204,0)),0)+IFERROR(SUMPRODUCT((INDEX(Attendance!$B$7:$AY$206,MATCH(A11,Attendance!$A$7:$A$206,0),0)=1)*Attendance!$B$4:$AY$4),0),"")} -> 90.769231 | C11: =IF(A11<>"",SUMIFS(Transactions!$F$7:$F$996,Transactions!$D$7:$D$996,"Income",Transactions!$E$7:$E$996,A11),"") -> 0 | D11: =IF(A11<>"",SUMIFS(Transactions!$F$7:$F$996,Transactions!$D$7:$D$996,"Expense",Transactions!$E$7:$E$996,A11),"") -> 0 | E11: =IF(A11<>"",B11-C11-D11,"") -> 90.769231 | F11: =IF(A11<>"",IF(E11=0,"Settled","Unsettled"),"") -> Unsettled
A12: =IF(Roster!$A$10<>"",Roster!$A$10,"") -> Griffin O'Neal-Freeman | B12: {=IF(A12<>"",IFERROR(INDEX(Roster!$B$5:$B$204,MATCH(A12,Roster!$A$5:$A$204,0)),0)+IFERROR(SUMPRODUCT((INDEX(Attendance!$B$7:$AY$206,MATCH(A12,Attendance!$A$7:$A$206,0),0)=1)*Attendance!$B$4:$AY$4),0),"")} -> 90.769231 | C12: =IF(A12<>"",SUMIFS(Transactions!$F$7:$F$996,Transactions!$D$7:$D$996,"Income",Transactions!$E$7:$E$996,A12),"") -> 0 | D12: =IF(A12<>"",SUMIFS(Transactions!$F$7:$F$996,Transactions!$D$7:$D$996,"Expense",Transactions!$E$7:$E$996,A12),"") -> 0 | E12: =IF(A12<>"",B12-C12-D12,"") -> 90.769231 | F12: =IF(A12<>"",IF(E12=0,"Settled","Unsettled"),"") -> Unsettled
A13: =IF(Roster!$A$11<>"",Roster!$A$11,"") -> Haley Young | B13: {=IF(A13<>"",IFERROR(INDEX(Roster!$B$5:$B$204,MATCH(A13,Roster!$A$5:$A$204,0)),0)+IFERROR(SUMPRODUCT((INDEX(Attendance!$B$7:$AY$206,MATCH(A13,Attendance!$A$7:$A$206,0),0)=1)*Attendance!$B$4:$AY$4),0),"")} -> 90.769231 | C13: =IF(A13<>"",SUMIFS(Transactions!$F$7:$F$996,Transactions!$D$7:$D$996,"Income",Transactions!$E$7:$E$996,A13),"") -> 0 | D13: =IF(A13<>"",SUMIFS(Transactions!$F$7:$F$996,Transactions!$D$7:$D$996,"Expense",Transactions!$E$7:$E$996,A13),"") -> 0 | E13: =IF(A13<>"",B13-C13-D13,"") -> 90.769231 | F13: =IF(A13<>"",IF(E13=0,"Settled","Unsettled"),"") -> Unsettled
A14: =IF(Roster!$A$12<>"",Roster!$A$12,"") -> Harry Park | B14: {=IF(A14<>"",IFERROR(INDEX(Roster!$B$5:$B$204,MATCH(A14,Roster!$A$5:$A$204,0)),0)+IFERROR(SUMPRODUCT((INDEX(Attendance!$B$7:$AY$206,MATCH(A14,Attendance!$A$7:$A$206,0),0)=1)*Attendance!$B$4:$AY$4),0),"")} -> 90.769231 | C14: =IF(A14<>"",SUMIFS(Transactions!$F$7:$F$996,Transactions!$D$7:$D$996,"Income",Transactions!$E$7:$E$996,A14),"") -> 0 | D14: =IF(A14<>"",SUMIFS(Transactions!$F$7:$F$996,Transactions!$D$7:$D$996,"Expense",Transactions!$E$7:$E$996,A14),"") -> 0 | E14: =IF(A14<>"",B14-C14-D14,"") -> 90.769231 | F14: =IF(A14<>"",IF(E14=0,"Settled","Unsettled"),"") -> Unsettled
A15: =IF(Roster!$A$13<>"",Roster!$A$13,"") -> Ian Piper | B15: {=IF(A15<>"",IFERROR(INDEX(Roster!$B$5:$B$204,MATCH(A15,Roster!$A$5:$A$204,0)),0)+IFERROR(SUMPRODUCT((INDEX(Attendance!$B$7:$AY$206,MATCH(A15,Attendance!$A$7:$A$206,0),0)=1)*Attendance!$B$4:$AY$4),0),"")} -> 90.769231 | C15: =IF(A15<>"",SUMIFS(Transactions!$F$7:$F$996,Transactions!$D$7:$D$996,"Income",Transactions!$E$7:$E$996,A15),"") -> 0 | D15: =IF(A15<>"",SUMIFS(Transactions!$F$7:$F$996,Transactions!$D$7:$D$996,"Expense",Transactions!$E$7:$E$996,A15),"") -> 0 | E15: =IF(A15<>"",B15-C15-D15,"") -> 90.769231 | F15: =IF(A15<>"",IF(E15=0,"Settled","Unsettled"),"") -> Unsettled
A16: =IF(Roster!$A$14<>"",Roster!$A$14,"") -> Jake Murray | B16: {=IF(A16<>"",IFERROR(INDEX(Roster!$B$5:$B$204,MATCH(A16,Roster!$A$5:$A$204,0)),0)+IFERROR(SUMPRODUCT((INDEX(Attendance!$B$7:$AY$206,MATCH(A16,Attendance!$A$7:$A$206,0),0)=1)*Attendance!$B$4:$AY$4),0),"")} -> 90.769231 | C16: =IF(A16<>"",SUMIFS(Transactions!$F$7:$F$996,Transactions!$D$7:$D$996,"Income",Transactions!$E$7:$E$996,A16),"") -> 0 | D16: =IF(A16<>"",SUMIFS(Transactions!$F$7:$F$996,Transactions!$D$7:$D$996,"Expense",Transactions!$E$7:$E$996,A16),"") -> 2070 | E16: =IF(A16<>"",B16-C16-D16,"") -> -1979.2308 | F16: =IF(A16<>"",IF(E16=0,"Settled","Unsettled"),"") -> Unsettled
A17: =IF(Roster!$A$15<>"",Roster!$A$15,"") -> Jenna Nold | B17: {=IF(A17<>"",IFERROR(INDEX(Roster!$B$5:$B$204,MATCH(A17,Roster!$A$5:$A$204,0)),0)+IFERROR(SUMPRODUCT((INDEX(Attendance!$B$7:$AY$206,MATCH(A17,Attendance!$A$7:$A$206,0),0)=1)*Attendance!$B$4:$AY$4),0),"")} -> 90.769231 | C17: =IF(A17<>"",SUMIFS(Transactions!$F$7:$F$996,Transactions!$D$7:$D$996,"Income",Transactions!$E$7:$E$996,A17),"") -> 0 | D17: =IF(A17<>"",SUMIFS(Transactions!$F$7:$F$996,Transactions!$D$7:$D$996,"Expense",Transactions!$E$7:$E$996,A17),"") -> 0 | E17: =IF(A17<>"",B17-C17-D17,"") -> 90.769231 | F17: =IF(A17<>"",IF(E17=0,"Settled","Unsettled"),"") -> Unsettled
A18: =IF(Roster!$A$16<>"",Roster!$A$16,"") -> Jimmy Towle | B18: {=IF(A18<>"",IFERROR(INDEX(Roster!$B$5:$B$204,MATCH(A18,Roster!$A$5:$A$204,0)),0)+IFERROR(SUMPRODUCT((INDEX(Attendance!$B$7:$AY$206,MATCH(A18,Attendance!$A$7:$A$206,0),0)=1)*Attendance!$B$4:$AY$4),0),"")} -> 0 | C18: =IF(A18<>"",SUMIFS(Transactions!$F$7:$F$996,Transactions!$D$7:$D$996,"Income",Transactions!$E$7:$E$996,A18),"") -> 0 | D18: =IF(A18<>"",SUMIFS(Transactions!$F$7:$F$996,Transactions!$D$7:$D$996,"Expense",Transactions!$E$7:$E$996,A18),"") -> 0 | E18: =IF(A18<>"",B18-C18-D18,"") -> 0 | F18: =IF(A18<>"",IF(E18=0,"Settled","Unsettled"),"") -> Settled
A19: =IF(Roster!$A$17<>"",Roster!$A$17,"") -> Kailey Rugani | B19: {=IF(A19<>"",IFERROR(INDEX(Roster!$B$5:$B$204,MATCH(A19,Roster!$A$5:$A$204,0)),0)+IFERROR(SUMPRODUCT((INDEX(Attendance!$B$7:$AY$206,MATCH(A19,Attendance!$A$7:$A$206,0),0)=1)*Attendance!$B$4:$AY$4),0),"")} -> 90.769231 | C19: =IF(A19<>"",SUMIFS(Transactions!$F$7:$F$996,Transactions!$D$7:$D$996,"Income",Transactions!$E$7:$E$996,A19),"") -> 0 | D19: =IF(A19<>"",SUMIFS(Transactions!$F$7:$F$996,Transactions!$D$7:$D$996,"Expense",Transactions!$E$7:$E$996,A19),"") -> 0 | E19: =IF(A19<>"",B19-C19-D19,"") -> 90.769231 | F19: =IF(A19<>"",IF(E19=0,"Settled","Unsettled"),"") -> Unsettled
A20: =IF(Roster!$A$18<>"",Roster!$A$18,"") -> Kasey Schock | B20: {=IF(A20<>"",IFERROR(INDEX(Roster!$B$5:$B$204,MATCH(A20,Roster!$A$5:$A$204,0)),0)+IFERROR(SUMPRODUCT((INDEX(Attendance!$B$7:$AY$206,MATCH(A20,Attendance!$A$7:$A$206,0),0)=1)*Attendance!$B$4:$AY$4),0),"")} -> 90.769231 | C20: =IF(A20<>"",SUMIFS(Transactions!$F$7:$F$996,Transactions!$D$7:$D$996,"Income",Transactions!$E$7:$E$996,A20),"") -> 0 | D20: =IF(A20<>"",SUMIFS(Transactions!$F$7:$F$996,Transactions!$D$7:$D$996,"Expense",Transactions!$E$7:$E$996,A20),"") -> 0 | E20: =IF(A20<>"",B20-C20-D20,"") -> 90.769231 | F20: =IF(A20<>"",IF(E20=0,"Settled","Unsettled"),"") -> Unsettled
A21: =IF(Roster!$A$19<>"",Roster!$A$19,"") -> Kevin Nicholl | B21: {=IF(A21<>"",IFERROR(INDEX(Roster!$B$5:$B$204,MATCH(A21,Roster!$A$5:$A$204,0)),0)+IFERROR(SUMPRODUCT((INDEX(Attendance!$B$7:$AY$206,MATCH(A21,Attendance!$A$7:$A$206,0),0)=1)*Attendance!$B$4:$AY$4),0),"")} -> 90.769231 | C21: =IF(A21<>"",SUMIFS(Transactions!$F$7:$F$996,Transactions!$D$7:$D$996,"Income",Transactions!$E$7:$E$996,A21),"") -> 0 | D21: =IF(A21<>"",SUMIFS(Transactions!$F$7:$F$996,Transactions!$D$7:$D$996,"Expense",Transactions!$E$7:$E$996,A21),"") -> 0 | E21: =IF(A21<>"",B21-C21-D21,"") -> 90.769231 | F21: =IF(A21<>"",IF(E21=0,"Settled","Unsettled"),"") -> Unsettled
A22: =IF(Roster!$A$20<>"",Roster!$A$20,"") -> Kit Asterin | B22: {=IF(A22<>"",IFERROR(INDEX(Roster!$B$5:$B$204,MATCH(A22,Roster!$A$5:$A$204,0)),0)+IFERROR(SUMPRODUCT((INDEX(Attendance!$B$7:$AY$206,MATCH(A22,Attendance!$A$7:$A$206,0),0)=1)*Attendance!$B$4:$AY$4),0),"")} -> 90.769231 | C22: =IF(A22<>"",SUMIFS(Transactions!$F$7:$F$996,Transactions!$D$7:$D$996,"Income",Transactions!$E$7:$E$996,A22),"") -> 0 | D22: =IF(A22<>"",SUMIFS(Transactions!$F$7:$F$996,Transactions!$D$7:$D$996,"Expense",Transactions!$E$7:$E$996,A22),"") -> 0 | E22: =IF(A22<>"",B22-C22-D22,"") -> 90.769231 | F22: =IF(A22<>"",IF(E22=0,"Settled","Unsettled"),"") -> Unsettled
A23: =IF(Roster!$A$21<>"",Roster!$A$21,"") -> Kristin Dudley | B23: {=IF(A23<>"",IFERROR(INDEX(Roster!$B$5:$B$204,MATCH(A23,Roster!$A$5:$A$204,0)),0)+IFERROR(SUMPRODUCT((INDEX(Attendance!$B$7:$AY$206,MATCH(A23,Attendance!$A$7:$A$206,0),0)=1)*Attendance!$B$4:$AY$4),0),"")} -> 90.769231 | C23: =IF(A23<>"",SUMIFS(Transactions!$F$7:$F$996,Transactions!$D$7:$D$996,"Income",Transactions!$E$7:$E$996,A23),"") -> 0 | D23: =IF(A23<>"",SUMIFS(Transactions!$F$7:$F$996,Transactions!$D$7:$D$996,"Expense",Transactions!$E$7:$E$996,A23),"") -> 0 | E23: =IF(A23<>"",B23-C23-D23,"") -> 90.769231 | F23: =IF(A23<>"",IF(E23=0,"Settled","Unsettled"),"") -> Unsettled
A24: =IF(Roster!$A$22<>"",Roster!$A$22,"") -> Lexie Thomas | B24: {=IF(A24<>"",IFERROR(INDEX(Roster!$B$5:$B$204,MATCH(A24,Roster!$A$5:$A$204,0)),0)+IFERROR(SUMPRODUCT((INDEX(Attendance!$B$7:$AY$206,MATCH(A24,Attendance!$A$7:$A$206,0),0)=1)*Attendance!$B$4:$AY$4),0),"")} -> 90.769231 | C24: =IF(A24<>"",SUMIFS(Transactions!$F$7:$F$996,Transactions!$D$7:$D$996,"Income",Transactions!$E$7:$E$996,A24),"") -> 0 | D24: =IF(A24<>"",SUMIFS(Transactions!$F$7:$F$996,Transactions!$D$7:$D$996,"Expense",Transactions!$E$7:$E$996,A24),"") -> 0 | E24: =IF(A24<>"",B24-C24-D24,"") -> 90.769231 | F24: =IF(A24<>"",IF(E24=0,"Settled","Unsettled"),"") -> Unsettled
A25: =IF(Roster!$A$23<>"",Roster!$A$23,"") -> Lucas Jones | B25: {=IF(A25<>"",IFERROR(INDEX(Roster!$B$5:$B$204,MATCH(A25,Roster!$A$5:$A$204,0)),0)+IFERROR(SUMPRODUCT((INDEX(Attendance!$B$7:$AY$206,MATCH(A25,Attendance!$A$7:$A$206,0),0)=1)*Attendance!$B$4:$AY$4),0),"")} -> 0 | C25: =IF(A25<>"",SUMIFS(Transactions!$F$7:$F$996,Transactions!$D$7:$D$996,"Income",Transactions!$E$7:$E$996,A25),"") -> 0 | D25: =IF(A25<>"",SUMIFS(Transactions!$F$7:$F$996,Transactions!$D$7:$D$996,"Expense",Transactions!$E$7:$E$996,A25),"") -> 0 | E25: =IF(A25<>"",B25-C25-D25,"") -> 0 | F25: =IF(A25<>"",IF(E25=0,"Settled","Unsettled"),"") -> Settled
A26: =IF(Roster!$A$24<>"",Roster!$A$24,"") -> Lucius Christie | B26: {=IF(A26<>"",IFERROR(INDEX(Roster!$B$5:$B$204,MATCH(A26,Roster!$A$5:$A$204,0)),0)+IFERROR(SUMPRODUCT((INDEX(Attendance!$B$7:$AY$206,MATCH(A26,Attendance!$A$7:$A$206,0),0)=1)*Attendance!$B$4:$AY$4),0),"")} -> 90.769231 | C26: =IF(A26<>"",SUMIFS(Transactions!$F$7:$F$996,Transactions!$D$7:$D$996,"Income",Transactions!$E$7:$E$996,A26),"") -> 0 | D26: =IF(A26<>"",SUMIFS(Transactions!$F$7:$F$996,Transactions!$D$7:$D$996,"Expense",Transactions!$E$7:$E$996,A26),"") -> 0 | E26: =IF(A26<>"",B26-C26-D26,"") -> 90.769231 | F26: =IF(A26<>"",IF(E26=0,"Settled","Unsettled"),"") -> Unsettled
A27: =IF(Roster!$A$25<>"",Roster!$A$25,"") -> Patrick McMullen | B27: {=IF(A27<>"",IFERROR(INDEX(Roster!$B$5:$B$204,MATCH(A27,Roster!$A$5:$A$204,0)),0)+IFERROR(SUMPRODUCT((INDEX(Attendance!$B$7:$AY$206,MATCH(A27,Attendance!$A$7:$A$206,0),0)=1)*Attendance!$B$4:$AY$4),0),"")} -> 90.769231 | C27: =IF(A27<>"",SUMIFS(Transactions!$F$7:$F$996,Transactions!$D$7:$D$996,"Income",Transactions!$E$7:$E$996,A27),"") -> 0 | D27: =IF(A27<>"",SUMIFS(Transactions!$F$7:$F$996,Transactions!$D$7:$D$996,"Expense",Transactions!$E$7:$E$996,A27),"") -> 0 | E27: =IF(A27<>"",B27-C27-D27,"") -> 90.769231 | F27: =IF(A27<>"",IF(E27=0,"Settled","Unsettled"),"") -> Unsettled
A28: =IF(Roster!$A$26<>"",Roster!$A$26,"") -> Rachel Graber | B28: {=IF(A28<>"",IFERROR(INDEX(Roster!$B$5:$B$204,MATCH(A28,Roster!$A$5:$A$204,0)),0)+IFERROR(SUMPRODUCT((INDEX(Attendance!$B$7:$AY$206,MATCH(A28,Attendance!$A$7:$A$206,0),0)=1)*Attendance!$B$4:$AY$4),0),"")} -> 90.769231 | C28: =IF(A28<>"",SUMIFS(Transactions!$F$7:$F$996,Transactions!$D$7:$D$996,"Income",Transactions!$E$7:$E$996,A28),"") -> 0 | D28: =IF(A28<>"",SUMIFS(Transactions!$F$7:$F$996,Transactions!$D$7:$D$996,"Expense",Transactions!$E$7:$E$996,A28),"") -> 0 | E28: =IF(A28<>"",B28-C28-D28,"") -> 90.769231 | F28: =IF(A28<>"",IF(E28=0,"Settled","Unsettled"),"") -> Unsettled
A29: =IF(Roster!$A$27<>"",Roster!$A$27,"") -> Ryan Kindell | B29: {=IF(A29<>"",IFERROR(INDEX(Roster!$B$5:$B$204,MATCH(A29,Roster!$A$5:$A$204,0)),0)+IFERROR(SUMPRODUCT((INDEX(Attendance!$B$7:$AY$206,MATCH(A29,Attendance!$A$7:$A$206,0),0)=1)*Attendance!$B$4:$AY$4),0),"")} -> 90.769231 | C29: =IF(A29<>"",SUMIFS(Transactions!$F$7:$F$996,Transactions!$D$7:$D$996,"Income",Transactions!$E$7:$E$996,A29),"") -> 0 | D29: =IF(A29<>"",SUMIFS(Transactions!$F$7:$F$996,Transactions!$D$7:$D$996,"Expense",Transactions!$E$7:$E$996,A29),"") -> 0 | E29: =IF(A29<>"",B29-C29-D29,"") -> 90.769231 | F29: =IF(A29<>"",IF(E29=0,"Settled","Unsettled"),"") -> Unsettled
A30: =IF(Roster!$A$28<>"",Roster!$A$28,"") -> Ryan Ward | B30: {=IF(A30<>"",IFERROR(INDEX(Roster!$B$5:$B$204,MATCH(A30,Roster!$A$5:$A$204,0)),0)+IFERROR(SUMPRODUCT((INDEX(Attendance!$B$7:$AY$206,MATCH(A30,Attendance!$A$7:$A$206,0),0)=1)*Attendance!$B$4:$AY$4),0),"")} -> 90.769231 | C30: =IF(A30<>"",SUMIFS(Transactions!$F$7:$F$996,Transactions!$D$7:$D$996,"Income",Transactions!$E$7:$E$996,A30),"") -> 0 | D30: =IF(A30<>"",SUMIFS(Transactions!$F$7:$F$996,Transactions!$D$7:$D$996,"Expense",Transactions!$E$7:$E$996,A30),"") -> 0 | E30: =IF(A30<>"",B30-C30-D30,"") -> 90.769231 | F30: =IF(A30<>"",IF(E30=0,"Settled","Unsettled"),"") -> Unsettled
A31: =IF(Roster!$A$29<>"",Roster!$A$29,"") -> Sam Gombiner | B31: {=IF(A31<>"",IFERROR(INDEX(Roster!$B$5:$B$204,MATCH(A31,Roster!$A$5:$A$204,0)),0)+IFERROR(SUMPRODUCT((INDEX(Attendance!$B$7:$AY$206,MATCH(A31,Attendance!$A$7:$A$206,0),0)=1)*Attendance!$B$4:$AY$4),0),"")} -> 0 | C31: =IF(A31<>"",SUMIFS(Transactions!$F$7:$F$996,Transactions!$D$7:$D$996,"Income",Transactions!$E$7:$E$996,A31),"") -> 0 | D31: =IF(A31<>"",SUMIFS(Transactions!$F$7:$F$996,Transactions!$D$7:$D$996,"Expense",Transactions!$E$7:$E$996,A31),"") -> 0 | E31: =IF(A31<>"",B31-C31-D31,"") -> 0 | F31: =IF(A31<>"",IF(E31=0,"Settled","Unsettled"),"") -> Settled
A32: =IF(Roster!$A$30<>"",Roster!$A$30,"") -> Sarah Kingsley-Hart | B32: {=IF(A32<>"",IFERROR(INDEX(Roster!$B$5:$B$204,MATCH(A32,Roster!$A$5:$A$204,0)),0)+IFERROR(SUMPRODUCT((INDEX(Attendance!$B$7:$AY$206,MATCH(A32,Attendance!$A$7:$A$206,0),0)=1)*Attendance!$B$4:$AY$4),0),"")} -> 90.769231 | C32: =IF(A32<>"",SUMIFS(Transactions!$F$7:$F$996,Transactions!$D$7:$D$996,"Income",Transactions!$E$7:$E$996,A32),"") -> 0 | D32: =IF(A32<>"",SUMIFS(Transactions!$F$7:$F$996,Transactions!$D$7:$D$996,"Expense",Transactions!$E$7:$E$996,A32),"") -> 0 | E32: =IF(A32<>"",B32-C32-D32,"") -> 90.769231 | F32: =IF(A32<>"",IF(E32=0,"Settled","Unsettled"),"") -> Unsettled
A33: =IF(Roster!$A$31<>"",Roster!$A$31,"") -> Sarah Lynch | B33: {=IF(A33<>"",IFERROR(INDEX(Roster!$B$5:$B$204,MATCH(A33,Roster!$A$5:$A$204,0)),0)+IFERROR(SUMPRODUCT((INDEX(Attendance!$B$7:$AY$206,MATCH(A33,Attendance!$A$7:$A$206,0),0)=1)*Attendance!$B$4:$AY$4),0),"")} -> 90.769231 | C33: =IF(A33<>"",SUMIFS(Transactions!$F$7:$F$996,Transactions!$D$7:$D$996,"Income",Transactions!$E$7:$E$996,A33),"") -> 0 | D33: =IF(A33<>"",SUMIFS(Transactions!$F$7:$F$996,Transactions!$D$7:$D$996,"Expense",Transactions!$E$7:$E$996,A33),"") -> 0 | E33: =IF(A33<>"",B33-C33-D33,"") -> 90.769231 | F33: =IF(A33<>"",IF(E33=0,"Settled","Unsettled"),"") -> Unsettled
A34: =IF(Roster!$A$32<>"",Roster!$A$32,"") -> Shani Rosenthal | B34: {=IF(A34<>"",IFERROR(INDEX(Roster!$B$5:$B$204,MATCH(A34,Roster!$A$5:$A$204,0)),0)+IFERROR(SUMPRODUCT((INDEX(Attendance!$B$7:$AY$206,MATCH(A34,Attendance!$A$7:$A$206,0),0)=1)*Attendance!$B$4:$AY$4),0),"")} -> 90.769231 | C34: =IF(A34<>"",SUMIFS(Transactions!$F$7:$F$996,Transactions!$D$7:$D$996,"Income",Transactions!$E$7:$E$996,A34),"") -> 0 | D34: =IF(A34<>"",SUMIFS(Transactions!$F$7:$F$996,Transactions!$D$7:$D$996,"Expense",Transactions!$E$7:$E$996,A34),"") -> 0 | E34: =IF(A34<>"",B34-C34-D34,"") -> 90.769231 | F34: =IF(A34<>"",IF(E34=0,"Settled","Unsettled"),"") -> Unsettled
A35: =IF(Roster!$A$33<>"",Roster!$A$33,"") -> Vivian Shen | B35: {=IF(A35<>"",IFERROR(INDEX(Roster!$B$5:$B$204,MATCH(A35,Roster!$A$5:$A$204,0)),0)+IFERROR(SUMPRODUCT((INDEX(Attendance!$B$7:$AY$206,MATCH(A35,Attendance!$A$7:$A$206,0),0)=1)*Attendance!$B$4:$AY$4),0),"")} -> 90.769231 | C35: =IF(A35<>"",SUMIFS(Transactions!$F$7:$F$996,Transactions!$D$7:$D$996,"Income",Transactions!$E$7:$E$996,A35),"") -> 0 | D35: =IF(A35<>"",SUMIFS(Transactions!$F$7:$F$996,Transactions!$D$7:$D$996,"Expense",Transactions!$E$7:$E$996,A35),"") -> 0 | E35: =IF(A35<>"",B35-C35-D35,"") -> 90.769231 | F35: =IF(A35<>"",IF(E35=0,"Settled","Unsettled"),"") -> Unsettled
A36: =IF(Roster!$A$34<>"",Roster!$A$34,"") -> Zach Esakof | B36: {=IF(A36<>"",IFERROR(INDEX(Roster!$B$5:$B$204,MATCH(A36,Roster!$A$5:$A$204,0)),0)+IFERROR(SUMPRODUCT((INDEX(Attendance!$B$7:$AY$206,MATCH(A36,Attendance!$A$7:$A$206,0),0)=1)*Attendance!$B$4:$AY$4),0),"")} -> 0 | C36: =IF(A36<>"",SUMIFS(Transactions!$F$7:$F$996,Transactions!$D$7:$D$996,"Income",Transactions!$E$7:$E$996,A36),"") -> 0 | D36: =IF(A36<>"",SUMIFS(Transactions!$F$7:$F$996,Transactions!$D$7:$D$996,"Expense",Transactions!$E$7:$E$996,A36),"") -> 0 | E36: =IF(A36<>"",B36-C36-D36,"") -> 0 | F36: =IF(A36<>"",IF(E36=0,"Settled","Unsettled"),"") -> Settled
A37: =IF(Roster!$A$35<>"",Roster!$A$35,"") -> Annette Kukunas-Piper | B37: {=IF(A37<>"",IFERROR(INDEX(Roster!$B$5:$B$204,MATCH(A37,Roster!$A$5:$A$204,0)),0)+IFERROR(SUMPRODUCT((INDEX(Attendance!$B$7:$AY$206,MATCH(A37,Attendance!$A$7:$A$206,0),0)=1)*Attendance!$B$4:$AY$4),0),"")} -> 0 | C37: =IF(A37<>"",SUMIFS(Transactions!$F$7:$F$996,Transactions!$D$7:$D$996,"Income",Transactions!$E$7:$E$996,A37),"") -> 0 | D37: =IF(A37<>"",SUMIFS(Transactions!$F$7:$F$996,Transactions!$D$7:$D$996,"Expense",Transactions!$E$7:$E$996,A37),"") -> 0 | E37: =IF(A37<>"",B37-C37-D37,"") -> 0 | F37: =IF(A37<>"",IF(E37=0,"Settled","Unsettled"),"") -> Settled
A38: =IF(Roster!$A$36<>"",Roster!$A$36,"") -> Matt Duffy | B38: {=IF(A38<>"",IFERROR(INDEX(Roster!$B$5:$B$204,MATCH(A38,Roster!$A$5:$A$204,0)),0)+IFERROR(SUMPRODUCT((INDEX(Attendance!$B$7:$AY$206,MATCH(A38,Attendance!$A$7:$A$206,0),0)=1)*Attendance!$B$4:$AY$4),0),"")} -> 0 | C38: =IF(A38<>"",SUMIFS(Transactions!$F$7:$F$996,Transactions!$D$7:$D$996,"Income",Transactions!$E$7:$E$996,A38),"") -> 0 | D38: =IF(A38<>"",SUMIFS(Transactions!$F$7:$F$996,Transactions!$D$7:$D$996,"Expense",Transactions!$E$7:$E$996,A38),"") -> 0 | E38: =IF(A38<>"",B38-C38-D38,"") -> 0 | F38: =IF(A38<>"",IF(E38=0,"Settled","Unsettled"),"") -> Settled
A39: =IF(Roster!$A$37<>"",Roster!$A$37,"") -> Ryan Birchard | B39: {=IF(A39<>"",IFERROR(INDEX(Roster!$B$5:$B$204,MATCH(A39,Roster!$A$5:$A$204,0)),0)+IFERROR(SUMPRODUCT((INDEX(Attendance!$B$7:$AY$206,MATCH(A39,Attendance!$A$7:$A$206,0),0)=1)*Attendance!$B$4:$AY$4),0),"")} -> 0 | C39: =IF(A39<>"",SUMIFS(Transactions!$F$7:$F$996,Transactions!$D$7:$D$996,"Income",Transactions!$E$7:$E$996,A39),"") -> 0 | D39: =IF(A39<>"",SUMIFS(Transactions!$F$7:$F$996,Transactions!$D$7:$D$996,"Expense",Transactions!$E$7:$E$996,A39),"") -> 0 | E39: =IF(A39<>"",B39-C39-D39,"") -> 0 | F39: =IF(A39<>"",IF(E39=0,"Settled","Unsettled"),"") -> Settled
A40: =IF(Roster!$A$38<>"",Roster!$A$38,"") -> Nick Blair | B40: {=IF(A40<>"",IFERROR(INDEX(Roster!$B$5:$B$204,MATCH(A40,Roster!$A$5:$A$204,0)),0)+IFERROR(SUMPRODUCT((INDEX(Attendance!$B$7:$AY$206,MATCH(A40,Attendance!$A$7:$A$206,0),0)=1)*Attendance!$B$4:$AY$4),0),"")} -> 0 | C40: =IF(A40<>"",SUMIFS(Transactions!$F$7:$F$996,Transactions!$D$7:$D$996,"Income",Transactions!$E$7:$E$996,A40),"") -> 0 | D40: =IF(A40<>"",SUMIFS(Transactions!$F$7:$F$996,Transactions!$D$7:$D$996,"Expense",Transactions!$E$7:$E$996,A40),"") -> 0 | E40: =IF(A40<>"",B40-C40-D40,"") -> 0 | F40: =IF(A40<>"",IF(E40=0,"Settled","Unsettled"),"") -> Settled
A41: =IF(Roster!$A$39<>"",Roster!$A$39,"") | B41: {=IF(A41<>"",IFERROR(INDEX(Roster!$B$5:$B$204,MATCH(A41,Roster!$A$5:$A$204,0)),0)+IFERROR(SUMPRODUCT((INDEX(Attendance!$B$7:$AY$206,MATCH(A41,Attendance!$A$7:$A$206,0),0)=1)*Attendance!$B$4:$AY$4),0),"")} | C41: =IF(A41<>"",SUMIFS(Transactions!$F$7:$F$996,Transactions!$D$7:$D$996,"Income",Transactions!$E$7:$E$996,A41),"") | D41: =IF(A41<>"",SUMIFS(Transactions!$F$7:$F$996,Transactions!$D$7:$D$996,"Expense",Transactions!$E$7:$E$996,A41),"") | E41: =IF(A41<>"",B41-C41-D41,"") | F41: =IF(A41<>"",IF(E41=0,"Settled","Unsettled"),"")
A42: =IF(Roster!$A$40<>"",Roster!$A$40,"") | B42: {=IF(A42<>"",IFERROR(INDEX(Roster!$B$5:$B$204,MATCH(A42,Roster!$A$5:$A$204,0)),0)+IFERROR(SUMPRODUCT((INDEX(Attendance!$B$7:$AY$206,MATCH(A42,Attendance!$A$7:$A$206,0),0)=1)*Attendance!$B$4:$AY$4),0),"")} | C42: =IF(A42<>"",SUMIFS(Transactions!$F$7:$F$996,Transactions!$D$7:$D$996,"Income",Transactions!$E$7:$E$996,A42),"") | D42: =IF(A42<>"",SUMIFS(Transactions!$F$7:$F$996,Transactions!$D$7:$D$996,"Expense",Transactions!$E$7:$E$996,A42),"") | E42: =IF(A42<>"",B42-C42-D42,"") | F42: =IF(A42<>"",IF(E42=0,"Settled","Unsettled"),"")
A43: =IF(Roster!$A$41<>"",Roster!$A$41,"") | B43: {=IF(A43<>"",IFERROR(INDEX(Roster!$B$5:$B$204,MATCH(A43,Roster!$A$5:$A$204,0)),0)+IFERROR(SUMPRODUCT((INDEX(Attendance!$B$7:$AY$206,MATCH(A43,Attendance!$A$7:$A$206,0),0)=1)*Attendance!$B$4:$AY$4),0),"")} | C43: =IF(A43<>"",SUMIFS(Transactions!$F$7:$F$996,Transactions!$D$7:$D$996,"Income",Transactions!$E$7:$E$996,A43),"") | D43: =IF(A43<>"",SUMIFS(Transactions!$F$7:$F$996,Transactions!$D$7:$D$996,"Expense",Transactions!$E$7:$E$996,A43),"") | E43: =IF(A43<>"",B43-C43-D43,"") | F43: =IF(A43<>"",IF(E43=0,"Settled","Unsettled"),"")
A44: =IF(Roster!$A$42<>"",Roster!$A$42,"") | B44: {=IF(A44<>"",IFERROR(INDEX(Roster!$B$5:$B$204,MATCH(A44,Roster!$A$5:$A$204,0)),0)+IFERROR(SUMPRODUCT((INDEX(Attendance!$B$7:$AY$206,MATCH(A44,Attendance!$A$7:$A$206,0),0)=1)*Attendance!$B$4:$AY$4),0),"")} | C44: =IF(A44<>"",SUMIFS(Transactions!$F$7:$F$996,Transactions!$D$7:$D$996,"Income",Transactions!$E$7:$E$996,A44),"") | D44: =IF(A44<>"",SUMIFS(Transactions!$F$7:$F$996,Transactions!$D$7:$D$996,"Expense",Transactions!$E$7:$E$996,A44),"") | E44: =IF(A44<>"",B44-C44-D44,"") | F44: =IF(A44<>"",IF(E44=0,"Settled","Unsettled"),"")
A45: =IF(Roster!$A$43<>"",Roster!$A$43,"") | B45: {=IF(A45<>"",IFERROR(INDEX(Roster!$B$5:$B$204,MATCH(A45,Roster!$A$5:$A$204,0)),0)+IFERROR(SUMPRODUCT((INDEX(Attendance!$B$7:$AY$206,MATCH(A45,Attendance!$A$7:$A$206,0),0)=1)*Attendance!$B$4:$AY$4),0),"")} | C45: =IF(A45<>"",SUMIFS(Transactions!$F$7:$F$996,Transactions!$D$7:$D$996,"Income",Transactions!$E$7:$E$996,A45),"") | D45: =IF(A45<>"",SUMIFS(Transactions!$F$7:$F$996,Transactions!$D$7:$D$996,"Expense",Transactions!$E$7:$E$996,A45),"") | E45: =IF(A45<>"",B45-C45-D45,"") | F45: =IF(A45<>"",IF(E45=0,"Settled","Unsettled"),"")
A46: =IF(Roster!$A$44<>"",Roster!$A$44,"") | B46: {=IF(A46<>"",IFERROR(INDEX(Roster!$B$5:$B$204,MATCH(A46,Roster!$A$5:$A$204,0)),0)+IFERROR(SUMPRODUCT((INDEX(Attendance!$B$7:$AY$206,MATCH(A46,Attendance!$A$7:$A$206,0),0)=1)*Attendance!$B$4:$AY$4),0),"")} | C46: =IF(A46<>"",SUMIFS(Transactions!$F$7:$F$996,Transactions!$D$7:$D$996,"Income",Transactions!$E$7:$E$996,A46),"") | D46: =IF(A46<>"",SUMIFS(Transactions!$F$7:$F$996,Transactions!$D$7:$D$996,"Expense",Transactions!$E$7:$E$996,A46),"") | E46: =IF(A46<>"",B46-C46-D46,"") | F46: =IF(A46<>"",IF(E46=0,"Settled","Unsettled"),"")
A47: =IF(Roster!$A$45<>"",Roster!$A$45,"") | B47: {=IF(A47<>"",IFERROR(INDEX(Roster!$B$5:$B$204,MATCH(A47,Roster!$A$5:$A$204,0)),0)+IFERROR(SUMPRODUCT((INDEX(Attendance!$B$7:$AY$206,MATCH(A47,Attendance!$A$7:$A$206,0),0)=1)*Attendance!$B$4:$AY$4),0),"")} | C47: =IF(A47<>"",SUMIFS(Transactions!$F$7:$F$996,Transactions!$D$7:$D$996,"Income",Transactions!$E$7:$E$996,A47),"") | D47: =IF(A47<>"",SUMIFS(Transactions!$F$7:$F$996,Transactions!$D$7:$D$996,"Expense",Transactions!$E$7:$E$996,A47),"") | E47: =IF(A47<>"",B47-C47-D47,"") | F47: =IF(A47<>"",IF(E47=0,"Settled","Unsettled"),"")
A48: =IF(Roster!$A$46<>"",Roster!$A$46,"") | B48: {=IF(A48<>"",IFERROR(INDEX(Roster!$B$5:$B$204,MATCH(A48,Roster!$A$5:$A$204,0)),0)+IFERROR(SUMPRODUCT((INDEX(Attendance!$B$7:$AY$206,MATCH(A48,Attendance!$A$7:$A$206,0),0)=1)*Attendance!$B$4:$AY$4),0),"")} | C48: =IF(A48<>"",SUMIFS(Transactions!$F$7:$F$996,Transactions!$D$7:$D$996,"Income",Transactions!$E$7:$E$996,A48),"") | D48: =IF(A48<>"",SUMIFS(Transactions!$F$7:$F$996,Transactions!$D$7:$D$996,"Expense",Transactions!$E$7:$E$996,A48),"") | E48: =IF(A48<>"",B48-C48-D48,"") | F48: =IF(A48<>"",IF(E48=0,"Settled","Unsettled"),"")
A49: =IF(Roster!$A$47<>"",Roster!$A$47,"") | B49: {=IF(A49<>"",IFERROR(INDEX(Roster!$B$5:$B$204,MATCH(A49,Roster!$A$5:$A$204,0)),0)+IFERROR(SUMPRODUCT((INDEX(Attendance!$B$7:$AY$206,MATCH(A49,Attendance!$A$7:$A$206,0),0)=1)*Attendance!$B$4:$AY$4),0),"")} | C49: =IF(A49<>"",SUMIFS(Transactions!$F$7:$F$996,Transactions!$D$7:$D$996,"Income",Transactions!$E$7:$E$996,A49),"") | D49: =IF(A49<>"",SUMIFS(Transactions!$F$7:$F$996,Transactions!$D$7:$D$996,"Expense",Transactions!$E$7:$E$996,A49),"") | E49: =IF(A49<>"",B49-C49-D49,"") | F49: =IF(A49<>"",IF(E49=0,"Settled","Unsettled"),"")
A50: =IF(Roster!$A$48<>"",Roster!$A$48,"") | B50: {=IF(A50<>"",IFERROR(INDEX(Roster!$B$5:$B$204,MATCH(A50,Roster!$A$5:$A$204,0)),0)+IFERROR(SUMPRODUCT((INDEX(Attendance!$B$7:$AY$206,MATCH(A50,Attendance!$A$7:$A$206,0),0)=1)*Attendance!$B$4:$AY$4),0),"")} | C50: =IF(A50<>"",SUMIFS(Transactions!$F$7:$F$996,Transactions!$D$7:$D$996,"Income",Transactions!$E$7:$E$996,A50),"") | D50: =IF(A50<>"",SUMIFS(Transactions!$F$7:$F$996,Transactions!$D$7:$D$996,"Expense",Transactions!$E$7:$E$996,A50),"") | E50: =IF(A50<>"",B50-C50-D50,"") | F50: =IF(A50<>"",IF(E50=0,"Settled","Unsettled"),"")
A51: =IF(Roster!$A$49<>"",Roster!$A$49,"") | B51: {=IF(A51<>"",IFERROR(INDEX(Roster!$B$5:$B$204,MATCH(A51,Roster!$A$5:$A$204,0)),0)+IFERROR(SUMPRODUCT((INDEX(Attendance!$B$7:$AY$206,MATCH(A51,Attendance!$A$7:$A$206,0),0)=1)*Attendance!$B$4:$AY$4),0),"")} | C51: =IF(A51<>"",SUMIFS(Transactions!$F$7:$F$996,Transactions!$D$7:$D$996,"Income",Transactions!$E$7:$E$996,A51),"") | D51: =IF(A51<>"",SUMIFS(Transactions!$F$7:$F$996,Transactions!$D$7:$D$996,"Expense",Transactions!$E$7:$E$996,A51),"") | E51: =IF(A51<>"",B51-C51-D51,"") | F51: =IF(A51<>"",IF(E51=0,"Settled","Unsettled"),"")
A52: =IF(Roster!$A$50<>"",Roster!$A$50,"") | B52: {=IF(A52<>"",IFERROR(INDEX(Roster!$B$5:$B$204,MATCH(A52,Roster!$A$5:$A$204,0)),0)+IFERROR(SUMPRODUCT((INDEX(Attendance!$B$7:$AY$206,MATCH(A52,Attendance!$A$7:$A$206,0),0)=1)*Attendance!$B$4:$AY$4),0),"")} | C52: =IF(A52<>"",SUMIFS(Transactions!$F$7:$F$996,Transactions!$D$7:$D$996,"Income",Transactions!$E$7:$E$996,A52),"") | D52: =IF(A52<>"",SUMIFS(Transactions!$F$7:$F$996,Transactions!$D$7:$D$996,"Expense",Transactions!$E$7:$E$996,A52),"") | E52: =IF(A52<>"",B52-C52-D52,"") | F52: =IF(A52<>"",IF(E52=0,"Settled","Unsettled"),"")
A53: =IF(Roster!$A$51<>"",Roster!$A$51,"") | B53: {=IF(A53<>"",IFERROR(INDEX(Roster!$B$5:$B$204,MATCH(A53,Roster!$A$5:$A$204,0)),0)+IFERROR(SUMPRODUCT((INDEX(Attendance!$B$7:$AY$206,MATCH(A53,Attendance!$A$7:$A$206,0),0)=1)*Attendance!$B$4:$AY$4),0),"")} | C53: =IF(A53<>"",SUMIFS(Transactions!$F$7:$F$996,Transactions!$D$7:$D$996,"Income",Transactions!$E$7:$E$996,A53),"") | D53: =IF(A53<>"",SUMIFS(Transactions!$F$7:$F$996,Transactions!$D$7:$D$996,"Expense",Transactions!$E$7:$E$996,A53),"") | E53: =IF(A53<>"",B53-C53-D53,"") | F53: =IF(A53<>"",IF(E53=0,"Settled","Unsettled"),"")
A54: =IF(Roster!$A$52<>"",Roster!$A$52,"") | B54: {=IF(A54<>"",IFERROR(INDEX(Roster!$B$5:$B$204,MATCH(A54,Roster!$A$5:$A$204,0)),0)+IFERROR(SUMPRODUCT((INDEX(Attendance!$B$7:$AY$206,MATCH(A54,Attendance!$A$7:$A$206,0),0)=1)*Attendance!$B$4:$AY$4),0),"")} | C54: =IF(A54<>"",SUMIFS(Transactions!$F$7:$F$996,Transactions!$D$7:$D$996,"Income",Transactions!$E$7:$E$996,A54),"") | D54: =IF(A54<>"",SUMIFS(Transactions!$F$7:$F$996,Transactions!$D$7:$D$996,"Expense",Transactions!$E$7:$E$996,A54),"") | E54: =IF(A54<>"",B54-C54-D54,"") | F54: =IF(A54<>"",IF(E54=0,"Settled","Unsettled"),"")
A55: =IF(Roster!$A$53<>"",Roster!$A$53,"") | B55: {=IF(A55<>"",IFERROR(INDEX(Roster!$B$5:$B$204,MATCH(A55,Roster!$A$5:$A$204,0)),0)+IFERROR(SUMPRODUCT((INDEX(Attendance!$B$7:$AY$206,MATCH(A55,Attendance!$A$7:$A$206,0),0)=1)*Attendance!$B$4:$AY$4),0),"")} | C55: =IF(A55<>"",SUMIFS(Transactions!$F$7:$F$996,Transactions!$D$7:$D$996,"Income",Transactions!$E$7:$E$996,A55),"") | D55: =IF(A55<>"",SUMIFS(Transactions!$F$7:$F$996,Transactions!$D$7:$D$996,"Expense",Transactions!$E$7:$E$996,A55),"") | E55: =IF(A55<>"",B55-C55-D55,"") | F55: =IF(A55<>"",IF(E55=0,"Settled","Unsettled"),"")
A56: =IF(Roster!$A$54<>"",Roster!$A$54,"") | B56: {=IF(A56<>"",IFERROR(INDEX(Roster!$B$5:$B$204,MATCH(A56,Roster!$A$5:$A$204,0)),0)+IFERROR(SUMPRODUCT((INDEX(Attendance!$B$7:$AY$206,MATCH(A56,Attendance!$A$7:$A$206,0),0)=1)*Attendance!$B$4:$AY$4),0),"")} | C56: =IF(A56<>"",SUMIFS(Transactions!$F$7:$F$996,Transactions!$D$7:$D$996,"Income",Transactions!$E$7:$E$996,A56),"") | D56: =IF(A56<>"",SUMIFS(Transactions!$F$7:$F$996,Transactions!$D$7:$D$996,"Expense",Transactions!$E$7:$E$996,A56),"") | E56: =IF(A56<>"",B56-C56-D56,"") | F56: =IF(A56<>"",IF(E56=0,"Settled","Unsettled"),"")
A57: =IF(Roster!$A$55<>"",Roster!$A$55,"") | B57: {=IF(A57<>"",IFERROR(INDEX(Roster!$B$5:$B$204,MATCH(A57,Roster!$A$5:$A$204,0)),0)+IFERROR(SUMPRODUCT((INDEX(Attendance!$B$7:$AY$206,MATCH(A57,Attendance!$A$7:$A$206,0),0)=1)*Attendance!$B$4:$AY$4),0),"")} | C57: =IF(A57<>"",SUMIFS(Transactions!$F$7:$F$996,Transactions!$D$7:$D$996,"Income",Transactions!$E$7:$E$996,A57),"") | D57: =IF(A57<>"",SUMIFS(Transactions!$F$7:$F$996,Transactions!$D$7:$D$996,"Expense",Transactions!$E$7:$E$996,A57),"") | E57: =IF(A57<>"",B57-C57-D57,"") | F57: =IF(A57<>"",IF(E57=0,"Settled","Unsettled"),"")
A58: =IF(Roster!$A$56<>"",Roster!$A$56,"") | B58: {=IF(A58<>"",IFERROR(INDEX(Roster!$B$5:$B$204,MATCH(A58,Roster!$A$5:$A$204,0)),0)+IFERROR(SUMPRODUCT((INDEX(Attendance!$B$7:$AY$206,MATCH(A58,Attendance!$A$7:$A$206,0),0)=1)*Attendance!$B$4:$AY$4),0),"")} | C58: =IF(A58<>"",SUMIFS(Transactions!$F$7:$F$996,Transactions!$D$7:$D$996,"Income",Transactions!$E$7:$E$996,A58),"") | D58: =IF(A58<>"",SUMIFS(Transactions!$F$7:$F$996,Transactions!$D$7:$D$996,"Expense",Transactions!$E$7:$E$996,A58),"") | E58: =IF(A58<>"",B58-C58-D58,"") | F58: =IF(A58<>"",IF(E58=0,"Settled","Unsettled"),"")
A59: =IF(Roster!$A$57<>"",Roster!$A$57,"") | B59: {=IF(A59<>"",IFERROR(INDEX(Roster!$B$5:$B$204,MATCH(A59,Roster!$A$5:$A$204,0)),0)+IFERROR(SUMPRODUCT((INDEX(Attendance!$B$7:$AY$206,MATCH(A59,Attendance!$A$7:$A$206,0),0)=1)*Attendance!$B$4:$AY$4),0),"")} | C59: =IF(A59<>"",SUMIFS(Transactions!$F$7:$F$996,Transactions!$D$7:$D$996,"Income",Transactions!$E$7:$E$996,A59),"") | D59: =IF(A59<>"",SUMIFS(Transactions!$F$7:$F$996,Transactions!$D$7:$D$996,"Expense",Transactions!$E$7:$E$996,A59),"") | E59: =IF(A59<>"",B59-C59-D59,"") | F59: =IF(A59<>"",IF(E59=0,"Settled","Unsettled"),"")
A60: =IF(Roster!$A$58<>"",Roster!$A$58,"") | B60: {=IF(A60<>"",IFERROR(INDEX(Roster!$B$5:$B$204,MATCH(A60,Roster!$A$5:$A$204,0)),0)+IFERROR(SUMPRODUCT((INDEX(Attendance!$B$7:$AY$206,MATCH(A60,Attendance!$A$7:$A$206,0),0)=1)*Attendance!$B$4:$AY$4),0),"")} | C60: =IF(A60<>"",SUMIFS(Transactions!$F$7:$F$996,Transactions!$D$7:$D$996,"Income",Transactions!$E$7:$E$996,A60),"") | D60: =IF(A60<>"",SUMIFS(Transactions!$F$7:$F$996,Transactions!$D$7:$D$996,"Expense",Transactions!$E$7:$E$996,A60),"") | E60: =IF(A60<>"",B60-C60-D60,"") | F60: =IF(A60<>"",IF(E60=0,"Settled","Unsettled"),"")
A61: =IF(Roster!$A$59<>"",Roster!$A$59,"") | B61: {=IF(A61<>"",IFERROR(INDEX(Roster!$B$5:$B$204,MATCH(A61,Roster!$A$5:$A$204,0)),0)+IFERROR(SUMPRODUCT((INDEX(Attendance!$B$7:$AY$206,MATCH(A61,Attendance!$A$7:$A$206,0),0)=1)*Attendance!$B$4:$AY$4),0),"")} | C61: =IF(A61<>"",SUMIFS(Transactions!$F$7:$F$996,Transactions!$D$7:$D$996,"Income",Transactions!$E$7:$E$996,A61),"") | D61: =IF(A61<>"",SUMIFS(Transactions!$F$7:$F$996,Transactions!$D$7:$D$996,"Expense",Transactions!$E$7:$E$996,A61),"") | E61: =IF(A61<>"",B61-C61-D61,"") | F61: =IF(A61<>"",IF(E61=0,"Settled","Unsettled"),"")
A62: =IF(Roster!$A$60<>"",Roster!$A$60,"") | B62: {=IF(A62<>"",IFERROR(INDEX(Roster!$B$5:$B$204,MATCH(A62,Roster!$A$5:$A$204,0)),0)+IFERROR(SUMPRODUCT((INDEX(Attendance!$B$7:$AY$206,MATCH(A62,Attendance!$A$7:$A$206,0),0)=1)*Attendance!$B$4:$AY$4),0),"")} | C62: =IF(A62<>"",SUMIFS(Transactions!$F$7:$F$996,Transactions!$D$7:$D$996,"Income",Transactions!$E$7:$E$996,A62),"") | D62: =IF(A62<>"",SUMIFS(Transactions!$F$7:$F$996,Transactions!$D$7:$D$996,"Expense",Transactions!$E$7:$E$996,A62),"") | E62: =IF(A62<>"",B62-C62-D62,"") | F62: =IF(A62<>"",IF(E62=0,"Settled","Unsettled"),"")
A63: =IF(Roster!$A$61<>"",Roster!$A$61,"") | B63: {=IF(A63<>"",IFERROR(INDEX(Roster!$B$5:$B$204,MATCH(A63,Roster!$A$5:$A$204,0)),0)+IFERROR(SUMPRODUCT((INDEX(Attendance!$B$7:$AY$206,MATCH(A63,Attendance!$A$7:$A$206,0),0)=1)*Attendance!$B$4:$AY$4),0),"")} | C63: =IF(A63<>"",SUMIFS(Transactions!$F$7:$F$996,Transactions!$D$7:$D$996,"Income",Transactions!$E$7:$E$996,A63),"") | D63: =IF(A63<>"",SUMIFS(Transactions!$F$7:$F$996,Transactions!$D$7:$D$996,"Expense",Transactions!$E$7:$E$996,A63),"") | E63: =IF(A63<>"",B63-C63-D63,"") | F63: =IF(A63<>"",IF(E63=0,"Settled","Unsettled"),"")
A64: =IF(Roster!$A$62<>"",Roster!$A$62,"") | B64: {=IF(A64<>"",IFERROR(INDEX(Roster!$B$5:$B$204,MATCH(A64,Roster!$A$5:$A$204,0)),0)+IFERROR(SUMPRODUCT((INDEX(Attendance!$B$7:$AY$206,MATCH(A64,Attendance!$A$7:$A$206,0),0)=1)*Attendance!$B$4:$AY$4),0),"")} | C64: =IF(A64<>"",SUMIFS(Transactions!$F$7:$F$996,Transactions!$D$7:$D$996,"Income",Transactions!$E$7:$E$996,A64),"") | D64: =IF(A64<>"",SUMIFS(Transactions!$F$7:$F$996,Transactions!$D$7:$D$996,"Expense",Transactions!$E$7:$E$996,A64),"") | E64: =IF(A64<>"",B64-C64-D64,"") | F64: =IF(A64<>"",IF(E64=0,"Settled","Unsettled"),"")
A65: =IF(Roster!$A$63<>"",Roster!$A$63,"") | B65: {=IF(A65<>"",IFERROR(INDEX(Roster!$B$5:$B$204,MATCH(A65,Roster!$A$5:$A$204,0)),0)+IFERROR(SUMPRODUCT((INDEX(Attendance!$B$7:$AY$206,MATCH(A65,Attendance!$A$7:$A$206,0),0)=1)*Attendance!$B$4:$AY$4),0),"")} | C65: =IF(A65<>"",SUMIFS(Transactions!$F$7:$F$996,Transactions!$D$7:$D$996,"Income",Transactions!$E$7:$E$996,A65),"") | D65: =IF(A65<>"",SUMIFS(Transactions!$F$7:$F$996,Transactions!$D$7:$D$996,"Expense",Transactions!$E$7:$E$996,A65),"") | E65: =IF(A65<>"",B65-C65-D65,"") | F65: =IF(A65<>"",IF(E65=0,"Settled","Unsettled"),"")
A66: =IF(Roster!$A$64<>"",Roster!$A$64,"") | B66: {=IF(A66<>"",IFERROR(INDEX(Roster!$B$5:$B$204,MATCH(A66,Roster!$A$5:$A$204,0)),0)+IFERROR(SUMPRODUCT((INDEX(Attendance!$B$7:$AY$206,MATCH(A66,Attendance!$A$7:$A$206,0),0)=1)*Attendance!$B$4:$AY$4),0),"")} | C66: =IF(A66<>"",SUMIFS(Transactions!$F$7:$F$996,Transactions!$D$7:$D$996,"Income",Transactions!$E$7:$E$996,A66),"") | D66: =IF(A66<>"",SUMIFS(Transactions!$F$7:$F$996,Transactions!$D$7:$D$996,"Expense",Transactions!$E$7:$E$996,A66),"") | E66: =IF(A66<>"",B66-C66-D66,"") | F66: =IF(A66<>"",IF(E66=0,"Settled","Unsettled"),"")
A67: =IF(Roster!$A$65<>"",Roster!$A$65,"") | B67: {=IF(A67<>"",IFERROR(INDEX(Roster!$B$5:$B$204,MATCH(A67,Roster!$A$5:$A$204,0)),0)+IFERROR(SUMPRODUCT((INDEX(Attendance!$B$7:$AY$206,MATCH(A67,Attendance!$A$7:$A$206,0),0)=1)*Attendance!$B$4:$AY$4),0),"")} | C67: =IF(A67<>"",SUMIFS(Transactions!$F$7:$F$996,Transactions!$D$7:$D$996,"Income",Transactions!$E$7:$E$996,A67),"") | D67: =IF(A67<>"",SUMIFS(Transactions!$F$7:$F$996,Transactions!$D$7:$D$996,"Expense",Transactions!$E$7:$E$996,A67),"") | E67: =IF(A67<>"",B67-C67-D67,"") | F67: =IF(A67<>"",IF(E67=0,"Settled","Unsettled"),"")
A68: =IF(Roster!$A$66<>"",Roster!$A$66,"") | B68: {=IF(A68<>"",IFERROR(INDEX(Roster!$B$5:$B$204,MATCH(A68,Roster!$A$5:$A$204,0)),0)+IFERROR(SUMPRODUCT((INDEX(Attendance!$B$7:$AY$206,MATCH(A68,Attendance!$A$7:$A$206,0),0)=1)*Attendance!$B$4:$AY$4),0),"")} | C68: =IF(A68<>"",SUMIFS(Transactions!$F$7:$F$996,Transactions!$D$7:$D$996,"Income",Transactions!$E$7:$E$996,A68),"") | D68: =IF(A68<>"",SUMIFS(Transactions!$F$7:$F$996,Transactions!$D$7:$D$996,"Expense",Transactions!$E$7:$E$996,A68),"") | E68: =IF(A68<>"",B68-C68-D68,"") | F68: =IF(A68<>"",IF(E68=0,"Settled","Unsettled"),"")
A69: =IF(Roster!$A$67<>"",Roster!$A$67,"") | B69: {=IF(A69<>"",IFERROR(INDEX(Roster!$B$5:$B$204,MATCH(A69,Roster!$A$5:$A$204,0)),0)+IFERROR(SUMPRODUCT((INDEX(Attendance!$B$7:$AY$206,MATCH(A69,Attendance!$A$7:$A$206,0),0)=1)*Attendance!$B$4:$AY$4),0),"")} | C69: =IF(A69<>"",SUMIFS(Transactions!$F$7:$F$996,Transactions!$D$7:$D$996,"Income",Transactions!$E$7:$E$996,A69),"") | D69: =IF(A69<>"",SUMIFS(Transactions!$F$7:$F$996,Transactions!$D$7:$D$996,"Expense",Transactions!$E$7:$E$996,A69),"") | E69: =IF(A69<>"",B69-C69-D69,"") | F69: =IF(A69<>"",IF(E69=0,"Settled","Unsettled"),"")
A70: =IF(Roster!$A$68<>"",Roster!$A$68,"") | B70: {=IF(A70<>"",IFERROR(INDEX(Roster!$B$5:$B$204,MATCH(A70,Roster!$A$5:$A$204,0)),0)+IFERROR(SUMPRODUCT((INDEX(Attendance!$B$7:$AY$206,MATCH(A70,Attendance!$A$7:$A$206,0),0)=1)*Attendance!$B$4:$AY$4),0),"")} | C70: =IF(A70<>"",SUMIFS(Transactions!$F$7:$F$996,Transactions!$D$7:$D$996,"Income",Transactions!$E$7:$E$996,A70),"") | D70: =IF(A70<>"",SUMIFS(Transactions!$F$7:$F$996,Transactions!$D$7:$D$996,"Expense",Transactions!$E$7:$E$996,A70),"") | E70: =IF(A70<>"",B70-C70-D70,"") | F70: =IF(A70<>"",IF(E70=0,"Settled","Unsettled"),"")
A71: =IF(Roster!$A$69<>"",Roster!$A$69,"") | B71: {=IF(A71<>"",IFERROR(INDEX(Roster!$B$5:$B$204,MATCH(A71,Roster!$A$5:$A$204,0)),0)+IFERROR(SUMPRODUCT((INDEX(Attendance!$B$7:$AY$206,MATCH(A71,Attendance!$A$7:$A$206,0),0)=1)*Attendance!$B$4:$AY$4),0),"")} | C71: =IF(A71<>"",SUMIFS(Transactions!$F$7:$F$996,Transactions!$D$7:$D$996,"Income",Transactions!$E$7:$E$996,A71),"") | D71: =IF(A71<>"",SUMIFS(Transactions!$F$7:$F$996,Transactions!$D$7:$D$996,"Expense",Transactions!$E$7:$E$996,A71),"") | E71: =IF(A71<>"",B71-C71-D71,"") | F71: =IF(A71<>"",IF(E71=0,"Settled","Unsettled"),"")
A72: =IF(Roster!$A$70<>"",Roster!$A$70,"") | B72: {=IF(A72<>"",IFERROR(INDEX(Roster!$B$5:$B$204,MATCH(A72,Roster!$A$5:$A$204,0)),0)+IFERROR(SUMPRODUCT((INDEX(Attendance!$B$7:$AY$206,MATCH(A72,Attendance!$A$7:$A$206,0),0)=1)*Attendance!$B$4:$AY$4),0),"")} | C72: =IF(A72<>"",SUMIFS(Transactions!$F$7:$F$996,Transactions!$D$7:$D$996,"Income",Transactions!$E$7:$E$996,A72),"") | D72: =IF(A72<>"",SUMIFS(Transactions!$F$7:$F$996,Transactions!$D$7:$D$996,"Expense",Transactions!$E$7:$E$996,A72),"") | E72: =IF(A72<>"",B72-C72-D72,"") | F72: =IF(A72<>"",IF(E72=0,"Settled","Unsettled"),"")
A73: =IF(Roster!$A$71<>"",Roster!$A$71,"") | B73: {=IF(A73<>"",IFERROR(INDEX(Roster!$B$5:$B$204,MATCH(A73,Roster!$A$5:$A$204,0)),0)+IFERROR(SUMPRODUCT((INDEX(Attendance!$B$7:$AY$206,MATCH(A73,Attendance!$A$7:$A$206,0),0)=1)*Attendance!$B$4:$AY$4),0),"")} | C73: =IF(A73<>"",SUMIFS(Transactions!$F$7:$F$996,Transactions!$D$7:$D$996,"Income",Transactions!$E$7:$E$996,A73),"") | D73: =IF(A73<>"",SUMIFS(Transactions!$F$7:$F$996,Transactions!$D$7:$D$996,"Expense",Transactions!$E$7:$E$996,A73),"") | E73: =IF(A73<>"",B73-C73-D73,"") | F73: =IF(A73<>"",IF(E73=0,"Settled","Unsettled"),"")
A74: =IF(Roster!$A$72<>"",Roster!$A$72,"") | B74: {=IF(A74<>"",IFERROR(INDEX(Roster!$B$5:$B$204,MATCH(A74,Roster!$A$5:$A$204,0)),0)+IFERROR(SUMPRODUCT((INDEX(Attendance!$B$7:$AY$206,MATCH(A74,Attendance!$A$7:$A$206,0),0)=1)*Attendance!$B$4:$AY$4),0),"")} | C74: =IF(A74<>"",SUMIFS(Transactions!$F$7:$F$996,Transactions!$D$7:$D$996,"Income",Transactions!$E$7:$E$996,A74),"") | D74: =IF(A74<>"",SUMIFS(Transactions!$F$7:$F$996,Transactions!$D$7:$D$996,"Expense",Transactions!$E$7:$E$996,A74),"") | E74: =IF(A74<>"",B74-C74-D74,"") | F74: =IF(A74<>"",IF(E74=0,"Settled","Unsettled"),"")
A75: =IF(Roster!$A$73<>"",Roster!$A$73,"") | B75: {=IF(A75<>"",IFERROR(INDEX(Roster!$B$5:$B$204,MATCH(A75,Roster!$A$5:$A$204,0)),0)+IFERROR(SUMPRODUCT((INDEX(Attendance!$B$7:$AY$206,MATCH(A75,Attendance!$A$7:$A$206,0),0)=1)*Attendance!$B$4:$AY$4),0),"")} | C75: =IF(A75<>"",SUMIFS(Transactions!$F$7:$F$996,Transactions!$D$7:$D$996,"Income",Transactions!$E$7:$E$996,A75),"") | D75: =IF(A75<>"",SUMIFS(Transactions!$F$7:$F$996,Transactions!$D$7:$D$996,"Expense",Transactions!$E$7:$E$996,A75),"") | E75: =IF(A75<>"",B75-C75-D75,"") | F75: =IF(A75<>"",IF(E75=0,"Settled","Unsettled"),"")
A76: =IF(Roster!$A$74<>"",Roster!$A$74,"") | B76: {=IF(A76<>"",IFERROR(INDEX(Roster!$B$5:$B$204,MATCH(A76,Roster!$A$5:$A$204,0)),0)+IFERROR(SUMPRODUCT((INDEX(Attendance!$B$7:$AY$206,MATCH(A76,Attendance!$A$7:$A$206,0),0)=1)*Attendance!$B$4:$AY$4),0),"")} | C76: =IF(A76<>"",SUMIFS(Transactions!$F$7:$F$996,Transactions!$D$7:$D$996,"Income",Transactions!$E$7:$E$996,A76),"") | D76: =IF(A76<>"",SUMIFS(Transactions!$F$7:$F$996,Transactions!$D$7:$D$996,"Expense",Transactions!$E$7:$E$996,A76),"") | E76: =IF(A76<>"",B76-C76-D76,"") | F76: =IF(A76<>"",IF(E76=0,"Settled","Unsettled"),"")
A77: =IF(Roster!$A$75<>"",Roster!$A$75,"") | B77: {=IF(A77<>"",IFERROR(INDEX(Roster!$B$5:$B$204,MATCH(A77,Roster!$A$5:$A$204,0)),0)+IFERROR(SUMPRODUCT((INDEX(Attendance!$B$7:$AY$206,MATCH(A77,Attendance!$A$7:$A$206,0),0)=1)*Attendance!$B$4:$AY$4),0),"")} | C77: =IF(A77<>"",SUMIFS(Transactions!$F$7:$F$996,Transactions!$D$7:$D$996,"Income",Transactions!$E$7:$E$996,A77),"") | D77: =IF(A77<>"",SUMIFS(Transactions!$F$7:$F$996,Transactions!$D$7:$D$996,"Expense",Transactions!$E$7:$E$996,A77),"") | E77: =IF(A77<>"",B77-C77-D77,"") | F77: =IF(A77<>"",IF(E77=0,"Settled","Unsettled"),"")
A78: =IF(Roster!$A$76<>"",Roster!$A$76,"") | B78: {=IF(A78<>"",IFERROR(INDEX(Roster!$B$5:$B$204,MATCH(A78,Roster!$A$5:$A$204,0)),0)+IFERROR(SUMPRODUCT((INDEX(Attendance!$B$7:$AY$206,MATCH(A78,Attendance!$A$7:$A$206,0),0)=1)*Attendance!$B$4:$AY$4),0),"")} | C78: =IF(A78<>"",SUMIFS(Transactions!$F$7:$F$996,Transactions!$D$7:$D$996,"Income",Transactions!$E$7:$E$996,A78),"") | D78: =IF(A78<>"",SUMIFS(Transactions!$F$7:$F$996,Transactions!$D$7:$D$996,"Expense",Transactions!$E$7:$E$996,A78),"") | E78: =IF(A78<>"",B78-C78-D78,"") | F78: =IF(A78<>"",IF(E78=0,"Settled","Unsettled"),"")
A79: =IF(Roster!$A$77<>"",Roster!$A$77,"") | B79: {=IF(A79<>"",IFERROR(INDEX(Roster!$B$5:$B$204,MATCH(A79,Roster!$A$5:$A$204,0)),0)+IFERROR(SUMPRODUCT((INDEX(Attendance!$B$7:$AY$206,MATCH(A79,Attendance!$A$7:$A$206,0),0)=1)*Attendance!$B$4:$AY$4),0),"")} | C79: =IF(A79<>"",SUMIFS(Transactions!$F$7:$F$996,Transactions!$D$7:$D$996,"Income",Transactions!$E$7:$E$996,A79),"") | D79: =IF(A79<>"",SUMIFS(Transactions!$F$7:$F$996,Transactions!$D$7:$D$996,"Expense",Transactions!$E$7:$E$996,A79),"") | E79: =IF(A79<>"",B79-C79-D79,"") | F79: =IF(A79<>"",IF(E79=0,"Settled","Unsettled"),"")
A80: =IF(Roster!$A$78<>"",Roster!$A$78,"") | B80: {=IF(A80<>"",IFERROR(INDEX(Roster!$B$5:$B$204,MATCH(A80,Roster!$A$5:$A$204,0)),0)+IFERROR(SUMPRODUCT((INDEX(Attendance!$B$7:$AY$206,MATCH(A80,Attendance!$A$7:$A$206,0),0)=1)*Attendance!$B$4:$AY$4),0),"")} | C80: =IF(A80<>"",SUMIFS(Transactions!$F$7:$F$996,Transactions!$D$7:$D$996,"Income",Transactions!$E$7:$E$996,A80),"") | D80: =IF(A80<>"",SUMIFS(Transactions!$F$7:$F$996,Transactions!$D$7:$D$996,"Expense",Transactions!$E$7:$E$996,A80),"") | E80: =IF(A80<>"",B80-C80-D80,"") | F80: =IF(A80<>"",IF(E80=0,"Settled","Unsettled"),"")
A81: =IF(Roster!$A$79<>"",Roster!$A$79,"") | B81: {=IF(A81<>"",IFERROR(INDEX(Roster!$B$5:$B$204,MATCH(A81,Roster!$A$5:$A$204,0)),0)+IFERROR(SUMPRODUCT((INDEX(Attendance!$B$7:$AY$206,MATCH(A81,Attendance!$A$7:$A$206,0),0)=1)*Attendance!$B$4:$AY$4),0),"")} | C81: =IF(A81<>"",SUMIFS(Transactions!$F$7:$F$996,Transactions!$D$7:$D$996,"Income",Transactions!$E$7:$E$996,A81),"") | D81: =IF(A81<>"",SUMIFS(Transactions!$F$7:$F$996,Transactions!$D$7:$D$996,"Expense",Transactions!$E$7:$E$996,A81),"") | E81: =IF(A81<>"",B81-C81-D81,"") | F81: =IF(A81<>"",IF(E81=0,"Settled","Unsettled"),"")
A82: =IF(Roster!$A$80<>"",Roster!$A$80,"") | B82: {=IF(A82<>"",IFERROR(INDEX(Roster!$B$5:$B$204,MATCH(A82,Roster!$A$5:$A$204,0)),0)+IFERROR(SUMPRODUCT((INDEX(Attendance!$B$7:$AY$206,MATCH(A82,Attendance!$A$7:$A$206,0),0)=1)*Attendance!$B$4:$AY$4),0),"")} | C82: =IF(A82<>"",SUMIFS(Transactions!$F$7:$F$996,Transactions!$D$7:$D$996,"Income",Transactions!$E$7:$E$996,A82),"") | D82: =IF(A82<>"",SUMIFS(Transactions!$F$7:$F$996,Transactions!$D$7:$D$996,"Expense",Transactions!$E$7:$E$996,A82),"") | E82: =IF(A82<>"",B82-C82-D82,"") | F82: =IF(A82<>"",IF(E82=0,"Settled","Unsettled"),"")
A83: =IF(Roster!$A$81<>"",Roster!$A$81,"") | B83: {=IF(A83<>"",IFERROR(INDEX(Roster!$B$5:$B$204,MATCH(A83,Roster!$A$5:$A$204,0)),0)+IFERROR(SUMPRODUCT((INDEX(Attendance!$B$7:$AY$206,MATCH(A83,Attendance!$A$7:$A$206,0),0)=1)*Attendance!$B$4:$AY$4),0),"")} | C83: =IF(A83<>"",SUMIFS(Transactions!$F$7:$F$996,Transactions!$D$7:$D$996,"Income",Transactions!$E$7:$E$996,A83),"") | D83: =IF(A83<>"",SUMIFS(Transactions!$F$7:$F$996,Transactions!$D$7:$D$996,"Expense",Transactions!$E$7:$E$996,A83),"") | E83: =IF(A83<>"",B83-C83-D83,"") | F83: =IF(A83<>"",IF(E83=0,"Settled","Unsettled"),"")
A84: =IF(Roster!$A$82<>"",Roster!$A$82,"") | B84: {=IF(A84<>"",IFERROR(INDEX(Roster!$B$5:$B$204,MATCH(A84,Roster!$A$5:$A$204,0)),0)+IFERROR(SUMPRODUCT((INDEX(Attendance!$B$7:$AY$206,MATCH(A84,Attendance!$A$7:$A$206,0),0)=1)*Attendance!$B$4:$AY$4),0),"")} | C84: =IF(A84<>"",SUMIFS(Transactions!$F$7:$F$996,Transactions!$D$7:$D$996,"Income",Transactions!$E$7:$E$996,A84),"") | D84: =IF(A84<>"",SUMIFS(Transactions!$F$7:$F$996,Transactions!$D$7:$D$996,"Expense",Transactions!$E$7:$E$996,A84),"") | E84: =IF(A84<>"",B84-C84-D84,"") | F84: =IF(A84<>"",IF(E84=0,"Settled","Unsettled"),"")
A85: =IF(Roster!$A$83<>"",Roster!$A$83,"") | B85: {=IF(A85<>"",IFERROR(INDEX(Roster!$B$5:$B$204,MATCH(A85,Roster!$A$5:$A$204,0)),0)+IFERROR(SUMPRODUCT((INDEX(Attendance!$B$7:$AY$206,MATCH(A85,Attendance!$A$7:$A$206,0),0)=1)*Attendance!$B$4:$AY$4),0),"")} | C85: =IF(A85<>"",SUMIFS(Transactions!$F$7:$F$996,Transactions!$D$7:$D$996,"Income",Transactions!$E$7:$E$996,A85),"") | D85: =IF(A85<>"",SUMIFS(Transactions!$F$7:$F$996,Transactions!$D$7:$D$996,"Expense",Transactions!$E$7:$E$996,A85),"") | E85: =IF(A85<>"",B85-C85-D85,"") | F85: =IF(A85<>"",IF(E85=0,"Settled","Unsettled"),"")
A86: =IF(Roster!$A$84<>"",Roster!$A$84,"") | B86: {=IF(A86<>"",IFERROR(INDEX(Roster!$B$5:$B$204,MATCH(A86,Roster!$A$5:$A$204,0)),0)+IFERROR(SUMPRODUCT((INDEX(Attendance!$B$7:$AY$206,MATCH(A86,Attendance!$A$7:$A$206,0),0)=1)*Attendance!$B$4:$AY$4),0),"")} | C86: =IF(A86<>"",SUMIFS(Transactions!$F$7:$F$996,Transactions!$D$7:$D$996,"Income",Transactions!$E$7:$E$996,A86),"") | D86: =IF(A86<>"",SUMIFS(Transactions!$F$7:$F$996,Transactions!$D$7:$D$996,"Expense",Transactions!$E$7:$E$996,A86),"") | E86: =IF(A86<>"",B86-C86-D86,"") | F86: =IF(A86<>"",IF(E86=0,"Settled","Unsettled"),"")
A87: =IF(Roster!$A$85<>"",Roster!$A$85,"") | B87: {=IF(A87<>"",IFERROR(INDEX(Roster!$B$5:$B$204,MATCH(A87,Roster!$A$5:$A$204,0)),0)+IFERROR(SUMPRODUCT((INDEX(Attendance!$B$7:$AY$206,MATCH(A87,Attendance!$A$7:$A$206,0),0)=1)*Attendance!$B$4:$AY$4),0),"")} | C87: =IF(A87<>"",SUMIFS(Transactions!$F$7:$F$996,Transactions!$D$7:$D$996,"Income",Transactions!$E$7:$E$996,A87),"") | D87: =IF(A87<>"",SUMIFS(Transactions!$F$7:$F$996,Transactions!$D$7:$D$996,"Expense",Transactions!$E$7:$E$996,A87),"") | E87: =IF(A87<>"",B87-C87-D87,"") | F87: =IF(A87<>"",IF(E87=0,"Settled","Unsettled"),"")
A88: =IF(Roster!$A$86<>"",Roster!$A$86,"") | B88: {=IF(A88<>"",IFERROR(INDEX(Roster!$B$5:$B$204,MATCH(A88,Roster!$A$5:$A$204,0)),0)+IFERROR(SUMPRODUCT((INDEX(Attendance!$B$7:$AY$206,MATCH(A88,Attendance!$A$7:$A$206,0),0)=1)*Attendance!$B$4:$AY$4),0),"")} | C88: =IF(A88<>"",SUMIFS(Transactions!$F$7:$F$996,Transactions!$D$7:$D$996,"Income",Transactions!$E$7:$E$996,A88),"") | D88: =IF(A88<>"",SUMIFS(Transactions!$F$7:$F$996,Transactions!$D$7:$D$996,"Expense",Transactions!$E$7:$E$996,A88),"") | E88: =IF(A88<>"",B88-C88-D88,"") | F88: =IF(A88<>"",IF(E88=0,"Settled","Unsettled"),"")
A89: =IF(Roster!$A$87<>"",Roster!$A$87,"") | B89: {=IF(A89<>"",IFERROR(INDEX(Roster!$B$5:$B$204,MATCH(A89,Roster!$A$5:$A$204,0)),0)+IFERROR(SUMPRODUCT((INDEX(Attendance!$B$7:$AY$206,MATCH(A89,Attendance!$A$7:$A$206,0),0)=1)*Attendance!$B$4:$AY$4),0),"")} | C89: =IF(A89<>"",SUMIFS(Transactions!$F$7:$F$996,Transactions!$D$7:$D$996,"Income",Transactions!$E$7:$E$996,A89),"") | D89: =IF(A89<>"",SUMIFS(Transactions!$F$7:$F$996,Transactions!$D$7:$D$996,"Expense",Transactions!$E$7:$E$996,A89),"") | E89: =IF(A89<>"",B89-C89-D89,"") | F89: =IF(A89<>"",IF(E89=0,"Settled","Unsettled"),"")
A90: =IF(Roster!$A$88<>"",Roster!$A$88,"") | B90: {=IF(A90<>"",IFERROR(INDEX(Roster!$B$5:$B$204,MATCH(A90,Roster!$A$5:$A$204,0)),0)+IFERROR(SUMPRODUCT((INDEX(Attendance!$B$7:$AY$206,MATCH(A90,Attendance!$A$7:$A$206,0),0)=1)*Attendance!$B$4:$AY$4),0),"")} | C90: =IF(A90<>"",SUMIFS(Transactions!$F$7:$F$996,Transactions!$D$7:$D$996,"Income",Transactions!$E$7:$E$996,A90),"") | D90: =IF(A90<>"",SUMIFS(Transactions!$F$7:$F$996,Transactions!$D$7:$D$996,"Expense",Transactions!$E$7:$E$996,A90),"") | E90: =IF(A90<>"",B90-C90-D90,"") | F90: =IF(A90<>"",IF(E90=0,"Settled","Unsettled"),"")
A91: =IF(Roster!$A$89<>"",Roster!$A$89,"") | B91: {=IF(A91<>"",IFERROR(INDEX(Roster!$B$5:$B$204,MATCH(A91,Roster!$A$5:$A$204,0)),0)+IFERROR(SUMPRODUCT((INDEX(Attendance!$B$7:$AY$206,MATCH(A91,Attendance!$A$7:$A$206,0),0)=1)*Attendance!$B$4:$AY$4),0),"")} | C91: =IF(A91<>"",SUMIFS(Transactions!$F$7:$F$996,Transactions!$D$7:$D$996,"Income",Transactions!$E$7:$E$996,A91),"") | D91: =IF(A91<>"",SUMIFS(Transactions!$F$7:$F$996,Transactions!$D$7:$D$996,"Expense",Transactions!$E$7:$E$996,A91),"") | E91: =IF(A91<>"",B91-C91-D91,"") | F91: =IF(A91<>"",IF(E91=0,"Settled","Unsettled"),"")
A92: =IF(Roster!$A$90<>"",Roster!$A$90,"") | B92: {=IF(A92<>"",IFERROR(INDEX(Roster!$B$5:$B$204,MATCH(A92,Roster!$A$5:$A$204,0)),0)+IFERROR(SUMPRODUCT((INDEX(Attendance!$B$7:$AY$206,MATCH(A92,Attendance!$A$7:$A$206,0),0)=1)*Attendance!$B$4:$AY$4),0),"")} | C92: =IF(A92<>"",SUMIFS(Transactions!$F$7:$F$996,Transactions!$D$7:$D$996,"Income",Transactions!$E$7:$E$996,A92),"") | D92: =IF(A92<>"",SUMIFS(Transactions!$F$7:$F$996,Transactions!$D$7:$D$996,"Expense",Transactions!$E$7:$E$996,A92),"") | E92: =IF(A92<>"",B92-C92-D92,"") | F92: =IF(A92<>"",IF(E92=0,"Settled","Unsettled"),"")
A93: =IF(Roster!$A$91<>"",Roster!$A$91,"") | B93: {=IF(A93<>"",IFERROR(INDEX(Roster!$B$5:$B$204,MATCH(A93,Roster!$A$5:$A$204,0)),0)+IFERROR(SUMPRODUCT((INDEX(Attendance!$B$7:$AY$206,MATCH(A93,Attendance!$A$7:$A$206,0),0)=1)*Attendance!$B$4:$AY$4),0),"")} | C93: =IF(A93<>"",SUMIFS(Transactions!$F$7:$F$996,Transactions!$D$7:$D$996,"Income",Transactions!$E$7:$E$996,A93),"") | D93: =IF(A93<>"",SUMIFS(Transactions!$F$7:$F$996,Transactions!$D$7:$D$996,"Expense",Transactions!$E$7:$E$996,A93),"") | E93: =IF(A93<>"",B93-C93-D93,"") | F93: =IF(A93<>"",IF(E93=0,"Settled","Unsettled"),"")
A94: =IF(Roster!$A$92<>"",Roster!$A$92,"") | B94: {=IF(A94<>"",IFERROR(INDEX(Roster!$B$5:$B$204,MATCH(A94,Roster!$A$5:$A$204,0)),0)+IFERROR(SUMPRODUCT((INDEX(Attendance!$B$7:$AY$206,MATCH(A94,Attendance!$A$7:$A$206,0),0)=1)*Attendance!$B$4:$AY$4),0),"")} | C94: =IF(A94<>"",SUMIFS(Transactions!$F$7:$F$996,Transactions!$D$7:$D$996,"Income",Transactions!$E$7:$E$996,A94),"") | D94: =IF(A94<>"",SUMIFS(Transactions!$F$7:$F$996,Transactions!$D$7:$D$996,"Expense",Transactions!$E$7:$E$996,A94),"") | E94: =IF(A94<>"",B94-C94-D94,"") | F94: =IF(A94<>"",IF(E94=0,"Settled","Unsettled"),"")
A95: =IF(Roster!$A$93<>"",Roster!$A$93,"") | B95: {=IF(A95<>"",IFERROR(INDEX(Roster!$B$5:$B$204,MATCH(A95,Roster!$A$5:$A$204,0)),0)+IFERROR(SUMPRODUCT((INDEX(Attendance!$B$7:$AY$206,MATCH(A95,Attendance!$A$7:$A$206,0),0)=1)*Attendance!$B$4:$AY$4),0),"")} | C95: =IF(A95<>"",SUMIFS(Transactions!$F$7:$F$996,Transactions!$D$7:$D$996,"Income",Transactions!$E$7:$E$996,A95),"") | D95: =IF(A95<>"",SUMIFS(Transactions!$F$7:$F$996,Transactions!$D$7:$D$996,"Expense",Transactions!$E$7:$E$996,A95),"") | E95: =IF(A95<>"",B95-C95-D95,"") | F95: =IF(A95<>"",IF(E95=0,"Settled","Unsettled"),"")
A96: =IF(Roster!$A$94<>"",Roster!$A$94,"") | B96: {=IF(A96<>"",IFERROR(INDEX(Roster!$B$5:$B$204,MATCH(A96,Roster!$A$5:$A$204,0)),0)+IFERROR(SUMPRODUCT((INDEX(Attendance!$B$7:$AY$206,MATCH(A96,Attendance!$A$7:$A$206,0),0)=1)*Attendance!$B$4:$AY$4),0),"")} | C96: =IF(A96<>"",SUMIFS(Transactions!$F$7:$F$996,Transactions!$D$7:$D$996,"Income",Transactions!$E$7:$E$996,A96),"") | D96: =IF(A96<>"",SUMIFS(Transactions!$F$7:$F$996,Transactions!$D$7:$D$996,"Expense",Transactions!$E$7:$E$996,A96),"") | E96: =IF(A96<>"",B96-C96-D96,"") | F96: =IF(A96<>"",IF(E96=0,"Settled","Unsettled"),"")
A97: =IF(Roster!$A$95<>"",Roster!$A$95,"") | B97: {=IF(A97<>"",IFERROR(INDEX(Roster!$B$5:$B$204,MATCH(A97,Roster!$A$5:$A$204,0)),0)+IFERROR(SUMPRODUCT((INDEX(Attendance!$B$7:$AY$206,MATCH(A97,Attendance!$A$7:$A$206,0),0)=1)*Attendance!$B$4:$AY$4),0),"")} | C97: =IF(A97<>"",SUMIFS(Transactions!$F$7:$F$996,Transactions!$D$7:$D$996,"Income",Transactions!$E$7:$E$996,A97),"") | D97: =IF(A97<>"",SUMIFS(Transactions!$F$7:$F$996,Transactions!$D$7:$D$996,"Expense",Transactions!$E$7:$E$996,A97),"") | E97: =IF(A97<>"",B97-C97-D97,"") | F97: =IF(A97<>"",IF(E97=0,"Settled","Unsettled"),"")
A98: =IF(Roster!$A$96<>"",Roster!$A$96,"") | B98: {=IF(A98<>"",IFERROR(INDEX(Roster!$B$5:$B$204,MATCH(A98,Roster!$A$5:$A$204,0)),0)+IFERROR(SUMPRODUCT((INDEX(Attendance!$B$7:$AY$206,MATCH(A98,Attendance!$A$7:$A$206,0),0)=1)*Attendance!$B$4:$AY$4),0),"")} | C98: =IF(A98<>"",SUMIFS(Transactions!$F$7:$F$996,Transactions!$D$7:$D$996,"Income",Transactions!$E$7:$E$996,A98),"") | D98: =IF(A98<>"",SUMIFS(Transactions!$F$7:$F$996,Transactions!$D$7:$D$996,"Expense",Transactions!$E$7:$E$996,A98),"") | E98: =IF(A98<>"",B98-C98-D98,"") | F98: =IF(A98<>"",IF(E98=0,"Settled","Unsettled"),"")
A99: =IF(Roster!$A$97<>"",Roster!$A$97,"") | B99: {=IF(A99<>"",IFERROR(INDEX(Roster!$B$5:$B$204,MATCH(A99,Roster!$A$5:$A$204,0)),0)+IFERROR(SUMPRODUCT((INDEX(Attendance!$B$7:$AY$206,MATCH(A99,Attendance!$A$7:$A$206,0),0)=1)*Attendance!$B$4:$AY$4),0),"")} | C99: =IF(A99<>"",SUMIFS(Transactions!$F$7:$F$996,Transactions!$D$7:$D$996,"Income",Transactions!$E$7:$E$996,A99),"") | D99: =IF(A99<>"",SUMIFS(Transactions!$F$7:$F$996,Transactions!$D$7:$D$996,"Expense",Transactions!$E$7:$E$996,A99),"") | E99: =IF(A99<>"",B99-C99-D99,"") | F99: =IF(A99<>"",IF(E99=0,"Settled","Unsettled"),"")
A100: =IF(Roster!$A$98<>"",Roster!$A$98,"") | B100: {=IF(A100<>"",IFERROR(INDEX(Roster!$B$5:$B$204,MATCH(A100,Roster!$A$5:$A$204,0)),0)+IFERROR(SUMPRODUCT((INDEX(Attendance!$B$7:$AY$206,MATCH(A100,Attendance!$A$7:$A$206,0),0)=1)*Attendance!$B$4:$AY$4),0),"")} | C100: =IF(A100<>"",SUMIFS(Transactions!$F$7:$F$996,Transactions!$D$7:$D$996,"Income",Transactions!$E$7:$E$996,A100),"") | D100: =IF(A100<>"",SUMIFS(Transactions!$F$7:$F$996,Transactions!$D$7:$D$996,"Expense",Transactions!$E$7:$E$996,A100),"") | E100: =IF(A100<>"",B100-C100-D100,"") | F100: =IF(A100<>"",IF(E100=0,"Settled","Unsettled"),"")
A101: =IF(Roster!$A$99<>"",Roster!$A$99,"") | B101: {=IF(A101<>"",IFERROR(INDEX(Roster!$B$5:$B$204,MATCH(A101,Roster!$A$5:$A$204,0)),0)+IFERROR(SUMPRODUCT((INDEX(Attendance!$B$7:$AY$206,MATCH(A101,Attendance!$A$7:$A$206,0),0)=1)*Attendance!$B$4:$AY$4),0),"")} | C101: =IF(A101<>"",SUMIFS(Transactions!$F$7:$F$996,Transactions!$D$7:$D$996,"Income",Transactions!$E$7:$E$996,A101),"") | D101: =IF(A101<>"",SUMIFS(Transactions!$F$7:$F$996,Transactions!$D$7:$D$996,"Expense",Transactions!$E$7:$E$996,A101),"") | E101: =IF(A101<>"",B101-C101-D101,"") | F101: =IF(A101<>"",IF(E101=0,"Settled","Unsettled"),"")
A102: =IF(Roster!$A$100<>"",Roster!$A$100,"") | B102: {=IF(A102<>"",IFERROR(INDEX(Roster!$B$5:$B$204,MATCH(A102,Roster!$A$5:$A$204,0)),0)+IFERROR(SUMPRODUCT((INDEX(Attendance!$B$7:$AY$206,MATCH(A102,Attendance!$A$7:$A$206,0),0)=1)*Attendance!$B$4:$AY$4),0),"")} | C102: =IF(A102<>"",SUMIFS(Transactions!$F$7:$F$996,Transactions!$D$7:$D$996,"Income",Transactions!$E$7:$E$996,A102),"") | D102: =IF(A102<>"",SUMIFS(Transactions!$F$7:$F$996,Transactions!$D$7:$D$996,"Expense",Transactions!$E$7:$E$996,A102),"") | E102: =IF(A102<>"",B102-C102-D102,"") | F102: =IF(A102<>"",IF(E102=0,"Settled","Unsettled"),"")
...

Sheet Pending Approval
A1: PENDING TRANSACTIONS - Player Submissions
A2: Players submit items here. Treasurer reviews and moves approved items to the Transactions sheet.
A4: Date | B4: Player Name | C4: Description | D4: Category | E4: Amount ($) | F4: Receipt / Notes | G4: Status
G5: Pending
G6: Pending
G7: Pending
G8: Pending
G9: Pending
G10: Pending
G11: Pending
G12: Pending
G13: Pending
G14: Pending
G15: Pending
G16: Pending
... G204: Pending

Sheet Dashboard
A1: DASHBOARD — Auto-calculated Summary (Website reads this)
A3: TEAM OVERVIEW
A4: Total Players | B4: =COUNTA(Roster!A5:A204) -> 34
A5: Active Players | B5: =COUNTIF(Roster!E5:E204,"Active") -> 5
A6: Coaches/Staff | B6: =COUNTIF(Roster!D5:D204,"Coach")+COUNTIF(Roster!D5:D204,"Treasurer") -> 4
A7: Captains | B7: =COUNTIF(Roster!D5:D204,"Captain") -> 3
A9: FINANCES
A10: Total Dues Owed | B10: =SUMIF(Roster!E5:E204,"Active",Roster!B5:B204) -> 0
A11: Total Dues Collected | B11: =SUMIFS(Transactions!F7:F996,Transactions!D7:D996,"Income",Transactions!C7:C996,"Dues") -> 0
A12: Dues Outstanding | B12: =B10-B11 -> 0
A13: Total Income | B13: =Transactions!A4 -> 2109
A14: Total Expenses | B14: =Transactions!B4 -> 2070
A15: Net Balance | B15: =Transactions!C4 -> 39
A16: Pending Transactions | B16: =Transactions!E4 -> 0
A18: EVENTS
A19: Total Events | B19: =COUNTA(Events!A5:A506) -> 8
A20: Practices | B20: =COUNTIF(Events!D5:D506,"Practice") -> 2
A21: Tournaments | B21: =Events!D4 -> Category
A22: Fundraisers | B22: =Events!D4 -> Category
A23: Total Budgeted | B23: =Events!H4 -> Who Paid Upfront
A24: Total Actual Spend | B24: =Events!I4 -> Split Method
A25: Budget Variance | B25: =Events!J4 -> Notes

Sheet Key & Instructions
A1: KEY & INSTRUCTIONS
A3: COLOR CODING
A4: Blue text | B4: Enter data here — these are your inputs
A5: Black text (formula) | B5: Auto-calculated — do not edit
A6: Green text | B6: Pulls from another sheet — do not edit
A8: ACCESS CODES
A9: Access codes | B9: Set unique codes in the 'Access Codes' tab. Share each player's code only with them.
A10: Player view | B10: Players enter their code → see only their own dues, balance, attendance
A11: Captain view | B11: Captains enter their code → see full roster balances, event attendance summary
A12: Coach/Treasurer | B12: Full dashboard: all finances, all player balances, all transactions
A14: ATTENDANCE
A15: 1 = Attended | 0 = Absent | X = Exempt | B15: Player was present
A16: N = Absent | B16: Player did not attend
A17: X = Exempt — absent but excused/exempt from cost | B17: Absent but excused — may waive cost
A18: Row 4 in Attendance is auto-calculated from Events (Actual Cost ÷ attendees for "Attendance" events; ÷ roster size for "Equal Split" events) | B18: Row 6 in Attendance sheet — enter per-event cost, auto-calculates totals
A20: WORKFLOW
A21: 1. Roster | B21: Add all players/coaches, set unique access codes, set dues amounts
A22: 2. Events | B22: Log every event with budget and actual cost
A23: 3. Attendance | B23: Mark Y/N/E for each player per event; set cost per person in row 6
A24: 4. Transactions | B24: Log all money in/out; link to events where possible
A25: 5. Player Balances | B25: Update dues paid, event costs owed, upfront payments — net auto-calculates
A26: 6. Dashboard | B26: Auto-updates — this is what the website displays
A27: 7. Commit to GitHub | B27: Save file → git add → git commit → git push → website updates!
A29: SPLIT METHODS
A30: Equal Split | B30: Total cost ÷ all active players
A31: Attendance | B31: Total cost ÷ attendees only
A32: Custom | B32: Manual — enter individual amounts in Player Balances
A33: Team Pays | B33: Covered by team funds, no individual charge
A34: Individual Pays | B34: Person pays their own way, no reimbursement

Sheet Access Codes
A1: 🔒 ACCESS CODES — TREASURER ONLY 🔒
A2: ⚠️ HIDE THIS SHEET BEFORE SHARING THE FILE WITH PLAYERS ⚠️
A3: To hide: right-click this sheet tab → 'Hide'. To unhide: right-click any tab → 'Unhide'.
A5: Player Name | B5: Access Code | C5: Role | D5: Status | E5: Notes / Share Method
A6: At | B6: AT | C6: Captain | D6: Active
A7: Alex Warrington | B7: AW | C7: Player | D7: Active
A8: Chris Wohl | B8: CW | C8: Player | D8: Active
A9: Darra Reppermund | B9: DR | C9: Player | D9: Active
A10: Dylan Best | B10: DB | C10: Player | D10: Active
A11: Griffin O'Neal-Freeman | B11: GOF | C11: Player | D11: Active
A12: Haley Young | B12: HY | C12: Player | D12: Active
A13: Harry Park | B13: HP | C13: Player | D13: Active
A14: Ian Piper | B14: IP | C14: Player | D14: Active
A15: Jake Murray | B15: JM | C15: Treasurer | D15: Active
A16: Jenna Nold | B16: JN | C16: Captain | D16: Active
A17: Jimmy Towle | B17: NT | C17: Player | D17: Active
... A39: Nick Blair | B39: NB | C39: Player | D39: Active
A107: 💡 Tip: Codes can be anything — e.g. initials + jersey # + year. Make them easy to remember but hard to guess.
